Workbook
Name Cap: Inputs!$B$4
Name Bonus: Inputs!$B$5
Name Barrier: Inputs!$B$6
Name Ratio: Inputs!$B$7
Name IssueDate: Inputs!$B$8
Name MatDate: Inputs!$B$9
Name AnnualDiv: Inputs!$B$11
Name RefSpot: Inputs!$B$12
Name q: Inputs!$B$13
Name EWMALam: Inputs!$B$14
Name dS: Inputs!$B$16
Name dSig: Inputs!$B$17
Name dT: Inputs!$B$18
Name dR: Inputs!$B$19
Name S0_d: Inputs!$B$21
Name K_d: Inputs!$B$22
Name KCap_d: Inputs!$B$23
Name T_d: Inputs!$B$24
Name Sig_d: Inputs!$B$25
Name svb0: Inputs!$B$27
Name svb1: Inputs!$B$28
Name svb2: Inputs!$B$29
Name svb3: Inputs!$B$30
Name svt1: Inputs!$B$31
Name svt2: Inputs!$B$32
Name W0_mc: Inputs!$B$34
Name T_mc: Inputs!$B$35
Name NSteps: Inputs!$B$36
Name NPaths: Inputs!$B$37
Name MCseed: Inputs!$B$38
Name S0_mc: Inputs!$B$39
Name mu_mc: Inputs!$B$40
Name Sig_mc: Inputs!$B$41
Name r_mc: Inputs!$B$42
Name q_mc: Inputs!$B$43

Sheet Cover
A1: B401 -- Continuous-Time Derivatives Pricing
A2: Unified Workbook: Parts 1, 2 and 3 (Tasks I through XI)
A3: Student: DU2076 | Date built: 2026-06-20 | Course: B401 Summer 2026
A5: Field | B5: Value | C5: Source
A6: Product name | B6: DZ BANK Bonus/Protection Cert on Rheinmetall | C6: [C] KID DE000DU20767
A7: WKN | B7: DU2076 | C7: [C]
A8: Issuer | B8: DZ BANK AG | C8: [C]
A9: Underlying | B9: Rheinmetall AG (RHM.DE) | C9: [C]
A10: Barrier | B10: 1,050 EUR | C10: [C] Barriere
A11: Cap / Bonus | B11: 2,000 EUR | C11: [C] Hoechstbetrag
A12: Issue date | B12: 2025-09-04 | C12: [C] Emissionstag
A13: Maturity date | B13: 2027-06-18 | C13: [C] Bewertungstag
A14: Pricing engine | B14: N=200 CRR binomial tree (Python, canonical) | C14: [P]
A15: Greeks / Rep. port. | B15: Rubinstein-Reiner (1991) closed-form (cross-check) | C15: [P]
A17: Sourcing legend
A18: [C] Contractual | B18: DZ BANK KID DE000DU20767 dated 12.06.2026
A19: [M] Market data | B19: Yahoo Finance (yfinance, RHM.DE) / onvista.de (cert prices)
A20: [E] ECB source | B20: ECB AAA sovereign yield-curve dataset, downloaded 2026-06-15
A21: [P] Model param | B21: Stated assumption, derivation shown in workbook
A23: Sheet index
A24: Tab | B24: Purpose
A25: Cover | B25: Product identity, methodology, sheet index, sourcing legend
A26: Inputs | B26: Named-range constants: contractual terms, model params, Part 1 design
A27: Data_Stock | B27: RHM.DE daily closes + EWMA vol (183 trading days, static)
A28: Data_Cert | B28: DU2076 certificate daily market prices (183 rows, static)
A29: Data_Svensson | B29: ECB AAA Svensson params per trading day (183 rows, static)
A30: MC_Paths | B30: Pre-computed GBM paths: S_term, S_half, S_term_shock (50,000 rows)
A31: P1_Tasks_I_IV | B31: Investor profile, product design, payoff table, market size
A32: P2_TaskV_Val | B32: Daily model vs market valuation (183 rows) + error metrics
A33: P2_TaskVI_Greeks | B33: Greeks cross-section (100 S values) + reference-point summary
A34: P2_TaskVII_Rep | B34: Daily replicating portfolio (183 rows) + equity fraction vs S
A35: P3_TaskVIII | B35: MC unhedged performance: Mean, Std, Sharpe, VaR, CVaR
... A39: CrossCheck | B39: Reconciliation: all 27 targets vs notebook, pass/fail flags
A41: IMPORTANT: Workbook calculation is set to MANUAL. Press Ctrl+Alt+F9 (Windows) or Cmd+Option+F9 (Mac) after opening to recalculate all formulas.

Sheet Inputs
A1: Inputs -- Named Ranges and Model Parameters
A2: Parameter | B2: Value | C2: Unit | D2: Source | E2: Description
A3: --- Contractual terms (KID DE000DU20767) ---
A4: Cap | B4: 2000 | C4: EUR | D4: [C] | E4: Hoechstbetrag -- maximum redemption
A5: Bonus | B5: 2000 | C5: EUR | D5: [C] | E5: Bonusbetrag -- bonus level
A6: Barrier | B6: 1050 | C6: EUR | D6: [C] | E6: Barriere -- knock-in barrier
A7: Ratio | B7: 1 | D7: [C] | E7: Bezugsverhaeltnis -- participation ratio
A8: IssueDate | B8: 2025-09-04 | D8: [C] | E8: Emissionstag -- issue / first trading date
A9: MatDate | B9: 2027-06-18 | D9: [C] | E9: Bewertungstag -- final valuation date
A10: --- Market-derived inputs ---
A11: AnnualDiv | B11: 7.2 | C11: EUR | D11: [M] | E11: Rheinmetall FY2024 DPS (investor relations)
A12: RefSpot | B12: 1207 | C12: EUR | D12: [M] | E12: Last RHM.DE close in valuation window (2026-06-01)
A13: q | B13: 0.006 | D13: [M] | E13: Continuous dividend yield = 7.20/1207.00
A14: EWMALam | B14: 0.94 | D14: [P] | E14: RiskMetrics standard EWMA lambda
A15: --- FD bump sizes ---
A16: dS | B16: 0.01 | D16: [P] | E16: 1% central bump on S (Delta/Gamma)
A17: dSig | B17: 0.02 | D17: [P] | E17: 2% central bump on sigma (Vega)
A18: dT | B18: 0.003968254 | C18: yr | D18: [P] | E18: 1 trading day in years (Theta step)
A19: dR | B19: 0.0001 | D19: [P] | E19: 1 bp central bump on r (Rho)
A20: --- Part 1 design parameters ---
A21: S0_d | B21: 1207 | C21: EUR | D21: [P] | E21: RefSpot on design date 2026-06-01
A22: K_d | B22: 1207 | C22: EUR | D22: [P] | E22: ATM strike = S0_d
A23: KCap_d | B23: 1569.1 | C23: EUR | D23: [P] | E23: Cap strike = 1.30 * S0_d
A24: T_d | B24: 3 | C24: yr | D24: [P] | E24: Product maturity (years)
A25: Sig_d | B25: 0.5417 | D25: [P] | E25: EWMA vol at design date (2026-06-01)
A26: --- Svensson params (ECB AAA, 2026-06-01) ---
A27: svb0 | B27: 1.330382 | D27: [E] | E27: Beta0
A28: svb1 | B28: 0.700052 | D28: [E] | E28: Beta1
A29: svb2 | B29: 1.816755 | D29: [E] | E29: Beta2
A30: svb3 | B30: 7.130184 | D30: [E] | E30: Beta3
A31: svt1 | B31: 0.966763 | D31: [E] | E31: Tau1
A32: svt2 | B32: 15.839369 | D32: [E] | E32: Tau2
A33: --- Part 3 Monte Carlo parameters ---
A34: W0_mc | B34: 10000 | C34: EUR | D34: [P] | E34: Initial capital
A35: T_mc | B35: 1 | C35: yr | D35: [P] | E35: Investment horizon
A36: NSteps | B36: 252 | D36: [P] | E36: GBM time steps per year
A37: NPaths | B37: 50000 | D37: [P] | E37: Monte Carlo paths
A38: MCseed | B38: 2026 | D38: [P] | E38: numpy random seed
A39: S0_mc | B39: 1207 | C39: EUR | D39: [P] | E39: GBM initial stock price = RefSpot
A40: mu_mc | B40: 0.5405 | D40: [P] | E40: Annualized historical mean log return (Jan2023-Jun2026)
A41: Sig_mc | B41: 0.3988 | D41: [P] | E41: Annualized historical vol (EWMA full-sample)
A42: r_mc | B42: 0.030681 | D42: [E] | E42: Risk-free rate = Svensson r(10y) on 2026-06-01
A43: q_mc | B43: 0.006 | D43: [M] | E43: Continuous dividend yield (same as q)

Sheet Data_Stock
A1: Data_Stock -- RHM.DE daily closes and EWMA volatility (183 trading days)
A2: [M] Source: Yahoo Finance yfinance RHM.DE auto-adjusted close. EWMA vol: lambda=0.94 RiskMetrics, annualized * sqrt(252). Window: 2025-09-04 to 2026-06-01.
A3: Date | B3: RHM_Spot_EUR | C3: EWMA_Vol_pct
A4: 45904 | B4: 1707.93 | C4: 0.39
A5: 45905 | B5: 1727.24 | C5: 0.38
A6: 45908 | B6: 1773.27 | C6: 0.383
A7: 45909 | B7: 1761.39 | C7: 0.372
A8: 45910 | B8: 1819.31 | C8: 0.382
A9: 45911 | B9: 1861.89 | C9: 0.381
A10: 45912 | B10: 1877.73 | C10: 0.371
A11: 45915 | B11: 1930.7 | C11: 0.376
A12: 45916 | B12: 1882.19 | C12: 0.377
A13: 45917 | B13: 1869.81 | C13: 0.367
A14: 45918 | B14: 1900.5 | C14: 0.361
A15: 45919 | B15: 1908.92 | C15: 0.351
... A186: 46174 | B186: 1207 | C186: 0.542

Sheet Data_Cert
A1: Data_Cert -- DU2076 daily market prices (183 trading days)
A2: [M] Source: onvista.de -- closing prices for DZ BANK certificate DE000DU20767.
A3: Date | B3: Market_Price_EUR
A4: 45904 | B4: 1635.75
A5: 45905 | B5: 1648.28
A6: 45908 | B6: 1675.51
A7: 45909 | B7: 1671.59
A8: 45910 | B8: 1699.14
A9: 45911 | B9: 1721.63
A10: 45912 | B10: 1713.91
A11: 45915 | B11: 1735.5
A12: 45916 | B12: 1728.41
A13: 45917 | B13: 1699.94
A14: 45918 | B14: 1708.18
A15: 45919 | B15: 1711.35
... A186: 46174 | B186: 1236.07

Sheet Data_Svensson
A1: Data_Svensson -- ECB AAA Svensson parameters per trading day (183 rows)
A2: [E] Source: ECB Data Portal, AAA sovereign yield curve, downloaded 2026-06-15. Parameters forward-filled for non-ECB-publication dates.
A3: Date | B3: b0 | C3: b1 | D3: b2 | E3: b3 | F3: tau1 | G3: tau2 | H3: T_rem_yr | I3: r_daily
A4: 45904 | B4: 1.168343 | C4: 0.791456 | D4: -1.558745 | E4: 7.547626 | F4: 2.877366 | G4: 12.757641 | H4: 1.7863014 | I4: 0.019161407
A5: 45905 | B5: 1.167426 | C5: 0.761807 | D5: -1.821262 | E5: 7.664804 | F5: 3.218451 | G5: 12.62628 | H5: 1.7835616 | I5: 0.01893438
A6: 45908 | B6: 1.198176 | C6: 0.752225 | D6: -2.297018 | E6: 7.725683 | F6: 3.438575 | G6: 11.802636 | H6: 1.7753425 | I6: 0.018881794
A7: 45909 | B7: 1.205197 | C7: 0.740409 | D7: -1.677676 | E7: 7.39418 | F7: 3.023955 | G7: 12.832287 | H7: 1.7726027 | I7: 0.018955417
A8: 45910 | B8: 1.202277 | C8: 0.761658 | D8: -1.692318 | E8: 7.386787 | F8: 3.026223 | G8: 12.836812 | H8: 1.769863 | I8: 0.019053388
A9: 45911 | B9: 1.204237 | C9: 0.75691 | D9: -1.615143 | E9: 7.356917 | F9: 3.268254 | G9: 12.889797 | H9: 1.7671233 | I9: 0.019423606
A10: 45912 | B10: 1.199688 | C10: 0.744959 | D10: -1.462092 | E10: 7.352704 | F10: 3.328068 | G10: 12.832385 | H10: 1.7643836 | I10: 0.019649879
A11: 45915 | B11: 1.194697 | C11: 0.750982 | D11: -1.484931 | E11: 7.34158 | F11: 3.322536 | G11: 12.848706 | H11: 1.7561644 | I11: 0.019581829
A12: 45916 | B12: 1.190226 | C12: 0.772804 | D12: -1.510362 | E12: 7.343672 | F12: 3.311418 | G12: 12.845352 | H12: 1.7534247 | I12: 0.019648921
A13: 45917 | B13: 1.203972 | C13: 0.747581 | D13: -1.13154 | E13: 6.979307 | F13: 2.868727 | G13: 13.349989 | H13: 1.7506849 | I13: 0.019507499
A14: 45918 | B14: 1.213035 | C14: 0.746271 | D14: -1.778341 | E14: 7.497673 | F14: 3.456473 | G14: 12.195202 | H14: 1.7479452 | I14: 0.019641012
A15: 45919 | B15: 1.202443 | C15: 0.767881 | D15: -1.45466 | E15: 7.402585 | F15: 3.145587 | G15: 12.699912 | H15: 1.7452055 | I15: 0.019749218
... A186: 46174 | B186: 1.330382 | C186: 0.700052 | D186: 1.816755 | E186: 7.130184 | F186: 0.966763 | G186: 15.839369 | H186: 1.0465753 | I186: 0.024778054

Sheet MC_Paths
A1: MC_Paths -- GBM simulation (numpy seed=2026, N=50000 paths, T*=1y, 252 steps)
A2: [P] Precomputed by build_workbook.py. S0=1207, mu=54.05%, sigma=39.88%, r=3.0681%, q=0.60%, seed=2026. S_term: T=1y price; S_half: T=0.5y price; S_term_shock: -20% at T/2 then continued.
A3: PathID | B3: S_term | C3: S_half | D3: S_term_shock
A4: 1 | B4: 2946.8728 | C4: 1906.8246 | D4: 2357.4982
A5: 2 | B5: 2692.8482 | C5: 1729.6466 | D5: 2154.2786
A6: 3 | B6: 3937.0408 | C6: 1986.7543 | D6: 3149.6327
A7: 4 | B7: 2691.347 | C7: 2458.3094 | D7: 2153.0776
A8: 5 | B8: 1682.2772 | C8: 1232.6847 | D8: 1345.8217
A9: 6 | B9: 2395.1052 | C9: 1467.7354 | D9: 1916.0841
A10: 7 | B10: 1834.5135 | C10: 1628.3854 | D10: 1467.6108
A11: 8 | B11: 1436.8572 | C11: 1773.2325 | D11: 1149.4858
A12: 9 | B12: 6938.9784 | C12: 2706.3416 | D12: 5551.1827
A13: 10 | B13: 1680.7342 | C13: 1112.6218 | D13: 1344.5874
A14: 11 | B14: 3033.0718 | C14: 1628.6637 | D14: 2426.4575
A15: 12 | B15: 1538.0721 | C15: 1145.9945 | D15: 1230.4577
... A50003: 50000 | B50003: 1857.2057 | C50003: 1536.2693 | D50003: 1485.7646

Sheet P1_Tasks_I_IV
A1: Part 1 -- Tasks I through IV
A3: Task I -- Investor Profile
A4: Target investor: aged 40-60 (5-10 years pre-retirement), holding a moderate-risk balanced portfolio, with a 3-year investment horizon. Bullish on European defence rearmament (Rheinmetall / NATO Sondervermogen theme) but unwilling to accept the 54% annualized EWMA volatility of the direct single stock. Prefers guaranteed capital return at maturity with partial upside participation capped at +30%. Suitable for an investor who would otherwise allocate to investment-grade credit (2-3% p.a. yield) and is willing to forgo full equity upside in exchange for principal protection. Source: Notebook Cell 16 / DZ BANK KID investor suitability section.
A7: Task II -- Product Design: Capital Protection Note (CPN)
A8: Replication formula: | B8: CPN = ZCB(S0, r_3y, T) + alpha * [Call(K=S0) - Call(K=Kcap)]
A10: Component | B10: Position | C10: Role
A11: Zero-coupon bond (face = S0_d = 1,207 EUR) | B11: Long (1 unit) | C11: Guarantees 100% capital return at maturity (S0 discounted at r_3y)
A12: ATM European call (K = S0_d = 1,207 EUR) | B12: Long (alpha units) | C12: Provides participation in RHM gains above S0
A13: OTM European call (K = KCap_d = 1,569.10 EUR) | B13: Short (alpha units) | C13: Caps gain at +30%; short premium funds higher alpha participation
A15: Design validation -- live formulas (Inputs named ranges)
A16: Parameter | B16: Formula / Value | C16: Target | D16: Status
A17: r_3y (Svensson, 3y) | B17: =(svb0+svb1*(1-EXP(-T_d/svt1))/(T_d/svt1)+svb2*((1-EXP(-T_d/svt1))/(T_d/svt1)-EXP(-T_d/svt1))+svb3*((1-EXP(-T_d/svt2))/(T_d/svt2)-EXP(-T_d/svt2)))/100 | C17: 2.6192% | D17: =IF(ABS($B$17-0.026192000000000003)<0.01,"PASS","CHECK")
A18: ZCB0 (EUR) | B18: =S0_d*EXP(-$B$17*T_d) | C18: 1,115.79 EUR | D18: =IF(ABS($B$18-1115.79)<0.01,"PASS","CHECK")
A19: Call_ATM (EUR) | B19: =S0_d*EXP(-q*T_d)*NORM.S.DIST((LN(S0_d/K_d)+($B$17-q+0.5*Sig_d^2)*T_d)/(Sig_d*SQRT(T_d)),1)-K_d*EXP(-$B$17*T_d)*NORM.S.DIST(((LN(S0_d/K_d)+($B$17-q+0.5*Sig_d^2)*T_d)/(Sig_d*SQRT(T_d)))-(Sig_d*SQRT(T_d)),1) | C19: 451.04 EUR | D19: =IF(ABS($B$19-451.04)<0.01,"PASS","CHECK")
A20: Call_Cap (EUR) | B20: =S0_d*EXP(-q*T_d)*NORM.S.DIST((LN(S0_d/KCap_d)+($B$17-q+0.5*Sig_d^2)*T_d)/(Sig_d*SQRT(T_d)),1)-KCap_d*EXP(-$B$17*T_d)*NORM.S.DIST(((LN(S0_d/KCap_d)+($B$17-q+0.5*Sig_d^2)*T_d)/(Sig_d*SQRT(T_d)))-(Sig_d*SQRT(T_d)),1) | C20: 353.43 EUR | D20: =IF(ABS($B$20-353.43)<0.01,"PASS","CHECK")
A21: Spread (EUR) | B21: =$B$19-$B$20 | C21: 97.61 EUR | D21: =IF(ABS($B$21-97.61)<0.01,"PASS","CHECK")
A22: Alpha | B22: =(S0_d-$B$18)/$B$21 | C22: 0.9344 | D22: =IF(ABS($B$22-0.9344)<0.01,"PASS","CHECK")
A25: Task III -- Payoff Table (CPN vs direct RHM stock)
A26: S_T / S0_d | B26: S_T (EUR) | C26: CPN payoff (EUR) | D26: vs Direct stock
A27: 0.5 | B27: 603.5 | C27: 1207 | D27: 1
A28: 0.7 | B28: 844.9 | C28: 1207 | D28: 0.42857143
A29: 0.8 | B29: 965.6 | C29: 1207 | D29: 0.25
A30: 0.9 | B30: 1086.3 | C30: 1207 | D30: 0.11111111
A31: 1 | B31: 1207 | C31: 1207 | D31: 0
A32: 1.1 | B32: 1327.7 | C32: 1319.7853 | D32: -0.0059611792
A33: 1.2 | B33: 1448.4 | C33: 1432.5707 | D33: -0.010928829
A34: 1.3 | B34: 1569.1 | C34: 1545.356 | D34: -0.015132224
A35: 1.4 | B35: 1689.8 | C35: 1545.356 | D35: -0.085479922
A36: 1.6 | B36: 1931.2 | C36: 1545.356 | D36: -0.19979493
A38: Payoff: If S_T < S0 => 1,207 EUR (full capital). If S0 <= S_T <= Kcap => 1,207 + 93.44% * (S_T - 1,207). If S_T > Kcap => 1,207 + 93.44% * (1,569.10 - 1,207) = max 1,545 EUR.
A41: Task IV -- German Structured Products Market Size
A42: Item | B42: Value | C42: Source
A43: Total German structured products market | B43: 112 | C43: [P] BSW 2023 slide 13
A44: Kapitalschutz (capital protection) share | B44: 0.038 | C44: [P] BSW 2023 slide 13
A45: Kapitalschutz segment size | B45: 4.256 | C45: [P] derived
A46: Participation notes share (est.) | B46: 0.55 | C46: [P] author estimate
A47: Participation notes market | B47: 2.3408 | C47: [P] derived
A48: Active issues (est.) | B48: 130 | C48: [P] 6 issuers x ~20
A49: Average issue size | B49: 18.006154 | C49: [P] derived

Sheet P2_TaskV_Val
A1: Task V -- Daily Model vs Market Valuation (N=200 CRR Binomial Tree)
A2: Metric | B2: Formula | C2: Value | D2: Target | E2: Tol | F2: Pass/Fail
A3: ME (EUR) | B3: =AVERAGE(F10:F192) | C3: -85.544153 | D3: -85.54 | E3: 0.1 | F3: PASS
A4: MAE (EUR) | B4: =SUMPRODUCT(ABS(F10:F192))/183 | C4: 94.491038 | D4: 94.49 | E4: 0.1 | F4: PASS
A5: RMSE (EUR) | B5: =SQRT(SUMPRODUCT(F10:F192,F10:F192)/183) | C5: 108.91915 | D5: 108.92 | E5: 0.1 | F5: PASS
A6: MAPE (%) | B6: =SUMPRODUCT(ABS(G10:G192))/183*100 | C6: 6.1091803 | D6: 6.11 | E6: 0.05 | F6: PASS
A7: Implied-vol model reference (Python notebook Cell 40): ME = -8.89 EUR, RMSE = 12.37 EUR, MAPE = 0.64%, mean IV = 37.77% vs mean EWMA = 44.27%.
A8: Key findings: (a) EWMA model systematically UNDERPRICES (ME = -85.54 EUR negative throughout valuation window). (b) Mean EWMA vol 44.27% exceeds market-implied vol 37.77% -- EWMA overstates volatility, making calls (and hence cert) appear more expensive than market. (c) Residual error after implied-vol calibration (~9 EUR) reflects issuer bid-ask spread and structuring margin.
A9: Date | B9: RHM_Spot_EUR | C9: EWMA_Vol_pct | D9: Tree_Model_Py | E9: Market_Price_EUR | F9: Error_EUR | G9: Error_pct
A10: 45904 | B10: 1707.93 | C10: 0.39 | D10: 1558.89 | E10: 1635.75 | F10: -76.86 | G10: -0.047
A11: 45905 | B11: 1727.24 | C11: 0.38 | D11: 1571.16 | E11: 1648.28 | F11: -77.12 | G11: -0.0468
A12: 45908 | B12: 1773.27 | C12: 0.383 | D12: 1601.18 | E12: 1675.51 | F12: -74.33 | G12: -0.0444
A13: 45909 | B13: 1761.39 | C13: 0.372 | D13: 1607.28 | E13: 1671.59 | F13: -64.31 | G13: -0.0385
A14: 45910 | B14: 1819.31 | C14: 0.382 | D14: 1628.9 | E14: 1699.14 | F14: -70.24 | G14: -0.0413
A15: 45911 | B15: 1861.89 | C15: 0.381 | D15: 1636.5 | E15: 1721.63 | F15: -85.13 | G15: -0.0494
A16: 45912 | B16: 1877.73 | C16: 0.371 | D16: 1666.15 | E16: 1713.91 | F16: -47.76 | G16: -0.0279
A17: 45915 | B17: 1930.7 | C17: 0.376 | D17: 1688.12 | E17: 1735.5 | F17: -47.38 | G17: -0.0273
A18: 45916 | B18: 1882.19 | C18: 0.377 | D18: 1663.42 | E18: 1728.41 | F18: -64.99 | G18: -0.0376
A19: 45917 | B19: 1869.81 | C19: 0.367 | D19: 1669.48 | E19: 1699.94 | F19: -30.46 | G19: -0.0179
A20: 45918 | B20: 1900.5 | C20: 0.361 | D20: 1694.37 | E20: 1708.18 | F20: -13.81 | G20: -0.0081
A21: 45919 | B21: 1908.92 | C21: 0.351 | D21: 1721 | E21: 1711.35 | F21: 9.65 | G21: 0.0056
... A192: 46174 | B192: 1207 | C192: 0.542 | D192: 1153.79 | E192: 1236.07 | F192: -82.28 | G192: -0.0666

Sheet P2_TaskVI_Greeks
A1: Task VI -- Greeks (Rubinstein-Reiner closed-form, central FD)
A2: Reference input | B2: Value | C2: Unit | D2: Note
A3: S_ref | B3: 1707.93 | C3: EUR | D3: First DU2076 trading-day close (2025-09-04)
A4: sigma | B4: 0.4455 | D4: Median EWMA vol over valuation window (notebook Cell 45)
A5: T_ref | B5: 1.7863014 | C5: yr | D5: Time to maturity from issue date: (2027-06-18 - 2025-09-04)/365
A6: r_ref | B6: =LET(_t,$B$5,_b0,Data_Svensson!$B$4,_b1,Data_Svensson!$C$4,_b2,Data_Svensson!$D$4,_b3,Data_Svensson!$E$4,_t1,Data_Svensson!$F$4,_t2,Data_Svensson!$G$4,(_b0+_b1*(1-EXP(-_t/_t1))/(_t/_t1)+_b2*((1-EXP(-_t/_t1))/(_t/_t1)-EXP(-_t/_t1))+_b3*((1-EXP(-_t/_t2))/(_t/_t2)-EXP(-_t/_t2)))/100) | D6: ECB Svensson r(T_ref) on 2025-09-04 -- LIVE formula
A7: q | B7: 0.006 | D7: Continuous dividend yield
A8: K | B8: 2000 | C8: EUR | D8: Certificate cap = barrier trigger level: Barriere=1050 (but model K=Cap=2000)
A9: H (Barrier) | B9: 1050 | C9: EUR | D9: Down-and-out barrier
A11: Reference-point Greeks (RR closed-form) | E11: Bumped price helper cells (live Excel LET formulas)
A12: Greek | B12: RR Value | C12: Notebook target | D12: Notes | E12: =LET(_S,$B$3,_sig,$B$4,_T,$B$5,_r,$B$6,_K,Cap,_H,Barrier,_q,q,_b,_r-_q,_sqT,_sig*SQRT(_T),_mu,(_b-0.5*_sig^2)/_sig^2,_x1,LN(_S/_K)/_sqT+(1+_mu)*_sqT,_x2,LN(_S/_H)/_sqT+(1+_mu)*_sqT,_y1,LN(_H^2/(_S*_K))/_sqT+(1+_mu)*_sqT,_y2,LN(_H/_S)/_sqT+(1+_mu)*_sqT,_Sbd,_S*EXP(-_q*_T),_Kdr,_K*EXP(-_r*_T),_h2m1,(_H/_S)^(2*(_mu+1)),_h2m,(_H/_S)^(2*_mu),_A1,_Kdr*NORM.S.DIST(_sqT-_x1,1)-_Sbd*NORM.S.DIST(-_x1,1),_A2,_Kdr*NORM.S.DIST(_sqT-_x2,1)-_Sbd*NORM.S.DIST(-_x2,1),_A3,_Kdr*_h2m*NORM.S.DIST(_y1-_sqT,1)-_Sbd*_h2m1*NORM.S.DIST(_y1,1),_A4,_Kdr*_h2m*NORM.S.DIST(_y2-_sqT,1)-_Sbd*_h2m1*NORM.S.DIST(_y2,1),_do,IF(_S<=_H,0,_A1-_A2+_A3-_A4),_cf,_Sbd*NORM.S.DIST(-_x1,1)+_Kdr*NORM.S.DIST(_x1-_sqT,1),IF(_S<=_H,_cf,_do+_cf)) | F12: Price_ref
A13: Price (EUR) | B13: =$E$12 | C13: 1,457.77 EUR | D13: RR vs N=200 tree divergence ~5 EUR expected | E13: =LET(_S,$B$3*(1+dS),_sig,$B$4,_T,$B$5,_r,$B$6,_K,Cap,_H,Barrier,_q,q,_b,_r-_q,_sqT,_sig*SQRT(_T),_mu,(_b-0.5*_sig^2)/_sig^2,_x1,LN(_S/_K)/_sqT+(1+_mu)*_sqT,_x2,LN(_S/_H)/_sqT+(1+_mu)*_sqT,_y1,LN(_H^2/(_S*_K))/_sqT+(1+_mu)*_sqT,_y2,LN(_H/_S)/_sqT+(1+_mu)*_sqT,_Sbd,_S*EXP(-_q*_T),_Kdr,_K*EXP(-_r*_T),_h2m1,(_H/_S)^(2*(_mu+1)),_h2m,(_H/_S)^(2*_mu),_A1,_Kdr*NORM.S.DIST(_sqT-_x1,1)-_Sbd*NORM.S.DIST(-_x1,1),_A2,_Kdr*NORM.S.DIST(_sqT-_x2,1)-_Sbd*NORM.S.DIST(-_x2,1),_A3,_Kdr*_h2m*NORM.S.DIST(_y1-_sqT,1)-_Sbd*_h2m1*NORM.S.DIST(_y1,1),_A4,_Kdr*_h2m*NORM.S.DIST(_y2-_sqT,1)-_Sbd*_h2m1*NORM.S.DIST(_y2,1),_do,IF(_S<=_H,0,_A1-_A2+_A3-_A4),_cf,_Sbd*NORM.S.DIST(-_x1,1)+_Kdr*NORM.S.DIST(_x1-_sqT,1),IF(_S<=_H,_cf,_do+_cf)) | F13: Price_Sp (S +1%)
A14: Delta | B14: =($E$13-$E$14)/(2*dS*$B$3) | C14: 0.2449 | D14: RR vs tree: see divergence note below | E14: =LET(_S,$B$3*(1-dS),_sig,$B$4,_T,$B$5,_r,$B$6,_K,Cap,_H,Barrier,_q,q,_b,_r-_q,_sqT,_sig*SQRT(_T),_mu,(_b-0.5*_sig^2)/_sig^2,_x1,LN(_S/_K)/_sqT+(1+_mu)*_sqT,_x2,LN(_S/_H)/_sqT+(1+_mu)*_sqT,_y1,LN(_H^2/(_S*_K))/_sqT+(1+_mu)*_sqT,_y2,LN(_H/_S)/_sqT+(1+_mu)*_sqT,_Sbd,_S*EXP(-_q*_T),_Kdr,_K*EXP(-_r*_T),_h2m1,(_H/_S)^(2*(_mu+1)),_h2m,(_H/_S)^(2*_mu),_A1,_Kdr*NORM.S.DIST(_sqT-_x1,1)-_Sbd*NORM.S.DIST(-_x1,1),_A2,_Kdr*NORM.S.DIST(_sqT-_x2,1)-_Sbd*NORM.S.DIST(-_x2,1),_A3,_Kdr*_h2m*NORM.S.DIST(_y1-_sqT,1)-_Sbd*_h2m1*NORM.S.DIST(_y1,1),_A4,_Kdr*_h2m*NORM.S.DIST(_y2-_sqT,1)-_Sbd*_h2m1*NORM.S.DIST(_y2,1),_do,IF(_S<=_H,0,_A1-_A2+_A3-_A4),_cf,_Sbd*NORM.S.DIST(-_x1,1)+_Kdr*NORM.S.DIST(_x1-_sqT,1),IF(_S<=_H,_cf,_do+_cf)) | F14: Price_Sm (S -1%)
A15: Gamma | B15: =($E$13-2*$E$12+$E$14)/(dS*$B$3)^2 | C15: ~0 (near 0) | D15: Tree gives near-zero; RR may differ at barrier | E15: =LET(_S,$B$3,_sig,$B$4+dSig,_T,$B$5,_r,$B$6,_K,Cap,_H,Barrier,_q,q,_b,_r-_q,_sqT,_sig*SQRT(_T),_mu,(_b-0.5*_sig^2)/_sig^2,_x1,LN(_S/_K)/_sqT+(1+_mu)*_sqT,_x2,LN(_S/_H)/_sqT+(1+_mu)*_sqT,_y1,LN(_H^2/(_S*_K))/_sqT+(1+_mu)*_sqT,_y2,LN(_H/_S)/_sqT+(1+_mu)*_sqT,_Sbd,_S*EXP(-_q*_T),_Kdr,_K*EXP(-_r*_T),_h2m1,(_H/_S)^(2*(_mu+1)),_h2m,(_H/_S)^(2*_mu),_A1,_Kdr*NORM.S.DIST(_sqT-_x1,1)-_Sbd*NORM.S.DIST(-_x1,1),_A2,_Kdr*NORM.S.DIST(_sqT-_x2,1)-_Sbd*NORM.S.DIST(-_x2,1),_A3,_Kdr*_h2m*NORM.S.DIST(_y1-_sqT,1)-_Sbd*_h2m1*NORM.S.DIST(_y1,1),_A4,_Kdr*_h2m*NORM.S.DIST(_y2-_sqT,1)-_Sbd*_h2m1*NORM.S.DIST(_y2,1),_do,IF(_S<=_H,0,_A1-_A2+_A3-_A4),_cf,_Sbd*NORM.S.DIST(-_x1,1)+_Kdr*NORM.S.DIST(_x1-_sqT,1),IF(_S<=_H,_cf,_do+_cf)) | F15: Price_sigp (sig +2pp)
A16: Vega (per 1% vol) | B16: =($E$15-$E$16)/(2*dSig)/100 | C16: -13.554 | D16: Per 1% absolute change in sigma | E16: =LET(_S,$B$3,_sig,$B$4-dSig,_T,$B$5,_r,$B$6,_K,Cap,_H,Barrier,_q,q,_b,_r-_q,_sqT,_sig*SQRT(_T),_mu,(_b-0.5*_sig^2)/_sig^2,_x1,LN(_S/_K)/_sqT+(1+_mu)*_sqT,_x2,LN(_S/_H)/_sqT+(1+_mu)*_sqT,_y1,LN(_H^2/(_S*_K))/_sqT+(1+_mu)*_sqT,_y2,LN(_H/_S)/_sqT+(1+_mu)*_sqT,_Sbd,_S*EXP(-_q*_T),_Kdr,_K*EXP(-_r*_T),_h2m1,(_H/_S)^(2*(_mu+1)),_h2m,(_H/_S)^(2*_mu),_A1,_Kdr*NORM.S.DIST(_sqT-_x1,1)-_Sbd*NORM.S.DIST(-_x1,1),_A2,_Kdr*NORM.S.DIST(_sqT-_x2,1)-_Sbd*NORM.S.DIST(-_x2,1),_A3,_Kdr*_h2m*NORM.S.DIST(_y1-_sqT,1)-_Sbd*_h2m1*NORM.S.DIST(_y1,1),_A4,_Kdr*_h2m*NORM.S.DIST(_y2-_sqT,1)-_Sbd*_h2m1*NORM.S.DIST(_y2,1),_do,IF(_S<=_H,0,_A1-_A2+_A3-_A4),_cf,_Sbd*NORM.S.DIST(-_x1,1)+_Kdr*NORM.S.DIST(_x1-_sqT,1),IF(_S<=_H,_cf,_do+_cf)) | F16: Price_sigm (sig -2pp)
A17: Theta (per day) | B17: =($E$17-$E$12)/dT/365 | C17: +0.357 | D17: Per 1 calendar day | E17: =LET(_S,$B$3,_sig,$B$4,_T,$B$5-dT,_r,$B$6,_K,Cap,_H,Barrier,_q,q,_b,_r-_q,_sqT,_sig*SQRT(_T),_mu,(_b-0.5*_sig^2)/_sig^2,_x1,LN(_S/_K)/_sqT+(1+_mu)*_sqT,_x2,LN(_S/_H)/_sqT+(1+_mu)*_sqT,_y1,LN(_H^2/(_S*_K))/_sqT+(1+_mu)*_sqT,_y2,LN(_H/_S)/_sqT+(1+_mu)*_sqT,_Sbd,_S*EXP(-_q*_T),_Kdr,_K*EXP(-_r*_T),_h2m1,(_H/_S)^(2*(_mu+1)),_h2m,(_H/_S)^(2*_mu),_A1,_Kdr*NORM.S.DIST(_sqT-_x1,1)-_Sbd*NORM.S.DIST(-_x1,1),_A2,_Kdr*NORM.S.DIST(_sqT-_x2,1)-_Sbd*NORM.S.DIST(-_x2,1),_A3,_Kdr*_h2m*NORM.S.DIST(_y1-_sqT,1)-_Sbd*_h2m1*NORM.S.DIST(_y1,1),_A4,_Kdr*_h2m*NORM.S.DIST(_y2-_sqT,1)-_Sbd*_h2m1*NORM.S.DIST(_y2,1),_do,IF(_S<=_H,0,_A1-_A2+_A3-_A4),_cf,_Sbd*NORM.S.DIST(-_x1,1)+_Kdr*NORM.S.DIST(_x1-_sqT,1),IF(_S<=_H,_cf,_do+_cf)) | F17: Price_Tm (T -1day)
A18: Rho (per 1% r) | B18: =($E$18-$E$19)/(2*dR)/100 | C18: N/A | D18: Bonus Greek, no specific target | E18: =LET(_S,$B$3,_sig,$B$4,_T,$B$5,_r,$B$6+dR,_K,Cap,_H,Barrier,_q,q,_b,_r-_q,_sqT,_sig*SQRT(_T),_mu,(_b-0.5*_sig^2)/_sig^2,_x1,LN(_S/_K)/_sqT+(1+_mu)*_sqT,_x2,LN(_S/_H)/_sqT+(1+_mu)*_sqT,_y1,LN(_H^2/(_S*_K))/_sqT+(1+_mu)*_sqT,_y2,LN(_H/_S)/_sqT+(1+_mu)*_sqT,_Sbd,_S*EXP(-_q*_T),_Kdr,_K*EXP(-_r*_T),_h2m1,(_H/_S)^(2*(_mu+1)),_h2m,(_H/_S)^(2*_mu),_A1,_Kdr*NORM.S.DIST(_sqT-_x1,1)-_Sbd*NORM.S.DIST(-_x1,1),_A2,_Kdr*NORM.S.DIST(_sqT-_x2,1)-_Sbd*NORM.S.DIST(-_x2,1),_A3,_Kdr*_h2m*NORM.S.DIST(_y1-_sqT,1)-_Sbd*_h2m1*NORM.S.DIST(_y1,1),_A4,_Kdr*_h2m*NORM.S.DIST(_y2-_sqT,1)-_Sbd*_h2m1*NORM.S.DIST(_y2,1),_do,IF(_S<=_H,0,_A1-_A2+_A3-_A4),_cf,_Sbd*NORM.S.DIST(-_x1,1)+_Kdr*NORM.S.DIST(_x1-_sqT,1),IF(_S<=_H,_cf,_do+_cf)) | F18: Price_rp (r +1bp)
E19: =LET(_S,$B$3,_sig,$B$4,_T,$B$5,_r,$B$6-dR,_K,Cap,_H,Barrier,_q,q,_b,_r-_q,_sqT,_sig*SQRT(_T),_mu,(_b-0.5*_sig^2)/_sig^2,_x1,LN(_S/_K)/_sqT+(1+_mu)*_sqT,_x2,LN(_S/_H)/_sqT+(1+_mu)*_sqT,_y1,LN(_H^2/(_S*_K))/_sqT+(1+_mu)*_sqT,_y2,LN(_H/_S)/_sqT+(1+_mu)*_sqT,_Sbd,_S*EXP(-_q*_T),_Kdr,_K*EXP(-_r*_T),_h2m1,(_H/_S)^(2*(_mu+1)),_h2m,(_H/_S)^(2*_mu),_A1,_Kdr*NORM.S.DIST(_sqT-_x1,1)-_Sbd*NORM.S.DIST(-_x1,1),_A2,_Kdr*NORM.S.DIST(_sqT-_x2,1)-_Sbd*NORM.S.DIST(-_x2,1),_A3,_Kdr*_h2m*NORM.S.DIST(_y1-_sqT,1)-_Sbd*_h2m1*NORM.S.DIST(_y1,1),_A4,_Kdr*_h2m*NORM.S.DIST(_y2-_sqT,1)-_Sbd*_h2m1*NORM.S.DIST(_y2,1),_do,IF(_S<=_H,0,_A1-_A2+_A3-_A4),_cf,_Sbd*NORM.S.DIST(-_x1,1)+_Kdr*NORM.S.DIST(_x1-_sqT,1),IF(_S<=_H,_cf,_do+_cf)) | F19: Price_rm (r -1bp)
A22: METHODOLOGICAL NOTE: RR closed-form delta at this reference point is approximately 0.532 (this sheet, live formula in B14) versus 0.244901 from the N=200 binomial tree (Python notebook Cell 45). The discrepancy arises because the RR formula treats the barrier as continuously monitored whereas the N=200 tree monitors at 200 discrete steps over 1.79 years. The Python notebook binomial tree is the AUTHORITATIVE engine; RR values here are provided as a cross-check only.
A24: Greeks cross-section (100 S values, RR closed-form -- live formulas)
A25: S (EUR) | B25: Price (EUR) | C25: Delta | D25: Gamma | E25: Vega (per 1%) | F25: Theta (per day)
A26: 577.5 | B26: =LET(_S,A26,_sig,$B$4,_T,$B$5,_r,$B$6,_K,Cap,_H,Barrier,_q,q,_b,_r-_q,_sqT,_sig*SQRT(_T),_mu,(_b-0.5*_sig^2)/_sig^2,_x1,LN(_S/_K)/_sqT+(1+_mu)*_sqT,_x2,LN(_S/_H)/_sqT+(1+_mu)*_sqT,_y1,LN(_H^2/(_S*_K))/_sqT+(1+_mu)*_sqT,_y2,LN(_H/_S)/_sqT+(1+_mu)*_sqT,_Sbd,_S*EXP(-_q*_T),_Kdr,_K*EXP(-_r*_T),_h2m1,(_H/_S)^(2*(_mu+1)),_h2m,(_H/_S)^(2*_mu),_A1,_Kdr*NORM.S.DIST(_sqT-_x1,1)-_Sbd*NORM.S.DIST(-_x1,1),_A2,_Kdr*NORM.S.DIST(_sqT-_x2,1)-_Sbd*NORM.S.DIST(-_x2,1),_A3,_Kdr*_h2m*NORM.S.DIST(_y1-_sqT,1)-_Sbd*_h2m1*NORM.S.DIST(_y1,1),_A4,_Kdr*_h2m*NORM.S.DIST(_y2-_sqT,1)-_Sbd*_h2m1*NORM.S.DIST(_y2,1),_do,IF(_S<=_H,0,_A1-_A2+_A3-_A4),_cf,_Sbd*NORM.S.DIST(-_x1,1)+_Kdr*NORM.S.DIST(_x1-_sqT,1),IF(_S<=_H,_cf,_do+_cf)) | C26: =LET(_S,A26,_sig,$B$4,_T,$B$5,_r,$B$6,_K,Cap,_H,Barrier,_q,q,_ds,dS,_b,_r-_q,_sqT,_sig*SQRT(_T),_mu,(_b-0.5*_sig^2)/_sig^2,_Kdr,_K*EXP(-_r*_T),_SP,_S*(1+_ds),_Sbdp,_SP*EXP(-_q*_T),_x1p,LN(_SP/_K)/_sqT+(1+_mu)*_sqT,_x2p,LN(_SP/_H)/_sqT+(1+_mu)*_sqT,_y1p,LN(_H^2/(_SP*_K))/_sqT+(1+_mu)*_sqT,_y2p,LN(_H/_SP)/_sqT+(1+_mu)*_sqT,_h2m1p,(_H/_SP)^(2*(_mu+1)),_h2mp,(_H/_SP)^(2*_mu),_A1p,_Kdr*NORM.S.DIST(_sqT-_x1p,1)-_Sbdp*NORM.S.DIST(-_x1p,1),_A2p,_Kdr*NORM.S.DIST(_sqT-_x2p,1)-_Sbdp*NORM.S.DIST(-_x2p,1),_A3p,_Kdr*_h2mp*NORM.S.DIST(_y1p-_sqT,1)-_Sbdp*_h2m1p*NORM.S.DIST(_y1p,1),_A4p,_Kdr*_h2mp*NORM.S.DIST(_y2p-_sqT,1)-_Sbdp*_h2m1p*NORM.S.DIST(_y2p,1),_cfp,_Sbdp*NORM.S.DIST(-_x1p,1)+_Kdr*NORM.S.DIST(_x1p-_sqT,1),_pp,IF(_SP<=_H,_cfp,(_A1p-_A2p+_A3p-_A4p)+_cfp),_SM,_S*(1-_ds),_Sbdm,_SM*EXP(-_q*_T),_x1m,LN(_SM/_K)/_sqT+(1+_mu)*_sqT,_x2m,LN(_SM/_H)/_sqT+(1+_mu)*_sqT,_y1m,LN(_H^2/(_SM*_K))/_sqT+(1+_mu)*_sqT,_y2m,LN(_H/_SM)/_sqT+(1+_mu)*_sqT,_h2m1m,(_H/_SM)^(2*(_mu+1)),_h2mm,(_H/_SM)^(2*_mu),_A1m,_Kdr*NORM.S.DIST(_sqT-_x1m,1)-_Sbdm*NORM.S.DIST(-_x1m,1),_A2m,_Kdr*NORM.S.DIST(_sqT-_x2m,1)-_Sbdm*NORM.S.DIST(-_x2m,1),_A3m,_Kdr*_h2mm*NORM.S.DIST(_y1m-_sqT,1)-_Sbdm*_h2m1m*NORM.S.DIST(_y1m,1),_A4m,_Kdr*_h2mm*NORM.S.DIST(_y2m-_sqT,1)-_Sbdm*_h2m1m*NORM.S.DIST(_y2m,1),_cfm,_Sbdm*NORM.S.DIST(-_x1m,1)+_Kdr*NORM.S.DIST(_x1m-_sqT,1),_pm,IF(_SM<=_H,_cfm,(_A1m-_A2m+_A3m-_A4m)+_cfm),(_pp-_pm)/(2*_ds*_S)) | D26: -0.000249 | E26: -0.6609 | F26: 0.0325
A27: 603.99 | B27: =LET(_S,A27,_sig,$B$4,_T,$B$5,_r,$B$6,_K,Cap,_H,Barrier,_q,q,_b,_r-_q,_sqT,_sig*SQRT(_T),_mu,(_b-0.5*_sig^2)/_sig^2,_x1,LN(_S/_K)/_sqT+(1+_mu)*_sqT,_x2,LN(_S/_H)/_sqT+(1+_mu)*_sqT,_y1,LN(_H^2/(_S*_K))/_sqT+(1+_mu)*_sqT,_y2,LN(_H/_S)/_sqT+(1+_mu)*_sqT,_Sbd,_S*EXP(-_q*_T),_Kdr,_K*EXP(-_r*_T),_h2m1,(_H/_S)^(2*(_mu+1)),_h2m,(_H/_S)^(2*_mu),_A1,_Kdr*NORM.S.DIST(_sqT-_x1,1)-_Sbd*NORM.S.DIST(-_x1,1),_A2,_Kdr*NORM.S.DIST(_sqT-_x2,1)-_Sbd*NORM.S.DIST(-_x2,1),_A3,_Kdr*_h2m*NORM.S.DIST(_y1-_sqT,1)-_Sbd*_h2m1*NORM.S.DIST(_y1,1),_A4,_Kdr*_h2m*NORM.S.DIST(_y2-_sqT,1)-_Sbd*_h2m1*NORM.S.DIST(_y2,1),_do,IF(_S<=_H,0,_A1-_A2+_A3-_A4),_cf,_Sbd*NORM.S.DIST(-_x1,1)+_Kdr*NORM.S.DIST(_x1-_sqT,1),IF(_S<=_H,_cf,_do+_cf)) | C27: =LET(_S,A27,_sig,$B$4,_T,$B$5,_r,$B$6,_K,Cap,_H,Barrier,_q,q,_ds,dS,_b,_r-_q,_sqT,_sig*SQRT(_T),_mu,(_b-0.5*_sig^2)/_sig^2,_Kdr,_K*EXP(-_r*_T),_SP,_S*(1+_ds),_Sbdp,_SP*EXP(-_q*_T),_x1p,LN(_SP/_K)/_sqT+(1+_mu)*_sqT,_x2p,LN(_SP/_H)/_sqT+(1+_mu)*_sqT,_y1p,LN(_H^2/(_SP*_K))/_sqT+(1+_mu)*_sqT,_y2p,LN(_H/_SP)/_sqT+(1+_mu)*_sqT,_h2m1p,(_H/_SP)^(2*(_mu+1)),_h2mp,(_H/_SP)^(2*_mu),_A1p,_Kdr*NORM.S.DIST(_sqT-_x1p,1)-_Sbdp*NORM.S.DIST(-_x1p,1),_A2p,_Kdr*NORM.S.DIST(_sqT-_x2p,1)-_Sbdp*NORM.S.DIST(-_x2p,1),_A3p,_Kdr*_h2mp*NORM.S.DIST(_y1p-_sqT,1)-_Sbdp*_h2m1p*NORM.S.DIST(_y1p,1),_A4p,_Kdr*_h2mp*NORM.S.DIST(_y2p-_sqT,1)-_Sbdp*_h2m1p*NORM.S.DIST(_y2p,1),_cfp,_Sbdp*NORM.S.DIST(-_x1p,1)+_Kdr*NORM.S.DIST(_x1p-_sqT,1),_pp,IF(_SP<=_H,_cfp,(_A1p-_A2p+_A3p-_A4p)+_cfp),_SM,_S*(1-_ds),_Sbdm,_SM*EXP(-_q*_T),_x1m,LN(_SM/_K)/_sqT+(1+_mu)*_sqT,_x2m,LN(_SM/_H)/_sqT+(1+_mu)*_sqT,_y1m,LN(_H^2/(_SM*_K))/_sqT+(1+_mu)*_sqT,_y2m,LN(_H/_SM)/_sqT+(1+_mu)*_sqT,_h2m1m,(_H/_SM)^(2*(_mu+1)),_h2mm,(_H/_SM)^(2*_mu),_A1m,_Kdr*NORM.S.DIST(_sqT-_x1m,1)-_Sbdm*NORM.S.DIST(-_x1m,1),_A2m,_Kdr*NORM.S.DIST(_sqT-_x2m,1)-_Sbdm*NORM.S.DIST(-_x2m,1),_A3m,_Kdr*_h2mm*NORM.S.DIST(_y1m-_sqT,1)-_Sbdm*_h2m1m*NORM.S.DIST(_y1m,1),_A4m,_Kdr*_h2mm*NORM.S.DIST(_y2m-_sqT,1)-_Sbdm*_h2m1m*NORM.S.DIST(_y2m,1),_cfm,_Sbdm*NORM.S.DIST(-_x1m,1)+_Kdr*NORM.S.DIST(_x1m-_sqT,1),_pm,IF(_SM<=_H,_cfm,(_A1m-_A2m+_A3m-_A4m)+_cfm),(_pp-_pm)/(2*_ds*_S)) | D27: -0.00027 | E27: -0.7859 | F27: 0.0373
A28: 630.48 | B28: =LET(_S,A28,_sig,$B$4,_T,$B$5,_r,$B$6,_K,Cap,_H,Barrier,_q,q,_b,_r-_q,_sqT,_sig*SQRT(_T),_mu,(_b-0.5*_sig^2)/_sig^2,_x1,LN(_S/_K)/_sqT+(1+_mu)*_sqT,_x2,LN(_S/_H)/_sqT+(1+_mu)*_sqT,_y1,LN(_H^2/(_S*_K))/_sqT+(1+_mu)*_sqT,_y2,LN(_H/_S)/_sqT+(1+_mu)*_sqT,_Sbd,_S*EXP(-_q*_T),_Kdr,_K*EXP(-_r*_T),_h2m1,(_H/_S)^(2*(_mu+1)),_h2m,(_H/_S)^(2*_mu),_A1,_Kdr*NORM.S.DIST(_sqT-_x1,1)-_Sbd*NORM.S.DIST(-_x1,1),_A2,_Kdr*NORM.S.DIST(_sqT-_x2,1)-_Sbd*NORM.S.DIST(-_x2,1),_A3,_Kdr*_h2m*NORM.S.DIST(_y1-_sqT,1)-_Sbd*_h2m1*NORM.S.DIST(_y1,1),_A4,_Kdr*_h2m*NORM.S.DIST(_y2-_sqT,1)-_Sbd*_h2m1*NORM.S.DIST(_y2,1),_do,IF(_S<=_H,0,_A1-_A2+_A3-_A4),_cf,_Sbd*NORM.S.DIST(-_x1,1)+_Kdr*NORM.S.DIST(_x1-_sqT,1),IF(_S<=_H,_cf,_do+_cf)) | C28: =LET(_S,A28,_sig,$B$4,_T,$B$5,_r,$B$6,_K,Cap,_H,Barrier,_q,q,_ds,dS,_b,_r-_q,_sqT,_sig*SQRT(_T),_mu,(_b-0.5*_sig^2)/_sig^2,_Kdr,_K*EXP(-_r*_T),_SP,_S*(1+_ds),_Sbdp,_SP*EXP(-_q*_T),_x1p,LN(_SP/_K)/_sqT+(1+_mu)*_sqT,_x2p,LN(_SP/_H)/_sqT+(1+_mu)*_sqT,_y1p,LN(_H^2/(_SP*_K))/_sqT+(1+_mu)*_sqT,_y2p,LN(_H/_SP)/_sqT+(1+_mu)*_sqT,_h2m1p,(_H/_SP)^(2*(_mu+1)),_h2mp,(_H/_SP)^(2*_mu),_A1p,_Kdr*NORM.S.DIST(_sqT-_x1p,1)-_Sbdp*NORM.S.DIST(-_x1p,1),_A2p,_Kdr*NORM.S.DIST(_sqT-_x2p,1)-_Sbdp*NORM.S.DIST(-_x2p,1),_A3p,_Kdr*_h2mp*NORM.S.DIST(_y1p-_sqT,1)-_Sbdp*_h2m1p*NORM.S.DIST(_y1p,1),_A4p,_Kdr*_h2mp*NORM.S.DIST(_y2p-_sqT,1)-_Sbdp*_h2m1p*NORM.S.DIST(_y2p,1),_cfp,_Sbdp*NORM.S.DIST(-_x1p,1)+_Kdr*NORM.S.DIST(_x1p-_sqT,1),_pp,IF(_SP<=_H,_cfp,(_A1p-_A2p+_A3p-_A4p)+_cfp),_SM,_S*(1-_ds),_Sbdm,_SM*EXP(-_q*_T),_x1m,LN(_SM/_K)/_sqT+(1+_mu)*_sqT,_x2m,LN(_SM/_H)/_sqT+(1+_mu)*_sqT,_y1m,LN(_H^2/(_SM*_K))/_sqT+(1+_mu)*_sqT,_y2m,LN(_H/_SM)/_sqT+(1+_mu)*_sqT,_h2m1m,(_H/_SM)^(2*(_mu+1)),_h2mm,(_H/_SM)^(2*_mu),_A1m,_Kdr*NORM.S.DIST(_sqT-_x1m,1)-_Sbdm*NORM.S.DIST(-_x1m,1),_A2m,_Kdr*NORM.S.DIST(_sqT-_x2m,1)-_Sbdm*NORM.S.DIST(-_x2m,1),_A3m,_Kdr*_h2mm*NORM.S.DIST(_y1m-_sqT,1)-_Sbdm*_h2m1m*NORM.S.DIST(_y1m,1),_A4m,_Kdr*_h2mm*NORM.S.DIST(_y2m-_sqT,1)-_Sbdm*_h2m1m*NORM.S.DIST(_y2m,1),_cfm,_Sbdm*NORM.S.DIST(-_x1m,1)+_Kdr*NORM.S.DIST(_x1m-_sqT,1),_pm,IF(_SM<=_H,_cfm,(_A1m-_A2m+_A3m-_A4m)+_cfm),(_pp-_pm)/(2*_ds*_S)) | D28: -0.000292 | E28: -0.9228 | F28: 0.0426
A29: 656.97 | B29: =LET(_S,A29,_sig,$B$4,_T,$B$5,_r,$B$6,_K,Cap,_H,Barrier,_q,q,_b,_r-_q,_sqT,_sig*SQRT(_T),_mu,(_b-0.5*_sig^2)/_sig^2,_x1,LN(_S/_K)/_sqT+(1+_mu)*_sqT,_x2,LN(_S/_H)/_sqT+(1+_mu)*_sqT,_y1,LN(_H^2/(_S*_K))/_sqT+(1+_mu)*_sqT,_y2,LN(_H/_S)/_sqT+(1+_mu)*_sqT,_Sbd,_S*EXP(-_q*_T),_Kdr,_K*EXP(-_r*_T),_h2m1,(_H/_S)^(2*(_mu+1)),_h2m,(_H/_S)^(2*_mu),_A1,_Kdr*NORM.S.DIST(_sqT-_x1,1)-_Sbd*NORM.S.DIST(-_x1,1),_A2,_Kdr*NORM.S.DIST(_sqT-_x2,1)-_Sbd*NORM.S.DIST(-_x2,1),_A3,_Kdr*_h2m*NORM.S.DIST(_y1-_sqT,1)-_Sbd*_h2m1*NORM.S.DIST(_y1,1),_A4,_Kdr*_h2m*NORM.S.DIST(_y2-_sqT,1)-_Sbd*_h2m1*NORM.S.DIST(_y2,1),_do,IF(_S<=_H,0,_A1-_A2+_A3-_A4),_cf,_Sbd*NORM.S.DIST(-_x1,1)+_Kdr*NORM.S.DIST(_x1-_sqT,1),IF(_S<=_H,_cf,_do+_cf)) | C29: =LET(_S,A29,_sig,$B$4,_T,$B$5,_r,$B$6,_K,Cap,_H,Barrier,_q,q,_ds,dS,_b,_r-_q,_sqT,_sig*SQRT(_T),_mu,(_b-0.5*_sig^2)/_sig^2,_Kdr,_K*EXP(-_r*_T),_SP,_S*(1+_ds),_Sbdp,_SP*EXP(-_q*_T),_x1p,LN(_SP/_K)/_sqT+(1+_mu)*_sqT,_x2p,LN(_SP/_H)/_sqT+(1+_mu)*_sqT,_y1p,LN(_H^2/(_SP*_K))/_sqT+(1+_mu)*_sqT,_y2p,LN(_H/_SP)/_sqT+(1+_mu)*_sqT,_h2m1p,(_H/_SP)^(2*(_mu+1)),_h2mp,(_H/_SP)^(2*_mu),_A1p,_Kdr*NORM.S.DIST(_sqT-_x1p,1)-_Sbdp*NORM.S.DIST(-_x1p,1),_A2p,_Kdr*NORM.S.DIST(_sqT-_x2p,1)-_Sbdp*NORM.S.DIST(-_x2p,1),_A3p,_Kdr*_h2mp*NORM.S.DIST(_y1p-_sqT,1)-_Sbdp*_h2m1p*NORM.S.DIST(_y1p,1),_A4p,_Kdr*_h2mp*NORM.S.DIST(_y2p-_sqT,1)-_Sbdp*_h2m1p*NORM.S.DIST(_y2p,1),_cfp,_Sbdp*NORM.S.DIST(-_x1p,1)+_Kdr*NORM.S.DIST(_x1p-_sqT,1),_pp,IF(_SP<=_H,_cfp,(_A1p-_A2p+_A3p-_A4p)+_cfp),_SM,_S*(1-_ds),_Sbdm,_SM*EXP(-_q*_T),_x1m,LN(_SM/_K)/_sqT+(1+_mu)*_sqT,_x2m,LN(_SM/_H)/_sqT+(1+_mu)*_sqT,_y1m,LN(_H^2/(_SM*_K))/_sqT+(1+_mu)*_sqT,_y2m,LN(_H/_SM)/_sqT+(1+_mu)*_sqT,_h2m1m,(_H/_SM)^(2*(_mu+1)),_h2mm,(_H/_SM)^(2*_mu),_A1m,_Kdr*NORM.S.DIST(_sqT-_x1m,1)-_Sbdm*NORM.S.DIST(-_x1m,1),_A2m,_Kdr*NORM.S.DIST(_sqT-_x2m,1)-_Sbdm*NORM.S.DIST(-_x2m,1),_A3m,_Kdr*_h2mm*NORM.S.DIST(_y1m-_sqT,1)-_Sbdm*_h2m1m*NORM.S.DIST(_y1m,1),_A4m,_Kdr*_h2mm*NORM.S.DIST(_y2m-_sqT,1)-_Sbdm*_h2m1m*NORM.S.DIST(_y2m,1),_cfm,_Sbdm*NORM.S.DIST(-_x1m,1)+_Kdr*NORM.S.DIST(_x1m-_sqT,1),_pm,IF(_SM<=_H,_cfm,(_A1m-_A2m+_A3m-_A4m)+_cfm),(_pp-_pm)/(2*_ds*_S)) | D29: -0.000312 | E29: -1.0712 | F29: 0.0482
A30: 683.46 | B30: =LET(_S,A30,_sig,$B$4,_T,$B$5,_r,$B$6,_K,Cap,_H,Barrier,_q,q,_b,_r-_q,_sqT,_sig*SQRT(_T),_mu,(_b-0.5*_sig^2)/_sig^2,_x1,LN(_S/_K)/_sqT+(1+_mu)*_sqT,_x2,LN(_S/_H)/_sqT+(1+_mu)*_sqT,_y1,LN(_H^2/(_S*_K))/_sqT+(1+_mu)*_sqT,_y2,LN(_H/_S)/_sqT+(1+_mu)*_sqT,_Sbd,_S*EXP(-_q*_T),_Kdr,_K*EXP(-_r*_T),_h2m1,(_H/_S)^(2*(_mu+1)),_h2m,(_H/_S)^(2*_mu),_A1,_Kdr*NORM.S.DIST(_sqT-_x1,1)-_Sbd*NORM.S.DIST(-_x1,1),_A2,_Kdr*NORM.S.DIST(_sqT-_x2,1)-_Sbd*NORM.S.DIST(-_x2,1),_A3,_Kdr*_h2m*NORM.S.DIST(_y1-_sqT,1)-_Sbd*_h2m1*NORM.S.DIST(_y1,1),_A4,_Kdr*_h2m*NORM.S.DIST(_y2-_sqT,1)-_Sbd*_h2m1*NORM.S.DIST(_y2,1),_do,IF(_S<=_H,0,_A1-_A2+_A3-_A4),_cf,_Sbd*NORM.S.DIST(-_x1,1)+_Kdr*NORM.S.DIST(_x1-_sqT,1),IF(_S<=_H,_cf,_do+_cf)) | C30: =LET(_S,A30,_sig,$B$4,_T,$B$5,_r,$B$6,_K,Cap,_H,Barrier,_q,q,_ds,dS,_b,_r-_q,_sqT,_sig*SQRT(_T),_mu,(_b-0.5*_sig^2)/_sig^2,_Kdr,_K*EXP(-_r*_T),_SP,_S*(1+_ds),_Sbdp,_SP*EXP(-_q*_T),_x1p,LN(_SP/_K)/_sqT+(1+_mu)*_sqT,_x2p,LN(_SP/_H)/_sqT+(1+_mu)*_sqT,_y1p,LN(_H^2/(_SP*_K))/_sqT+(1+_mu)*_sqT,_y2p,LN(_H/_SP)/_sqT+(1+_mu)*_sqT,_h2m1p,(_H/_SP)^(2*(_mu+1)),_h2mp,(_H/_SP)^(2*_mu),_A1p,_Kdr*NORM.S.DIST(_sqT-_x1p,1)-_Sbdp*NORM.S.DIST(-_x1p,1),_A2p,_Kdr*NORM.S.DIST(_sqT-_x2p,1)-_Sbdp*NORM.S.DIST(-_x2p,1),_A3p,_Kdr*_h2mp*NORM.S.DIST(_y1p-_sqT,1)-_Sbdp*_h2m1p*NORM.S.DIST(_y1p,1),_A4p,_Kdr*_h2mp*NORM.S.DIST(_y2p-_sqT,1)-_Sbdp*_h2m1p*NORM.S.DIST(_y2p,1),_cfp,_Sbdp*NORM.S.DIST(-_x1p,1)+_Kdr*NORM.S.DIST(_x1p-_sqT,1),_pp,IF(_SP<=_H,_cfp,(_A1p-_A2p+_A3p-_A4p)+_cfp),_SM,_S*(1-_ds),_Sbdm,_SM*EXP(-_q*_T),_x1m,LN(_SM/_K)/_sqT+(1+_mu)*_sqT,_x2m,LN(_SM/_H)/_sqT+(1+_mu)*_sqT,_y1m,LN(_H^2/(_SM*_K))/_sqT+(1+_mu)*_sqT,_y2m,LN(_H/_SM)/_sqT+(1+_mu)*_sqT,_h2m1m,(_H/_SM)^(2*(_mu+1)),_h2mm,(_H/_SM)^(2*_mu),_A1m,_Kdr*NORM.S.DIST(_sqT-_x1m,1)-_Sbdm*NORM.S.DIST(-_x1m,1),_A2m,_Kdr*NORM.S.DIST(_sqT-_x2m,1)-_Sbdm*NORM.S.DIST(-_x2m,1),_A3m,_Kdr*_h2mm*NORM.S.DIST(_y1m-_sqT,1)-_Sbdm*_h2m1m*NORM.S.DIST(_y1m,1),_A4m,_Kdr*_h2mm*NORM.S.DIST(_y2m-_sqT,1)-_Sbdm*_h2m1m*NORM.S.DIST(_y2m,1),_cfm,_Sbdm*NORM.S.DIST(-_x1m,1)+_Kdr*NORM.S.DIST(_x1m-_sqT,1),_pm,IF(_SM<=_H,_cfm,(_A1m-_A2m+_A3m-_A4m)+_cfm),(_pp-_pm)/(2*_ds*_S)) | D30: -0.000331 | E30: -1.2307 | F30: 0.0543
A31: 709.95 | B31: =LET(_S,A31,_sig,$B$4,_T,$B$5,_r,$B$6,_K,Cap,_H,Barrier,_q,q,_b,_r-_q,_sqT,_sig*SQRT(_T),_mu,(_b-0.5*_sig^2)/_sig^2,_x1,LN(_S/_K)/_sqT+(1+_mu)*_sqT,_x2,LN(_S/_H)/_sqT+(1+_mu)*_sqT,_y1,LN(_H^2/(_S*_K))/_sqT+(1+_mu)*_sqT,_y2,LN(_H/_S)/_sqT+(1+_mu)*_sqT,_Sbd,_S*EXP(-_q*_T),_Kdr,_K*EXP(-_r*_T),_h2m1,(_H/_S)^(2*(_mu+1)),_h2m,(_H/_S)^(2*_mu),_A1,_Kdr*NORM.S.DIST(_sqT-_x1,1)-_Sbd*NORM.S.DIST(-_x1,1),_A2,_Kdr*NORM.S.DIST(_sqT-_x2,1)-_Sbd*NORM.S.DIST(-_x2,1),_A3,_Kdr*_h2m*NORM.S.DIST(_y1-_sqT,1)-_Sbd*_h2m1*NORM.S.DIST(_y1,1),_A4,_Kdr*_h2m*NORM.S.DIST(_y2-_sqT,1)-_Sbd*_h2m1*NORM.S.DIST(_y2,1),_do,IF(_S<=_H,0,_A1-_A2+_A3-_A4),_cf,_Sbd*NORM.S.DIST(-_x1,1)+_Kdr*NORM.S.DIST(_x1-_sqT,1),IF(_S<=_H,_cf,_do+_cf)) | C31: =LET(_S,A31,_sig,$B$4,_T,$B$5,_r,$B$6,_K,Cap,_H,Barrier,_q,q,_ds,dS,_b,_r-_q,_sqT,_sig*SQRT(_T),_mu,(_b-0.5*_sig^2)/_sig^2,_Kdr,_K*EXP(-_r*_T),_SP,_S*(1+_ds),_Sbdp,_SP*EXP(-_q*_T),_x1p,LN(_SP/_K)/_sqT+(1+_mu)*_sqT,_x2p,LN(_SP/_H)/_sqT+(1+_mu)*_sqT,_y1p,LN(_H^2/(_SP*_K))/_sqT+(1+_mu)*_sqT,_y2p,LN(_H/_SP)/_sqT+(1+_mu)*_sqT,_h2m1p,(_H/_SP)^(2*(_mu+1)),_h2mp,(_H/_SP)^(2*_mu),_A1p,_Kdr*NORM.S.DIST(_sqT-_x1p,1)-_Sbdp*NORM.S.DIST(-_x1p,1),_A2p,_Kdr*NORM.S.DIST(_sqT-_x2p,1)-_Sbdp*NORM.S.DIST(-_x2p,1),_A3p,_Kdr*_h2mp*NORM.S.DIST(_y1p-_sqT,1)-_Sbdp*_h2m1p*NORM.S.DIST(_y1p,1),_A4p,_Kdr*_h2mp*NORM.S.DIST(_y2p-_sqT,1)-_Sbdp*_h2m1p*NORM.S.DIST(_y2p,1),_cfp,_Sbdp*NORM.S.DIST(-_x1p,1)+_Kdr*NORM.S.DIST(_x1p-_sqT,1),_pp,IF(_SP<=_H,_cfp,(_A1p-_A2p+_A3p-_A4p)+_cfp),_SM,_S*(1-_ds),_Sbdm,_SM*EXP(-_q*_T),_x1m,LN(_SM/_K)/_sqT+(1+_mu)*_sqT,_x2m,LN(_SM/_H)/_sqT+(1+_mu)*_sqT,_y1m,LN(_H^2/(_SM*_K))/_sqT+(1+_mu)*_sqT,_y2m,LN(_H/_SM)/_sqT+(1+_mu)*_sqT,_h2m1m,(_H/_SM)^(2*(_mu+1)),_h2mm,(_H/_SM)^(2*_mu),_A1m,_Kdr*NORM.S.DIST(_sqT-_x1m,1)-_Sbdm*NORM.S.DIST(-_x1m,1),_A2m,_Kdr*NORM.S.DIST(_sqT-_x2m,1)-_Sbdm*NORM.S.DIST(-_x2m,1),_A3m,_Kdr*_h2mm*NORM.S.DIST(_y1m-_sqT,1)-_Sbdm*_h2m1m*NORM.S.DIST(_y1m,1),_A4m,_Kdr*_h2mm*NORM.S.DIST(_y2m-_sqT,1)-_Sbdm*_h2m1m*NORM.S.DIST(_y2m,1),_cfm,_Sbdm*NORM.S.DIST(-_x1m,1)+_Kdr*NORM.S.DIST(_x1m-_sqT,1),_pm,IF(_SM<=_H,_cfm,(_A1m-_A2m+_A3m-_A4m)+_cfm),(_pp-_pm)/(2*_ds*_S)) | D31: -0.000349 | E31: -1.4007 | F31: 0.0608
A32: 736.44 | B32: =LET(_S,A32,_sig,$B$4,_T,$B$5,_r,$B$6,_K,Cap,_H,Barrier,_q,q,_b,_r-_q,_sqT,_sig*SQRT(_T),_mu,(_b-0.5*_sig^2)/_sig^2,_x1,LN(_S/_K)/_sqT+(1+_mu)*_sqT,_x2,LN(_S/_H)/_sqT+(1+_mu)*_sqT,_y1,LN(_H^2/(_S*_K))/_sqT+(1+_mu)*_sqT,_y2,LN(_H/_S)/_sqT+(1+_mu)*_sqT,_Sbd,_S*EXP(-_q*_T),_Kdr,_K*EXP(-_r*_T),_h2m1,(_H/_S)^(2*(_mu+1)),_h2m,(_H/_S)^(2*_mu),_A1,_Kdr*NORM.S.DIST(_sqT-_x1,1)-_Sbd*NORM.S.DIST(-_x1,1),_A2,_Kdr*NORM.S.DIST(_sqT-_x2,1)-_Sbd*NORM.S.DIST(-_x2,1),_A3,_Kdr*_h2m*NORM.S.DIST(_y1-_sqT,1)-_Sbd*_h2m1*NORM.S.DIST(_y1,1),_A4,_Kdr*_h2m*NORM.S.DIST(_y2-_sqT,1)-_Sbd*_h2m1*NORM.S.DIST(_y2,1),_do,IF(_S<=_H,0,_A1-_A2+_A3-_A4),_cf,_Sbd*NORM.S.DIST(-_x1,1)+_Kdr*NORM.S.DIST(_x1-_sqT,1),IF(_S<=_H,_cf,_do+_cf)) | C32: =LET(_S,A32,_sig,$B$4,_T,$B$5,_r,$B$6,_K,Cap,_H,Barrier,_q,q,_ds,dS,_b,_r-_q,_sqT,_sig*SQRT(_T),_mu,(_b-0.5*_sig^2)/_sig^2,_Kdr,_K*EXP(-_r*_T),_SP,_S*(1+_ds),_Sbdp,_SP*EXP(-_q*_T),_x1p,LN(_SP/_K)/_sqT+(1+_mu)*_sqT,_x2p,LN(_SP/_H)/_sqT+(1+_mu)*_sqT,_y1p,LN(_H^2/(_SP*_K))/_sqT+(1+_mu)*_sqT,_y2p,LN(_H/_SP)/_sqT+(1+_mu)*_sqT,_h2m1p,(_H/_SP)^(2*(_mu+1)),_h2mp,(_H/_SP)^(2*_mu),_A1p,_Kdr*NORM.S.DIST(_sqT-_x1p,1)-_Sbdp*NORM.S.DIST(-_x1p,1),_A2p,_Kdr*NORM.S.DIST(_sqT-_x2p,1)-_Sbdp*NORM.S.DIST(-_x2p,1),_A3p,_Kdr*_h2mp*NORM.S.DIST(_y1p-_sqT,1)-_Sbdp*_h2m1p*NORM.S.DIST(_y1p,1),_A4p,_Kdr*_h2mp*NORM.S.DIST(_y2p-_sqT,1)-_Sbdp*_h2m1p*NORM.S.DIST(_y2p,1),_cfp,_Sbdp*NORM.S.DIST(-_x1p,1)+_Kdr*NORM.S.DIST(_x1p-_sqT,1),_pp,IF(_SP<=_H,_cfp,(_A1p-_A2p+_A3p-_A4p)+_cfp),_SM,_S*(1-_ds),_Sbdm,_SM*EXP(-_q*_T),_x1m,LN(_SM/_K)/_sqT+(1+_mu)*_sqT,_x2m,LN(_SM/_H)/_sqT+(1+_mu)*_sqT,_y1m,LN(_H^2/(_SM*_K))/_sqT+(1+_mu)*_sqT,_y2m,LN(_H/_SM)/_sqT+(1+_mu)*_sqT,_h2m1m,(_H/_SM)^(2*(_mu+1)),_h2mm,(_H/_SM)^(2*_mu),_A1m,_Kdr*NORM.S.DIST(_sqT-_x1m,1)-_Sbdm*NORM.S.DIST(-_x1m,1),_A2m,_Kdr*NORM.S.DIST(_sqT-_x2m,1)-_Sbdm*NORM.S.DIST(-_x2m,1),_A3m,_Kdr*_h2mm*NORM.S.DIST(_y1m-_sqT,1)-_Sbdm*_h2m1m*NORM.S.DIST(_y1m,1),_A4m,_Kdr*_h2mm*NORM.S.DIST(_y2m-_sqT,1)-_Sbdm*_h2m1m*NORM.S.DIST(_y2m,1),_cfm,_Sbdm*NORM.S.DIST(-_x1m,1)+_Kdr*NORM.S.DIST(_x1m-_sqT,1),_pm,IF(_SM<=_H,_cfm,(_A1m-_A2m+_A3m-_A4m)+_cfm),(_pp-_pm)/(2*_ds*_S)) | D32: -0.000366 | E32: -1.5806 | F32: 0.0676
A33: 762.93 | B33: =LET(_S,A33,_sig,$B$4,_T,$B$5,_r,$B$6,_K,Cap,_H,Barrier,_q,q,_b,_r-_q,_sqT,_sig*SQRT(_T),_mu,(_b-0.5*_sig^2)/_sig^2,_x1,LN(_S/_K)/_sqT+(1+_mu)*_sqT,_x2,LN(_S/_H)/_sqT+(1+_mu)*_sqT,_y1,LN(_H^2/(_S*_K))/_sqT+(1+_mu)*_sqT,_y2,LN(_H/_S)/_sqT+(1+_mu)*_sqT,_Sbd,_S*EXP(-_q*_T),_Kdr,_K*EXP(-_r*_T),_h2m1,(_H/_S)^(2*(_mu+1)),_h2m,(_H/_S)^(2*_mu),_A1,_Kdr*NORM.S.DIST(_sqT-_x1,1)-_Sbd*NORM.S.DIST(-_x1,1),_A2,_Kdr*NORM.S.DIST(_sqT-_x2,1)-_Sbd*NORM.S.DIST(-_x2,1),_A3,_Kdr*_h2m*NORM.S.DIST(_y1-_sqT,1)-_Sbd*_h2m1*NORM.S.DIST(_y1,1),_A4,_Kdr*_h2m*NORM.S.DIST(_y2-_sqT,1)-_Sbd*_h2m1*NORM.S.DIST(_y2,1),_do,IF(_S<=_H,0,_A1-_A2+_A3-_A4),_cf,_Sbd*NORM.S.DIST(-_x1,1)+_Kdr*NORM.S.DIST(_x1-_sqT,1),IF(_S<=_H,_cf,_do+_cf)) | C33: =LET(_S,A33,_sig,$B$4,_T,$B$5,_r,$B$6,_K,Cap,_H,Barrier,_q,q,_ds,dS,_b,_r-_q,_sqT,_sig*SQRT(_T),_mu,(_b-0.5*_sig^2)/_sig^2,_Kdr,_K*EXP(-_r*_T),_SP,_S*(1+_ds),_Sbdp,_SP*EXP(-_q*_T),_x1p,LN(_SP/_K)/_sqT+(1+_mu)*_sqT,_x2p,LN(_SP/_H)/_sqT+(1+_mu)*_sqT,_y1p,LN(_H^2/(_SP*_K))/_sqT+(1+_mu)*_sqT,_y2p,LN(_H/_SP)/_sqT+(1+_mu)*_sqT,_h2m1p,(_H/_SP)^(2*(_mu+1)),_h2mp,(_H/_SP)^(2*_mu),_A1p,_Kdr*NORM.S.DIST(_sqT-_x1p,1)-_Sbdp*NORM.S.DIST(-_x1p,1),_A2p,_Kdr*NORM.S.DIST(_sqT-_x2p,1)-_Sbdp*NORM.S.DIST(-_x2p,1),_A3p,_Kdr*_h2mp*NORM.S.DIST(_y1p-_sqT,1)-_Sbdp*_h2m1p*NORM.S.DIST(_y1p,1),_A4p,_Kdr*_h2mp*NORM.S.DIST(_y2p-_sqT,1)-_Sbdp*_h2m1p*NORM.S.DIST(_y2p,1),_cfp,_Sbdp*NORM.S.DIST(-_x1p,1)+_Kdr*NORM.S.DIST(_x1p-_sqT,1),_pp,IF(_SP<=_H,_cfp,(_A1p-_A2p+_A3p-_A4p)+_cfp),_SM,_S*(1-_ds),_Sbdm,_SM*EXP(-_q*_T),_x1m,LN(_SM/_K)/_sqT+(1+_mu)*_sqT,_x2m,LN(_SM/_H)/_sqT+(1+_mu)*_sqT,_y1m,LN(_H^2/(_SM*_K))/_sqT+(1+_mu)*_sqT,_y2m,LN(_H/_SM)/_sqT+(1+_mu)*_sqT,_h2m1m,(_H/_SM)^(2*(_mu+1)),_h2mm,(_H/_SM)^(2*_mu),_A1m,_Kdr*NORM.S.DIST(_sqT-_x1m,1)-_Sbdm*NORM.S.DIST(-_x1m,1),_A2m,_Kdr*NORM.S.DIST(_sqT-_x2m,1)-_Sbdm*NORM.S.DIST(-_x2m,1),_A3m,_Kdr*_h2mm*NORM.S.DIST(_y1m-_sqT,1)-_Sbdm*_h2m1m*NORM.S.DIST(_y1m,1),_A4m,_Kdr*_h2mm*NORM.S.DIST(_y2m-_sqT,1)-_Sbdm*_h2m1m*NORM.S.DIST(_y2m,1),_cfm,_Sbdm*NORM.S.DIST(-_x1m,1)+_Kdr*NORM.S.DIST(_x1m-_sqT,1),_pm,IF(_SM<=_H,_cfm,(_A1m-_A2m+_A3m-_A4m)+_cfm),(_pp-_pm)/(2*_ds*_S)) | D33: -0.000382 | E33: -1.7698 | F33: 0.0747
A34: 789.42 | B34: =LET(_S,A34,_sig,$B$4,_T,$B$5,_r,$B$6,_K,Cap,_H,Barrier,_q,q,_b,_r-_q,_sqT,_sig*SQRT(_T),_mu,(_b-0.5*_sig^2)/_sig^2,_x1,LN(_S/_K)/_sqT+(1+_mu)*_sqT,_x2,LN(_S/_H)/_sqT+(1+_mu)*_sqT,_y1,LN(_H^2/(_S*_K))/_sqT+(1+_mu)*_sqT,_y2,LN(_H/_S)/_sqT+(1+_mu)*_sqT,_Sbd,_S*EXP(-_q*_T),_Kdr,_K*EXP(-_r*_T),_h2m1,(_H/_S)^(2*(_mu+1)),_h2m,(_H/_S)^(2*_mu),_A1,_Kdr*NORM.S.DIST(_sqT-_x1,1)-_Sbd*NORM.S.DIST(-_x1,1),_A2,_Kdr*NORM.S.DIST(_sqT-_x2,1)-_Sbd*NORM.S.DIST(-_x2,1),_A3,_Kdr*_h2m*NORM.S.DIST(_y1-_sqT,1)-_Sbd*_h2m1*NORM.S.DIST(_y1,1),_A4,_Kdr*_h2m*NORM.S.DIST(_y2-_sqT,1)-_Sbd*_h2m1*NORM.S.DIST(_y2,1),_do,IF(_S<=_H,0,_A1-_A2+_A3-_A4),_cf,_Sbd*NORM.S.DIST(-_x1,1)+_Kdr*NORM.S.DIST(_x1-_sqT,1),IF(_S<=_H,_cf,_do+_cf)) | C34: =LET(_S,A34,_sig,$B$4,_T,$B$5,_r,$B$6,_K,Cap,_H,Barrier,_q,q,_ds,dS,_b,_r-_q,_sqT,_sig*SQRT(_T),_mu,(_b-0.5*_sig^2)/_sig^2,_Kdr,_K*EXP(-_r*_T),_SP,_S*(1+_ds),_Sbdp,_SP*EXP(-_q*_T),_x1p,LN(_SP/_K)/_sqT+(1+_mu)*_sqT,_x2p,LN(_SP/_H)/_sqT+(1+_mu)*_sqT,_y1p,LN(_H^2/(_SP*_K))/_sqT+(1+_mu)*_sqT,_y2p,LN(_H/_SP)/_sqT+(1+_mu)*_sqT,_h2m1p,(_H/_SP)^(2*(_mu+1)),_h2mp,(_H/_SP)^(2*_mu),_A1p,_Kdr*NORM.S.DIST(_sqT-_x1p,1)-_Sbdp*NORM.S.DIST(-_x1p,1),_A2p,_Kdr*NORM.S.DIST(_sqT-_x2p,1)-_Sbdp*NORM.S.DIST(-_x2p,1),_A3p,_Kdr*_h2mp*NORM.S.DIST(_y1p-_sqT,1)-_Sbdp*_h2m1p*NORM.S.DIST(_y1p,1),_A4p,_Kdr*_h2mp*NORM.S.DIST(_y2p-_sqT,1)-_Sbdp*_h2m1p*NORM.S.DIST(_y2p,1),_cfp,_Sbdp*NORM.S.DIST(-_x1p,1)+_Kdr*NORM.S.DIST(_x1p-_sqT,1),_pp,IF(_SP<=_H,_cfp,(_A1p-_A2p+_A3p-_A4p)+_cfp),_SM,_S*(1-_ds),_Sbdm,_SM*EXP(-_q*_T),_x1m,LN(_SM/_K)/_sqT+(1+_mu)*_sqT,_x2m,LN(_SM/_H)/_sqT+(1+_mu)*_sqT,_y1m,LN(_H^2/(_SM*_K))/_sqT+(1+_mu)*_sqT,_y2m,LN(_H/_SM)/_sqT+(1+_mu)*_sqT,_h2m1m,(_H/_SM)^(2*(_mu+1)),_h2mm,(_H/_SM)^(2*_mu),_A1m,_Kdr*NORM.S.DIST(_sqT-_x1m,1)-_Sbdm*NORM.S.DIST(-_x1m,1),_A2m,_Kdr*NORM.S.DIST(_sqT-_x2m,1)-_Sbdm*NORM.S.DIST(-_x2m,1),_A3m,_Kdr*_h2mm*NORM.S.DIST(_y1m-_sqT,1)-_Sbdm*_h2m1m*NORM.S.DIST(_y1m,1),_A4m,_Kdr*_h2mm*NORM.S.DIST(_y2m-_sqT,1)-_Sbdm*_h2m1m*NORM.S.DIST(_y2m,1),_cfm,_Sbdm*NORM.S.DIST(-_x1m,1)+_Kdr*NORM.S.DIST(_x1m-_sqT,1),_pm,IF(_SM<=_H,_cfm,(_A1m-_A2m+_A3m-_A4m)+_cfm),(_pp-_pm)/(2*_ds*_S)) | D34: -0.000397 | E34: -1.9674 | F34: 0.0821
A35: 815.91 | B35: =LET(_S,A35,_sig,$B$4,_T,$B$5,_r,$B$6,_K,Cap,_H,Barrier,_q,q,_b,_r-_q,_sqT,_sig*SQRT(_T),_mu,(_b-0.5*_sig^2)/_sig^2,_x1,LN(_S/_K)/_sqT+(1+_mu)*_sqT,_x2,LN(_S/_H)/_sqT+(1+_mu)*_sqT,_y1,LN(_H^2/(_S*_K))/_sqT+(1+_mu)*_sqT,_y2,LN(_H/_S)/_sqT+(1+_mu)*_sqT,_Sbd,_S*EXP(-_q*_T),_Kdr,_K*EXP(-_r*_T),_h2m1,(_H/_S)^(2*(_mu+1)),_h2m,(_H/_S)^(2*_mu),_A1,_Kdr*NORM.S.DIST(_sqT-_x1,1)-_Sbd*NORM.S.DIST(-_x1,1),_A2,_Kdr*NORM.S.DIST(_sqT-_x2,1)-_Sbd*NORM.S.DIST(-_x2,1),_A3,_Kdr*_h2m*NORM.S.DIST(_y1-_sqT,1)-_Sbd*_h2m1*NORM.S.DIST(_y1,1),_A4,_Kdr*_h2m*NORM.S.DIST(_y2-_sqT,1)-_Sbd*_h2m1*NORM.S.DIST(_y2,1),_do,IF(_S<=_H,0,_A1-_A2+_A3-_A4),_cf,_Sbd*NORM.S.DIST(-_x1,1)+_Kdr*NORM.S.DIST(_x1-_sqT,1),IF(_S<=_H,_cf,_do+_cf)) | C35: =LET(_S,A35,_sig,$B$4,_T,$B$5,_r,$B$6,_K,Cap,_H,Barrier,_q,q,_ds,dS,_b,_r-_q,_sqT,_sig*SQRT(_T),_mu,(_b-0.5*_sig^2)/_sig^2,_Kdr,_K*EXP(-_r*_T),_SP,_S*(1+_ds),_Sbdp,_SP*EXP(-_q*_T),_x1p,LN(_SP/_K)/_sqT+(1+_mu)*_sqT,_x2p,LN(_SP/_H)/_sqT+(1+_mu)*_sqT,_y1p,LN(_H^2/(_SP*_K))/_sqT+(1+_mu)*_sqT,_y2p,LN(_H/_SP)/_sqT+(1+_mu)*_sqT,_h2m1p,(_H/_SP)^(2*(_mu+1)),_h2mp,(_H/_SP)^(2*_mu),_A1p,_Kdr*NORM.S.DIST(_sqT-_x1p,1)-_Sbdp*NORM.S.DIST(-_x1p,1),_A2p,_Kdr*NORM.S.DIST(_sqT-_x2p,1)-_Sbdp*NORM.S.DIST(-_x2p,1),_A3p,_Kdr*_h2mp*NORM.S.DIST(_y1p-_sqT,1)-_Sbdp*_h2m1p*NORM.S.DIST(_y1p,1),_A4p,_Kdr*_h2mp*NORM.S.DIST(_y2p-_sqT,1)-_Sbdp*_h2m1p*NORM.S.DIST(_y2p,1),_cfp,_Sbdp*NORM.S.DIST(-_x1p,1)+_Kdr*NORM.S.DIST(_x1p-_sqT,1),_pp,IF(_SP<=_H,_cfp,(_A1p-_A2p+_A3p-_A4p)+_cfp),_SM,_S*(1-_ds),_Sbdm,_SM*EXP(-_q*_T),_x1m,LN(_SM/_K)/_sqT+(1+_mu)*_sqT,_x2m,LN(_SM/_H)/_sqT+(1+_mu)*_sqT,_y1m,LN(_H^2/(_SM*_K))/_sqT+(1+_mu)*_sqT,_y2m,LN(_H/_SM)/_sqT+(1+_mu)*_sqT,_h2m1m,(_H/_SM)^(2*(_mu+1)),_h2mm,(_H/_SM)^(2*_mu),_A1m,_Kdr*NORM.S.DIST(_sqT-_x1m,1)-_Sbdm*NORM.S.DIST(-_x1m,1),_A2m,_Kdr*NORM.S.DIST(_sqT-_x2m,1)-_Sbdm*NORM.S.DIST(-_x2m,1),_A3m,_Kdr*_h2mm*NORM.S.DIST(_y1m-_sqT,1)-_Sbdm*_h2m1m*NORM.S.DIST(_y1m,1),_A4m,_Kdr*_h2mm*NORM.S.DIST(_y2m-_sqT,1)-_Sbdm*_h2m1m*NORM.S.DIST(_y2m,1),_cfm,_Sbdm*NORM.S.DIST(-_x1m,1)+_Kdr*NORM.S.DIST(_x1m-_sqT,1),_pm,IF(_SM<=_H,_cfm,(_A1m-_A2m+_A3m-_A4m)+_cfm),(_pp-_pm)/(2*_ds*_S)) | D35: -0.00041 | E35: -2.1726 | F35: 0.0898
A36: 842.4 | B36: =LET(_S,A36,_sig,$B$4,_T,$B$5,_r,$B$6,_K,Cap,_H,Barrier,_q,q,_b,_r-_q,_sqT,_sig*SQRT(_T),_mu,(_b-0.5*_sig^2)/_sig^2,_x1,LN(_S/_K)/_sqT+(1+_mu)*_sqT,_x2,LN(_S/_H)/_sqT+(1+_mu)*_sqT,_y1,LN(_H^2/(_S*_K))/_sqT+(1+_mu)*_sqT,_y2,LN(_H/_S)/_sqT+(1+_mu)*_sqT,_Sbd,_S*EXP(-_q*_T),_Kdr,_K*EXP(-_r*_T),_h2m1,(_H/_S)^(2*(_mu+1)),_h2m,(_H/_S)^(2*_mu),_A1,_Kdr*NORM.S.DIST(_sqT-_x1,1)-_Sbd*NORM.S.DIST(-_x1,1),_A2,_Kdr*NORM.S.DIST(_sqT-_x2,1)-_Sbd*NORM.S.DIST(-_x2,1),_A3,_Kdr*_h2m*NORM.S.DIST(_y1-_sqT,1)-_Sbd*_h2m1*NORM.S.DIST(_y1,1),_A4,_Kdr*_h2m*NORM.S.DIST(_y2-_sqT,1)-_Sbd*_h2m1*NORM.S.DIST(_y2,1),_do,IF(_S<=_H,0,_A1-_A2+_A3-_A4),_cf,_Sbd*NORM.S.DIST(-_x1,1)+_Kdr*NORM.S.DIST(_x1-_sqT,1),IF(_S<=_H,_cf,_do+_cf)) | C36: =LET(_S,A36,_sig,$B$4,_T,$B$5,_r,$B$6,_K,Cap,_H,Barrier,_q,q,_ds,dS,_b,_r-_q,_sqT,_sig*SQRT(_T),_mu,(_b-0.5*_sig^2)/_sig^2,_Kdr,_K*EXP(-_r*_T),_SP,_S*(1+_ds),_Sbdp,_SP*EXP(-_q*_T),_x1p,LN(_SP/_K)/_sqT+(1+_mu)*_sqT,_x2p,LN(_SP/_H)/_sqT+(1+_mu)*_sqT,_y1p,LN(_H^2/(_SP*_K))/_sqT+(1+_mu)*_sqT,_y2p,LN(_H/_SP)/_sqT+(1+_mu)*_sqT,_h2m1p,(_H/_SP)^(2*(_mu+1)),_h2mp,(_H/_SP)^(2*_mu),_A1p,_Kdr*NORM.S.DIST(_sqT-_x1p,1)-_Sbdp*NORM.S.DIST(-_x1p,1),_A2p,_Kdr*NORM.S.DIST(_sqT-_x2p,1)-_Sbdp*NORM.S.DIST(-_x2p,1),_A3p,_Kdr*_h2mp*NORM.S.DIST(_y1p-_sqT,1)-_Sbdp*_h2m1p*NORM.S.DIST(_y1p,1),_A4p,_Kdr*_h2mp*NORM.S.DIST(_y2p-_sqT,1)-_Sbdp*_h2m1p*NORM.S.DIST(_y2p,1),_cfp,_Sbdp*NORM.S.DIST(-_x1p,1)+_Kdr*NORM.S.DIST(_x1p-_sqT,1),_pp,IF(_SP<=_H,_cfp,(_A1p-_A2p+_A3p-_A4p)+_cfp),_SM,_S*(1-_ds),_Sbdm,_SM*EXP(-_q*_T),_x1m,LN(_SM/_K)/_sqT+(1+_mu)*_sqT,_x2m,LN(_SM/_H)/_sqT+(1+_mu)*_sqT,_y1m,LN(_H^2/(_SM*_K))/_sqT+(1+_mu)*_sqT,_y2m,LN(_H/_SM)/_sqT+(1+_mu)*_sqT,_h2m1m,(_H/_SM)^(2*(_mu+1)),_h2mm,(_H/_SM)^(2*_mu),_A1m,_Kdr*NORM.S.DIST(_sqT-_x1m,1)-_Sbdm*NORM.S.DIST(-_x1m,1),_A2m,_Kdr*NORM.S.DIST(_sqT-_x2m,1)-_Sbdm*NORM.S.DIST(-_x2m,1),_A3m,_Kdr*_h2mm*NORM.S.DIST(_y1m-_sqT,1)-_Sbdm*_h2m1m*NORM.S.DIST(_y1m,1),_A4m,_Kdr*_h2mm*NORM.S.DIST(_y2m-_sqT,1)-_Sbdm*_h2m1m*NORM.S.DIST(_y2m,1),_cfm,_Sbdm*NORM.S.DIST(-_x1m,1)+_Kdr*NORM.S.DIST(_x1m-_sqT,1),_pm,IF(_SM<=_H,_cfm,(_A1m-_A2m+_A3m-_A4m)+_cfm),(_pp-_pm)/(2*_ds*_S)) | D36: -0.000423 | E36: -2.3848 | F36: 0.0978
A37: 868.89 | B37: =LET(_S,A37,_sig,$B$4,_T,$B$5,_r,$B$6,_K,Cap,_H,Barrier,_q,q,_b,_r-_q,_sqT,_sig*SQRT(_T),_mu,(_b-0.5*_sig^2)/_sig^2,_x1,LN(_S/_K)/_sqT+(1+_mu)*_sqT,_x2,LN(_S/_H)/_sqT+(1+_mu)*_sqT,_y1,LN(_H^2/(_S*_K))/_sqT+(1+_mu)*_sqT,_y2,LN(_H/_S)/_sqT+(1+_mu)*_sqT,_Sbd,_S*EXP(-_q*_T),_Kdr,_K*EXP(-_r*_T),_h2m1,(_H/_S)^(2*(_mu+1)),_h2m,(_H/_S)^(2*_mu),_A1,_Kdr*NORM.S.DIST(_sqT-_x1,1)-_Sbd*NORM.S.DIST(-_x1,1),_A2,_Kdr*NORM.S.DIST(_sqT-_x2,1)-_Sbd*NORM.S.DIST(-_x2,1),_A3,_Kdr*_h2m*NORM.S.DIST(_y1-_sqT,1)-_Sbd*_h2m1*NORM.S.DIST(_y1,1),_A4,_Kdr*_h2m*NORM.S.DIST(_y2-_sqT,1)-_Sbd*_h2m1*NORM.S.DIST(_y2,1),_do,IF(_S<=_H,0,_A1-_A2+_A3-_A4),_cf,_Sbd*NORM.S.DIST(-_x1,1)+_Kdr*NORM.S.DIST(_x1-_sqT,1),IF(_S<=_H,_cf,_do+_cf)) | C37: =LET(_S,A37,_sig,$B$4,_T,$B$5,_r,$B$6,_K,Cap,_H,Barrier,_q,q,_ds,dS,_b,_r-_q,_sqT,_sig*SQRT(_T),_mu,(_b-0.5*_sig^2)/_sig^2,_Kdr,_K*EXP(-_r*_T),_SP,_S*(1+_ds),_Sbdp,_SP*EXP(-_q*_T),_x1p,LN(_SP/_K)/_sqT+(1+_mu)*_sqT,_x2p,LN(_SP/_H)/_sqT+(1+_mu)*_sqT,_y1p,LN(_H^2/(_SP*_K))/_sqT+(1+_mu)*_sqT,_y2p,LN(_H/_SP)/_sqT+(1+_mu)*_sqT,_h2m1p,(_H/_SP)^(2*(_mu+1)),_h2mp,(_H/_SP)^(2*_mu),_A1p,_Kdr*NORM.S.DIST(_sqT-_x1p,1)-_Sbdp*NORM.S.DIST(-_x1p,1),_A2p,_Kdr*NORM.S.DIST(_sqT-_x2p,1)-_Sbdp*NORM.S.DIST(-_x2p,1),_A3p,_Kdr*_h2mp*NORM.S.DIST(_y1p-_sqT,1)-_Sbdp*_h2m1p*NORM.S.DIST(_y1p,1),_A4p,_Kdr*_h2mp*NORM.S.DIST(_y2p-_sqT,1)-_Sbdp*_h2m1p*NORM.S.DIST(_y2p,1),_cfp,_Sbdp*NORM.S.DIST(-_x1p,1)+_Kdr*NORM.S.DIST(_x1p-_sqT,1),_pp,IF(_SP<=_H,_cfp,(_A1p-_A2p+_A3p-_A4p)+_cfp),_SM,_S*(1-_ds),_Sbdm,_SM*EXP(-_q*_T),_x1m,LN(_SM/_K)/_sqT+(1+_mu)*_sqT,_x2m,LN(_SM/_H)/_sqT+(1+_mu)*_sqT,_y1m,LN(_H^2/(_SM*_K))/_sqT+(1+_mu)*_sqT,_y2m,LN(_H/_SM)/_sqT+(1+_mu)*_sqT,_h2m1m,(_H/_SM)^(2*(_mu+1)),_h2mm,(_H/_SM)^(2*_mu),_A1m,_Kdr*NORM.S.DIST(_sqT-_x1m,1)-_Sbdm*NORM.S.DIST(-_x1m,1),_A2m,_Kdr*NORM.S.DIST(_sqT-_x2m,1)-_Sbdm*NORM.S.DIST(-_x2m,1),_A3m,_Kdr*_h2mm*NORM.S.DIST(_y1m-_sqT,1)-_Sbdm*_h2m1m*NORM.S.DIST(_y1m,1),_A4m,_Kdr*_h2mm*NORM.S.DIST(_y2m-_sqT,1)-_Sbdm*_h2m1m*NORM.S.DIST(_y2m,1),_cfm,_Sbdm*NORM.S.DIST(-_x1m,1)+_Kdr*NORM.S.DIST(_x1m-_sqT,1),_pm,IF(_SM<=_H,_cfm,(_A1m-_A2m+_A3m-_A4m)+_cfm),(_pp-_pm)/(2*_ds*_S)) | D37: -0.000434 | E37: -2.603 | F37: 0.106
... A125: 3200 | B125: =LET(_S,A125,_sig,$B$4,_T,$B$5,_r,$B$6,_K,Cap,_H,Barrier,_q,q,_b,_r-_q,_sqT,_sig*SQRT(_T),_mu,(_b-0.5*_sig^2)/_sig^2,_x1,LN(_S/_K)/_sqT+(1+_mu)*_sqT,_x2,LN(_S/_H)/_sqT+(1+_mu)*_sqT,_y1,LN(_H^2/(_S*_K))/_sqT+(1+_mu)*_sqT,_y2,LN(_H/_S)/_sqT+(1+_mu)*_sqT,_Sbd,_S*EXP(-_q*_T),_Kdr,_K*EXP(-_r*_T),_h2m1,(_H/_S)^(2*(_mu+1)),_h2m,(_H/_S)^(2*_mu),_A1,_Kdr*NORM.S.DIST(_sqT-_x1,1)-_Sbd*NORM.S.DIST(-_x1,1),_A2,_Kdr*NORM.S.DIST(_sqT-_x2,1)-_Sbd*NORM.S.DIST(-_x2,1),_A3,_Kdr*_h2m*NORM.S.DIST(_y1-_sqT,1)-_Sbd*_h2m1*NORM.S.DIST(_y1,1),_A4,_Kdr*_h2m*NORM.S.DIST(_y2-_sqT,1)-_Sbd*_h2m1*NORM.S.DIST(_y2,1),_do,IF(_S<=_H,0,_A1-_A2+_A3-_A4),_cf,_Sbd*NORM.S.DIST(-_x1,1)+_Kdr*NORM.S.DIST(_x1-_sqT,1),IF(_S<=_H,_cf,_do+_cf)) | C125: =LET(_S,A125,_sig,$B$4,_T,$B$5,_r,$B$6,_K,Cap,_H,Barrier,_q,q,_ds,dS,_b,_r-_q,_sqT,_sig*SQRT(_T),_mu,(_b-0.5*_sig^2)/_sig^2,_Kdr,_K*EXP(-_r*_T),_SP,_S*(1+_ds),_Sbdp,_SP*EXP(-_q*_T),_x1p,LN(_SP/_K)/_sqT+(1+_mu)*_sqT,_x2p,LN(_SP/_H)/_sqT+(1+_mu)*_sqT,_y1p,LN(_H^2/(_SP*_K))/_sqT+(1+_mu)*_sqT,_y2p,LN(_H/_SP)/_sqT+(1+_mu)*_sqT,_h2m1p,(_H/_SP)^(2*(_mu+1)),_h2mp,(_H/_SP)^(2*_mu),_A1p,_Kdr*NORM.S.DIST(_sqT-_x1p,1)-_Sbdp*NORM.S.DIST(-_x1p,1),_A2p,_Kdr*NORM.S.DIST(_sqT-_x2p,1)-_Sbdp*NORM.S.DIST(-_x2p,1),_A3p,_Kdr*_h2mp*NORM.S.DIST(_y1p-_sqT,1)-_Sbdp*_h2m1p*NORM.S.DIST(_y1p,1),_A4p,_Kdr*_h2mp*NORM.S.DIST(_y2p-_sqT,1)-_Sbdp*_h2m1p*NORM.S.DIST(_y2p,1),_cfp,_Sbdp*NORM.S.DIST(-_x1p,1)+_Kdr*NORM.S.DIST(_x1p-_sqT,1),_pp,IF(_SP<=_H,_cfp,(_A1p-_A2p+_A3p-_A4p)+_cfp),_SM,_S*(1-_ds),_Sbdm,_SM*EXP(-_q*_T),_x1m,LN(_SM/_K)/_sqT+(1+_mu)*_sqT,_x2m,LN(_SM/_H)/_sqT+(1+_mu)*_sqT,_y1m,LN(_H^2/(_SM*_K))/_sqT+(1+_mu)*_sqT,_y2m,LN(_H/_SM)/_sqT+(1+_mu)*_sqT,_h2m1m,(_H/_SM)^(2*(_mu+1)),_h2mm,(_H/_SM)^(2*_mu),_A1m,_Kdr*NORM.S.DIST(_sqT-_x1m,1)-_Sbdm*NORM.S.DIST(-_x1m,1),_A2m,_Kdr*NORM.S.DIST(_sqT-_x2m,1)-_Sbdm*NORM.S.DIST(-_x2m,1),_A3m,_Kdr*_h2mm*NORM.S.DIST(_y1m-_sqT,1)-_Sbdm*_h2m1m*NORM.S.DIST(_y1m,1),_A4m,_Kdr*_h2mm*NORM.S.DIST(_y2m-_sqT,1)-_Sbdm*_h2m1m*NORM.S.DIST(_y2m,1),_cfm,_Sbdm*NORM.S.DIST(-_x1m,1)+_Kdr*NORM.S.DIST(_x1m-_sqT,1),_pm,IF(_SM<=_H,_cfm,(_A1m-_A2m+_A3m-_A4m)+_cfm),(_pp-_pm)/(2*_ds*_S)) | D125: -0.000107 | E125: -8.706 | F125: 0.3847

Sheet P2_TaskVII_Rep
A1: Task VII -- Daily Replicating Portfolio (RR closed-form)
A2: Columns B-E: live formulas pulling from Data_Stock / Data_Svensson. Columns F-G: live Haug RR LET formulas (Excel 365). Columns H-J: live arithmetic on F-G. Press Ctrl+Alt+F9 to recalculate.
A3: Date | B3: S (EUR) | C3: sigma | D3: T_rem (yr) | E3: r | F3: Price (RR) | G3: Delta (RR) | H3: Equity (EUR) | I3: Bond (EUR) | J3: Eq Fraction
A4: =Data_Stock!A4 | B4: =Data_Stock!B4 | C4: =Data_Stock!C4 | D4: =Data_Svensson!H4 | E4: =Data_Svensson!I4 | F4: =LET(_S,B4,_sig,C4,_T,D4,_r,E4,_K,Cap,_H,Barrier,_q,q,_b,_r-_q,_sqT,_sig*SQRT(_T),_mu,(_b-0.5*_sig^2)/_sig^2,_x1,LN(_S/_K)/_sqT+(1+_mu)*_sqT,_x2,LN(_S/_H)/_sqT+(1+_mu)*_sqT,_y1,LN(_H^2/(_S*_K))/_sqT+(1+_mu)*_sqT,_y2,LN(_H/_S)/_sqT+(1+_mu)*_sqT,_Sbd,_S*EXP(-_q*_T),_Kdr,_K*EXP(-_r*_T),_h2m1,(_H/_S)^(2*(_mu+1)),_h2m,(_H/_S)^(2*_mu),_A1,_Kdr*NORM.S.DIST(_sqT-_x1,1)-_Sbd*NORM.S.DIST(-_x1,1),_A2,_Kdr*NORM.S.DIST(_sqT-_x2,1)-_Sbd*NORM.S.DIST(-_x2,1),_A3,_Kdr*_h2m*NORM.S.DIST(_y1-_sqT,1)-_Sbd*_h2m1*NORM.S.DIST(_y1,1),_A4,_Kdr*_h2m*NORM.S.DIST(_y2-_sqT,1)-_Sbd*_h2m1*NORM.S.DIST(_y2,1),_do,IF(_S<=_H,0,_A1-_A2+_A3-_A4),_cf,_Sbd*NORM.S.DIST(-_x1,1)+_Kdr*NORM.S.DIST(_x1-_sqT,1),IF(_S<=_H,_cf,_do+_cf)) | G4: =LET(_S,B4,_sig,C4,_T,D4,_r,E4,_K,Cap,_H,Barrier,_q,q,_ds,dS,_b,_r-_q,_sqT,_sig*SQRT(_T),_mu,(_b-0.5*_sig^2)/_sig^2,_Kdr,_K*EXP(-_r*_T),_SP,_S*(1+_ds),_Sbdp,_SP*EXP(-_q*_T),_x1p,LN(_SP/_K)/_sqT+(1+_mu)*_sqT,_x2p,LN(_SP/_H)/_sqT+(1+_mu)*_sqT,_y1p,LN(_H^2/(_SP*_K))/_sqT+(1+_mu)*_sqT,_y2p,LN(_H/_SP)/_sqT+(1+_mu)*_sqT,_h2m1p,(_H/_SP)^(2*(_mu+1)),_h2mp,(_H/_SP)^(2*_mu),_A1p,_Kdr*NORM.S.DIST(_sqT-_x1p,1)-_Sbdp*NORM.S.DIST(-_x1p,1),_A2p,_Kdr*NORM.S.DIST(_sqT-_x2p,1)-_Sbdp*NORM.S.DIST(-_x2p,1),_A3p,_Kdr*_h2mp*NORM.S.DIST(_y1p-_sqT,1)-_Sbdp*_h2m1p*NORM.S.DIST(_y1p,1),_A4p,_Kdr*_h2mp*NORM.S.DIST(_y2p-_sqT,1)-_Sbdp*_h2m1p*NORM.S.DIST(_y2p,1),_cfp,_Sbdp*NORM.S.DIST(-_x1p,1)+_Kdr*NORM.S.DIST(_x1p-_sqT,1),_pp,IF(_SP<=_H,_cfp,(_A1p-_A2p+_A3p-_A4p)+_cfp),_SM,_S*(1-_ds),_Sbdm,_SM*EXP(-_q*_T),_x1m,LN(_SM/_K)/_sqT+(1+_mu)*_sqT,_x2m,LN(_SM/_H)/_sqT+(1+_mu)*_sqT,_y1m,LN(_H^2/(_SM*_K))/_sqT+(1+_mu)*_sqT,_y2m,LN(_H/_SM)/_sqT+(1+_mu)*_sqT,_h2m1m,(_H/_SM)^(2*(_mu+1)),_h2mm,(_H/_SM)^(2*_mu),_A1m,_Kdr*NORM.S.DIST(_sqT-_x1m,1)-_Sbdm*NORM.S.DIST(-_x1m,1),_A2m,_Kdr*NORM.S.DIST(_sqT-_x2m,1)-_Sbdm*NORM.S.DIST(-_x2m,1),_A3m,_Kdr*_h2mm*NORM.S.DIST(_y1m-_sqT,1)-_Sbdm*_h2m1m*NORM.S.DIST(_y1m,1),_A4m,_Kdr*_h2mm*NORM.S.DIST(_y2m-_sqT,1)-_Sbdm*_h2m1m*NORM.S.DIST(_y2m,1),_cfm,_Sbdm*NORM.S.DIST(-_x1m,1)+_Kdr*NORM.S.DIST(_x1m-_sqT,1),_pm,IF(_SM<=_H,_cfm,(_A1m-_A2m+_A3m-_A4m)+_cfm),(_pp-_pm)/(2*_ds*_S)) | H4: =G4*B4 | I4: =F4-H4 | J4: =IF(F4>0,H4/F4,0)
A5: =Data_Stock!A5 | B5: =Data_Stock!B5 | C5: =Data_Stock!C5 | D5: =Data_Svensson!H5 | E5: =Data_Svensson!I5 | F5: =LET(_S,B5,_sig,C5,_T,D5,_r,E5,_K,Cap,_H,Barrier,_q,q,_b,_r-_q,_sqT,_sig*SQRT(_T),_mu,(_b-0.5*_sig^2)/_sig^2,_x1,LN(_S/_K)/_sqT+(1+_mu)*_sqT,_x2,LN(_S/_H)/_sqT+(1+_mu)*_sqT,_y1,LN(_H^2/(_S*_K))/_sqT+(1+_mu)*_sqT,_y2,LN(_H/_S)/_sqT+(1+_mu)*_sqT,_Sbd,_S*EXP(-_q*_T),_Kdr,_K*EXP(-_r*_T),_h2m1,(_H/_S)^(2*(_mu+1)),_h2m,(_H/_S)^(2*_mu),_A1,_Kdr*NORM.S.DIST(_sqT-_x1,1)-_Sbd*NORM.S.DIST(-_x1,1),_A2,_Kdr*NORM.S.DIST(_sqT-_x2,1)-_Sbd*NORM.S.DIST(-_x2,1),_A3,_Kdr*_h2m*NORM.S.DIST(_y1-_sqT,1)-_Sbd*_h2m1*NORM.S.DIST(_y1,1),_A4,_Kdr*_h2m*NORM.S.DIST(_y2-_sqT,1)-_Sbd*_h2m1*NORM.S.DIST(_y2,1),_do,IF(_S<=_H,0,_A1-_A2+_A3-_A4),_cf,_Sbd*NORM.S.DIST(-_x1,1)+_Kdr*NORM.S.DIST(_x1-_sqT,1),IF(_S<=_H,_cf,_do+_cf)) | G5: =LET(_S,B5,_sig,C5,_T,D5,_r,E5,_K,Cap,_H,Barrier,_q,q,_ds,dS,_b,_r-_q,_sqT,_sig*SQRT(_T),_mu,(_b-0.5*_sig^2)/_sig^2,_Kdr,_K*EXP(-_r*_T),_SP,_S*(1+_ds),_Sbdp,_SP*EXP(-_q*_T),_x1p,LN(_SP/_K)/_sqT+(1+_mu)*_sqT,_x2p,LN(_SP/_H)/_sqT+(1+_mu)*_sqT,_y1p,LN(_H^2/(_SP*_K))/_sqT+(1+_mu)*_sqT,_y2p,LN(_H/_SP)/_sqT+(1+_mu)*_sqT,_h2m1p,(_H/_SP)^(2*(_mu+1)),_h2mp,(_H/_SP)^(2*_mu),_A1p,_Kdr*NORM.S.DIST(_sqT-_x1p,1)-_Sbdp*NORM.S.DIST(-_x1p,1),_A2p,_Kdr*NORM.S.DIST(_sqT-_x2p,1)-_Sbdp*NORM.S.DIST(-_x2p,1),_A3p,_Kdr*_h2mp*NORM.S.DIST(_y1p-_sqT,1)-_Sbdp*_h2m1p*NORM.S.DIST(_y1p,1),_A4p,_Kdr*_h2mp*NORM.S.DIST(_y2p-_sqT,1)-_Sbdp*_h2m1p*NORM.S.DIST(_y2p,1),_cfp,_Sbdp*NORM.S.DIST(-_x1p,1)+_Kdr*NORM.S.DIST(_x1p-_sqT,1),_pp,IF(_SP<=_H,_cfp,(_A1p-_A2p+_A3p-_A4p)+_cfp),_SM,_S*(1-_ds),_Sbdm,_SM*EXP(-_q*_T),_x1m,LN(_SM/_K)/_sqT+(1+_mu)*_sqT,_x2m,LN(_SM/_H)/_sqT+(1+_mu)*_sqT,_y1m,LN(_H^2/(_SM*_K))/_sqT+(1+_mu)*_sqT,_y2m,LN(_H/_SM)/_sqT+(1+_mu)*_sqT,_h2m1m,(_H/_SM)^(2*(_mu+1)),_h2mm,(_H/_SM)^(2*_mu),_A1m,_Kdr*NORM.S.DIST(_sqT-_x1m,1)-_Sbdm*NORM.S.DIST(-_x1m,1),_A2m,_Kdr*NORM.S.DIST(_sqT-_x2m,1)-_Sbdm*NORM.S.DIST(-_x2m,1),_A3m,_Kdr*_h2mm*NORM.S.DIST(_y1m-_sqT,1)-_Sbdm*_h2m1m*NORM.S.DIST(_y1m,1),_A4m,_Kdr*_h2mm*NORM.S.DIST(_y2m-_sqT,1)-_Sbdm*_h2m1m*NORM.S.DIST(_y2m,1),_cfm,_Sbdm*NORM.S.DIST(-_x1m,1)+_Kdr*NORM.S.DIST(_x1m-_sqT,1),_pm,IF(_SM<=_H,_cfm,(_A1m-_A2m+_A3m-_A4m)+_cfm),(_pp-_pm)/(2*_ds*_S)) | H5: =G5*B5 | I5: =F5-H5 | J5: =IF(F5>0,H5/F5,0)
A6: =Data_Stock!A6 | B6: =Data_Stock!B6 | C6: =Data_Stock!C6 | D6: =Data_Svensson!H6 | E6: =Data_Svensson!I6 | F6: =LET(_S,B6,_sig,C6,_T,D6,_r,E6,_K,Cap,_H,Barrier,_q,q,_b,_r-_q,_sqT,_sig*SQRT(_T),_mu,(_b-0.5*_sig^2)/_sig^2,_x1,LN(_S/_K)/_sqT+(1+_mu)*_sqT,_x2,LN(_S/_H)/_sqT+(1+_mu)*_sqT,_y1,LN(_H^2/(_S*_K))/_sqT+(1+_mu)*_sqT,_y2,LN(_H/_S)/_sqT+(1+_mu)*_sqT,_Sbd,_S*EXP(-_q*_T),_Kdr,_K*EXP(-_r*_T),_h2m1,(_H/_S)^(2*(_mu+1)),_h2m,(_H/_S)^(2*_mu),_A1,_Kdr*NORM.S.DIST(_sqT-_x1,1)-_Sbd*NORM.S.DIST(-_x1,1),_A2,_Kdr*NORM.S.DIST(_sqT-_x2,1)-_Sbd*NORM.S.DIST(-_x2,1),_A3,_Kdr*_h2m*NORM.S.DIST(_y1-_sqT,1)-_Sbd*_h2m1*NORM.S.DIST(_y1,1),_A4,_Kdr*_h2m*NORM.S.DIST(_y2-_sqT,1)-_Sbd*_h2m1*NORM.S.DIST(_y2,1),_do,IF(_S<=_H,0,_A1-_A2+_A3-_A4),_cf,_Sbd*NORM.S.DIST(-_x1,1)+_Kdr*NORM.S.DIST(_x1-_sqT,1),IF(_S<=_H,_cf,_do+_cf)) | G6: =LET(_S,B6,_sig,C6,_T,D6,_r,E6,_K,Cap,_H,Barrier,_q,q,_ds,dS,_b,_r-_q,_sqT,_sig*SQRT(_T),_mu,(_b-0.5*_sig^2)/_sig^2,_Kdr,_K*EXP(-_r*_T),_SP,_S*(1+_ds),_Sbdp,_SP*EXP(-_q*_T),_x1p,LN(_SP/_K)/_sqT+(1+_mu)*_sqT,_x2p,LN(_SP/_H)/_sqT+(1+_mu)*_sqT,_y1p,LN(_H^2/(_SP*_K))/_sqT+(1+_mu)*_sqT,_y2p,LN(_H/_SP)/_sqT+(1+_mu)*_sqT,_h2m1p,(_H/_SP)^(2*(_mu+1)),_h2mp,(_H/_SP)^(2*_mu),_A1p,_Kdr*NORM.S.DIST(_sqT-_x1p,1)-_Sbdp*NORM.S.DIST(-_x1p,1),_A2p,_Kdr*NORM.S.DIST(_sqT-_x2p,1)-_Sbdp*NORM.S.DIST(-_x2p,1),_A3p,_Kdr*_h2mp*NORM.S.DIST(_y1p-_sqT,1)-_Sbdp*_h2m1p*NORM.S.DIST(_y1p,1),_A4p,_Kdr*_h2mp*NORM.S.DIST(_y2p-_sqT,1)-_Sbdp*_h2m1p*NORM.S.DIST(_y2p,1),_cfp,_Sbdp*NORM.S.DIST(-_x1p,1)+_Kdr*NORM.S.DIST(_x1p-_sqT,1),_pp,IF(_SP<=_H,_cfp,(_A1p-_A2p+_A3p-_A4p)+_cfp),_SM,_S*(1-_ds),_Sbdm,_SM*EXP(-_q*_T),_x1m,LN(_SM/_K)/_sqT+(1+_mu)*_sqT,_x2m,LN(_SM/_H)/_sqT+(1+_mu)*_sqT,_y1m,LN(_H^2/(_SM*_K))/_sqT+(1+_mu)*_sqT,_y2m,LN(_H/_SM)/_sqT+(1+_mu)*_sqT,_h2m1m,(_H/_SM)^(2*(_mu+1)),_h2mm,(_H/_SM)^(2*_mu),_A1m,_Kdr*NORM.S.DIST(_sqT-_x1m,1)-_Sbdm*NORM.S.DIST(-_x1m,1),_A2m,_Kdr*NORM.S.DIST(_sqT-_x2m,1)-_Sbdm*NORM.S.DIST(-_x2m,1),_A3m,_Kdr*_h2mm*NORM.S.DIST(_y1m-_sqT,1)-_Sbdm*_h2m1m*NORM.S.DIST(_y1m,1),_A4m,_Kdr*_h2mm*NORM.S.DIST(_y2m-_sqT,1)-_Sbdm*_h2m1m*NORM.S.DIST(_y2m,1),_cfm,_Sbdm*NORM.S.DIST(-_x1m,1)+_Kdr*NORM.S.DIST(_x1m-_sqT,1),_pm,IF(_SM<=_H,_cfm,(_A1m-_A2m+_A3m-_A4m)+_cfm),(_pp-_pm)/(2*_ds*_S)) | H6: =G6*B6 | I6: =F6-H6 | J6: =IF(F6>0,H6/F6,0)
A7: =Data_Stock!A7 | B7: =Data_Stock!B7 | C7: =Data_Stock!C7 | D7: =Data_Svensson!H7 | E7: =Data_Svensson!I7 | F7: =LET(_S,B7,_sig,C7,_T,D7,_r,E7,_K,Cap,_H,Barrier,_q,q,_b,_r-_q,_sqT,_sig*SQRT(_T),_mu,(_b-0.5*_sig^2)/_sig^2,_x1,LN(_S/_K)/_sqT+(1+_mu)*_sqT,_x2,LN(_S/_H)/_sqT+(1+_mu)*_sqT,_y1,LN(_H^2/(_S*_K))/_sqT+(1+_mu)*_sqT,_y2,LN(_H/_S)/_sqT+(1+_mu)*_sqT,_Sbd,_S*EXP(-_q*_T),_Kdr,_K*EXP(-_r*_T),_h2m1,(_H/_S)^(2*(_mu+1)),_h2m,(_H/_S)^(2*_mu),_A1,_Kdr*NORM.S.DIST(_sqT-_x1,1)-_Sbd*NORM.S.DIST(-_x1,1),_A2,_Kdr*NORM.S.DIST(_sqT-_x2,1)-_Sbd*NORM.S.DIST(-_x2,1),_A3,_Kdr*_h2m*NORM.S.DIST(_y1-_sqT,1)-_Sbd*_h2m1*NORM.S.DIST(_y1,1),_A4,_Kdr*_h2m*NORM.S.DIST(_y2-_sqT,1)-_Sbd*_h2m1*NORM.S.DIST(_y2,1),_do,IF(_S<=_H,0,_A1-_A2+_A3-_A4),_cf,_Sbd*NORM.S.DIST(-_x1,1)+_Kdr*NORM.S.DIST(_x1-_sqT,1),IF(_S<=_H,_cf,_do+_cf)) | G7: =LET(_S,B7,_sig,C7,_T,D7,_r,E7,_K,Cap,_H,Barrier,_q,q,_ds,dS,_b,_r-_q,_sqT,_sig*SQRT(_T),_mu,(_b-0.5*_sig^2)/_sig^2,_Kdr,_K*EXP(-_r*_T),_SP,_S*(1+_ds),_Sbdp,_SP*EXP(-_q*_T),_x1p,LN(_SP/_K)/_sqT+(1+_mu)*_sqT,_x2p,LN(_SP/_H)/_sqT+(1+_mu)*_sqT,_y1p,LN(_H^2/(_SP*_K))/_sqT+(1+_mu)*_sqT,_y2p,LN(_H/_SP)/_sqT+(1+_mu)*_sqT,_h2m1p,(_H/_SP)^(2*(_mu+1)),_h2mp,(_H/_SP)^(2*_mu),_A1p,_Kdr*NORM.S.DIST(_sqT-_x1p,1)-_Sbdp*NORM.S.DIST(-_x1p,1),_A2p,_Kdr*NORM.S.DIST(_sqT-_x2p,1)-_Sbdp*NORM.S.DIST(-_x2p,1),_A3p,_Kdr*_h2mp*NORM.S.DIST(_y1p-_sqT,1)-_Sbdp*_h2m1p*NORM.S.DIST(_y1p,1),_A4p,_Kdr*_h2mp*NORM.S.DIST(_y2p-_sqT,1)-_Sbdp*_h2m1p*NORM.S.DIST(_y2p,1),_cfp,_Sbdp*NORM.S.DIST(-_x1p,1)+_Kdr*NORM.S.DIST(_x1p-_sqT,1),_pp,IF(_SP<=_H,_cfp,(_A1p-_A2p+_A3p-_A4p)+_cfp),_SM,_S*(1-_ds),_Sbdm,_SM*EXP(-_q*_T),_x1m,LN(_SM/_K)/_sqT+(1+_mu)*_sqT,_x2m,LN(_SM/_H)/_sqT+(1+_mu)*_sqT,_y1m,LN(_H^2/(_SM*_K))/_sqT+(1+_mu)*_sqT,_y2m,LN(_H/_SM)/_sqT+(1+_mu)*_sqT,_h2m1m,(_H/_SM)^(2*(_mu+1)),_h2mm,(_H/_SM)^(2*_mu),_A1m,_Kdr*NORM.S.DIST(_sqT-_x1m,1)-_Sbdm*NORM.S.DIST(-_x1m,1),_A2m,_Kdr*NORM.S.DIST(_sqT-_x2m,1)-_Sbdm*NORM.S.DIST(-_x2m,1),_A3m,_Kdr*_h2mm*NORM.S.DIST(_y1m-_sqT,1)-_Sbdm*_h2m1m*NORM.S.DIST(_y1m,1),_A4m,_Kdr*_h2mm*NORM.S.DIST(_y2m-_sqT,1)-_Sbdm*_h2m1m*NORM.S.DIST(_y2m,1),_cfm,_Sbdm*NORM.S.DIST(-_x1m,1)+_Kdr*NORM.S.DIST(_x1m-_sqT,1),_pm,IF(_SM<=_H,_cfm,(_A1m-_A2m+_A3m-_A4m)+_cfm),(_pp-_pm)/(2*_ds*_S)) | H7: =G7*B7 | I7: =F7-H7 | J7: =IF(F7>0,H7/F7,0)
A8: =Data_Stock!A8 | B8: =Data_Stock!B8 | C8: =Data_Stock!C8 | D8: =Data_Svensson!H8 | E8: =Data_Svensson!I8 | F8: =LET(_S,B8,_sig,C8,_T,D8,_r,E8,_K,Cap,_H,Barrier,_q,q,_b,_r-_q,_sqT,_sig*SQRT(_T),_mu,(_b-0.5*_sig^2)/_sig^2,_x1,LN(_S/_K)/_sqT+(1+_mu)*_sqT,_x2,LN(_S/_H)/_sqT+(1+_mu)*_sqT,_y1,LN(_H^2/(_S*_K))/_sqT+(1+_mu)*_sqT,_y2,LN(_H/_S)/_sqT+(1+_mu)*_sqT,_Sbd,_S*EXP(-_q*_T),_Kdr,_K*EXP(-_r*_T),_h2m1,(_H/_S)^(2*(_mu+1)),_h2m,(_H/_S)^(2*_mu),_A1,_Kdr*NORM.S.DIST(_sqT-_x1,1)-_Sbd*NORM.S.DIST(-_x1,1),_A2,_Kdr*NORM.S.DIST(_sqT-_x2,1)-_Sbd*NORM.S.DIST(-_x2,1),_A3,_Kdr*_h2m*NORM.S.DIST(_y1-_sqT,1)-_Sbd*_h2m1*NORM.S.DIST(_y1,1),_A4,_Kdr*_h2m*NORM.S.DIST(_y2-_sqT,1)-_Sbd*_h2m1*NORM.S.DIST(_y2,1),_do,IF(_S<=_H,0,_A1-_A2+_A3-_A4),_cf,_Sbd*NORM.S.DIST(-_x1,1)+_Kdr*NORM.S.DIST(_x1-_sqT,1),IF(_S<=_H,_cf,_do+_cf)) | G8: =LET(_S,B8,_sig,C8,_T,D8,_r,E8,_K,Cap,_H,Barrier,_q,q,_ds,dS,_b,_r-_q,_sqT,_sig*SQRT(_T),_mu,(_b-0.5*_sig^2)/_sig^2,_Kdr,_K*EXP(-_r*_T),_SP,_S*(1+_ds),_Sbdp,_SP*EXP(-_q*_T),_x1p,LN(_SP/_K)/_sqT+(1+_mu)*_sqT,_x2p,LN(_SP/_H)/_sqT+(1+_mu)*_sqT,_y1p,LN(_H^2/(_SP*_K))/_sqT+(1+_mu)*_sqT,_y2p,LN(_H/_SP)/_sqT+(1+_mu)*_sqT,_h2m1p,(_H/_SP)^(2*(_mu+1)),_h2mp,(_H/_SP)^(2*_mu),_A1p,_Kdr*NORM.S.DIST(_sqT-_x1p,1)-_Sbdp*NORM.S.DIST(-_x1p,1),_A2p,_Kdr*NORM.S.DIST(_sqT-_x2p,1)-_Sbdp*NORM.S.DIST(-_x2p,1),_A3p,_Kdr*_h2mp*NORM.S.DIST(_y1p-_sqT,1)-_Sbdp*_h2m1p*NORM.S.DIST(_y1p,1),_A4p,_Kdr*_h2mp*NORM.S.DIST(_y2p-_sqT,1)-_Sbdp*_h2m1p*NORM.S.DIST(_y2p,1),_cfp,_Sbdp*NORM.S.DIST(-_x1p,1)+_Kdr*NORM.S.DIST(_x1p-_sqT,1),_pp,IF(_SP<=_H,_cfp,(_A1p-_A2p+_A3p-_A4p)+_cfp),_SM,_S*(1-_ds),_Sbdm,_SM*EXP(-_q*_T),_x1m,LN(_SM/_K)/_sqT+(1+_mu)*_sqT,_x2m,LN(_SM/_H)/_sqT+(1+_mu)*_sqT,_y1m,LN(_H^2/(_SM*_K))/_sqT+(1+_mu)*_sqT,_y2m,LN(_H/_SM)/_sqT+(1+_mu)*_sqT,_h2m1m,(_H/_SM)^(2*(_mu+1)),_h2mm,(_H/_SM)^(2*_mu),_A1m,_Kdr*NORM.S.DIST(_sqT-_x1m,1)-_Sbdm*NORM.S.DIST(-_x1m,1),_A2m,_Kdr*NORM.S.DIST(_sqT-_x2m,1)-_Sbdm*NORM.S.DIST(-_x2m,1),_A3m,_Kdr*_h2mm*NORM.S.DIST(_y1m-_sqT,1)-_Sbdm*_h2m1m*NORM.S.DIST(_y1m,1),_A4m,_Kdr*_h2mm*NORM.S.DIST(_y2m-_sqT,1)-_Sbdm*_h2m1m*NORM.S.DIST(_y2m,1),_cfm,_Sbdm*NORM.S.DIST(-_x1m,1)+_Kdr*NORM.S.DIST(_x1m-_sqT,1),_pm,IF(_SM<=_H,_cfm,(_A1m-_A2m+_A3m-_A4m)+_cfm),(_pp-_pm)/(2*_ds*_S)) | H8: =G8*B8 | I8: =F8-H8 | J8: =IF(F8>0,H8/F8,0)
A9: =Data_Stock!A9 | B9: =Data_Stock!B9 | C9: =Data_Stock!C9 | D9: =Data_Svensson!H9 | E9: =Data_Svensson!I9 | F9: =LET(_S,B9,_sig,C9,_T,D9,_r,E9,_K,Cap,_H,Barrier,_q,q,_b,_r-_q,_sqT,_sig*SQRT(_T),_mu,(_b-0.5*_sig^2)/_sig^2,_x1,LN(_S/_K)/_sqT+(1+_mu)*_sqT,_x2,LN(_S/_H)/_sqT+(1+_mu)*_sqT,_y1,LN(_H^2/(_S*_K))/_sqT+(1+_mu)*_sqT,_y2,LN(_H/_S)/_sqT+(1+_mu)*_sqT,_Sbd,_S*EXP(-_q*_T),_Kdr,_K*EXP(-_r*_T),_h2m1,(_H/_S)^(2*(_mu+1)),_h2m,(_H/_S)^(2*_mu),_A1,_Kdr*NORM.S.DIST(_sqT-_x1,1)-_Sbd*NORM.S.DIST(-_x1,1),_A2,_Kdr*NORM.S.DIST(_sqT-_x2,1)-_Sbd*NORM.S.DIST(-_x2,1),_A3,_Kdr*_h2m*NORM.S.DIST(_y1-_sqT,1)-_Sbd*_h2m1*NORM.S.DIST(_y1,1),_A4,_Kdr*_h2m*NORM.S.DIST(_y2-_sqT,1)-_Sbd*_h2m1*NORM.S.DIST(_y2,1),_do,IF(_S<=_H,0,_A1-_A2+_A3-_A4),_cf,_Sbd*NORM.S.DIST(-_x1,1)+_Kdr*NORM.S.DIST(_x1-_sqT,1),IF(_S<=_H,_cf,_do+_cf)) | G9: =LET(_S,B9,_sig,C9,_T,D9,_r,E9,_K,Cap,_H,Barrier,_q,q,_ds,dS,_b,_r-_q,_sqT,_sig*SQRT(_T),_mu,(_b-0.5*_sig^2)/_sig^2,_Kdr,_K*EXP(-_r*_T),_SP,_S*(1+_ds),_Sbdp,_SP*EXP(-_q*_T),_x1p,LN(_SP/_K)/_sqT+(1+_mu)*_sqT,_x2p,LN(_SP/_H)/_sqT+(1+_mu)*_sqT,_y1p,LN(_H^2/(_SP*_K))/_sqT+(1+_mu)*_sqT,_y2p,LN(_H/_SP)/_sqT+(1+_mu)*_sqT,_h2m1p,(_H/_SP)^(2*(_mu+1)),_h2mp,(_H/_SP)^(2*_mu),_A1p,_Kdr*NORM.S.DIST(_sqT-_x1p,1)-_Sbdp*NORM.S.DIST(-_x1p,1),_A2p,_Kdr*NORM.S.DIST(_sqT-_x2p,1)-_Sbdp*NORM.S.DIST(-_x2p,1),_A3p,_Kdr*_h2mp*NORM.S.DIST(_y1p-_sqT,1)-_Sbdp*_h2m1p*NORM.S.DIST(_y1p,1),_A4p,_Kdr*_h2mp*NORM.S.DIST(_y2p-_sqT,1)-_Sbdp*_h2m1p*NORM.S.DIST(_y2p,1),_cfp,_Sbdp*NORM.S.DIST(-_x1p,1)+_Kdr*NORM.S.DIST(_x1p-_sqT,1),_pp,IF(_SP<=_H,_cfp,(_A1p-_A2p+_A3p-_A4p)+_cfp),_SM,_S*(1-_ds),_Sbdm,_SM*EXP(-_q*_T),_x1m,LN(_SM/_K)/_sqT+(1+_mu)*_sqT,_x2m,LN(_SM/_H)/_sqT+(1+_mu)*_sqT,_y1m,LN(_H^2/(_SM*_K))/_sqT+(1+_mu)*_sqT,_y2m,LN(_H/_SM)/_sqT+(1+_mu)*_sqT,_h2m1m,(_H/_SM)^(2*(_mu+1)),_h2mm,(_H/_SM)^(2*_mu),_A1m,_Kdr*NORM.S.DIST(_sqT-_x1m,1)-_Sbdm*NORM.S.DIST(-_x1m,1),_A2m,_Kdr*NORM.S.DIST(_sqT-_x2m,1)-_Sbdm*NORM.S.DIST(-_x2m,1),_A3m,_Kdr*_h2mm*NORM.S.DIST(_y1m-_sqT,1)-_Sbdm*_h2m1m*NORM.S.DIST(_y1m,1),_A4m,_Kdr*_h2mm*NORM.S.DIST(_y2m-_sqT,1)-_Sbdm*_h2m1m*NORM.S.DIST(_y2m,1),_cfm,_Sbdm*NORM.S.DIST(-_x1m,1)+_Kdr*NORM.S.DIST(_x1m-_sqT,1),_pm,IF(_SM<=_H,_cfm,(_A1m-_A2m+_A3m-_A4m)+_cfm),(_pp-_pm)/(2*_ds*_S)) | H9: =G9*B9 | I9: =F9-H9 | J9: =IF(F9>0,H9/F9,0)
A10: =Data_Stock!A10 | B10: =Data_Stock!B10 | C10: =Data_Stock!C10 | D10: =Data_Svensson!H10 | E10: =Data_Svensson!I10 | F10: =LET(_S,B10,_sig,C10,_T,D10,_r,E10,_K,Cap,_H,Barrier,_q,q,_b,_r-_q,_sqT,_sig*SQRT(_T),_mu,(_b-0.5*_sig^2)/_sig^2,_x1,LN(_S/_K)/_sqT+(1+_mu)*_sqT,_x2,LN(_S/_H)/_sqT+(1+_mu)*_sqT,_y1,LN(_H^2/(_S*_K))/_sqT+(1+_mu)*_sqT,_y2,LN(_H/_S)/_sqT+(1+_mu)*_sqT,_Sbd,_S*EXP(-_q*_T),_Kdr,_K*EXP(-_r*_T),_h2m1,(_H/_S)^(2*(_mu+1)),_h2m,(_H/_S)^(2*_mu),_A1,_Kdr*NORM.S.DIST(_sqT-_x1,1)-_Sbd*NORM.S.DIST(-_x1,1),_A2,_Kdr*NORM.S.DIST(_sqT-_x2,1)-_Sbd*NORM.S.DIST(-_x2,1),_A3,_Kdr*_h2m*NORM.S.DIST(_y1-_sqT,1)-_Sbd*_h2m1*NORM.S.DIST(_y1,1),_A4,_Kdr*_h2m*NORM.S.DIST(_y2-_sqT,1)-_Sbd*_h2m1*NORM.S.DIST(_y2,1),_do,IF(_S<=_H,0,_A1-_A2+_A3-_A4),_cf,_Sbd*NORM.S.DIST(-_x1,1)+_Kdr*NORM.S.DIST(_x1-_sqT,1),IF(_S<=_H,_cf,_do+_cf)) | G10: =LET(_S,B10,_sig,C10,_T,D10,_r,E10,_K,Cap,_H,Barrier,_q,q,_ds,dS,_b,_r-_q,_sqT,_sig*SQRT(_T),_mu,(_b-0.5*_sig^2)/_sig^2,_Kdr,_K*EXP(-_r*_T),_SP,_S*(1+_ds),_Sbdp,_SP*EXP(-_q*_T),_x1p,LN(_SP/_K)/_sqT+(1+_mu)*_sqT,_x2p,LN(_SP/_H)/_sqT+(1+_mu)*_sqT,_y1p,LN(_H^2/(_SP*_K))/_sqT+(1+_mu)*_sqT,_y2p,LN(_H/_SP)/_sqT+(1+_mu)*_sqT,_h2m1p,(_H/_SP)^(2*(_mu+1)),_h2mp,(_H/_SP)^(2*_mu),_A1p,_Kdr*NORM.S.DIST(_sqT-_x1p,1)-_Sbdp*NORM.S.DIST(-_x1p,1),_A2p,_Kdr*NORM.S.DIST(_sqT-_x2p,1)-_Sbdp*NORM.S.DIST(-_x2p,1),_A3p,_Kdr*_h2mp*NORM.S.DIST(_y1p-_sqT,1)-_Sbdp*_h2m1p*NORM.S.DIST(_y1p,1),_A4p,_Kdr*_h2mp*NORM.S.DIST(_y2p-_sqT,1)-_Sbdp*_h2m1p*NORM.S.DIST(_y2p,1),_cfp,_Sbdp*NORM.S.DIST(-_x1p,1)+_Kdr*NORM.S.DIST(_x1p-_sqT,1),_pp,IF(_SP<=_H,_cfp,(_A1p-_A2p+_A3p-_A4p)+_cfp),_SM,_S*(1-_ds),_Sbdm,_SM*EXP(-_q*_T),_x1m,LN(_SM/_K)/_sqT+(1+_mu)*_sqT,_x2m,LN(_SM/_H)/_sqT+(1+_mu)*_sqT,_y1m,LN(_H^2/(_SM*_K))/_sqT+(1+_mu)*_sqT,_y2m,LN(_H/_SM)/_sqT+(1+_mu)*_sqT,_h2m1m,(_H/_SM)^(2*(_mu+1)),_h2mm,(_H/_SM)^(2*_mu),_A1m,_Kdr*NORM.S.DIST(_sqT-_x1m,1)-_Sbdm*NORM.S.DIST(-_x1m,1),_A2m,_Kdr*NORM.S.DIST(_sqT-_x2m,1)-_Sbdm*NORM.S.DIST(-_x2m,1),_A3m,_Kdr*_h2mm*NORM.S.DIST(_y1m-_sqT,1)-_Sbdm*_h2m1m*NORM.S.DIST(_y1m,1),_A4m,_Kdr*_h2mm*NORM.S.DIST(_y2m-_sqT,1)-_Sbdm*_h2m1m*NORM.S.DIST(_y2m,1),_cfm,_Sbdm*NORM.S.DIST(-_x1m,1)+_Kdr*NORM.S.DIST(_x1m-_sqT,1),_pm,IF(_SM<=_H,_cfm,(_A1m-_A2m+_A3m-_A4m)+_cfm),(_pp-_pm)/(2*_ds*_S)) | H10: =G10*B10 | I10: =F10-H10 | J10: =IF(F10>0,H10/F10,0)
A11: =Data_Stock!A11 | B11: =Data_Stock!B11 | C11: =Data_Stock!C11 | D11: =Data_Svensson!H11 | E11: =Data_Svensson!I11 | F11: =LET(_S,B11,_sig,C11,_T,D11,_r,E11,_K,Cap,_H,Barrier,_q,q,_b,_r-_q,_sqT,_sig*SQRT(_T),_mu,(_b-0.5*_sig^2)/_sig^2,_x1,LN(_S/_K)/_sqT+(1+_mu)*_sqT,_x2,LN(_S/_H)/_sqT+(1+_mu)*_sqT,_y1,LN(_H^2/(_S*_K))/_sqT+(1+_mu)*_sqT,_y2,LN(_H/_S)/_sqT+(1+_mu)*_sqT,_Sbd,_S*EXP(-_q*_T),_Kdr,_K*EXP(-_r*_T),_h2m1,(_H/_S)^(2*(_mu+1)),_h2m,(_H/_S)^(2*_mu),_A1,_Kdr*NORM.S.DIST(_sqT-_x1,1)-_Sbd*NORM.S.DIST(-_x1,1),_A2,_Kdr*NORM.S.DIST(_sqT-_x2,1)-_Sbd*NORM.S.DIST(-_x2,1),_A3,_Kdr*_h2m*NORM.S.DIST(_y1-_sqT,1)-_Sbd*_h2m1*NORM.S.DIST(_y1,1),_A4,_Kdr*_h2m*NORM.S.DIST(_y2-_sqT,1)-_Sbd*_h2m1*NORM.S.DIST(_y2,1),_do,IF(_S<=_H,0,_A1-_A2+_A3-_A4),_cf,_Sbd*NORM.S.DIST(-_x1,1)+_Kdr*NORM.S.DIST(_x1-_sqT,1),IF(_S<=_H,_cf,_do+_cf)) | G11: =LET(_S,B11,_sig,C11,_T,D11,_r,E11,_K,Cap,_H,Barrier,_q,q,_ds,dS,_b,_r-_q,_sqT,_sig*SQRT(_T),_mu,(_b-0.5*_sig^2)/_sig^2,_Kdr,_K*EXP(-_r*_T),_SP,_S*(1+_ds),_Sbdp,_SP*EXP(-_q*_T),_x1p,LN(_SP/_K)/_sqT+(1+_mu)*_sqT,_x2p,LN(_SP/_H)/_sqT+(1+_mu)*_sqT,_y1p,LN(_H^2/(_SP*_K))/_sqT+(1+_mu)*_sqT,_y2p,LN(_H/_SP)/_sqT+(1+_mu)*_sqT,_h2m1p,(_H/_SP)^(2*(_mu+1)),_h2mp,(_H/_SP)^(2*_mu),_A1p,_Kdr*NORM.S.DIST(_sqT-_x1p,1)-_Sbdp*NORM.S.DIST(-_x1p,1),_A2p,_Kdr*NORM.S.DIST(_sqT-_x2p,1)-_Sbdp*NORM.S.DIST(-_x2p,1),_A3p,_Kdr*_h2mp*NORM.S.DIST(_y1p-_sqT,1)-_Sbdp*_h2m1p*NORM.S.DIST(_y1p,1),_A4p,_Kdr*_h2mp*NORM.S.DIST(_y2p-_sqT,1)-_Sbdp*_h2m1p*NORM.S.DIST(_y2p,1),_cfp,_Sbdp*NORM.S.DIST(-_x1p,1)+_Kdr*NORM.S.DIST(_x1p-_sqT,1),_pp,IF(_SP<=_H,_cfp,(_A1p-_A2p+_A3p-_A4p)+_cfp),_SM,_S*(1-_ds),_Sbdm,_SM*EXP(-_q*_T),_x1m,LN(_SM/_K)/_sqT+(1+_mu)*_sqT,_x2m,LN(_SM/_H)/_sqT+(1+_mu)*_sqT,_y1m,LN(_H^2/(_SM*_K))/_sqT+(1+_mu)*_sqT,_y2m,LN(_H/_SM)/_sqT+(1+_mu)*_sqT,_h2m1m,(_H/_SM)^(2*(_mu+1)),_h2mm,(_H/_SM)^(2*_mu),_A1m,_Kdr*NORM.S.DIST(_sqT-_x1m,1)-_Sbdm*NORM.S.DIST(-_x1m,1),_A2m,_Kdr*NORM.S.DIST(_sqT-_x2m,1)-_Sbdm*NORM.S.DIST(-_x2m,1),_A3m,_Kdr*_h2mm*NORM.S.DIST(_y1m-_sqT,1)-_Sbdm*_h2m1m*NORM.S.DIST(_y1m,1),_A4m,_Kdr*_h2mm*NORM.S.DIST(_y2m-_sqT,1)-_Sbdm*_h2m1m*NORM.S.DIST(_y2m,1),_cfm,_Sbdm*NORM.S.DIST(-_x1m,1)+_Kdr*NORM.S.DIST(_x1m-_sqT,1),_pm,IF(_SM<=_H,_cfm,(_A1m-_A2m+_A3m-_A4m)+_cfm),(_pp-_pm)/(2*_ds*_S)) | H11: =G11*B11 | I11: =F11-H11 | J11: =IF(F11>0,H11/F11,0)
A12: =Data_Stock!A12 | B12: =Data_Stock!B12 | C12: =Data_Stock!C12 | D12: =Data_Svensson!H12 | E12: =Data_Svensson!I12 | F12: =LET(_S,B12,_sig,C12,_T,D12,_r,E12,_K,Cap,_H,Barrier,_q,q,_b,_r-_q,_sqT,_sig*SQRT(_T),_mu,(_b-0.5*_sig^2)/_sig^2,_x1,LN(_S/_K)/_sqT+(1+_mu)*_sqT,_x2,LN(_S/_H)/_sqT+(1+_mu)*_sqT,_y1,LN(_H^2/(_S*_K))/_sqT+(1+_mu)*_sqT,_y2,LN(_H/_S)/_sqT+(1+_mu)*_sqT,_Sbd,_S*EXP(-_q*_T),_Kdr,_K*EXP(-_r*_T),_h2m1,(_H/_S)^(2*(_mu+1)),_h2m,(_H/_S)^(2*_mu),_A1,_Kdr*NORM.S.DIST(_sqT-_x1,1)-_Sbd*NORM.S.DIST(-_x1,1),_A2,_Kdr*NORM.S.DIST(_sqT-_x2,1)-_Sbd*NORM.S.DIST(-_x2,1),_A3,_Kdr*_h2m*NORM.S.DIST(_y1-_sqT,1)-_Sbd*_h2m1*NORM.S.DIST(_y1,1),_A4,_Kdr*_h2m*NORM.S.DIST(_y2-_sqT,1)-_Sbd*_h2m1*NORM.S.DIST(_y2,1),_do,IF(_S<=_H,0,_A1-_A2+_A3-_A4),_cf,_Sbd*NORM.S.DIST(-_x1,1)+_Kdr*NORM.S.DIST(_x1-_sqT,1),IF(_S<=_H,_cf,_do+_cf)) | G12: =LET(_S,B12,_sig,C12,_T,D12,_r,E12,_K,Cap,_H,Barrier,_q,q,_ds,dS,_b,_r-_q,_sqT,_sig*SQRT(_T),_mu,(_b-0.5*_sig^2)/_sig^2,_Kdr,_K*EXP(-_r*_T),_SP,_S*(1+_ds),_Sbdp,_SP*EXP(-_q*_T),_x1p,LN(_SP/_K)/_sqT+(1+_mu)*_sqT,_x2p,LN(_SP/_H)/_sqT+(1+_mu)*_sqT,_y1p,LN(_H^2/(_SP*_K))/_sqT+(1+_mu)*_sqT,_y2p,LN(_H/_SP)/_sqT+(1+_mu)*_sqT,_h2m1p,(_H/_SP)^(2*(_mu+1)),_h2mp,(_H/_SP)^(2*_mu),_A1p,_Kdr*NORM.S.DIST(_sqT-_x1p,1)-_Sbdp*NORM.S.DIST(-_x1p,1),_A2p,_Kdr*NORM.S.DIST(_sqT-_x2p,1)-_Sbdp*NORM.S.DIST(-_x2p,1),_A3p,_Kdr*_h2mp*NORM.S.DIST(_y1p-_sqT,1)-_Sbdp*_h2m1p*NORM.S.DIST(_y1p,1),_A4p,_Kdr*_h2mp*NORM.S.DIST(_y2p-_sqT,1)-_Sbdp*_h2m1p*NORM.S.DIST(_y2p,1),_cfp,_Sbdp*NORM.S.DIST(-_x1p,1)+_Kdr*NORM.S.DIST(_x1p-_sqT,1),_pp,IF(_SP<=_H,_cfp,(_A1p-_A2p+_A3p-_A4p)+_cfp),_SM,_S*(1-_ds),_Sbdm,_SM*EXP(-_q*_T),_x1m,LN(_SM/_K)/_sqT+(1+_mu)*_sqT,_x2m,LN(_SM/_H)/_sqT+(1+_mu)*_sqT,_y1m,LN(_H^2/(_SM*_K))/_sqT+(1+_mu)*_sqT,_y2m,LN(_H/_SM)/_sqT+(1+_mu)*_sqT,_h2m1m,(_H/_SM)^(2*(_mu+1)),_h2mm,(_H/_SM)^(2*_mu),_A1m,_Kdr*NORM.S.DIST(_sqT-_x1m,1)-_Sbdm*NORM.S.DIST(-_x1m,1),_A2m,_Kdr*NORM.S.DIST(_sqT-_x2m,1)-_Sbdm*NORM.S.DIST(-_x2m,1),_A3m,_Kdr*_h2mm*NORM.S.DIST(_y1m-_sqT,1)-_Sbdm*_h2m1m*NORM.S.DIST(_y1m,1),_A4m,_Kdr*_h2mm*NORM.S.DIST(_y2m-_sqT,1)-_Sbdm*_h2m1m*NORM.S.DIST(_y2m,1),_cfm,_Sbdm*NORM.S.DIST(-_x1m,1)+_Kdr*NORM.S.DIST(_x1m-_sqT,1),_pm,IF(_SM<=_H,_cfm,(_A1m-_A2m+_A3m-_A4m)+_cfm),(_pp-_pm)/(2*_ds*_S)) | H12: =G12*B12 | I12: =F12-H12 | J12: =IF(F12>0,H12/F12,0)
A13: =Data_Stock!A13 | B13: =Data_Stock!B13 | C13: =Data_Stock!C13 | D13: =Data_Svensson!H13 | E13: =Data_Svensson!I13 | F13: =LET(_S,B13,_sig,C13,_T,D13,_r,E13,_K,Cap,_H,Barrier,_q,q,_b,_r-_q,_sqT,_sig*SQRT(_T),_mu,(_b-0.5*_sig^2)/_sig^2,_x1,LN(_S/_K)/_sqT+(1+_mu)*_sqT,_x2,LN(_S/_H)/_sqT+(1+_mu)*_sqT,_y1,LN(_H^2/(_S*_K))/_sqT+(1+_mu)*_sqT,_y2,LN(_H/_S)/_sqT+(1+_mu)*_sqT,_Sbd,_S*EXP(-_q*_T),_Kdr,_K*EXP(-_r*_T),_h2m1,(_H/_S)^(2*(_mu+1)),_h2m,(_H/_S)^(2*_mu),_A1,_Kdr*NORM.S.DIST(_sqT-_x1,1)-_Sbd*NORM.S.DIST(-_x1,1),_A2,_Kdr*NORM.S.DIST(_sqT-_x2,1)-_Sbd*NORM.S.DIST(-_x2,1),_A3,_Kdr*_h2m*NORM.S.DIST(_y1-_sqT,1)-_Sbd*_h2m1*NORM.S.DIST(_y1,1),_A4,_Kdr*_h2m*NORM.S.DIST(_y2-_sqT,1)-_Sbd*_h2m1*NORM.S.DIST(_y2,1),_do,IF(_S<=_H,0,_A1-_A2+_A3-_A4),_cf,_Sbd*NORM.S.DIST(-_x1,1)+_Kdr*NORM.S.DIST(_x1-_sqT,1),IF(_S<=_H,_cf,_do+_cf)) | G13: =LET(_S,B13,_sig,C13,_T,D13,_r,E13,_K,Cap,_H,Barrier,_q,q,_ds,dS,_b,_r-_q,_sqT,_sig*SQRT(_T),_mu,(_b-0.5*_sig^2)/_sig^2,_Kdr,_K*EXP(-_r*_T),_SP,_S*(1+_ds),_Sbdp,_SP*EXP(-_q*_T),_x1p,LN(_SP/_K)/_sqT+(1+_mu)*_sqT,_x2p,LN(_SP/_H)/_sqT+(1+_mu)*_sqT,_y1p,LN(_H^2/(_SP*_K))/_sqT+(1+_mu)*_sqT,_y2p,LN(_H/_SP)/_sqT+(1+_mu)*_sqT,_h2m1p,(_H/_SP)^(2*(_mu+1)),_h2mp,(_H/_SP)^(2*_mu),_A1p,_Kdr*NORM.S.DIST(_sqT-_x1p,1)-_Sbdp*NORM.S.DIST(-_x1p,1),_A2p,_Kdr*NORM.S.DIST(_sqT-_x2p,1)-_Sbdp*NORM.S.DIST(-_x2p,1),_A3p,_Kdr*_h2mp*NORM.S.DIST(_y1p-_sqT,1)-_Sbdp*_h2m1p*NORM.S.DIST(_y1p,1),_A4p,_Kdr*_h2mp*NORM.S.DIST(_y2p-_sqT,1)-_Sbdp*_h2m1p*NORM.S.DIST(_y2p,1),_cfp,_Sbdp*NORM.S.DIST(-_x1p,1)+_Kdr*NORM.S.DIST(_x1p-_sqT,1),_pp,IF(_SP<=_H,_cfp,(_A1p-_A2p+_A3p-_A4p)+_cfp),_SM,_S*(1-_ds),_Sbdm,_SM*EXP(-_q*_T),_x1m,LN(_SM/_K)/_sqT+(1+_mu)*_sqT,_x2m,LN(_SM/_H)/_sqT+(1+_mu)*_sqT,_y1m,LN(_H^2/(_SM*_K))/_sqT+(1+_mu)*_sqT,_y2m,LN(_H/_SM)/_sqT+(1+_mu)*_sqT,_h2m1m,(_H/_SM)^(2*(_mu+1)),_h2mm,(_H/_SM)^(2*_mu),_A1m,_Kdr*NORM.S.DIST(_sqT-_x1m,1)-_Sbdm*NORM.S.DIST(-_x1m,1),_A2m,_Kdr*NORM.S.DIST(_sqT-_x2m,1)-_Sbdm*NORM.S.DIST(-_x2m,1),_A3m,_Kdr*_h2mm*NORM.S.DIST(_y1m-_sqT,1)-_Sbdm*_h2m1m*NORM.S.DIST(_y1m,1),_A4m,_Kdr*_h2mm*NORM.S.DIST(_y2m-_sqT,1)-_Sbdm*_h2m1m*NORM.S.DIST(_y2m,1),_cfm,_Sbdm*NORM.S.DIST(-_x1m,1)+_Kdr*NORM.S.DIST(_x1m-_sqT,1),_pm,IF(_SM<=_H,_cfm,(_A1m-_A2m+_A3m-_A4m)+_cfm),(_pp-_pm)/(2*_ds*_S)) | H13: =G13*B13 | I13: =F13-H13 | J13: =IF(F13>0,H13/F13,0)
A14: =Data_Stock!A14 | B14: =Data_Stock!B14 | C14: =Data_Stock!C14 | D14: =Data_Svensson!H14 | E14: =Data_Svensson!I14 | F14: =LET(_S,B14,_sig,C14,_T,D14,_r,E14,_K,Cap,_H,Barrier,_q,q,_b,_r-_q,_sqT,_sig*SQRT(_T),_mu,(_b-0.5*_sig^2)/_sig^2,_x1,LN(_S/_K)/_sqT+(1+_mu)*_sqT,_x2,LN(_S/_H)/_sqT+(1+_mu)*_sqT,_y1,LN(_H^2/(_S*_K))/_sqT+(1+_mu)*_sqT,_y2,LN(_H/_S)/_sqT+(1+_mu)*_sqT,_Sbd,_S*EXP(-_q*_T),_Kdr,_K*EXP(-_r*_T),_h2m1,(_H/_S)^(2*(_mu+1)),_h2m,(_H/_S)^(2*_mu),_A1,_Kdr*NORM.S.DIST(_sqT-_x1,1)-_Sbd*NORM.S.DIST(-_x1,1),_A2,_Kdr*NORM.S.DIST(_sqT-_x2,1)-_Sbd*NORM.S.DIST(-_x2,1),_A3,_Kdr*_h2m*NORM.S.DIST(_y1-_sqT,1)-_Sbd*_h2m1*NORM.S.DIST(_y1,1),_A4,_Kdr*_h2m*NORM.S.DIST(_y2-_sqT,1)-_Sbd*_h2m1*NORM.S.DIST(_y2,1),_do,IF(_S<=_H,0,_A1-_A2+_A3-_A4),_cf,_Sbd*NORM.S.DIST(-_x1,1)+_Kdr*NORM.S.DIST(_x1-_sqT,1),IF(_S<=_H,_cf,_do+_cf)) | G14: =LET(_S,B14,_sig,C14,_T,D14,_r,E14,_K,Cap,_H,Barrier,_q,q,_ds,dS,_b,_r-_q,_sqT,_sig*SQRT(_T),_mu,(_b-0.5*_sig^2)/_sig^2,_Kdr,_K*EXP(-_r*_T),_SP,_S*(1+_ds),_Sbdp,_SP*EXP(-_q*_T),_x1p,LN(_SP/_K)/_sqT+(1+_mu)*_sqT,_x2p,LN(_SP/_H)/_sqT+(1+_mu)*_sqT,_y1p,LN(_H^2/(_SP*_K))/_sqT+(1+_mu)*_sqT,_y2p,LN(_H/_SP)/_sqT+(1+_mu)*_sqT,_h2m1p,(_H/_SP)^(2*(_mu+1)),_h2mp,(_H/_SP)^(2*_mu),_A1p,_Kdr*NORM.S.DIST(_sqT-_x1p,1)-_Sbdp*NORM.S.DIST(-_x1p,1),_A2p,_Kdr*NORM.S.DIST(_sqT-_x2p,1)-_Sbdp*NORM.S.DIST(-_x2p,1),_A3p,_Kdr*_h2mp*NORM.S.DIST(_y1p-_sqT,1)-_Sbdp*_h2m1p*NORM.S.DIST(_y1p,1),_A4p,_Kdr*_h2mp*NORM.S.DIST(_y2p-_sqT,1)-_Sbdp*_h2m1p*NORM.S.DIST(_y2p,1),_cfp,_Sbdp*NORM.S.DIST(-_x1p,1)+_Kdr*NORM.S.DIST(_x1p-_sqT,1),_pp,IF(_SP<=_H,_cfp,(_A1p-_A2p+_A3p-_A4p)+_cfp),_SM,_S*(1-_ds),_Sbdm,_SM*EXP(-_q*_T),_x1m,LN(_SM/_K)/_sqT+(1+_mu)*_sqT,_x2m,LN(_SM/_H)/_sqT+(1+_mu)*_sqT,_y1m,LN(_H^2/(_SM*_K))/_sqT+(1+_mu)*_sqT,_y2m,LN(_H/_SM)/_sqT+(1+_mu)*_sqT,_h2m1m,(_H/_SM)^(2*(_mu+1)),_h2mm,(_H/_SM)^(2*_mu),_A1m,_Kdr*NORM.S.DIST(_sqT-_x1m,1)-_Sbdm*NORM.S.DIST(-_x1m,1),_A2m,_Kdr*NORM.S.DIST(_sqT-_x2m,1)-_Sbdm*NORM.S.DIST(-_x2m,1),_A3m,_Kdr*_h2mm*NORM.S.DIST(_y1m-_sqT,1)-_Sbdm*_h2m1m*NORM.S.DIST(_y1m,1),_A4m,_Kdr*_h2mm*NORM.S.DIST(_y2m-_sqT,1)-_Sbdm*_h2m1m*NORM.S.DIST(_y2m,1),_cfm,_Sbdm*NORM.S.DIST(-_x1m,1)+_Kdr*NORM.S.DIST(_x1m-_sqT,1),_pm,IF(_SM<=_H,_cfm,(_A1m-_A2m+_A3m-_A4m)+_cfm),(_pp-_pm)/(2*_ds*_S)) | H14: =G14*B14 | I14: =F14-H14 | J14: =IF(F14>0,H14/F14,0)
A15: =Data_Stock!A15 | B15: =Data_Stock!B15 | C15: =Data_Stock!C15 | D15: =Data_Svensson!H15 | E15: =Data_Svensson!I15 | F15: =LET(_S,B15,_sig,C15,_T,D15,_r,E15,_K,Cap,_H,Barrier,_q,q,_b,_r-_q,_sqT,_sig*SQRT(_T),_mu,(_b-0.5*_sig^2)/_sig^2,_x1,LN(_S/_K)/_sqT+(1+_mu)*_sqT,_x2,LN(_S/_H)/_sqT+(1+_mu)*_sqT,_y1,LN(_H^2/(_S*_K))/_sqT+(1+_mu)*_sqT,_y2,LN(_H/_S)/_sqT+(1+_mu)*_sqT,_Sbd,_S*EXP(-_q*_T),_Kdr,_K*EXP(-_r*_T),_h2m1,(_H/_S)^(2*(_mu+1)),_h2m,(_H/_S)^(2*_mu),_A1,_Kdr*NORM.S.DIST(_sqT-_x1,1)-_Sbd*NORM.S.DIST(-_x1,1),_A2,_Kdr*NORM.S.DIST(_sqT-_x2,1)-_Sbd*NORM.S.DIST(-_x2,1),_A3,_Kdr*_h2m*NORM.S.DIST(_y1-_sqT,1)-_Sbd*_h2m1*NORM.S.DIST(_y1,1),_A4,_Kdr*_h2m*NORM.S.DIST(_y2-_sqT,1)-_Sbd*_h2m1*NORM.S.DIST(_y2,1),_do,IF(_S<=_H,0,_A1-_A2+_A3-_A4),_cf,_Sbd*NORM.S.DIST(-_x1,1)+_Kdr*NORM.S.DIST(_x1-_sqT,1),IF(_S<=_H,_cf,_do+_cf)) | G15: =LET(_S,B15,_sig,C15,_T,D15,_r,E15,_K,Cap,_H,Barrier,_q,q,_ds,dS,_b,_r-_q,_sqT,_sig*SQRT(_T),_mu,(_b-0.5*_sig^2)/_sig^2,_Kdr,_K*EXP(-_r*_T),_SP,_S*(1+_ds),_Sbdp,_SP*EXP(-_q*_T),_x1p,LN(_SP/_K)/_sqT+(1+_mu)*_sqT,_x2p,LN(_SP/_H)/_sqT+(1+_mu)*_sqT,_y1p,LN(_H^2/(_SP*_K))/_sqT+(1+_mu)*_sqT,_y2p,LN(_H/_SP)/_sqT+(1+_mu)*_sqT,_h2m1p,(_H/_SP)^(2*(_mu+1)),_h2mp,(_H/_SP)^(2*_mu),_A1p,_Kdr*NORM.S.DIST(_sqT-_x1p,1)-_Sbdp*NORM.S.DIST(-_x1p,1),_A2p,_Kdr*NORM.S.DIST(_sqT-_x2p,1)-_Sbdp*NORM.S.DIST(-_x2p,1),_A3p,_Kdr*_h2mp*NORM.S.DIST(_y1p-_sqT,1)-_Sbdp*_h2m1p*NORM.S.DIST(_y1p,1),_A4p,_Kdr*_h2mp*NORM.S.DIST(_y2p-_sqT,1)-_Sbdp*_h2m1p*NORM.S.DIST(_y2p,1),_cfp,_Sbdp*NORM.S.DIST(-_x1p,1)+_Kdr*NORM.S.DIST(_x1p-_sqT,1),_pp,IF(_SP<=_H,_cfp,(_A1p-_A2p+_A3p-_A4p)+_cfp),_SM,_S*(1-_ds),_Sbdm,_SM*EXP(-_q*_T),_x1m,LN(_SM/_K)/_sqT+(1+_mu)*_sqT,_x2m,LN(_SM/_H)/_sqT+(1+_mu)*_sqT,_y1m,LN(_H^2/(_SM*_K))/_sqT+(1+_mu)*_sqT,_y2m,LN(_H/_SM)/_sqT+(1+_mu)*_sqT,_h2m1m,(_H/_SM)^(2*(_mu+1)),_h2mm,(_H/_SM)^(2*_mu),_A1m,_Kdr*NORM.S.DIST(_sqT-_x1m,1)-_Sbdm*NORM.S.DIST(-_x1m,1),_A2m,_Kdr*NORM.S.DIST(_sqT-_x2m,1)-_Sbdm*NORM.S.DIST(-_x2m,1),_A3m,_Kdr*_h2mm*NORM.S.DIST(_y1m-_sqT,1)-_Sbdm*_h2m1m*NORM.S.DIST(_y1m,1),_A4m,_Kdr*_h2mm*NORM.S.DIST(_y2m-_sqT,1)-_Sbdm*_h2m1m*NORM.S.DIST(_y2m,1),_cfm,_Sbdm*NORM.S.DIST(-_x1m,1)+_Kdr*NORM.S.DIST(_x1m-_sqT,1),_pm,IF(_SM<=_H,_cfm,(_A1m-_A2m+_A3m-_A4m)+_cfm),(_pp-_pm)/(2*_ds*_S)) | H15: =G15*B15 | I15: =F15-H15 | J15: =IF(F15>0,H15/F15,0)
... A186: =Data_Stock!A186 | B186: =Data_Stock!B186 | C186: =Data_Stock!C186 | D186: =Data_Svensson!H186 | E186: =Data_Svensson!I186 | F186: =LET(_S,B186,_sig,C186,_T,D186,_r,E186,_K,Cap,_H,Barrier,_q,q,_b,_r-_q,_sqT,_sig*SQRT(_T),_mu,(_b-0.5*_sig^2)/_sig^2,_x1,LN(_S/_K)/_sqT+(1+_mu)*_sqT,_x2,LN(_S/_H)/_sqT+(1+_mu)*_sqT,_y1,LN(_H^2/(_S*_K))/_sqT+(1+_mu)*_sqT,_y2,LN(_H/_S)/_sqT+(1+_mu)*_sqT,_Sbd,_S*EXP(-_q*_T),_Kdr,_K*EXP(-_r*_T),_h2m1,(_H/_S)^(2*(_mu+1)),_h2m,(_H/_S)^(2*_mu),_A1,_Kdr*NORM.S.DIST(_sqT-_x1,1)-_Sbd*NORM.S.DIST(-_x1,1),_A2,_Kdr*NORM.S.DIST(_sqT-_x2,1)-_Sbd*NORM.S.DIST(-_x2,1),_A3,_Kdr*_h2m*NORM.S.DIST(_y1-_sqT,1)-_Sbd*_h2m1*NORM.S.DIST(_y1,1),_A4,_Kdr*_h2m*NORM.S.DIST(_y2-_sqT,1)-_Sbd*_h2m1*NORM.S.DIST(_y2,1),_do,IF(_S<=_H,0,_A1-_A2+_A3-_A4),_cf,_Sbd*NORM.S.DIST(-_x1,1)+_Kdr*NORM.S.DIST(_x1-_sqT,1),IF(_S<=_H,_cf,_do+_cf)) | G186: =LET(_S,B186,_sig,C186,_T,D186,_r,E186,_K,Cap,_H,Barrier,_q,q,_ds,dS,_b,_r-_q,_sqT,_sig*SQRT(_T),_mu,(_b-0.5*_sig^2)/_sig^2,_Kdr,_K*EXP(-_r*_T),_SP,_S*(1+_ds),_Sbdp,_SP*EXP(-_q*_T),_x1p,LN(_SP/_K)/_sqT+(1+_mu)*_sqT,_x2p,LN(_SP/_H)/_sqT+(1+_mu)*_sqT,_y1p,LN(_H^2/(_SP*_K))/_sqT+(1+_mu)*_sqT,_y2p,LN(_H/_SP)/_sqT+(1+_mu)*_sqT,_h2m1p,(_H/_SP)^(2*(_mu+1)),_h2mp,(_H/_SP)^(2*_mu),_A1p,_Kdr*NORM.S.DIST(_sqT-_x1p,1)-_Sbdp*NORM.S.DIST(-_x1p,1),_A2p,_Kdr*NORM.S.DIST(_sqT-_x2p,1)-_Sbdp*NORM.S.DIST(-_x2p,1),_A3p,_Kdr*_h2mp*NORM.S.DIST(_y1p-_sqT,1)-_Sbdp*_h2m1p*NORM.S.DIST(_y1p,1),_A4p,_Kdr*_h2mp*NORM.S.DIST(_y2p-_sqT,1)-_Sbdp*_h2m1p*NORM.S.DIST(_y2p,1),_cfp,_Sbdp*NORM.S.DIST(-_x1p,1)+_Kdr*NORM.S.DIST(_x1p-_sqT,1),_pp,IF(_SP<=_H,_cfp,(_A1p-_A2p+_A3p-_A4p)+_cfp),_SM,_S*(1-_ds),_Sbdm,_SM*EXP(-_q*_T),_x1m,LN(_SM/_K)/_sqT+(1+_mu)*_sqT,_x2m,LN(_SM/_H)/_sqT+(1+_mu)*_sqT,_y1m,LN(_H^2/(_SM*_K))/_sqT+(1+_mu)*_sqT,_y2m,LN(_H/_SM)/_sqT+(1+_mu)*_sqT,_h2m1m,(_H/_SM)^(2*(_mu+1)),_h2mm,(_H/_SM)^(2*_mu),_A1m,_Kdr*NORM.S.DIST(_sqT-_x1m,1)-_Sbdm*NORM.S.DIST(-_x1m,1),_A2m,_Kdr*NORM.S.DIST(_sqT-_x2m,1)-_Sbdm*NORM.S.DIST(-_x2m,1),_A3m,_Kdr*_h2mm*NORM.S.DIST(_y1m-_sqT,1)-_Sbdm*_h2m1m*NORM.S.DIST(_y1m,1),_A4m,_Kdr*_h2mm*NORM.S.DIST(_y2m-_sqT,1)-_Sbdm*_h2m1m*NORM.S.DIST(_y2m,1),_cfm,_Sbdm*NORM.S.DIST(-_x1m,1)+_Kdr*NORM.S.DIST(_x1m-_sqT,1),_pm,IF(_SM<=_H,_cfm,(_A1m-_A2m+_A3m-_A4m)+_cfm),(_pp-_pm)/(2*_ds*_S)) | H186: =G186*B186 | I186: =F186-H186 | J186: =IF(F186>0,H186/F186,0)
A189: Summary statistics (live formulas)
A190: Metric | B190: Value
A191: Mean Delta | B191: =AVERAGE(G4:G186)
A192: Mean Equity Fraction | B192: =AVERAGE(J4:J186)
A193: Mean Price (EUR) | B193: =AVERAGE(F4:F186)
A194: Min Eq Fraction | B194: =MIN(J4:J186)
A195: Max Eq Fraction | B195: =MAX(J4:J186)
A198: Equity fraction vs S cross-section (50 values, live RR formulas)
A199: S (EUR) | B199: Price (RR) | C199: Delta (RR) | D199: Eq Fraction | E199: Note: sig, T, r taken from P2_TaskVI_Greeks reference-point inputs (B4, B5, B6)
A200: 525 | B200: =LET(_S,A200,_sig,$P2_TaskVI_Greeks.$B$4,_T,$P2_TaskVI_Greeks.$B$5,_r,$P2_TaskVI_Greeks.$B$6,_K,Cap,_H,Barrier,_q,q,_b,_r-_q,_sqT,_sig*SQRT(_T),_mu,(_b-0.5*_sig^2)/_sig^2,_x1,LN(_S/_K)/_sqT+(1+_mu)*_sqT,_x2,LN(_S/_H)/_sqT+(1+_mu)*_sqT,_y1,LN(_H^2/(_S*_K))/_sqT+(1+_mu)*_sqT,_y2,LN(_H/_S)/_sqT+(1+_mu)*_sqT,_Sbd,_S*EXP(-_q*_T),_Kdr,_K*EXP(-_r*_T),_h2m1,(_H/_S)^(2*(_mu+1)),_h2m,(_H/_S)^(2*_mu),_A1,_Kdr*NORM.S.DIST(_sqT-_x1,1)-_Sbd*NORM.S.DIST(-_x1,1),_A2,_Kdr*NORM.S.DIST(_sqT-_x2,1)-_Sbd*NORM.S.DIST(-_x2,1),_A3,_Kdr*_h2m*NORM.S.DIST(_y1-_sqT,1)-_Sbd*_h2m1*NORM.S.DIST(_y1,1),_A4,_Kdr*_h2m*NORM.S.DIST(_y2-_sqT,1)-_Sbd*_h2m1*NORM.S.DIST(_y2,1),_do,IF(_S<=_H,0,_A1-_A2+_A3-_A4),_cf,_Sbd*NORM.S.DIST(-_x1,1)+_Kdr*NORM.S.DIST(_x1-_sqT,1),IF(_S<=_H,_cf,_do+_cf)) | C200: =LET(_S,A200,_sig,$P2_TaskVI_Greeks.$B$4,_T,$P2_TaskVI_Greeks.$B$5,_r,$P2_TaskVI_Greeks.$B$6,_K,Cap,_H,Barrier,_q,q,_ds,dS,_b,_r-_q,_sqT,_sig*SQRT(_T),_mu,(_b-0.5*_sig^2)/_sig^2,_Kdr,_K*EXP(-_r*_T),_SP,_S*(1+_ds),_Sbdp,_SP*EXP(-_q*_T),_x1p,LN(_SP/_K)/_sqT+(1+_mu)*_sqT,_x2p,LN(_SP/_H)/_sqT+(1+_mu)*_sqT,_y1p,LN(_H^2/(_SP*_K))/_sqT+(1+_mu)*_sqT,_y2p,LN(_H/_SP)/_sqT+(1+_mu)*_sqT,_h2m1p,(_H/_SP)^(2*(_mu+1)),_h2mp,(_H/_SP)^(2*_mu),_A1p,_Kdr*NORM.S.DIST(_sqT-_x1p,1)-_Sbdp*NORM.S.DIST(-_x1p,1),_A2p,_Kdr*NORM.S.DIST(_sqT-_x2p,1)-_Sbdp*NORM.S.DIST(-_x2p,1),_A3p,_Kdr*_h2mp*NORM.S.DIST(_y1p-_sqT,1)-_Sbdp*_h2m1p*NORM.S.DIST(_y1p,1),_A4p,_Kdr*_h2mp*NORM.S.DIST(_y2p-_sqT,1)-_Sbdp*_h2m1p*NORM.S.DIST(_y2p,1),_cfp,_Sbdp*NORM.S.DIST(-_x1p,1)+_Kdr*NORM.S.DIST(_x1p-_sqT,1),_pp,IF(_SP<=_H,_cfp,(_A1p-_A2p+_A3p-_A4p)+_cfp),_SM,_S*(1-_ds),_Sbdm,_SM*EXP(-_q*_T),_x1m,LN(_SM/_K)/_sqT+(1+_mu)*_sqT,_x2m,LN(_SM/_H)/_sqT+(1+_mu)*_sqT,_y1m,LN(_H^2/(_SM*_K))/_sqT+(1+_mu)*_sqT,_y2m,LN(_H/_SM)/_sqT+(1+_mu)*_sqT,_h2m1m,(_H/_SM)^(2*(_mu+1)),_h2mm,(_H/_SM)^(2*_mu),_A1m,_Kdr*NORM.S.DIST(_sqT-_x1m,1)-_Sbdm*NORM.S.DIST(-_x1m,1),_A2m,_Kdr*NORM.S.DIST(_sqT-_x2m,1)-_Sbdm*NORM.S.DIST(-_x2m,1),_A3m,_Kdr*_h2mm*NORM.S.DIST(_y1m-_sqT,1)-_Sbdm*_h2m1m*NORM.S.DIST(_y1m,1),_A4m,_Kdr*_h2mm*NORM.S.DIST(_y2m-_sqT,1)-_Sbdm*_h2m1m*NORM.S.DIST(_y2m,1),_cfm,_Sbdm*NORM.S.DIST(-_x1m,1)+_Kdr*NORM.S.DIST(_x1m-_sqT,1),_pm,IF(_SM<=_H,_cfm,(_A1m-_A2m+_A3m-_A4m)+_cfm),(_pp-_pm)/(2*_ds*_S)) | D200: =IF(B200>0,C200*A200/B200,0)
A201: 579.59 | B201: =LET(_S,A201,_sig,$P2_TaskVI_Greeks.$B$4,_T,$P2_TaskVI_Greeks.$B$5,_r,$P2_TaskVI_Greeks.$B$6,_K,Cap,_H,Barrier,_q,q,_b,_r-_q,_sqT,_sig*SQRT(_T),_mu,(_b-0.5*_sig^2)/_sig^2,_x1,LN(_S/_K)/_sqT+(1+_mu)*_sqT,_x2,LN(_S/_H)/_sqT+(1+_mu)*_sqT,_y1,LN(_H^2/(_S*_K))/_sqT+(1+_mu)*_sqT,_y2,LN(_H/_S)/_sqT+(1+_mu)*_sqT,_Sbd,_S*EXP(-_q*_T),_Kdr,_K*EXP(-_r*_T),_h2m1,(_H/_S)^(2*(_mu+1)),_h2m,(_H/_S)^(2*_mu),_A1,_Kdr*NORM.S.DIST(_sqT-_x1,1)-_Sbd*NORM.S.DIST(-_x1,1),_A2,_Kdr*NORM.S.DIST(_sqT-_x2,1)-_Sbd*NORM.S.DIST(-_x2,1),_A3,_Kdr*_h2m*NORM.S.DIST(_y1-_sqT,1)-_Sbd*_h2m1*NORM.S.DIST(_y1,1),_A4,_Kdr*_h2m*NORM.S.DIST(_y2-_sqT,1)-_Sbd*_h2m1*NORM.S.DIST(_y2,1),_do,IF(_S<=_H,0,_A1-_A2+_A3-_A4),_cf,_Sbd*NORM.S.DIST(-_x1,1)+_Kdr*NORM.S.DIST(_x1-_sqT,1),IF(_S<=_H,_cf,_do+_cf)) | C201: =LET(_S,A201,_sig,$P2_TaskVI_Greeks.$B$4,_T,$P2_TaskVI_Greeks.$B$5,_r,$P2_TaskVI_Greeks.$B$6,_K,Cap,_H,Barrier,_q,q,_ds,dS,_b,_r-_q,_sqT,_sig*SQRT(_T),_mu,(_b-0.5*_sig^2)/_sig^2,_Kdr,_K*EXP(-_r*_T),_SP,_S*(1+_ds),_Sbdp,_SP*EXP(-_q*_T),_x1p,LN(_SP/_K)/_sqT+(1+_mu)*_sqT,_x2p,LN(_SP/_H)/_sqT+(1+_mu)*_sqT,_y1p,LN(_H^2/(_SP*_K))/_sqT+(1+_mu)*_sqT,_y2p,LN(_H/_SP)/_sqT+(1+_mu)*_sqT,_h2m1p,(_H/_SP)^(2*(_mu+1)),_h2mp,(_H/_SP)^(2*_mu),_A1p,_Kdr*NORM.S.DIST(_sqT-_x1p,1)-_Sbdp*NORM.S.DIST(-_x1p,1),_A2p,_Kdr*NORM.S.DIST(_sqT-_x2p,1)-_Sbdp*NORM.S.DIST(-_x2p,1),_A3p,_Kdr*_h2mp*NORM.S.DIST(_y1p-_sqT,1)-_Sbdp*_h2m1p*NORM.S.DIST(_y1p,1),_A4p,_Kdr*_h2mp*NORM.S.DIST(_y2p-_sqT,1)-_Sbdp*_h2m1p*NORM.S.DIST(_y2p,1),_cfp,_Sbdp*NORM.S.DIST(-_x1p,1)+_Kdr*NORM.S.DIST(_x1p-_sqT,1),_pp,IF(_SP<=_H,_cfp,(_A1p-_A2p+_A3p-_A4p)+_cfp),_SM,_S*(1-_ds),_Sbdm,_SM*EXP(-_q*_T),_x1m,LN(_SM/_K)/_sqT+(1+_mu)*_sqT,_x2m,LN(_SM/_H)/_sqT+(1+_mu)*_sqT,_y1m,LN(_H^2/(_SM*_K))/_sqT+(1+_mu)*_sqT,_y2m,LN(_H/_SM)/_sqT+(1+_mu)*_sqT,_h2m1m,(_H/_SM)^(2*(_mu+1)),_h2mm,(_H/_SM)^(2*_mu),_A1m,_Kdr*NORM.S.DIST(_sqT-_x1m,1)-_Sbdm*NORM.S.DIST(-_x1m,1),_A2m,_Kdr*NORM.S.DIST(_sqT-_x2m,1)-_Sbdm*NORM.S.DIST(-_x2m,1),_A3m,_Kdr*_h2mm*NORM.S.DIST(_y1m-_sqT,1)-_Sbdm*_h2m1m*NORM.S.DIST(_y1m,1),_A4m,_Kdr*_h2mm*NORM.S.DIST(_y2m-_sqT,1)-_Sbdm*_h2m1m*NORM.S.DIST(_y2m,1),_cfm,_Sbdm*NORM.S.DIST(-_x1m,1)+_Kdr*NORM.S.DIST(_x1m-_sqT,1),_pm,IF(_SM<=_H,_cfm,(_A1m-_A2m+_A3m-_A4m)+_cfm),(_pp-_pm)/(2*_ds*_S)) | D201: =IF(B201>0,C201*A201/B201,0)
A202: 634.18 | B202: =LET(_S,A202,_sig,$P2_TaskVI_Greeks.$B$4,_T,$P2_TaskVI_Greeks.$B$5,_r,$P2_TaskVI_Greeks.$B$6,_K,Cap,_H,Barrier,_q,q,_b,_r-_q,_sqT,_sig*SQRT(_T),_mu,(_b-0.5*_sig^2)/_sig^2,_x1,LN(_S/_K)/_sqT+(1+_mu)*_sqT,_x2,LN(_S/_H)/_sqT+(1+_mu)*_sqT,_y1,LN(_H^2/(_S*_K))/_sqT+(1+_mu)*_sqT,_y2,LN(_H/_S)/_sqT+(1+_mu)*_sqT,_Sbd,_S*EXP(-_q*_T),_Kdr,_K*EXP(-_r*_T),_h2m1,(_H/_S)^(2*(_mu+1)),_h2m,(_H/_S)^(2*_mu),_A1,_Kdr*NORM.S.DIST(_sqT-_x1,1)-_Sbd*NORM.S.DIST(-_x1,1),_A2,_Kdr*NORM.S.DIST(_sqT-_x2,1)-_Sbd*NORM.S.DIST(-_x2,1),_A3,_Kdr*_h2m*NORM.S.DIST(_y1-_sqT,1)-_Sbd*_h2m1*NORM.S.DIST(_y1,1),_A4,_Kdr*_h2m*NORM.S.DIST(_y2-_sqT,1)-_Sbd*_h2m1*NORM.S.DIST(_y2,1),_do,IF(_S<=_H,0,_A1-_A2+_A3-_A4),_cf,_Sbd*NORM.S.DIST(-_x1,1)+_Kdr*NORM.S.DIST(_x1-_sqT,1),IF(_S<=_H,_cf,_do+_cf)) | C202: =LET(_S,A202,_sig,$P2_TaskVI_Greeks.$B$4,_T,$P2_TaskVI_Greeks.$B$5,_r,$P2_TaskVI_Greeks.$B$6,_K,Cap,_H,Barrier,_q,q,_ds,dS,_b,_r-_q,_sqT,_sig*SQRT(_T),_mu,(_b-0.5*_sig^2)/_sig^2,_Kdr,_K*EXP(-_r*_T),_SP,_S*(1+_ds),_Sbdp,_SP*EXP(-_q*_T),_x1p,LN(_SP/_K)/_sqT+(1+_mu)*_sqT,_x2p,LN(_SP/_H)/_sqT+(1+_mu)*_sqT,_y1p,LN(_H^2/(_SP*_K))/_sqT+(1+_mu)*_sqT,_y2p,LN(_H/_SP)/_sqT+(1+_mu)*_sqT,_h2m1p,(_H/_SP)^(2*(_mu+1)),_h2mp,(_H/_SP)^(2*_mu),_A1p,_Kdr*NORM.S.DIST(_sqT-_x1p,1)-_Sbdp*NORM.S.DIST(-_x1p,1),_A2p,_Kdr*NORM.S.DIST(_sqT-_x2p,1)-_Sbdp*NORM.S.DIST(-_x2p,1),_A3p,_Kdr*_h2mp*NORM.S.DIST(_y1p-_sqT,1)-_Sbdp*_h2m1p*NORM.S.DIST(_y1p,1),_A4p,_Kdr*_h2mp*NORM.S.DIST(_y2p-_sqT,1)-_Sbdp*_h2m1p*NORM.S.DIST(_y2p,1),_cfp,_Sbdp*NORM.S.DIST(-_x1p,1)+_Kdr*NORM.S.DIST(_x1p-_sqT,1),_pp,IF(_SP<=_H,_cfp,(_A1p-_A2p+_A3p-_A4p)+_cfp),_SM,_S*(1-_ds),_Sbdm,_SM*EXP(-_q*_T),_x1m,LN(_SM/_K)/_sqT+(1+_mu)*_sqT,_x2m,LN(_SM/_H)/_sqT+(1+_mu)*_sqT,_y1m,LN(_H^2/(_SM*_K))/_sqT+(1+_mu)*_sqT,_y2m,LN(_H/_SM)/_sqT+(1+_mu)*_sqT,_h2m1m,(_H/_SM)^(2*(_mu+1)),_h2mm,(_H/_SM)^(2*_mu),_A1m,_Kdr*NORM.S.DIST(_sqT-_x1m,1)-_Sbdm*NORM.S.DIST(-_x1m,1),_A2m,_Kdr*NORM.S.DIST(_sqT-_x2m,1)-_Sbdm*NORM.S.DIST(-_x2m,1),_A3m,_Kdr*_h2mm*NORM.S.DIST(_y1m-_sqT,1)-_Sbdm*_h2m1m*NORM.S.DIST(_y1m,1),_A4m,_Kdr*_h2mm*NORM.S.DIST(_y2m-_sqT,1)-_Sbdm*_h2m1m*NORM.S.DIST(_y2m,1),_cfm,_Sbdm*NORM.S.DIST(-_x1m,1)+_Kdr*NORM.S.DIST(_x1m-_sqT,1),_pm,IF(_SM<=_H,_cfm,(_A1m-_A2m+_A3m-_A4m)+_cfm),(_pp-_pm)/(2*_ds*_S)) | D202: =IF(B202>0,C202*A202/B202,0)
A203: 688.78 | B203: =LET(_S,A203,_sig,$P2_TaskVI_Greeks.$B$4,_T,$P2_TaskVI_Greeks.$B$5,_r,$P2_TaskVI_Greeks.$B$6,_K,Cap,_H,Barrier,_q,q,_b,_r-_q,_sqT,_sig*SQRT(_T),_mu,(_b-0.5*_sig^2)/_sig^2,_x1,LN(_S/_K)/_sqT+(1+_mu)*_sqT,_x2,LN(_S/_H)/_sqT+(1+_mu)*_sqT,_y1,LN(_H^2/(_S*_K))/_sqT+(1+_mu)*_sqT,_y2,LN(_H/_S)/_sqT+(1+_mu)*_sqT,_Sbd,_S*EXP(-_q*_T),_Kdr,_K*EXP(-_r*_T),_h2m1,(_H/_S)^(2*(_mu+1)),_h2m,(_H/_S)^(2*_mu),_A1,_Kdr*NORM.S.DIST(_sqT-_x1,1)-_Sbd*NORM.S.DIST(-_x1,1),_A2,_Kdr*NORM.S.DIST(_sqT-_x2,1)-_Sbd*NORM.S.DIST(-_x2,1),_A3,_Kdr*_h2m*NORM.S.DIST(_y1-_sqT,1)-_Sbd*_h2m1*NORM.S.DIST(_y1,1),_A4,_Kdr*_h2m*NORM.S.DIST(_y2-_sqT,1)-_Sbd*_h2m1*NORM.S.DIST(_y2,1),_do,IF(_S<=_H,0,_A1-_A2+_A3-_A4),_cf,_Sbd*NORM.S.DIST(-_x1,1)+_Kdr*NORM.S.DIST(_x1-_sqT,1),IF(_S<=_H,_cf,_do+_cf)) | C203: =LET(_S,A203,_sig,$P2_TaskVI_Greeks.$B$4,_T,$P2_TaskVI_Greeks.$B$5,_r,$P2_TaskVI_Greeks.$B$6,_K,Cap,_H,Barrier,_q,q,_ds,dS,_b,_r-_q,_sqT,_sig*SQRT(_T),_mu,(_b-0.5*_sig^2)/_sig^2,_Kdr,_K*EXP(-_r*_T),_SP,_S*(1+_ds),_Sbdp,_SP*EXP(-_q*_T),_x1p,LN(_SP/_K)/_sqT+(1+_mu)*_sqT,_x2p,LN(_SP/_H)/_sqT+(1+_mu)*_sqT,_y1p,LN(_H^2/(_SP*_K))/_sqT+(1+_mu)*_sqT,_y2p,LN(_H/_SP)/_sqT+(1+_mu)*_sqT,_h2m1p,(_H/_SP)^(2*(_mu+1)),_h2mp,(_H/_SP)^(2*_mu),_A1p,_Kdr*NORM.S.DIST(_sqT-_x1p,1)-_Sbdp*NORM.S.DIST(-_x1p,1),_A2p,_Kdr*NORM.S.DIST(_sqT-_x2p,1)-_Sbdp*NORM.S.DIST(-_x2p,1),_A3p,_Kdr*_h2mp*NORM.S.DIST(_y1p-_sqT,1)-_Sbdp*_h2m1p*NORM.S.DIST(_y1p,1),_A4p,_Kdr*_h2mp*NORM.S.DIST(_y2p-_sqT,1)-_Sbdp*_h2m1p*NORM.S.DIST(_y2p,1),_cfp,_Sbdp*NORM.S.DIST(-_x1p,1)+_Kdr*NORM.S.DIST(_x1p-_sqT,1),_pp,IF(_SP<=_H,_cfp,(_A1p-_A2p+_A3p-_A4p)+_cfp),_SM,_S*(1-_ds),_Sbdm,_SM*EXP(-_q*_T),_x1m,LN(_SM/_K)/_sqT+(1+_mu)*_sqT,_x2m,LN(_SM/_H)/_sqT+(1+_mu)*_sqT,_y1m,LN(_H^2/(_SM*_K))/_sqT+(1+_mu)*_sqT,_y2m,LN(_H/_SM)/_sqT+(1+_mu)*_sqT,_h2m1m,(_H/_SM)^(2*(_mu+1)),_h2mm,(_H/_SM)^(2*_mu),_A1m,_Kdr*NORM.S.DIST(_sqT-_x1m,1)-_Sbdm*NORM.S.DIST(-_x1m,1),_A2m,_Kdr*NORM.S.DIST(_sqT-_x2m,1)-_Sbdm*NORM.S.DIST(-_x2m,1),_A3m,_Kdr*_h2mm*NORM.S.DIST(_y1m-_sqT,1)-_Sbdm*_h2m1m*NORM.S.DIST(_y1m,1),_A4m,_Kdr*_h2mm*NORM.S.DIST(_y2m-_sqT,1)-_Sbdm*_h2m1m*NORM.S.DIST(_y2m,1),_cfm,_Sbdm*NORM.S.DIST(-_x1m,1)+_Kdr*NORM.S.DIST(_x1m-_sqT,1),_pm,IF(_SM<=_H,_cfm,(_A1m-_A2m+_A3m-_A4m)+_cfm),(_pp-_pm)/(2*_ds*_S)) | D203: =IF(B203>0,C203*A203/B203,0)
A204: 743.37 | B204: =LET(_S,A204,_sig,$P2_TaskVI_Greeks.$B$4,_T,$P2_TaskVI_Greeks.$B$5,_r,$P2_TaskVI_Greeks.$B$6,_K,Cap,_H,Barrier,_q,q,_b,_r-_q,_sqT,_sig*SQRT(_T),_mu,(_b-0.5*_sig^2)/_sig^2,_x1,LN(_S/_K)/_sqT+(1+_mu)*_sqT,_x2,LN(_S/_H)/_sqT+(1+_mu)*_sqT,_y1,LN(_H^2/(_S*_K))/_sqT+(1+_mu)*_sqT,_y2,LN(_H/_S)/_sqT+(1+_mu)*_sqT,_Sbd,_S*EXP(-_q*_T),_Kdr,_K*EXP(-_r*_T),_h2m1,(_H/_S)^(2*(_mu+1)),_h2m,(_H/_S)^(2*_mu),_A1,_Kdr*NORM.S.DIST(_sqT-_x1,1)-_Sbd*NORM.S.DIST(-_x1,1),_A2,_Kdr*NORM.S.DIST(_sqT-_x2,1)-_Sbd*NORM.S.DIST(-_x2,1),_A3,_Kdr*_h2m*NORM.S.DIST(_y1-_sqT,1)-_Sbd*_h2m1*NORM.S.DIST(_y1,1),_A4,_Kdr*_h2m*NORM.S.DIST(_y2-_sqT,1)-_Sbd*_h2m1*NORM.S.DIST(_y2,1),_do,IF(_S<=_H,0,_A1-_A2+_A3-_A4),_cf,_Sbd*NORM.S.DIST(-_x1,1)+_Kdr*NORM.S.DIST(_x1-_sqT,1),IF(_S<=_H,_cf,_do+_cf)) | C204: =LET(_S,A204,_sig,$P2_TaskVI_Greeks.$B$4,_T,$P2_TaskVI_Greeks.$B$5,_r,$P2_TaskVI_Greeks.$B$6,_K,Cap,_H,Barrier,_q,q,_ds,dS,_b,_r-_q,_sqT,_sig*SQRT(_T),_mu,(_b-0.5*_sig^2)/_sig^2,_Kdr,_K*EXP(-_r*_T),_SP,_S*(1+_ds),_Sbdp,_SP*EXP(-_q*_T),_x1p,LN(_SP/_K)/_sqT+(1+_mu)*_sqT,_x2p,LN(_SP/_H)/_sqT+(1+_mu)*_sqT,_y1p,LN(_H^2/(_SP*_K))/_sqT+(1+_mu)*_sqT,_y2p,LN(_H/_SP)/_sqT+(1+_mu)*_sqT,_h2m1p,(_H/_SP)^(2*(_mu+1)),_h2mp,(_H/_SP)^(2*_mu),_A1p,_Kdr*NORM.S.DIST(_sqT-_x1p,1)-_Sbdp*NORM.S.DIST(-_x1p,1),_A2p,_Kdr*NORM.S.DIST(_sqT-_x2p,1)-_Sbdp*NORM.S.DIST(-_x2p,1),_A3p,_Kdr*_h2mp*NORM.S.DIST(_y1p-_sqT,1)-_Sbdp*_h2m1p*NORM.S.DIST(_y1p,1),_A4p,_Kdr*_h2mp*NORM.S.DIST(_y2p-_sqT,1)-_Sbdp*_h2m1p*NORM.S.DIST(_y2p,1),_cfp,_Sbdp*NORM.S.DIST(-_x1p,1)+_Kdr*NORM.S.DIST(_x1p-_sqT,1),_pp,IF(_SP<=_H,_cfp,(_A1p-_A2p+_A3p-_A4p)+_cfp),_SM,_S*(1-_ds),_Sbdm,_SM*EXP(-_q*_T),_x1m,LN(_SM/_K)/_sqT+(1+_mu)*_sqT,_x2m,LN(_SM/_H)/_sqT+(1+_mu)*_sqT,_y1m,LN(_H^2/(_SM*_K))/_sqT+(1+_mu)*_sqT,_y2m,LN(_H/_SM)/_sqT+(1+_mu)*_sqT,_h2m1m,(_H/_SM)^(2*(_mu+1)),_h2mm,(_H/_SM)^(2*_mu),_A1m,_Kdr*NORM.S.DIST(_sqT-_x1m,1)-_Sbdm*NORM.S.DIST(-_x1m,1),_A2m,_Kdr*NORM.S.DIST(_sqT-_x2m,1)-_Sbdm*NORM.S.DIST(-_x2m,1),_A3m,_Kdr*_h2mm*NORM.S.DIST(_y1m-_sqT,1)-_Sbdm*_h2m1m*NORM.S.DIST(_y1m,1),_A4m,_Kdr*_h2mm*NORM.S.DIST(_y2m-_sqT,1)-_Sbdm*_h2m1m*NORM.S.DIST(_y2m,1),_cfm,_Sbdm*NORM.S.DIST(-_x1m,1)+_Kdr*NORM.S.DIST(_x1m-_sqT,1),_pm,IF(_SM<=_H,_cfm,(_A1m-_A2m+_A3m-_A4m)+_cfm),(_pp-_pm)/(2*_ds*_S)) | D204: =IF(B204>0,C204*A204/B204,0)
A205: 797.96 | B205: =LET(_S,A205,_sig,$P2_TaskVI_Greeks.$B$4,_T,$P2_TaskVI_Greeks.$B$5,_r,$P2_TaskVI_Greeks.$B$6,_K,Cap,_H,Barrier,_q,q,_b,_r-_q,_sqT,_sig*SQRT(_T),_mu,(_b-0.5*_sig^2)/_sig^2,_x1,LN(_S/_K)/_sqT+(1+_mu)*_sqT,_x2,LN(_S/_H)/_sqT+(1+_mu)*_sqT,_y1,LN(_H^2/(_S*_K))/_sqT+(1+_mu)*_sqT,_y2,LN(_H/_S)/_sqT+(1+_mu)*_sqT,_Sbd,_S*EXP(-_q*_T),_Kdr,_K*EXP(-_r*_T),_h2m1,(_H/_S)^(2*(_mu+1)),_h2m,(_H/_S)^(2*_mu),_A1,_Kdr*NORM.S.DIST(_sqT-_x1,1)-_Sbd*NORM.S.DIST(-_x1,1),_A2,_Kdr*NORM.S.DIST(_sqT-_x2,1)-_Sbd*NORM.S.DIST(-_x2,1),_A3,_Kdr*_h2m*NORM.S.DIST(_y1-_sqT,1)-_Sbd*_h2m1*NORM.S.DIST(_y1,1),_A4,_Kdr*_h2m*NORM.S.DIST(_y2-_sqT,1)-_Sbd*_h2m1*NORM.S.DIST(_y2,1),_do,IF(_S<=_H,0,_A1-_A2+_A3-_A4),_cf,_Sbd*NORM.S.DIST(-_x1,1)+_Kdr*NORM.S.DIST(_x1-_sqT,1),IF(_S<=_H,_cf,_do+_cf)) | C205: =LET(_S,A205,_sig,$P2_TaskVI_Greeks.$B$4,_T,$P2_TaskVI_Greeks.$B$5,_r,$P2_TaskVI_Greeks.$B$6,_K,Cap,_H,Barrier,_q,q,_ds,dS,_b,_r-_q,_sqT,_sig*SQRT(_T),_mu,(_b-0.5*_sig^2)/_sig^2,_Kdr,_K*EXP(-_r*_T),_SP,_S*(1+_ds),_Sbdp,_SP*EXP(-_q*_T),_x1p,LN(_SP/_K)/_sqT+(1+_mu)*_sqT,_x2p,LN(_SP/_H)/_sqT+(1+_mu)*_sqT,_y1p,LN(_H^2/(_SP*_K))/_sqT+(1+_mu)*_sqT,_y2p,LN(_H/_SP)/_sqT+(1+_mu)*_sqT,_h2m1p,(_H/_SP)^(2*(_mu+1)),_h2mp,(_H/_SP)^(2*_mu),_A1p,_Kdr*NORM.S.DIST(_sqT-_x1p,1)-_Sbdp*NORM.S.DIST(-_x1p,1),_A2p,_Kdr*NORM.S.DIST(_sqT-_x2p,1)-_Sbdp*NORM.S.DIST(-_x2p,1),_A3p,_Kdr*_h2mp*NORM.S.DIST(_y1p-_sqT,1)-_Sbdp*_h2m1p*NORM.S.DIST(_y1p,1),_A4p,_Kdr*_h2mp*NORM.S.DIST(_y2p-_sqT,1)-_Sbdp*_h2m1p*NORM.S.DIST(_y2p,1),_cfp,_Sbdp*NORM.S.DIST(-_x1p,1)+_Kdr*NORM.S.DIST(_x1p-_sqT,1),_pp,IF(_SP<=_H,_cfp,(_A1p-_A2p+_A3p-_A4p)+_cfp),_SM,_S*(1-_ds),_Sbdm,_SM*EXP(-_q*_T),_x1m,LN(_SM/_K)/_sqT+(1+_mu)*_sqT,_x2m,LN(_SM/_H)/_sqT+(1+_mu)*_sqT,_y1m,LN(_H^2/(_SM*_K))/_sqT+(1+_mu)*_sqT,_y2m,LN(_H/_SM)/_sqT+(1+_mu)*_sqT,_h2m1m,(_H/_SM)^(2*(_mu+1)),_h2mm,(_H/_SM)^(2*_mu),_A1m,_Kdr*NORM.S.DIST(_sqT-_x1m,1)-_Sbdm*NORM.S.DIST(-_x1m,1),_A2m,_Kdr*NORM.S.DIST(_sqT-_x2m,1)-_Sbdm*NORM.S.DIST(-_x2m,1),_A3m,_Kdr*_h2mm*NORM.S.DIST(_y1m-_sqT,1)-_Sbdm*_h2m1m*NORM.S.DIST(_y1m,1),_A4m,_Kdr*_h2mm*NORM.S.DIST(_y2m-_sqT,1)-_Sbdm*_h2m1m*NORM.S.DIST(_y2m,1),_cfm,_Sbdm*NORM.S.DIST(-_x1m,1)+_Kdr*NORM.S.DIST(_x1m-_sqT,1),_pm,IF(_SM<=_H,_cfm,(_A1m-_A2m+_A3m-_A4m)+_cfm),(_pp-_pm)/(2*_ds*_S)) | D205: =IF(B205>0,C205*A205/B205,0)
A206: 852.55 | B206: =LET(_S,A206,_sig,$P2_TaskVI_Greeks.$B$4,_T,$P2_TaskVI_Greeks.$B$5,_r,$P2_TaskVI_Greeks.$B$6,_K,Cap,_H,Barrier,_q,q,_b,_r-_q,_sqT,_sig*SQRT(_T),_mu,(_b-0.5*_sig^2)/_sig^2,_x1,LN(_S/_K)/_sqT+(1+_mu)*_sqT,_x2,LN(_S/_H)/_sqT+(1+_mu)*_sqT,_y1,LN(_H^2/(_S*_K))/_sqT+(1+_mu)*_sqT,_y2,LN(_H/_S)/_sqT+(1+_mu)*_sqT,_Sbd,_S*EXP(-_q*_T),_Kdr,_K*EXP(-_r*_T),_h2m1,(_H/_S)^(2*(_mu+1)),_h2m,(_H/_S)^(2*_mu),_A1,_Kdr*NORM.S.DIST(_sqT-_x1,1)-_Sbd*NORM.S.DIST(-_x1,1),_A2,_Kdr*NORM.S.DIST(_sqT-_x2,1)-_Sbd*NORM.S.DIST(-_x2,1),_A3,_Kdr*_h2m*NORM.S.DIST(_y1-_sqT,1)-_Sbd*_h2m1*NORM.S.DIST(_y1,1),_A4,_Kdr*_h2m*NORM.S.DIST(_y2-_sqT,1)-_Sbd*_h2m1*NORM.S.DIST(_y2,1),_do,IF(_S<=_H,0,_A1-_A2+_A3-_A4),_cf,_Sbd*NORM.S.DIST(-_x1,1)+_Kdr*NORM.S.DIST(_x1-_sqT,1),IF(_S<=_H,_cf,_do+_cf)) | C206: =LET(_S,A206,_sig,$P2_TaskVI_Greeks.$B$4,_T,$P2_TaskVI_Greeks.$B$5,_r,$P2_TaskVI_Greeks.$B$6,_K,Cap,_H,Barrier,_q,q,_ds,dS,_b,_r-_q,_sqT,_sig*SQRT(_T),_mu,(_b-0.5*_sig^2)/_sig^2,_Kdr,_K*EXP(-_r*_T),_SP,_S*(1+_ds),_Sbdp,_SP*EXP(-_q*_T),_x1p,LN(_SP/_K)/_sqT+(1+_mu)*_sqT,_x2p,LN(_SP/_H)/_sqT+(1+_mu)*_sqT,_y1p,LN(_H^2/(_SP*_K))/_sqT+(1+_mu)*_sqT,_y2p,LN(_H/_SP)/_sqT+(1+_mu)*_sqT,_h2m1p,(_H/_SP)^(2*(_mu+1)),_h2mp,(_H/_SP)^(2*_mu),_A1p,_Kdr*NORM.S.DIST(_sqT-_x1p,1)-_Sbdp*NORM.S.DIST(-_x1p,1),_A2p,_Kdr*NORM.S.DIST(_sqT-_x2p,1)-_Sbdp*NORM.S.DIST(-_x2p,1),_A3p,_Kdr*_h2mp*NORM.S.DIST(_y1p-_sqT,1)-_Sbdp*_h2m1p*NORM.S.DIST(_y1p,1),_A4p,_Kdr*_h2mp*NORM.S.DIST(_y2p-_sqT,1)-_Sbdp*_h2m1p*NORM.S.DIST(_y2p,1),_cfp,_Sbdp*NORM.S.DIST(-_x1p,1)+_Kdr*NORM.S.DIST(_x1p-_sqT,1),_pp,IF(_SP<=_H,_cfp,(_A1p-_A2p+_A3p-_A4p)+_cfp),_SM,_S*(1-_ds),_Sbdm,_SM*EXP(-_q*_T),_x1m,LN(_SM/_K)/_sqT+(1+_mu)*_sqT,_x2m,LN(_SM/_H)/_sqT+(1+_mu)*_sqT,_y1m,LN(_H^2/(_SM*_K))/_sqT+(1+_mu)*_sqT,_y2m,LN(_H/_SM)/_sqT+(1+_mu)*_sqT,_h2m1m,(_H/_SM)^(2*(_mu+1)),_h2mm,(_H/_SM)^(2*_mu),_A1m,_Kdr*NORM.S.DIST(_sqT-_x1m,1)-_Sbdm*NORM.S.DIST(-_x1m,1),_A2m,_Kdr*NORM.S.DIST(_sqT-_x2m,1)-_Sbdm*NORM.S.DIST(-_x2m,1),_A3m,_Kdr*_h2mm*NORM.S.DIST(_y1m-_sqT,1)-_Sbdm*_h2m1m*NORM.S.DIST(_y1m,1),_A4m,_Kdr*_h2mm*NORM.S.DIST(_y2m-_sqT,1)-_Sbdm*_h2m1m*NORM.S.DIST(_y2m,1),_cfm,_Sbdm*NORM.S.DIST(-_x1m,1)+_Kdr*NORM.S.DIST(_x1m-_sqT,1),_pm,IF(_SM<=_H,_cfm,(_A1m-_A2m+_A3m-_A4m)+_cfm),(_pp-_pm)/(2*_ds*_S)) | D206: =IF(B206>0,C206*A206/B206,0)
A207: 907.14 | B207: =LET(_S,A207,_sig,$P2_TaskVI_Greeks.$B$4,_T,$P2_TaskVI_Greeks.$B$5,_r,$P2_TaskVI_Greeks.$B$6,_K,Cap,_H,Barrier,_q,q,_b,_r-_q,_sqT,_sig*SQRT(_T),_mu,(_b-0.5*_sig^2)/_sig^2,_x1,LN(_S/_K)/_sqT+(1+_mu)*_sqT,_x2,LN(_S/_H)/_sqT+(1+_mu)*_sqT,_y1,LN(_H^2/(_S*_K))/_sqT+(1+_mu)*_sqT,_y2,LN(_H/_S)/_sqT+(1+_mu)*_sqT,_Sbd,_S*EXP(-_q*_T),_Kdr,_K*EXP(-_r*_T),_h2m1,(_H/_S)^(2*(_mu+1)),_h2m,(_H/_S)^(2*_mu),_A1,_Kdr*NORM.S.DIST(_sqT-_x1,1)-_Sbd*NORM.S.DIST(-_x1,1),_A2,_Kdr*NORM.S.DIST(_sqT-_x2,1)-_Sbd*NORM.S.DIST(-_x2,1),_A3,_Kdr*_h2m*NORM.S.DIST(_y1-_sqT,1)-_Sbd*_h2m1*NORM.S.DIST(_y1,1),_A4,_Kdr*_h2m*NORM.S.DIST(_y2-_sqT,1)-_Sbd*_h2m1*NORM.S.DIST(_y2,1),_do,IF(_S<=_H,0,_A1-_A2+_A3-_A4),_cf,_Sbd*NORM.S.DIST(-_x1,1)+_Kdr*NORM.S.DIST(_x1-_sqT,1),IF(_S<=_H,_cf,_do+_cf)) | C207: =LET(_S,A207,_sig,$P2_TaskVI_Greeks.$B$4,_T,$P2_TaskVI_Greeks.$B$5,_r,$P2_TaskVI_Greeks.$B$6,_K,Cap,_H,Barrier,_q,q,_ds,dS,_b,_r-_q,_sqT,_sig*SQRT(_T),_mu,(_b-0.5*_sig^2)/_sig^2,_Kdr,_K*EXP(-_r*_T),_SP,_S*(1+_ds),_Sbdp,_SP*EXP(-_q*_T),_x1p,LN(_SP/_K)/_sqT+(1+_mu)*_sqT,_x2p,LN(_SP/_H)/_sqT+(1+_mu)*_sqT,_y1p,LN(_H^2/(_SP*_K))/_sqT+(1+_mu)*_sqT,_y2p,LN(_H/_SP)/_sqT+(1+_mu)*_sqT,_h2m1p,(_H/_SP)^(2*(_mu+1)),_h2mp,(_H/_SP)^(2*_mu),_A1p,_Kdr*NORM.S.DIST(_sqT-_x1p,1)-_Sbdp*NORM.S.DIST(-_x1p,1),_A2p,_Kdr*NORM.S.DIST(_sqT-_x2p,1)-_Sbdp*NORM.S.DIST(-_x2p,1),_A3p,_Kdr*_h2mp*NORM.S.DIST(_y1p-_sqT,1)-_Sbdp*_h2m1p*NORM.S.DIST(_y1p,1),_A4p,_Kdr*_h2mp*NORM.S.DIST(_y2p-_sqT,1)-_Sbdp*_h2m1p*NORM.S.DIST(_y2p,1),_cfp,_Sbdp*NORM.S.DIST(-_x1p,1)+_Kdr*NORM.S.DIST(_x1p-_sqT,1),_pp,IF(_SP<=_H,_cfp,(_A1p-_A2p+_A3p-_A4p)+_cfp),_SM,_S*(1-_ds),_Sbdm,_SM*EXP(-_q*_T),_x1m,LN(_SM/_K)/_sqT+(1+_mu)*_sqT,_x2m,LN(_SM/_H)/_sqT+(1+_mu)*_sqT,_y1m,LN(_H^2/(_SM*_K))/_sqT+(1+_mu)*_sqT,_y2m,LN(_H/_SM)/_sqT+(1+_mu)*_sqT,_h2m1m,(_H/_SM)^(2*(_mu+1)),_h2mm,(_H/_SM)^(2*_mu),_A1m,_Kdr*NORM.S.DIST(_sqT-_x1m,1)-_Sbdm*NORM.S.DIST(-_x1m,1),_A2m,_Kdr*NORM.S.DIST(_sqT-_x2m,1)-_Sbdm*NORM.S.DIST(-_x2m,1),_A3m,_Kdr*_h2mm*NORM.S.DIST(_y1m-_sqT,1)-_Sbdm*_h2m1m*NORM.S.DIST(_y1m,1),_A4m,_Kdr*_h2mm*NORM.S.DIST(_y2m-_sqT,1)-_Sbdm*_h2m1m*NORM.S.DIST(_y2m,1),_cfm,_Sbdm*NORM.S.DIST(-_x1m,1)+_Kdr*NORM.S.DIST(_x1m-_sqT,1),_pm,IF(_SM<=_H,_cfm,(_A1m-_A2m+_A3m-_A4m)+_cfm),(_pp-_pm)/(2*_ds*_S)) | D207: =IF(B207>0,C207*A207/B207,0)
A208: 961.73 | B208: =LET(_S,A208,_sig,$P2_TaskVI_Greeks.$B$4,_T,$P2_TaskVI_Greeks.$B$5,_r,$P2_TaskVI_Greeks.$B$6,_K,Cap,_H,Barrier,_q,q,_b,_r-_q,_sqT,_sig*SQRT(_T),_mu,(_b-0.5*_sig^2)/_sig^2,_x1,LN(_S/_K)/_sqT+(1+_mu)*_sqT,_x2,LN(_S/_H)/_sqT+(1+_mu)*_sqT,_y1,LN(_H^2/(_S*_K))/_sqT+(1+_mu)*_sqT,_y2,LN(_H/_S)/_sqT+(1+_mu)*_sqT,_Sbd,_S*EXP(-_q*_T),_Kdr,_K*EXP(-_r*_T),_h2m1,(_H/_S)^(2*(_mu+1)),_h2m,(_H/_S)^(2*_mu),_A1,_Kdr*NORM.S.DIST(_sqT-_x1,1)-_Sbd*NORM.S.DIST(-_x1,1),_A2,_Kdr*NORM.S.DIST(_sqT-_x2,1)-_Sbd*NORM.S.DIST(-_x2,1),_A3,_Kdr*_h2m*NORM.S.DIST(_y1-_sqT,1)-_Sbd*_h2m1*NORM.S.DIST(_y1,1),_A4,_Kdr*_h2m*NORM.S.DIST(_y2-_sqT,1)-_Sbd*_h2m1*NORM.S.DIST(_y2,1),_do,IF(_S<=_H,0,_A1-_A2+_A3-_A4),_cf,_Sbd*NORM.S.DIST(-_x1,1)+_Kdr*NORM.S.DIST(_x1-_sqT,1),IF(_S<=_H,_cf,_do+_cf)) | C208: =LET(_S,A208,_sig,$P2_TaskVI_Greeks.$B$4,_T,$P2_TaskVI_Greeks.$B$5,_r,$P2_TaskVI_Greeks.$B$6,_K,Cap,_H,Barrier,_q,q,_ds,dS,_b,_r-_q,_sqT,_sig*SQRT(_T),_mu,(_b-0.5*_sig^2)/_sig^2,_Kdr,_K*EXP(-_r*_T),_SP,_S*(1+_ds),_Sbdp,_SP*EXP(-_q*_T),_x1p,LN(_SP/_K)/_sqT+(1+_mu)*_sqT,_x2p,LN(_SP/_H)/_sqT+(1+_mu)*_sqT,_y1p,LN(_H^2/(_SP*_K))/_sqT+(1+_mu)*_sqT,_y2p,LN(_H/_SP)/_sqT+(1+_mu)*_sqT,_h2m1p,(_H/_SP)^(2*(_mu+1)),_h2mp,(_H/_SP)^(2*_mu),_A1p,_Kdr*NORM.S.DIST(_sqT-_x1p,1)-_Sbdp*NORM.S.DIST(-_x1p,1),_A2p,_Kdr*NORM.S.DIST(_sqT-_x2p,1)-_Sbdp*NORM.S.DIST(-_x2p,1),_A3p,_Kdr*_h2mp*NORM.S.DIST(_y1p-_sqT,1)-_Sbdp*_h2m1p*NORM.S.DIST(_y1p,1),_A4p,_Kdr*_h2mp*NORM.S.DIST(_y2p-_sqT,1)-_Sbdp*_h2m1p*NORM.S.DIST(_y2p,1),_cfp,_Sbdp*NORM.S.DIST(-_x1p,1)+_Kdr*NORM.S.DIST(_x1p-_sqT,1),_pp,IF(_SP<=_H,_cfp,(_A1p-_A2p+_A3p-_A4p)+_cfp),_SM,_S*(1-_ds),_Sbdm,_SM*EXP(-_q*_T),_x1m,LN(_SM/_K)/_sqT+(1+_mu)*_sqT,_x2m,LN(_SM/_H)/_sqT+(1+_mu)*_sqT,_y1m,LN(_H^2/(_SM*_K))/_sqT+(1+_mu)*_sqT,_y2m,LN(_H/_SM)/_sqT+(1+_mu)*_sqT,_h2m1m,(_H/_SM)^(2*(_mu+1)),_h2mm,(_H/_SM)^(2*_mu),_A1m,_Kdr*NORM.S.DIST(_sqT-_x1m,1)-_Sbdm*NORM.S.DIST(-_x1m,1),_A2m,_Kdr*NORM.S.DIST(_sqT-_x2m,1)-_Sbdm*NORM.S.DIST(-_x2m,1),_A3m,_Kdr*_h2mm*NORM.S.DIST(_y1m-_sqT,1)-_Sbdm*_h2m1m*NORM.S.DIST(_y1m,1),_A4m,_Kdr*_h2mm*NORM.S.DIST(_y2m-_sqT,1)-_Sbdm*_h2m1m*NORM.S.DIST(_y2m,1),_cfm,_Sbdm*NORM.S.DIST(-_x1m,1)+_Kdr*NORM.S.DIST(_x1m-_sqT,1),_pm,IF(_SM<=_H,_cfm,(_A1m-_A2m+_A3m-_A4m)+_cfm),(_pp-_pm)/(2*_ds*_S)) | D208: =IF(B208>0,C208*A208/B208,0)
A209: 1016.33 | B209: =LET(_S,A209,_sig,$P2_TaskVI_Greeks.$B$4,_T,$P2_TaskVI_Greeks.$B$5,_r,$P2_TaskVI_Greeks.$B$6,_K,Cap,_H,Barrier,_q,q,_b,_r-_q,_sqT,_sig*SQRT(_T),_mu,(_b-0.5*_sig^2)/_sig^2,_x1,LN(_S/_K)/_sqT+(1+_mu)*_sqT,_x2,LN(_S/_H)/_sqT+(1+_mu)*_sqT,_y1,LN(_H^2/(_S*_K))/_sqT+(1+_mu)*_sqT,_y2,LN(_H/_S)/_sqT+(1+_mu)*_sqT,_Sbd,_S*EXP(-_q*_T),_Kdr,_K*EXP(-_r*_T),_h2m1,(_H/_S)^(2*(_mu+1)),_h2m,(_H/_S)^(2*_mu),_A1,_Kdr*NORM.S.DIST(_sqT-_x1,1)-_Sbd*NORM.S.DIST(-_x1,1),_A2,_Kdr*NORM.S.DIST(_sqT-_x2,1)-_Sbd*NORM.S.DIST(-_x2,1),_A3,_Kdr*_h2m*NORM.S.DIST(_y1-_sqT,1)-_Sbd*_h2m1*NORM.S.DIST(_y1,1),_A4,_Kdr*_h2m*NORM.S.DIST(_y2-_sqT,1)-_Sbd*_h2m1*NORM.S.DIST(_y2,1),_do,IF(_S<=_H,0,_A1-_A2+_A3-_A4),_cf,_Sbd*NORM.S.DIST(-_x1,1)+_Kdr*NORM.S.DIST(_x1-_sqT,1),IF(_S<=_H,_cf,_do+_cf)) | C209: =LET(_S,A209,_sig,$P2_TaskVI_Greeks.$B$4,_T,$P2_TaskVI_Greeks.$B$5,_r,$P2_TaskVI_Greeks.$B$6,_K,Cap,_H,Barrier,_q,q,_ds,dS,_b,_r-_q,_sqT,_sig*SQRT(_T),_mu,(_b-0.5*_sig^2)/_sig^2,_Kdr,_K*EXP(-_r*_T),_SP,_S*(1+_ds),_Sbdp,_SP*EXP(-_q*_T),_x1p,LN(_SP/_K)/_sqT+(1+_mu)*_sqT,_x2p,LN(_SP/_H)/_sqT+(1+_mu)*_sqT,_y1p,LN(_H^2/(_SP*_K))/_sqT+(1+_mu)*_sqT,_y2p,LN(_H/_SP)/_sqT+(1+_mu)*_sqT,_h2m1p,(_H/_SP)^(2*(_mu+1)),_h2mp,(_H/_SP)^(2*_mu),_A1p,_Kdr*NORM.S.DIST(_sqT-_x1p,1)-_Sbdp*NORM.S.DIST(-_x1p,1),_A2p,_Kdr*NORM.S.DIST(_sqT-_x2p,1)-_Sbdp*NORM.S.DIST(-_x2p,1),_A3p,_Kdr*_h2mp*NORM.S.DIST(_y1p-_sqT,1)-_Sbdp*_h2m1p*NORM.S.DIST(_y1p,1),_A4p,_Kdr*_h2mp*NORM.S.DIST(_y2p-_sqT,1)-_Sbdp*_h2m1p*NORM.S.DIST(_y2p,1),_cfp,_Sbdp*NORM.S.DIST(-_x1p,1)+_Kdr*NORM.S.DIST(_x1p-_sqT,1),_pp,IF(_SP<=_H,_cfp,(_A1p-_A2p+_A3p-_A4p)+_cfp),_SM,_S*(1-_ds),_Sbdm,_SM*EXP(-_q*_T),_x1m,LN(_SM/_K)/_sqT+(1+_mu)*_sqT,_x2m,LN(_SM/_H)/_sqT+(1+_mu)*_sqT,_y1m,LN(_H^2/(_SM*_K))/_sqT+(1+_mu)*_sqT,_y2m,LN(_H/_SM)/_sqT+(1+_mu)*_sqT,_h2m1m,(_H/_SM)^(2*(_mu+1)),_h2mm,(_H/_SM)^(2*_mu),_A1m,_Kdr*NORM.S.DIST(_sqT-_x1m,1)-_Sbdm*NORM.S.DIST(-_x1m,1),_A2m,_Kdr*NORM.S.DIST(_sqT-_x2m,1)-_Sbdm*NORM.S.DIST(-_x2m,1),_A3m,_Kdr*_h2mm*NORM.S.DIST(_y1m-_sqT,1)-_Sbdm*_h2m1m*NORM.S.DIST(_y1m,1),_A4m,_Kdr*_h2mm*NORM.S.DIST(_y2m-_sqT,1)-_Sbdm*_h2m1m*NORM.S.DIST(_y2m,1),_cfm,_Sbdm*NORM.S.DIST(-_x1m,1)+_Kdr*NORM.S.DIST(_x1m-_sqT,1),_pm,IF(_SM<=_H,_cfm,(_A1m-_A2m+_A3m-_A4m)+_cfm),(_pp-_pm)/(2*_ds*_S)) | D209: =IF(B209>0,C209*A209/B209,0)
A210: 1070.92 | B210: =LET(_S,A210,_sig,$P2_TaskVI_Greeks.$B$4,_T,$P2_TaskVI_Greeks.$B$5,_r,$P2_TaskVI_Greeks.$B$6,_K,Cap,_H,Barrier,_q,q,_b,_r-_q,_sqT,_sig*SQRT(_T),_mu,(_b-0.5*_sig^2)/_sig^2,_x1,LN(_S/_K)/_sqT+(1+_mu)*_sqT,_x2,LN(_S/_H)/_sqT+(1+_mu)*_sqT,_y1,LN(_H^2/(_S*_K))/_sqT+(1+_mu)*_sqT,_y2,LN(_H/_S)/_sqT+(1+_mu)*_sqT,_Sbd,_S*EXP(-_q*_T),_Kdr,_K*EXP(-_r*_T),_h2m1,(_H/_S)^(2*(_mu+1)),_h2m,(_H/_S)^(2*_mu),_A1,_Kdr*NORM.S.DIST(_sqT-_x1,1)-_Sbd*NORM.S.DIST(-_x1,1),_A2,_Kdr*NORM.S.DIST(_sqT-_x2,1)-_Sbd*NORM.S.DIST(-_x2,1),_A3,_Kdr*_h2m*NORM.S.DIST(_y1-_sqT,1)-_Sbd*_h2m1*NORM.S.DIST(_y1,1),_A4,_Kdr*_h2m*NORM.S.DIST(_y2-_sqT,1)-_Sbd*_h2m1*NORM.S.DIST(_y2,1),_do,IF(_S<=_H,0,_A1-_A2+_A3-_A4),_cf,_Sbd*NORM.S.DIST(-_x1,1)+_Kdr*NORM.S.DIST(_x1-_sqT,1),IF(_S<=_H,_cf,_do+_cf)) | C210: =LET(_S,A210,_sig,$P2_TaskVI_Greeks.$B$4,_T,$P2_TaskVI_Greeks.$B$5,_r,$P2_TaskVI_Greeks.$B$6,_K,Cap,_H,Barrier,_q,q,_ds,dS,_b,_r-_q,_sqT,_sig*SQRT(_T),_mu,(_b-0.5*_sig^2)/_sig^2,_Kdr,_K*EXP(-_r*_T),_SP,_S*(1+_ds),_Sbdp,_SP*EXP(-_q*_T),_x1p,LN(_SP/_K)/_sqT+(1+_mu)*_sqT,_x2p,LN(_SP/_H)/_sqT+(1+_mu)*_sqT,_y1p,LN(_H^2/(_SP*_K))/_sqT+(1+_mu)*_sqT,_y2p,LN(_H/_SP)/_sqT+(1+_mu)*_sqT,_h2m1p,(_H/_SP)^(2*(_mu+1)),_h2mp,(_H/_SP)^(2*_mu),_A1p,_Kdr*NORM.S.DIST(_sqT-_x1p,1)-_Sbdp*NORM.S.DIST(-_x1p,1),_A2p,_Kdr*NORM.S.DIST(_sqT-_x2p,1)-_Sbdp*NORM.S.DIST(-_x2p,1),_A3p,_Kdr*_h2mp*NORM.S.DIST(_y1p-_sqT,1)-_Sbdp*_h2m1p*NORM.S.DIST(_y1p,1),_A4p,_Kdr*_h2mp*NORM.S.DIST(_y2p-_sqT,1)-_Sbdp*_h2m1p*NORM.S.DIST(_y2p,1),_cfp,_Sbdp*NORM.S.DIST(-_x1p,1)+_Kdr*NORM.S.DIST(_x1p-_sqT,1),_pp,IF(_SP<=_H,_cfp,(_A1p-_A2p+_A3p-_A4p)+_cfp),_SM,_S*(1-_ds),_Sbdm,_SM*EXP(-_q*_T),_x1m,LN(_SM/_K)/_sqT+(1+_mu)*_sqT,_x2m,LN(_SM/_H)/_sqT+(1+_mu)*_sqT,_y1m,LN(_H^2/(_SM*_K))/_sqT+(1+_mu)*_sqT,_y2m,LN(_H/_SM)/_sqT+(1+_mu)*_sqT,_h2m1m,(_H/_SM)^(2*(_mu+1)),_h2mm,(_H/_SM)^(2*_mu),_A1m,_Kdr*NORM.S.DIST(_sqT-_x1m,1)-_Sbdm*NORM.S.DIST(-_x1m,1),_A2m,_Kdr*NORM.S.DIST(_sqT-_x2m,1)-_Sbdm*NORM.S.DIST(-_x2m,1),_A3m,_Kdr*_h2mm*NORM.S.DIST(_y1m-_sqT,1)-_Sbdm*_h2m1m*NORM.S.DIST(_y1m,1),_A4m,_Kdr*_h2mm*NORM.S.DIST(_y2m-_sqT,1)-_Sbdm*_h2m1m*NORM.S.DIST(_y2m,1),_cfm,_Sbdm*NORM.S.DIST(-_x1m,1)+_Kdr*NORM.S.DIST(_x1m-_sqT,1),_pm,IF(_SM<=_H,_cfm,(_A1m-_A2m+_A3m-_A4m)+_cfm),(_pp-_pm)/(2*_ds*_S)) | D210: =IF(B210>0,C210*A210/B210,0)
A211: 1125.51 | B211: =LET(_S,A211,_sig,$P2_TaskVI_Greeks.$B$4,_T,$P2_TaskVI_Greeks.$B$5,_r,$P2_TaskVI_Greeks.$B$6,_K,Cap,_H,Barrier,_q,q,_b,_r-_q,_sqT,_sig*SQRT(_T),_mu,(_b-0.5*_sig^2)/_sig^2,_x1,LN(_S/_K)/_sqT+(1+_mu)*_sqT,_x2,LN(_S/_H)/_sqT+(1+_mu)*_sqT,_y1,LN(_H^2/(_S*_K))/_sqT+(1+_mu)*_sqT,_y2,LN(_H/_S)/_sqT+(1+_mu)*_sqT,_Sbd,_S*EXP(-_q*_T),_Kdr,_K*EXP(-_r*_T),_h2m1,(_H/_S)^(2*(_mu+1)),_h2m,(_H/_S)^(2*_mu),_A1,_Kdr*NORM.S.DIST(_sqT-_x1,1)-_Sbd*NORM.S.DIST(-_x1,1),_A2,_Kdr*NORM.S.DIST(_sqT-_x2,1)-_Sbd*NORM.S.DIST(-_x2,1),_A3,_Kdr*_h2m*NORM.S.DIST(_y1-_sqT,1)-_Sbd*_h2m1*NORM.S.DIST(_y1,1),_A4,_Kdr*_h2m*NORM.S.DIST(_y2-_sqT,1)-_Sbd*_h2m1*NORM.S.DIST(_y2,1),_do,IF(_S<=_H,0,_A1-_A2+_A3-_A4),_cf,_Sbd*NORM.S.DIST(-_x1,1)+_Kdr*NORM.S.DIST(_x1-_sqT,1),IF(_S<=_H,_cf,_do+_cf)) | C211: =LET(_S,A211,_sig,$P2_TaskVI_Greeks.$B$4,_T,$P2_TaskVI_Greeks.$B$5,_r,$P2_TaskVI_Greeks.$B$6,_K,Cap,_H,Barrier,_q,q,_ds,dS,_b,_r-_q,_sqT,_sig*SQRT(_T),_mu,(_b-0.5*_sig^2)/_sig^2,_Kdr,_K*EXP(-_r*_T),_SP,_S*(1+_ds),_Sbdp,_SP*EXP(-_q*_T),_x1p,LN(_SP/_K)/_sqT+(1+_mu)*_sqT,_x2p,LN(_SP/_H)/_sqT+(1+_mu)*_sqT,_y1p,LN(_H^2/(_SP*_K))/_sqT+(1+_mu)*_sqT,_y2p,LN(_H/_SP)/_sqT+(1+_mu)*_sqT,_h2m1p,(_H/_SP)^(2*(_mu+1)),_h2mp,(_H/_SP)^(2*_mu),_A1p,_Kdr*NORM.S.DIST(_sqT-_x1p,1)-_Sbdp*NORM.S.DIST(-_x1p,1),_A2p,_Kdr*NORM.S.DIST(_sqT-_x2p,1)-_Sbdp*NORM.S.DIST(-_x2p,1),_A3p,_Kdr*_h2mp*NORM.S.DIST(_y1p-_sqT,1)-_Sbdp*_h2m1p*NORM.S.DIST(_y1p,1),_A4p,_Kdr*_h2mp*NORM.S.DIST(_y2p-_sqT,1)-_Sbdp*_h2m1p*NORM.S.DIST(_y2p,1),_cfp,_Sbdp*NORM.S.DIST(-_x1p,1)+_Kdr*NORM.S.DIST(_x1p-_sqT,1),_pp,IF(_SP<=_H,_cfp,(_A1p-_A2p+_A3p-_A4p)+_cfp),_SM,_S*(1-_ds),_Sbdm,_SM*EXP(-_q*_T),_x1m,LN(_SM/_K)/_sqT+(1+_mu)*_sqT,_x2m,LN(_SM/_H)/_sqT+(1+_mu)*_sqT,_y1m,LN(_H^2/(_SM*_K))/_sqT+(1+_mu)*_sqT,_y2m,LN(_H/_SM)/_sqT+(1+_mu)*_sqT,_h2m1m,(_H/_SM)^(2*(_mu+1)),_h2mm,(_H/_SM)^(2*_mu),_A1m,_Kdr*NORM.S.DIST(_sqT-_x1m,1)-_Sbdm*NORM.S.DIST(-_x1m,1),_A2m,_Kdr*NORM.S.DIST(_sqT-_x2m,1)-_Sbdm*NORM.S.DIST(-_x2m,1),_A3m,_Kdr*_h2mm*NORM.S.DIST(_y1m-_sqT,1)-_Sbdm*_h2m1m*NORM.S.DIST(_y1m,1),_A4m,_Kdr*_h2mm*NORM.S.DIST(_y2m-_sqT,1)-_Sbdm*_h2m1m*NORM.S.DIST(_y2m,1),_cfm,_Sbdm*NORM.S.DIST(-_x1m,1)+_Kdr*NORM.S.DIST(_x1m-_sqT,1),_pm,IF(_SM<=_H,_cfm,(_A1m-_A2m+_A3m-_A4m)+_cfm),(_pp-_pm)/(2*_ds*_S)) | D211: =IF(B211>0,C211*A211/B211,0)
... A249: 3200 | B249: =LET(_S,A249,_sig,$P2_TaskVI_Greeks.$B$4,_T,$P2_TaskVI_Greeks.$B$5,_r,$P2_TaskVI_Greeks.$B$6,_K,Cap,_H,Barrier,_q,q,_b,_r-_q,_sqT,_sig*SQRT(_T),_mu,(_b-0.5*_sig^2)/_sig^2,_x1,LN(_S/_K)/_sqT+(1+_mu)*_sqT,_x2,LN(_S/_H)/_sqT+(1+_mu)*_sqT,_y1,LN(_H^2/(_S*_K))/_sqT+(1+_mu)*_sqT,_y2,LN(_H/_S)/_sqT+(1+_mu)*_sqT,_Sbd,_S*EXP(-_q*_T),_Kdr,_K*EXP(-_r*_T),_h2m1,(_H/_S)^(2*(_mu+1)),_h2m,(_H/_S)^(2*_mu),_A1,_Kdr*NORM.S.DIST(_sqT-_x1,1)-_Sbd*NORM.S.DIST(-_x1,1),_A2,_Kdr*NORM.S.DIST(_sqT-_x2,1)-_Sbd*NORM.S.DIST(-_x2,1),_A3,_Kdr*_h2m*NORM.S.DIST(_y1-_sqT,1)-_Sbd*_h2m1*NORM.S.DIST(_y1,1),_A4,_Kdr*_h2m*NORM.S.DIST(_y2-_sqT,1)-_Sbd*_h2m1*NORM.S.DIST(_y2,1),_do,IF(_S<=_H,0,_A1-_A2+_A3-_A4),_cf,_Sbd*NORM.S.DIST(-_x1,1)+_Kdr*NORM.S.DIST(_x1-_sqT,1),IF(_S<=_H,_cf,_do+_cf)) | C249: =LET(_S,A249,_sig,$P2_TaskVI_Greeks.$B$4,_T,$P2_TaskVI_Greeks.$B$5,_r,$P2_TaskVI_Greeks.$B$6,_K,Cap,_H,Barrier,_q,q,_ds,dS,_b,_r-_q,_sqT,_sig*SQRT(_T),_mu,(_b-0.5*_sig^2)/_sig^2,_Kdr,_K*EXP(-_r*_T),_SP,_S*(1+_ds),_Sbdp,_SP*EXP(-_q*_T),_x1p,LN(_SP/_K)/_sqT+(1+_mu)*_sqT,_x2p,LN(_SP/_H)/_sqT+(1+_mu)*_sqT,_y1p,LN(_H^2/(_SP*_K))/_sqT+(1+_mu)*_sqT,_y2p,LN(_H/_SP)/_sqT+(1+_mu)*_sqT,_h2m1p,(_H/_SP)^(2*(_mu+1)),_h2mp,(_H/_SP)^(2*_mu),_A1p,_Kdr*NORM.S.DIST(_sqT-_x1p,1)-_Sbdp*NORM.S.DIST(-_x1p,1),_A2p,_Kdr*NORM.S.DIST(_sqT-_x2p,1)-_Sbdp*NORM.S.DIST(-_x2p,1),_A3p,_Kdr*_h2mp*NORM.S.DIST(_y1p-_sqT,1)-_Sbdp*_h2m1p*NORM.S.DIST(_y1p,1),_A4p,_Kdr*_h2mp*NORM.S.DIST(_y2p-_sqT,1)-_Sbdp*_h2m1p*NORM.S.DIST(_y2p,1),_cfp,_Sbdp*NORM.S.DIST(-_x1p,1)+_Kdr*NORM.S.DIST(_x1p-_sqT,1),_pp,IF(_SP<=_H,_cfp,(_A1p-_A2p+_A3p-_A4p)+_cfp),_SM,_S*(1-_ds),_Sbdm,_SM*EXP(-_q*_T),_x1m,LN(_SM/_K)/_sqT+(1+_mu)*_sqT,_x2m,LN(_SM/_H)/_sqT+(1+_mu)*_sqT,_y1m,LN(_H^2/(_SM*_K))/_sqT+(1+_mu)*_sqT,_y2m,LN(_H/_SM)/_sqT+(1+_mu)*_sqT,_h2m1m,(_H/_SM)^(2*(_mu+1)),_h2mm,(_H/_SM)^(2*_mu),_A1m,_Kdr*NORM.S.DIST(_sqT-_x1m,1)-_Sbdm*NORM.S.DIST(-_x1m,1),_A2m,_Kdr*NORM.S.DIST(_sqT-_x2m,1)-_Sbdm*NORM.S.DIST(-_x2m,1),_A3m,_Kdr*_h2mm*NORM.S.DIST(_y1m-_sqT,1)-_Sbdm*_h2m1m*NORM.S.DIST(_y1m,1),_A4m,_Kdr*_h2mm*NORM.S.DIST(_y2m-_sqT,1)-_Sbdm*_h2m1m*NORM.S.DIST(_y2m,1),_cfm,_Sbdm*NORM.S.DIST(-_x1m,1)+_Kdr*NORM.S.DIST(_x1m-_sqT,1),_pm,IF(_SM<=_H,_cfm,(_A1m-_A2m+_A3m-_A4m)+_cfm),(_pp-_pm)/(2*_ds*_S)) | D249: =IF(B249>0,C249*A249/B249,0)
A252: Interpretation: As S approaches the barrier H=1050 from above, Delta rises toward 1.0 -- the certificate mimics the stock. Equity fraction exceeds 100% just above the barrier (bond component becomes negative -- the replicating portfolio shorts bonds to fund the stock). Once S breaches H, the DO-put knocks out; the certificate becomes a capped forward with full downside exposure and no protective element remaining.

Sheet P3_TaskVIII
A1: Task VIII -- MC Performance (No Risk Management)
A2: Parameters: S0=1207.0, mu=0.5405, sigma=0.3988, r=0.030681, seed=2026, paths=50000, T*=1.0y, steps=252
A3: Metric | B3: Live formula value | C3: Notebook target
A4: Mean log return | B4: =AVERAGE(B15:B50014) | C4: 0.4608
A5: Median log return | B5: =MEDIAN(B15:B50014) | C5: 0.4621
A6: Std dev | B6: =STDEV(B15:B50014) | C6: 0.3992
A7: Skewness | B7: =SKEW(B15:B50014) | C7: 0.007
A8: Sharpe ratio | B8: =(AVERAGE(B15:B50014)-r_mc)/STDEV(B15:B50014) | C8: 1.078
A9: 95% VaR (loss) | B9: =-PERCENTILE(B15:B50014,0.05) | C9: 0.1927
A10: 95% CVaR (loss) | B10: =AVERAGE(IF(B15:B50014<=PERCENTILE(B15:B50014,0.05),B15:B50014))*-1 | C10: 0.3633
A11: P(loss) | B11: =COUNTIF(B15:B50014,"<0")/NPaths | C11: 0.124
A13: Log returns (live formulas referencing MC_Paths!B / named range S0_mc)
A14: PathID | B14: Log_Return
A15: 1 | B15: =LN(MC_Paths!B4/S0_mc)
A16: 2 | B16: =LN(MC_Paths!B5/S0_mc)
A17: 3 | B17: =LN(MC_Paths!B6/S0_mc)
A18: 4 | B18: =LN(MC_Paths!B7/S0_mc)
A19: 5 | B19: =LN(MC_Paths!B8/S0_mc)
A20: 6 | B20: =LN(MC_Paths!B9/S0_mc)
A21: 7 | B21: =LN(MC_Paths!B10/S0_mc)
A22: 8 | B22: =LN(MC_Paths!B11/S0_mc)
A23: 9 | B23: =LN(MC_Paths!B12/S0_mc)
A24: 10 | B24: =LN(MC_Paths!B13/S0_mc)
A25: 11 | B25: =LN(MC_Paths!B14/S0_mc)
A26: 12 | B26: =LN(MC_Paths!B15/S0_mc)
... A50014: 50000 | B50014: =LN(MC_Paths!B50003/S0_mc)
A50016: Interpretation: Sharpe = 1.078 reflects Rheinmetall's historical defence re-rating drift of ~54% p.a. -- well above typical equity risk premia of 6-8%. 95% VaR = 19.27%: in 95% of simulated years, the investor loses less than 19.27% of capital.

Sheet P3_TaskIX
A1: Task IX -- Portfolio Insurance Grid (alpha x strike)
A2: BS put prices and shares allocation (W0=10,000 EUR, S0=1,207 EUR)
A3: Alpha / Strike | B3: K=90%*S0 = 1086.30 EUR | C3: K=95%*S0 = 1146.65 EUR | D3: K=100%*S0 = 1207.00 EUR | E3: K=105%*S0 = 1267.35 EUR
A4: Put price (EUR)
A5: alpha=5% | B5: 114.1564 | C5: 142.0606 | D5: 173.0431 | E5: 206.9236
A6: alpha=10% | B6: 114.1564 | C6: 142.0606 | D6: 173.0431 | E6: 206.9236
A7: alpha=15% | B7: 114.1564 | C7: 142.0606 | D7: 173.0431 | E7: 206.9236
A8: alpha=20% | B8: 114.1564 | C8: 142.0606 | D8: 173.0431 | E8: 206.9236
A10: Number of puts (n_puts = alpha*W0/PutPrice)
A11: alpha=5% | B11: 4.38 | C11: 3.5196 | D11: 2.8895 | E11: 2.4164
A12: alpha=10% | B12: 8.7599 | C12: 7.0393 | D12: 5.7789 | E12: 4.8327
A13: alpha=15% | B13: 13.1399 | C13: 10.5589 | D13: 8.6684 | E13: 7.2491
A14: alpha=20% | B14: 17.5198 | C14: 14.0785 | D14: 11.5578 | E14: 9.6654
A16: Performance summary (precomputed from 50,000 paths)
A17: Alpha | B17: Strike | C17: Mean ret | D17: Std | E17: Sharpe | F17: VaR95 | G17: CVaR95 | H17: P(loss) | I17: NB target VaR95
A18: 5% | B18: 90% = 1086.30 EUR | C18: 0.4178426 | D18: 0.38200995 | E18: 1.0134857 | F18: 0.19442931 | G18: 0.2602353 | H18: 0.15158 | I18: 0.1945
A19: 5% | B19: 95% = 1146.65 EUR | C19: 0.41866875 | D19: 0.38088453 | E19: 1.0186493 | F19: 0.17824943 | G19: 0.26004885 | H19: 0.15158 | I19: 0.1783
A20: 5% | B20: 100% = 1207.00 EUR | C20: 0.41948985 | D20: 0.37988412 | E20: 1.0234933 | F20: 0.16883692 | G20: 0.26254476 | H20: 0.15158 | I20: 0.1689
A21: 5% | B21: 105% = 1267.35 EUR | C21: 0.42030344 | D21: 0.37899978 | E21: 1.0280281 | F21: 0.1634331 | G21: 0.26628409 | H21: 0.15158 | I21: 0.1635
A22: 10% | B22: 90% = 1086.30 EUR | C22: 0.37148768 | D22: 0.36932606 | E22: 0.92277994 | F22: 0.18701661 | G22: 0.19951926 | H22: 0.18624 | I22: 0.187
A23: 10% | B23: 95% = 1146.65 EUR | C23: 0.37326864 | D23: 0.36663303 | E23: 0.93441564 | F23: 0.16405739 | G23: 0.17132721 | H23: 0.18624 | I23: 0.1641
A24: 10% | B24: 100% = 1207.00 EUR | C24: 0.37503578 | D24: 0.36420042 | E24: 0.94550901 | F24: 0.14558175 | G24: 0.1747974 | H24: 0.18624 | I24: 0.1456
A25: 10% | B25: 105% = 1267.35 EUR | C25: 0.37678324 | D25: 0.36201989 | E25: 0.95603099 | F25: 0.13504962 | G25: 0.180891 | H25: 0.18624 | I25: 0.1351
A26: 15% | B26: 90% = 1086.30 EUR | C26: 0.3217076 | D26: 0.35979498 | E26: 0.80886787 | F26: 0.20556948 | G26: 0.23677671 | H26: 0.2222 | I26: 0.2055
A27: 15% | B27: 95% = 1146.65 EUR | C27: 0.32453125 | D27: 0.35538886 | E27: 0.82684147 | F27: 0.1750126 | G27: 0.1945488 | H27: 0.22608 | I27: 0.175
A28: 15% | B28: 100% = 1207.00 EUR | C28: 0.32733797 | D28: 0.35133112 | E28: 0.84438 | F28: 0.14314149 | G28: 0.15313699 | H28: 0.22818 | I28: 0.1431
A29: 15% | B29: 105% = 1267.35 EUR | C29: 0.33011606 | D29: 0.34762998 | E29: 0.86136145 | F29: 0.11111068 | G29: 0.11244568 | H29: 0.22818 | I29: 0.1111
... A33: 20% | B33: 105% = 1267.35 EUR | C33: 0.28006795 | D33: 0.33563029 | E33: 0.74304064 | F33: 0.14780495 | G33: 0.16097725 | H33: 0.26718 | I33: 0.1478
A36: Discussion: Under high-drift regime (mu=54%), the VaR vs alpha curve is U-shaped at K=95%. VaR first falls then rises as alpha increases. Minimum VaR (~16.4%) is at alpha=10%, K=95%. At the 5th percentile outcome, RHM has risen modestly, so puts expire OTM, but the premium paid reduces terminal wealth. Larger alpha = more premium burned with no put payoff.

Sheet P3_TaskX
A1: Task X -- Stress Scenarios (alpha=10%, K=95%*S0=1146.65 EUR)
A2: Chosen allocation: | B2: alpha = 10%, K_s = 95% * 1207 = 1146.65 EUR
A3: Parameter | B3: Baseline | C3: Vol+5pp | D3: Vol-5pp | E3: Shock(-20% at T/2)
A4: Put price (EUR) | B4: 142.06057 | C4: 164.22822 | D4: 119.88491 | E4: 142.06057
A5: n_puts | B5: 7.0392507 | C5: 6.0890876 | D5: 8.3413337 | E5: 7.0392507
A6: n_shares | B6: 7.4565037 | C6: 7.4565037 | D6: 7.4565037 | E6: 7.4565037
A7: GBM terminal | B7: S_term | C7: S_term | D7: S_term | E7: S_term_shock
A9: Scenario results (precomputed from 50,000 paths)
A10: Metric | B10: Baseline | C10: Vol+5pp | D10: Vol-5pp | E10: Shock(-20% T/2)
A11: Mean return | B11: 0.37326864 | C11: 0.3711642 | D11: 0.37603989 | E11: 0.1842894
A12: 95% VaR | B12: 0.16405739 | C12: 0.18112409 | D12: 0.14301245 | E12: 0.17389422
A13: 95% CVaR | B13: 0.17132721 | C13: 0.20570547 | D13: 0.15018175 | E13: 0.17976083
A14: P(loss) | B14: 0.18624 | C14: 0.18624 | D14: 0.18624 | E14: 0.36946
A15: Std dev | B15: 0.36663303 | C15: 0.3698393 | D15: 0.36265417 | E15: 0.32412428
A16: Sharpe | B16: 0.93441564 | C16: 0.92062471 | D16: 0.95230916 | E16: 0.47391822
A18: Discussion: (a) Vol+5pp raises VaR from 16.41% to 18.11% -- breaching the 15% regulatory limit from Task XI, illustrating model risk from volatility mis-estimation. (b) The -20% mid-horizon shock more than doubles P(loss) (18.6% to 36.9%) and nearly halves mean return (37.3% to 18.4%), because the residual 90% stock position absorbs most of the crash. (c) The put (struck at 95%*S0, still has time value at T/2) only partially offsets the shock.

Sheet P3_TaskXI
A1: Task XI -- VaR Constraint Scan (K=95%*S0, VAR limit=15%)
A2: VaR limit: | B2: 0.15
A3: K_xi: | B3: 1146.65
A4: FEASIBILITY NOTE: With K=95%*S0=1146.65 EUR and 50,000 paths (seed=2026), the minimum achievable 95% VaR is approximately 16.1% (at alpha~12%). The 15% VaR constraint CANNOT be satisfied at this strike. At K=100%*S0=1207 EUR the constraint IS achievable: alpha=10% yields VaR=14.56% and alpha=5% yields VaR=16.89%, so the binding alpha* at K=100% lies between 5% and 10%. Linear interpolation: alpha* = 5% + (16.89%-15.00%)/(16.89%-14.56%)*5% = 9.0%. At K=100%, alpha=9% fully utilizes the 15% VaR budget.
A7: Alpha | B7: Put price (EUR) | C7: 95% VaR | D7: Status | E7: vs 15% limit
A8: 0.01 | B8: 142.06057 | C8: 0.18974989 | D8: infeasible | E8: 0.03974989
A9: 0.015 | B9: 142.06057 | C9: 0.18830508 | D9: infeasible | E9: 0.038305079
A10: 0.02 | B10: 142.06057 | C10: 0.18686235 | D10: infeasible | E10: 0.036862352
A11: 0.025 | B11: 142.06057 | C11: 0.1854217 | D11: infeasible | E11: 0.035421703
A12: 0.03 | B12: 142.06057 | C12: 0.18398313 | D12: infeasible | E12: 0.033983128
A13: 0.035 | B13: 142.06057 | C13: 0.18254662 | D13: infeasible | E13: 0.032546618
A14: 0.04 | B14: 142.06057 | C14: 0.18111217 | D14: infeasible | E14: 0.031112169
A15: 0.045 | B15: 142.06057 | C15: 0.17967978 | D15: infeasible | E15: 0.029679775
A16: 0.05 | B16: 142.06057 | C16: 0.17824943 | D16: infeasible | E16: 0.02824943
A17: 0.055 | B17: 142.06057 | C17: 0.17682113 | D17: infeasible | E17: 0.026821128
A18: 0.06 | B18: 142.06057 | C18: 0.17539486 | D18: infeasible | E18: 0.025394862
A19: 0.065 | B19: 142.06057 | C19: 0.17397063 | D19: infeasible | E19: 0.023970629
... A86: 0.4 | B86: 142.06057 | C86: 0.47820091 | D86: infeasible | E86: 0.32820091
A88: Verification -- alpha=9%, K=100%*S0=1207 EUR:
A89: VaR95 (computed): | B89: 0.15018972 | C89: Target: ~15.0% | D89: PASS

Sheet CrossCheck
A1: CrossCheck -- Reconciliation against Python notebook targets
A2: Label | B2: Workbook value | C2: Notebook target | D2: Tolerance | E2: Pass/Fail
A3: Part 1: r(3y) Svensson | B3: 0.026191594 | C3: 0.026192 | D3: 0.0001 | E3: PASS
A4: Part 1: ZCB0 (EUR) | B4: 1115.7905 | C4: 1115.79 | D4: 0.1 | E4: PASS
A5: Part 1: ATM call (EUR) | B5: 451.04309 | C5: 451.04 | D5: 0.1 | E5: PASS
A6: Part 1: Cap call (EUR) | B6: 353.43305 | C6: 353.43 | D6: 0.1 | E6: PASS
A7: Part 1: Spread (EUR) | B7: 97.610038 | C7: 97.61 | D7: 0.1 | E7: PASS
A8: Part 1: Alpha | B8: 0.93442703 | C8: 0.9344 | D8: 0.001 | E8: PASS
A9: Part 1: Kapitalschutz (EUR bn) | B9: 4.256 | C9: 4.256 | D9: 0.001 | E9: PASS
A10: Part 2: Task V ME (EUR) | B10: -85.544153 | C10: -85.54 | D10: 0.1 | E10: PASS
A11: Part 2: Task V MAE (EUR) | B11: 94.491038 | C11: 94.49 | D11: 0.1 | E11: PASS
A12: Part 2: Task V RMSE (EUR) | B12: 108.91915 | C12: 108.92 | D12: 0.1 | E12: PASS
A13: Part 2: Task V MAPE (%) | B13: 6.1091803 | C13: 6.11 | D13: 0.05 | E13: PASS
A14: Part 2: Task VI Price at ref (EUR) | B14: 1465.2064 | C14: 1457.77 | D14: 15 | E14: PASS
... A30: Delta method divergence (RR vs N=200 tree) | B30: 0.53159756 | C30: 0.244901 | D30: 0.5 | E30: KNOWN DIVERGENCE
A33: TOTAL PASS: 28 | TOTAL FAIL: 0 (RR delta/theta vs N=200 tree documented in KNOWN DIVERGENCE row -- methodological, not an error)
