Workbook
Name AnnualDiv: Inputs!$B$11
Name Barrier: Inputs!$B$6
Name Bonus: Inputs!$B$5
Name Cap: Inputs!$B$4
Name dR: Inputs!$B$18
Name dS: Inputs!$B$15
Name dSig: Inputs!$B$16
Name dT: Inputs!$B$17
Name EWMAlambda: Inputs!$B$14
Name IssueDate: Inputs!$B$8
Name K_d: Inputs!$B$22
Name KCap_d: Inputs!$B$23
Name MaturityDate: Inputs!$B$9
Name q: Inputs!$B$13
Name Ratio: Inputs!$B$7
Name RedemptionDate: Inputs!$B$10
Name RefSpot: Inputs!$B$12
Name S0_d: Inputs!$B$21
Name Sig_d: Inputs!$B$25
Name svb0: Inputs!$B$26
Name svb1: Inputs!$B$27
Name svb2: Inputs!$B$28
Name svb3: Inputs!$B$29
Name svt1: Inputs!$B$30
Name svt2: Inputs!$B$31
Name T_d: Inputs!$B$24

Sheet Cover
B2: B401 — Continuous-Time Derivatives Pricing
B3: Parts 1 & 2 (Tasks I–VII) — Live-Formula Workbook
B6: Product | C6: Bonus-Zertifikat mit Cap (Bonus Cap certificate)
B7: WKN / ISIN | C7: DU2076 / DE000DU20767
B8: Issuer | C8: DZ BANK AG
B9: Underlying | C9: Rheinmetall AG (ISIN DE0007030009), XETRA, EUR
B10: Valuation method | C10: Closed-form Rubinstein-Reiner (1991): capped forward + down-and-out put
B11: Risk-free curve | C11: ECB AAA Svensson (1994), daily, maturity-matched
B12: Volatility | C12: EWMA (lambda=0.94), imported per day (derived in Python notebook)
B14: SOURCING LEGEND
B15: Blue text | C15: Hard input / contractual term (entered once, sourced)
B16: Black text | C16: Formula / calculation
B17: Green text | C17: Link to a raw data worksheet
B18: Yellow fill | C18: Key assumption
B20: WORKSHEETS
B21: Data_Stock | C21: RHM.DE daily close + EWMA vol + Python tree cross-check
B22: Data_Cert | C22: DU2076 market prices (onvista/ariva export, German format)
B23: Data_Svensson | C23: ECB AAA Svensson parameters, daily (window)
B24: Inputs | C24: All named ranges (contractual terms + model params)
B25: P1_Tasks_I_IV | C25: Investor profile, product design, payoff, market size
B26: P2_TaskV_Valuation | C26: Daily model vs market price, ME/MAE/RMSE
B27: P2_TaskVI_Greeks | C27: Delta/Gamma/Vega/Theta/Rho via finite differences
B28: P2_TaskVII_Replication | C28: Daily replicating portfolio, equity fraction
B29: CRR_CrossCheck | C29: Binomial tree (N=50) cross-check of the closed form
B30: Results | C30: Key-output summary

Sheet Inputs
A1: INPUTS — named ranges (contractual terms & model parameters)
A3: Parameter | B3: Value | C3: Name | D3: Source / Derivation
A4: Cap / Höchstbetrag (EUR) | B4: 2000 | C4: Cap | D4: DZ BANK KID DE000DU20767, 12.06.2026 (dzbank-derivate.de)
A5: Bonus level (EUR) | B5: 2000 | C5: Bonus | D5: DZ BANK KID — Bonusbetrag
A6: Barrier / Schwelle (EUR) | B6: 1050 | C6: Barrier | D6: DZ BANK KID — Barriere, observed continuously
A7: Subscription ratio | B7: 1 | C7: Ratio | D7: DZ BANK KID — Bezugsverhältnis
A8: Issue date | B8: 45904 | C8: IssueDate | D8: DZ BANK KID — Emissionstag
A9: Valuation date (Bewertungstag) | B9: 46556 | C9: MaturityDate | D9: DZ BANK KID — final fixing; T measured to this date
A10: Redemption date | B10: 46563 | C10: RedemptionDate | D10: DZ BANK KID — Rückzahlungstermin
A11: Annual dividend / share (EUR) | B11: 7.2 | C11: AnnualDiv | D11: Rheinmetall AG FY guidance (investor relations)
A12: Reference spot (latest, EUR) | B12: =Data_Stock!B186 -> 1207 | C12: RefSpot | D12: Last RHM.DE close in window (Data_Stock)
A13: Dividend yield q | B13: =ROUND(AnnualDiv/RefSpot,4) -> 0.006 | C13: q | D13: Continuous q = annual dividend / reference spot
A14: EWMA lambda | B14: 0.94 | C14: EWMAlambda | D14: RiskMetrics standard; EWMA computed in Python notebook
A15: Delta/Gamma bump (dS) | B15: 0.01 | C15: dS | D15: Central finite-difference step on S
A16: Vega bump (dSig) | B16: 0.02 | C16: dSig | D16: Central FD step on volatility
A17: Theta step (years) | B17: =1/252 -> 0.003968254 | C17: dT | D17: One trading day (Theta annualised on 365 convention)
A18: Rho bump (dR) | B18: 0.0001 | C18: dR | D18: Central FD step on rate (1 bp)
A20: PART 1 — DESIGN-DATE SNAPSHOT (01 Jun 2026)
A21: Design spot S0 (EUR) | B21: =RefSpot -> 1207 | C21: S0_d | D21: Latest RHM.DE close
A22: ATM strike K = S0 | B22: =S0_d -> 1207 | C22: K_d | D22: At-the-money
A23: Cap strike (130% of S0) | B23: =1.3*S0_d -> 1569.1 | C23: KCap_d | D23: Cap at +30%
A24: Design horizon T (yrs) | B24: 3 | C24: T_d | D24: 3-year note
A25: Design vol (EWMA latest) | B25: =Data_Stock!C186 -> 0.542 | C25: Sig_d | D25: Latest EWMA vol (Data_Stock)
A26: Svensson beta0 (design) | B26: 1.330382 | C26: svb0 | D26: ECB AAA params 01 Jun 2026
A27: Svensson beta1 (design) | B27: 0.700052 | C27: svb1 | D27: ECB AAA params 01 Jun 2026
A28: Svensson beta2 (design) | B28: 1.816755 | C28: svb2 | D28: ECB AAA params 01 Jun 2026
A29: Svensson beta3 (design) | B29: 7.130184 | C29: svb3 | D29: ECB AAA params 01 Jun 2026
A30: Svensson tau1 (design) | B30: 0.966763 | C30: svt1 | D30: ECB AAA params 01 Jun 2026
A31: Svensson tau2 (design) | B31: 15.839369 | C31: svt2 | D31: ECB AAA params 01 Jun 2026

Sheet Data_Stock
A1: Data_Stock — Rheinmetall AG (RHM.DE) daily
A2: Source: Yahoo Finance RHM.DE (auto-adjusted close), XETRA EUR | EWMA sigma (lambda=0.94) & Python N=200 tree price reconciled from notebook | export 2026-06-15
A3: Date | B3: RHM_Spot_EUR | C3: EWMA_sigma | D3: Tree_Model_Py
A4: 45904 | B4: 1707.93 | C4: 0.39 | D4: 1558.89
A5: 45905 | B5: 1727.24 | C5: 0.38 | D5: 1571.16
A6: 45908 | B6: 1773.27 | C6: 0.383 | D6: 1601.18
A7: 45909 | B7: 1761.39 | C7: 0.372 | D7: 1607.28
A8: 45910 | B8: 1819.31 | C8: 0.382 | D8: 1628.9
A9: 45911 | B9: 1861.89 | C9: 0.381 | D9: 1636.5
A10: 45912 | B10: 1877.73 | C10: 0.371 | D10: 1666.15
A11: 45915 | B11: 1930.7 | C11: 0.376 | D11: 1688.12
A12: 45916 | B12: 1882.19 | C12: 0.377 | D12: 1663.42
A13: 45917 | B13: 1869.81 | C13: 0.367 | D13: 1669.48
A14: 45918 | B14: 1900.5 | C14: 0.361 | D14: 1694.37
A15: 45919 | B15: 1908.92 | C15: 0.351 | D15: 1721
... A186: 46174 | B186: 1207 | C186: 0.542 | D186: 1153.79

Sheet Data_Cert
A1: Data_Cert — DU2076 certificate market prices
A2: Source: onvista.de / ariva.de historical export (DU2076) | German format parsed (";" sep, comma decimal) | Schluss = closing price (EUR)
A3: Date | B3: Open | C3: High | D3: Low | E3: Close_EUR
A4: 45904 | B4: 1658.44 | C4: 1658.67 | D4: 1627.07 | E4: 1635.75
A5: 45905 | B5: 1640.27 | C5: 1657.3 | D5: 1638.78 | E5: 1648.28
A6: 45908 | B6: 1656.37 | C6: 1679.73 | D6: 1656.05 | E6: 1675.51
A7: 45909 | B7: 1683.01 | C7: 1684.43 | D7: 1647.75 | E7: 1671.59
A8: 45910 | B8: 1677.11 | C8: 1700.7 | D8: 1675.16 | E8: 1699.14
A9: 45911 | B9: 1706.63 | C9: 1723.87 | D9: 1691.8 | E9: 1721.63
A10: 45912 | B10: 1721.39 | C10: 1726.5 | D10: 1710.88 | E10: 1713.91
A11: 45915 | B11: 1720.16 | C11: 1736.82 | D11: 1720.02 | E11: 1735.5
A12: 45916 | B12: 1740.5 | C12: 1747.87 | D12: 1713.39 | E12: 1728.41
A13: 45917 | B13: 1726.16 | C13: 1738.88 | D13: 1695.26 | E13: 1699.94
A14: 45918 | B14: 1705.82 | C14: 1711.61 | D14: 1696.04 | E14: 1708.18
A15: 45919 | B15: 1709.86 | C15: 1715.64 | D15: 1703.53 | E15: 1711.35
... A195: 46185 | B195: 1266.18 | C195: 1266.74 | D195: 1198.61 | E195: 1220.23

Sheet Data_Svensson
A1: Data_Svensson — ECB AAA yield-curve parameters (Svensson 1994)
A2: Source: ECB Data Portal, AAA-rated euro-area sovereign curve, series SV_C_YM (data.ecb.europa.eu) | window from 2025-09-01 | dates ascending for approx-match lookup
A3: Date | B3: beta0 | C3: beta1 | D3: beta2 | E3: beta3 | F3: tau1 | G3: tau2
A4: 45901 | B4: 1.169597 | C4: 0.803566 | D4: -1.467045 | E4: 7.589717 | F4: 2.668143 | G4: 12.846858
A5: 45902 | B5: 1.184179 | C5: 0.780869 | D5: -1.365573 | E5: 7.66682 | F5: 2.705239 | G5: 13.019474
A6: 45903 | B6: 1.182767 | C6: 0.779823 | D6: -1.439882 | E6: 7.580719 | F6: 2.718588 | G6: 12.987219
A7: 45904 | B7: 1.168343 | C7: 0.791456 | D7: -1.558745 | E7: 7.547626 | F7: 2.877366 | G7: 12.757641
A8: 45905 | B8: 1.167426 | C8: 0.761807 | D8: -1.821262 | E8: 7.664804 | F8: 3.218451 | G8: 12.62628
A9: 45908 | B9: 1.198176 | C9: 0.752225 | D9: -2.297018 | E9: 7.725683 | F9: 3.438575 | G9: 11.802636
A10: 45909 | B10: 1.205197 | C10: 0.740409 | D10: -1.677676 | E10: 7.39418 | F10: 3.023955 | G10: 12.832287
A11: 45910 | B11: 1.202277 | C11: 0.761658 | D11: -1.692318 | E11: 7.386787 | F11: 3.026223 | G11: 12.836812
A12: 45911 | B12: 1.204237 | C12: 0.75691 | D12: -1.615143 | E12: 7.356917 | F12: 3.268254 | G12: 12.889797
A13: 45912 | B13: 1.199688 | C13: 0.744959 | D13: -1.462092 | E13: 7.352704 | F13: 3.328068 | G13: 12.832385
A14: 45915 | B14: 1.194697 | C14: 0.750982 | D14: -1.484931 | E14: 7.34158 | F14: 3.322536 | G14: 12.848706
A15: 45916 | B15: 1.190226 | C15: 0.772804 | D15: -1.510362 | E15: 7.343672 | F15: 3.311418 | G15: 12.845352
... A202: 46185 | B202: 1.30874 | C202: 0.784584 | D202: 1.729877 | E202: 7.236039 | F202: 0.99304 | G202: 15.935159

Sheet P1_Tasks_I_IV
A1: PART 1 — Tasks I–IV (no pricing required; figures below are design-validation only)
A3: Task I — Investor profile
A4: Target: German retail 'Sicherheitsorientierter Verteidigungsinvestor' (age 40–60, 3–5y horizon, low-to-moderate risk). Structurally bullish on European re-armament and Rheinmetall (record order backlog) over ~3y (+15–30% view), but cannot tolerate Rheinmetall's ~54% single-stock volatility / drawdown risk. Capital preservation at maturity is non-negotiable. Needs Rheinmetall upside without permanent capital impairment.
A9: Task II — Product design: Capped Capital-Protected Participation Note on RHM.DE
A11: Component | B11: Position | C11: Role
A12: Zero-coupon bond (face = S0) | B12: Long | C12: Guarantees 100% capital back at maturity
A13: ATM European call (K = S0) | B13: Long (alpha units) | C13: Participation in RHM gains above S0
A14: OTM European call (K = 130% S0) | B14: Short (alpha units) | C14: Caps gain at ~30%; premium funds higher alpha
A17: Design pricing (Svensson 3y, BS calls) — validation of alpha
A18: 3y Svensson factor f1 | B18: =(1-EXP(-T_d/SVT1))/(T_d/SVT1) -> #DIV/0!
A19: 3y Svensson factor f2 | B19: =(1-EXP(-T_d/SVT1))/(T_d/SVT1)-EXP(-T_d/SVT1) -> #DIV/0!
A20: 3y Svensson factor f3 | B20: =(1-EXP(-T_d/SVT2))/(T_d/SVT2)-EXP(-T_d/SVT2) -> #DIV/0!
A21: Design rate r(3y) | B21: =(svb0+SVB1*B18+SVB2*B19+SVB3*B20)/100 -> #DIV/0!
A22: ZCB present value | B22: =S0_d*EXP(-B21*T_d) -> #DIV/0!
A23: ATM call d1 | B23: =(LN(S0_d/K_d)+(B21-q+0.5*Sig_d^2)*T_d)/(Sig_d*SQRT(T_d)) -> #DIV/0!
A24: ATM call value | B24: =S0_d*EXP(-q*T_d)*NORMSDIST(B23)-K_d*EXP(-B21*T_d)*NORMSDIST(B23-Sig_d*SQRT(T_d)) -> #DIV/0!
A25: Cap call d1 | B25: =(LN(S0_d/KCap_d)+(B21-q+0.5*Sig_d^2)*T_d)/(Sig_d*SQRT(T_d)) -> #DIV/0!
A26: Cap call value | B26: =S0_d*EXP(-q*T_d)*NORMSDIST(B25)-KCap_d*EXP(-B21*T_d)*NORMSDIST(B25-Sig_d*SQRT(T_d)) -> #DIV/0!
A27: Call spread (long-short) | B27: =B24-B26 -> #DIV/0!
A28: Participation rate alpha | B28: =(S0_d-B22)/B27 -> #DIV/0!
A29: Max gain (S_T>=Cap), % nominal | B29: =B28*(KCap_d-K_d)/S0_d -> #DIV/0!
A31: Task III — Payoff at maturity (per unit nominal S0)
A32: S_T / S0 | B32: S_T (EUR) | C32: Note payoff (EUR) | D32: Return %
A33: 0.5 | B33: =A33*S0_d -> 603.5 | C33: =S0_d+B$28*(MAX(B33-K_d,0)-MAX(B33-KCap_d,0)) -> #DIV/0! | D33: =C33/S0_d-1 -> #DIV/0!
A34: 0.7 | B34: =A34*S0_d -> 844.9 | C34: =S0_d+B$28*(MAX(B34-K_d,0)-MAX(B34-KCap_d,0)) -> #DIV/0! | D34: =C34/S0_d-1 -> #DIV/0!
A35: 0.8 | B35: =A35*S0_d -> 965.6 | C35: =S0_d+B$28*(MAX(B35-K_d,0)-MAX(B35-KCap_d,0)) -> #DIV/0! | D35: =C35/S0_d-1 -> #DIV/0!
A36: 0.9 | B36: =A36*S0_d -> 1086.3 | C36: =S0_d+B$28*(MAX(B36-K_d,0)-MAX(B36-KCap_d,0)) -> #DIV/0! | D36: =C36/S0_d-1 -> #DIV/0!
A37: 1 | B37: =A37*S0_d -> 1207 | C37: =S0_d+B$28*(MAX(B37-K_d,0)-MAX(B37-KCap_d,0)) -> #DIV/0! | D37: =C37/S0_d-1 -> #DIV/0!
A38: 1.1 | B38: =A38*S0_d -> 1327.7 | C38: =S0_d+B$28*(MAX(B38-K_d,0)-MAX(B38-KCap_d,0)) -> #DIV/0! | D38: =C38/S0_d-1 -> #DIV/0!
A39: 1.2 | B39: =A39*S0_d -> 1448.4 | C39: =S0_d+B$28*(MAX(B39-K_d,0)-MAX(B39-KCap_d,0)) -> #DIV/0! | D39: =C39/S0_d-1 -> #DIV/0!
A40: 1.3 | B40: =A40*S0_d -> 1569.1 | C40: =S0_d+B$28*(MAX(B40-K_d,0)-MAX(B40-KCap_d,0)) -> #DIV/0! | D40: =C40/S0_d-1 -> #DIV/0!
A41: 1.4 | B41: =A41*S0_d -> 1689.8 | C41: =S0_d+B$28*(MAX(B41-K_d,0)-MAX(B41-KCap_d,0)) -> #DIV/0! | D41: =C41/S0_d-1 -> #DIV/0!
A42: 1.6 | B42: =A42*S0_d -> 1931.2 | C42: =S0_d+B$28*(MAX(B42-K_d,0)-MAX(B42-KCap_d,0)) -> #DIV/0! | D42: =C42/S0_d-1 -> #DIV/0!
A44: Task IV — German market-size estimate (capital-protection participation segment)
A45: Total German structured-product market (EUR bn) | B45: 112 | C45: Source: BSW 2023 market report
A46: Kapitalschutz share of total | B46: 0.038 | C46: Source: BSW 2023, slide 13
A47: Kapitalschutz segment (EUR bn) | B47: =B45*B46 -> 4.256
A48: Participation-note share of segment | B48: 0.55 | C48: Source: Author estimate
A49: Participation-note market (EUR bn) | B49: =B47*B48 -> 2.3408
A50: Active issues (est.) | B50: 130 | C50: Source: ~6 issuers x ~20 products
A51: Average issue size (EUR mn) | B51: =B47*1000/B50 -> 32.738462

Sheet P2_TaskV_Valuation
A1: Task V — Daily valuation: closed-form Bonus Cap (Rubinstein-Reiner) vs market
A2: Model = capped forward [K*e^-rT - vanilla put] + down-and-out put (RR 1991, X>H). r = daily ECB Svensson r(T_rem); sigma = EWMA(0.94); q from Inputs. All cells live formulas.
A3: Date | B3: S (EUR) | C3: sigma | D3: T_rem | E3: beta0 | F3: beta1 | G3: beta2 | H3: beta3 | I3: tau1 | J3: tau2 | K3: f1 | L3: f2 | M3: f3 | N3: r(T) | O3: carry b | P3: sig*sqrtT | Q3: mu | R3: x1 | S3: x2 | T3: y1 | U3: y2 | V3: A (van.put) | W3: B | X3: C | Y3: D | Z3: DO put | AA3: capped fwd | AB3: Model (EUR) | AC3: Market (EUR) | AD3: Error | AE3: Error % | AF3: Py tree (xchk)
A4: =Data_Stock!A4 -> 45904 | B4: =Data_Stock!B4 -> 1707.93 | C4: =Data_Stock!C4 -> 0.39 | D4: =MAX((MaturityDate-A4)/365,1/365) -> 1.7863014 | E4: =INDEX(Data_Svensson!$B$4:$B$202,MATCH($A4,Data_Svensson!$A$4:$A$202,1)) -> 1.168343 | F4: =INDEX(Data_Svensson!$C$4:$C$202,MATCH($A4,Data_Svensson!$A$4:$A$202,1)) -> 0.791456 | G4: =INDEX(Data_Svensson!$D$4:$D$202,MATCH($A4,Data_Svensson!$A$4:$A$202,1)) -> -1.558745 | H4: =INDEX(Data_Svensson!$E$4:$E$202,MATCH($A4,Data_Svensson!$A$4:$A$202,1)) -> 7.547626 | I4: =INDEX(Data_Svensson!$F$4:$F$202,MATCH($A4,Data_Svensson!$A$4:$A$202,1)) -> 2.877366 | J4: =INDEX(Data_Svensson!$G$4:$G$202,MATCH($A4,Data_Svensson!$A$4:$A$202,1)) -> 12.757641 | K4: =(1-EXP(-D4/I4))/(D4/I4) -> 0.7449797 | L4: =K4-EXP(-D4/I4) -> 0.20747153 | M4: =(1-EXP(-D4/J4))/(D4/J4)-EXP(-D4/J4) -> 0.063804736 | N4: =(E4+F4*K4+G4*L4+H4*M4)/100 -> 0.019161407 | O4: =N4-q -> 0.013161407 | P4: =C4*SQRT(D4) -> 0.52124508 | Q4: =(O4-0.5*C4^2)/C4^2 -> -0.41346872 | R4: =LN(B4/Cap)/P4+(1+Q4)*P4 -> 0.0028650429 | S4: =LN(B4/Barrier)/P4+(1+Q4)*P4 -> 1.2390532 | T4: =LN(Barrier^2/(B4*Cap))/P4+(1+Q4)*P4 -> -1.8637883 | U4: =LN(Barrier/B4)/P4+(1+Q4)*P4 -> -0.62760014 | V4: =-B4*EXP((O4-N4)*D4)*NORMSDIST(-R4)+Cap*EXP(-N4*D4)*NORMSDIST(-R4+P4) -> 505.90959 | W4: =-B4*EXP((O4-N4)*D4)*NORMSDIST(-S4)+Cap*EXP(-N4*D4)*NORMSDIST(-S4+P4) -> 275.04344 | X4: =-B4*EXP((O4-N4)*D4)*(Barrier/B4)^(2*(Q4+1))*NORMSDIST(T4)+Cap*EXP(-N4*D4)*(Barrier/B4)^(2*Q4)*NORMSDIST(T4-P4) -> -5.0943833 | Y4: =-B4*EXP((O4-N4)*D4)*(Barrier/B4)^(2*(Q4+1))*NORMSDIST(U4)+Cap*EXP(-N4*D4)*(Barrier/B4)^(2*Q4)*NORMSDIST(U4-P4) -> 108.94909 | Z4: =IF(B4<=Barrier,0,V4-W4+X4-Y4) -> 116.82268 | AA4: =Cap*EXP(-N4*D4)-V4 -> 1426.7926 | AB4: =AA4+Z4 -> 1543.6153 | AC4: =INDEX(Data_Cert!$E$4:$E$195,MATCH($A4,Data_Cert!$A$4:$A$195,0)) -> 1635.75 | AD4: =AB4-AC4 -> -92.134707 | AE4: =AD4/AC4 -> -0.056325665 | AF4: =Data_Stock!D4 -> 1558.89
A5: =Data_Stock!A5 -> 45905 | B5: =Data_Stock!B5 -> 1727.24 | C5: =Data_Stock!C5 -> 0.38 | D5: =MAX((MaturityDate-A5)/365,1/365) -> 1.7835616 | E5: =INDEX(Data_Svensson!$B$4:$B$202,MATCH($A5,Data_Svensson!$A$4:$A$202,1)) -> 1.167426 | F5: =INDEX(Data_Svensson!$C$4:$C$202,MATCH($A5,Data_Svensson!$A$4:$A$202,1)) -> 0.761807 | G5: =INDEX(Data_Svensson!$D$4:$D$202,MATCH($A5,Data_Svensson!$A$4:$A$202,1)) -> -1.821262 | H5: =INDEX(Data_Svensson!$E$4:$E$202,MATCH($A5,Data_Svensson!$A$4:$A$202,1)) -> 7.664804 | I5: =INDEX(Data_Svensson!$F$4:$F$202,MATCH($A5,Data_Svensson!$A$4:$A$202,1)) -> 3.218451 | J5: =INDEX(Data_Svensson!$G$4:$G$202,MATCH($A5,Data_Svensson!$A$4:$A$202,1)) -> 12.62628 | K5: =(1-EXP(-D5/I5))/(D5/I5) -> 0.76772742 | L5: =K5-EXP(-D5/I5) -> 0.19317717 | M5: =(1-EXP(-D5/J5))/(D5/J5)-EXP(-D5/J5) -> 0.064317119 | N5: =(E5+F5*K5+G5*L5+H5*M5)/100 -> 0.01893438 | O5: =N5-q -> 0.01293438 | P5: =C5*SQRT(D5) -> 0.5074902 | Q5: =(O5-0.5*C5^2)/C5^2 -> -0.41042673 | R5: =LN(B5/Cap)/P5+(1+Q5)*P5 -> 0.010285899 | S5: =LN(B5/Barrier)/P5+(1+Q5)*P5 -> 1.2799794 | T5: =LN(Barrier^2/(B5*Cap))/P5+(1+Q5)*P5 -> -1.9512676 | U5: =LN(Barrier/B5)/P5+(1+Q5)*P5 -> -0.68157411 | V5: =-B5*EXP((O5-N5)*D5)*NORMSDIST(-R5)+Cap*EXP(-N5*D5)*NORMSDIST(-R5+P5) -> 487.68272 | W5: =-B5*EXP((O5-N5)*D5)*NORMSDIST(-S5)+Cap*EXP(-N5*D5)*NORMSDIST(-S5+P5) -> 253.86213 | X5: =-B5*EXP((O5-N5)*D5)*(Barrier/B5)^(2*(Q5+1))*NORMSDIST(T5)+Cap*EXP(-N5*D5)*(Barrier/B5)^(2*Q5)*NORMSDIST(T5-P5) -> -3.961018 | Y5: =-B5*EXP((O5-N5)*D5)*(Barrier/B5)^(2*(Q5+1))*NORMSDIST(U5)+Cap*EXP(-N5*D5)*(Barrier/B5)^(2*Q5)*NORMSDIST(U5-P5) -> 105.58453 | Z5: =IF(B5<=Barrier,0,V5-W5+X5-Y5) -> 124.27504 | AA5: =Cap*EXP(-N5*D5)-V5 -> 1445.9037 | AB5: =AA5+Z5 -> 1570.1788 | AC5: =INDEX(Data_Cert!$E$4:$E$195,MATCH($A5,Data_Cert!$A$4:$A$195,0)) -> 1648.28 | AD5: =AB5-AC5 -> -78.101222 | AE5: =AD5/AC5 -> -0.047383468 | AF5: =Data_Stock!D5 -> 1571.16
A6: =Data_Stock!A6 -> 45908 | B6: =Data_Stock!B6 -> 1773.27 | C6: =Data_Stock!C6 -> 0.383 | D6: =MAX((MaturityDate-A6)/365,1/365) -> 1.7753425 | E6: =INDEX(Data_Svensson!$B$4:$B$202,MATCH($A6,Data_Svensson!$A$4:$A$202,1)) -> 1.198176 | F6: =INDEX(Data_Svensson!$C$4:$C$202,MATCH($A6,Data_Svensson!$A$4:$A$202,1)) -> 0.752225 | G6: =INDEX(Data_Svensson!$D$4:$D$202,MATCH($A6,Data_Svensson!$A$4:$A$202,1)) -> -2.297018 | H6: =INDEX(Data_Svensson!$E$4:$E$202,MATCH($A6,Data_Svensson!$A$4:$A$202,1)) -> 7.725683 | I6: =INDEX(Data_Svensson!$F$4:$F$202,MATCH($A6,Data_Svensson!$A$4:$A$202,1)) -> 3.438575 | J6: =INDEX(Data_Svensson!$G$4:$G$202,MATCH($A6,Data_Svensson!$A$4:$A$202,1)) -> 11.802636 | K6: =(1-EXP(-D6/I6))/(D6/I6) -> 0.7810872 | L6: =K6-EXP(-D6/I6) -> 0.18436392 | M6: =(1-EXP(-D6/J6))/(D6/J6)-EXP(-D6/J6) -> 0.068076479 | N6: =(E6+F6*K6+G6*L6+H6*M6)/100 -> 0.018881794 | O6: =N6-q -> 0.012881794 | P6: =C6*SQRT(D6) -> 0.51031678 | Q6: =(O6-0.5*C6^2)/C6^2 -> -0.41218296 | R6: =LN(B6/Cap)/P6+(1+Q6)*P6 -> 0.064194088 | S6: =LN(B6/Barrier)/P6+(1+Q6)*P6 -> 1.3268549 | T6: =LN(Barrier^2/(B6*Cap))/P6+(1+Q6)*P6 -> -1.98957 | U6: =LN(Barrier/B6)/P6+(1+Q6)*P6 -> -0.72690915 | V6: =-B6*EXP((O6-N6)*D6)*NORMSDIST(-R6)+Cap*EXP(-N6*D6)*NORMSDIST(-R6+P6) -> 467.82916 | W6: =-B6*EXP((O6-N6)*D6)*NORMSDIST(-S6)+Cap*EXP(-N6*D6)*NORMSDIST(-S6+P6) -> 238.63751 | X6: =-B6*EXP((O6-N6)*D6)*(Barrier/B6)^(2*(Q6+1))*NORMSDIST(T6)+Cap*EXP(-N6*D6)*(Barrier/B6)^(2*Q6)*NORMSDIST(T6-P6) -> -3.5903793 | Y6: =-B6*EXP((O6-N6)*D6)*(Barrier/B6)^(2*(Q6+1))*NORMSDIST(U6)+Cap*EXP(-N6*D6)*(Barrier/B6)^(2*Q6)*NORMSDIST(U6-P6) -> 100.36705 | Z6: =IF(B6<=Barrier,0,V6-W6+X6-Y6) -> 125.23422 | AA6: =Cap*EXP(-N6*D6)-V6 -> 1466.2388 | AB6: =AA6+Z6 -> 1591.473 | AC6: =INDEX(Data_Cert!$E$4:$E$195,MATCH($A6,Data_Cert!$A$4:$A$195,0)) -> 1675.51 | AD6: =AB6-AC6 -> -84.036991 | AE6: =AD6/AC6 -> -0.050156067 | AF6: =Data_Stock!D6 -> 1601.18
A7: =Data_Stock!A7 -> 45909 | B7: =Data_Stock!B7 -> 1761.39 | C7: =Data_Stock!C7 -> 0.372 | D7: =MAX((MaturityDate-A7)/365,1/365) -> 1.7726027 | E7: =INDEX(Data_Svensson!$B$4:$B$202,MATCH($A7,Data_Svensson!$A$4:$A$202,1)) -> 1.205197 | F7: =INDEX(Data_Svensson!$C$4:$C$202,MATCH($A7,Data_Svensson!$A$4:$A$202,1)) -> 0.740409 | G7: =INDEX(Data_Svensson!$D$4:$D$202,MATCH($A7,Data_Svensson!$A$4:$A$202,1)) -> -1.677676 | H7: =INDEX(Data_Svensson!$E$4:$E$202,MATCH($A7,Data_Svensson!$A$4:$A$202,1)) -> 7.39418 | I7: =INDEX(Data_Svensson!$F$4:$F$202,MATCH($A7,Data_Svensson!$A$4:$A$202,1)) -> 3.023955 | J7: =INDEX(Data_Svensson!$G$4:$G$202,MATCH($A7,Data_Svensson!$A$4:$A$202,1)) -> 12.832287 | K7: =(1-EXP(-D7/I7))/(D7/I7) -> 0.75667842 | L7: =K7-EXP(-D7/I7) -> 0.20023339 | M7: =(1-EXP(-D7/J7))/(D7/J7)-EXP(-D7/J7) -> 0.06302523 | N7: =(E7+F7*K7+G7*L7+H7*M7)/100 -> 0.018955417 | O7: =N7-q -> 0.012955417 | P7: =C7*SQRT(D7) -> 0.49527756 | Q7: =(O7-0.5*C7^2)/C7^2 -> -0.40638068 | R7: =LN(B7/Cap)/P7+(1+Q7)*P7 -> 0.037495794 | S7: =LN(B7/Barrier)/P7+(1+Q7)*P7 -> 1.3384976 | T7: =LN(Barrier^2/(B7*Cap))/P7+(1+Q7)*P7 -> -2.0514868 | U7: =LN(Barrier/B7)/P7+(1+Q7)*P7 -> -0.75048499 | V7: =-B7*EXP((O7-N7)*D7)*NORMSDIST(-R7)+Cap*EXP(-N7*D7)*NORMSDIST(-R7+P7) -> 462.87355 | W7: =-B7*EXP((O7-N7)*D7)*NORMSDIST(-S7)+Cap*EXP(-N7*D7)*NORMSDIST(-S7+P7) -> 228.4302 | X7: =-B7*EXP((O7-N7)*D7)*(Barrier/B7)^(2*(Q7+1))*NORMSDIST(T7)+Cap*EXP(-N7*D7)*(Barrier/B7)^(2*Q7)*NORMSDIST(T7-P7) -> -2.9549286 | Y7: =-B7*EXP((O7-N7)*D7)*(Barrier/B7)^(2*(Q7+1))*NORMSDIST(U7)+Cap*EXP(-N7*D7)*(Barrier/B7)^(2*Q7)*NORMSDIST(U7-P7) -> 99.82133 | Z7: =IF(B7<=Barrier,0,V7-W7+X7-Y7) -> 131.6671 | AA7: =Cap*EXP(-N7*D7)-V7 -> 1471.042 | AB7: =AA7+Z7 -> 1602.7091 | AC7: =INDEX(Data_Cert!$E$4:$E$195,MATCH($A7,Data_Cert!$A$4:$A$195,0)) -> 1671.59 | AD7: =AB7-AC7 -> -68.880857 | AE7: =AD7/AC7 -> -0.041206789 | AF7: =Data_Stock!D7 -> 1607.28
A8: =Data_Stock!A8 -> 45910 | B8: =Data_Stock!B8 -> 1819.31 | C8: =Data_Stock!C8 -> 0.382 | D8: =MAX((MaturityDate-A8)/365,1/365) -> 1.769863 | E8: =INDEX(Data_Svensson!$B$4:$B$202,MATCH($A8,Data_Svensson!$A$4:$A$202,1)) -> 1.202277 | F8: =INDEX(Data_Svensson!$C$4:$C$202,MATCH($A8,Data_Svensson!$A$4:$A$202,1)) -> 0.761658 | G8: =INDEX(Data_Svensson!$D$4:$D$202,MATCH($A8,Data_Svensson!$A$4:$A$202,1)) -> -1.692318 | H8: =INDEX(Data_Svensson!$E$4:$E$202,MATCH($A8,Data_Svensson!$A$4:$A$202,1)) -> 7.386787 | I8: =INDEX(Data_Svensson!$F$4:$F$202,MATCH($A8,Data_Svensson!$A$4:$A$202,1)) -> 3.026223 | J8: =INDEX(Data_Svensson!$G$4:$G$202,MATCH($A8,Data_Svensson!$A$4:$A$202,1)) -> 12.836812 | K8: =(1-EXP(-D8/I8))/(D8/I8) -> 0.75713793 | L8: =K8-EXP(-D8/I8) -> 0.19994417 | M8: =(1-EXP(-D8/J8))/(D8/J8)-EXP(-D8/J8) -> 0.062916502 | N8: =(E8+F8*K8+G8*L8+H8*M8)/100 -> 0.019053388 | O8: =N8-q -> 0.013053388 | P8: =C8*SQRT(D8) -> 0.50819828 | Q8: =(O8-0.5*C8^2)/C8^2 -> -0.41054666 | R8: =LN(B8/Cap)/P8+(1+Q8)*P8 -> 0.11323451 | S8: =LN(B8/Barrier)/P8+(1+Q8)*P8 -> 1.3811589 | T8: =LN(Barrier^2/(B8*Cap))/P8+(1+Q8)*P8 -> -2.049965 | U8: =LN(Barrier/B8)/P8+(1+Q8)*P8 -> -0.78204061 | V8: =-B8*EXP((O8-N8)*D8)*NORMSDIST(-R8)+Cap*EXP(-N8*D8)*NORMSDIST(-R8+P8) -> 444.88408 | W8: =-B8*EXP((O8-N8)*D8)*NORMSDIST(-S8)+Cap*EXP(-N8*D8)*NORMSDIST(-S8+P8) -> 219.48 | X8: =-B8*EXP((O8-N8)*D8)*(Barrier/B8)^(2*(Q8+1))*NORMSDIST(T8)+Cap*EXP(-N8*D8)*(Barrier/B8)^(2*Q8)*NORMSDIST(T8-P8) -> -3.0285045 | Y8: =-B8*EXP((O8-N8)*D8)*(Barrier/B8)^(2*(Q8+1))*NORMSDIST(U8)+Cap*EXP(-N8*D8)*(Barrier/B8)^(2*Q8)*NORMSDIST(U8-P8) -> 94.642211 | Z8: =IF(B8<=Barrier,0,V8-W8+X8-Y8) -> 127.73336 | AA8: =Cap*EXP(-N8*D8)-V8 -> 1488.7966 | AB8: =AA8+Z8 -> 1616.53 | AC8: =INDEX(Data_Cert!$E$4:$E$195,MATCH($A8,Data_Cert!$A$4:$A$195,0)) -> 1699.14 | AD8: =AB8-AC8 -> -82.610004 | AE8: =AD8/AC8 -> -0.048618715 | AF8: =Data_Stock!D8 -> 1628.9
A9: =Data_Stock!A9 -> 45911 | B9: =Data_Stock!B9 -> 1861.89 | C9: =Data_Stock!C9 -> 0.381 | D9: =MAX((MaturityDate-A9)/365,1/365) -> 1.7671233 | E9: =INDEX(Data_Svensson!$B$4:$B$202,MATCH($A9,Data_Svensson!$A$4:$A$202,1)) -> 1.204237 | F9: =INDEX(Data_Svensson!$C$4:$C$202,MATCH($A9,Data_Svensson!$A$4:$A$202,1)) -> 0.75691 | G9: =INDEX(Data_Svensson!$D$4:$D$202,MATCH($A9,Data_Svensson!$A$4:$A$202,1)) -> -1.615143 | H9: =INDEX(Data_Svensson!$E$4:$E$202,MATCH($A9,Data_Svensson!$A$4:$A$202,1)) -> 7.356917 | I9: =INDEX(Data_Svensson!$F$4:$F$202,MATCH($A9,Data_Svensson!$A$4:$A$202,1)) -> 3.268254 | J9: =INDEX(Data_Svensson!$G$4:$G$202,MATCH($A9,Data_Svensson!$A$4:$A$202,1)) -> 12.889797 | K9: =(1-EXP(-D9/I9))/(D9/I9) -> 0.77244459 | L9: =K9-EXP(-D9/I9) -> 0.19010026 | M9: =(1-EXP(-D9/J9))/(D9/J9)-EXP(-D9/J9) -> 0.062593018 | N9: =(E9+F9*K9+G9*L9+H9*M9)/100 -> 0.019423606 | O9: =N9-q -> 0.013423606 | P9: =C9*SQRT(D9) -> 0.50647545 | Q9: =(O9-0.5*C9^2)/C9^2 -> -0.40752609 | R9: =LN(B9/Cap)/P9+(1+Q9)*P9 -> 0.15879304 | S9: =LN(B9/Barrier)/P9+(1+Q9)*P9 -> 1.4310305 | T9: =LN(Barrier^2/(B9*Cap))/P9+(1+Q9)*P9 -> -2.1031209 | U9: =LN(Barrier/B9)/P9+(1+Q9)*P9 -> -0.83088347 | V9: =-B9*EXP((O9-N9)*D9)*NORMSDIST(-R9)+Cap*EXP(-N9*D9)*NORMSDIST(-R9+P9) -> 424.09492 | W9: =-B9*EXP((O9-N9)*D9)*NORMSDIST(-S9)+Cap*EXP(-N9*D9)*NORMSDIST(-S9+P9) -> 202.81304 | X9: =-B9*EXP((O9-N9)*D9)*(Barrier/B9)^(2*(Q9+1))*NORMSDIST(T9)+Cap*EXP(-N9*D9)*(Barrier/B9)^(2*Q9)*NORMSDIST(T9-P9) -> -2.5957836 | Y9: =-B9*EXP((O9-N9)*D9)*(Barrier/B9)^(2*(Q9+1))*NORMSDIST(U9)+Cap*EXP(-N9*D9)*(Barrier/B9)^(2*Q9)*NORMSDIST(U9-P9) -> 89.393194 | Z9: =IF(B9<=Barrier,0,V9-W9+X9-Y9) -> 129.29289 | AA9: =Cap*EXP(-N9*D9)-V9 -> 1508.422 | AB9: =AA9+Z9 -> 1637.7149 | AC9: =INDEX(Data_Cert!$E$4:$E$195,MATCH($A9,Data_Cert!$A$4:$A$195,0)) -> 1721.63 | AD9: =AB9-AC9 -> -83.915068 | AE9: =AD9/AC9 -> -0.048741639 | AF9: =Data_Stock!D9 -> 1636.5
A10: =Data_Stock!A10 -> 45912 | B10: =Data_Stock!B10 -> 1877.73 | C10: =Data_Stock!C10 -> 0.371 | D10: =MAX((MaturityDate-A10)/365,1/365) -> 1.7643836 | E10: =INDEX(Data_Svensson!$B$4:$B$202,MATCH($A10,Data_Svensson!$A$4:$A$202,1)) -> 1.199688 | F10: =INDEX(Data_Svensson!$C$4:$C$202,MATCH($A10,Data_Svensson!$A$4:$A$202,1)) -> 0.744959 | G10: =INDEX(Data_Svensson!$D$4:$D$202,MATCH($A10,Data_Svensson!$A$4:$A$202,1)) -> -1.462092 | H10: =INDEX(Data_Svensson!$E$4:$E$202,MATCH($A10,Data_Svensson!$A$4:$A$202,1)) -> 7.352704 | I10: =INDEX(Data_Svensson!$F$4:$F$202,MATCH($A10,Data_Svensson!$A$4:$A$202,1)) -> 3.328068 | J10: =INDEX(Data_Svensson!$G$4:$G$202,MATCH($A10,Data_Svensson!$A$4:$A$202,1)) -> 12.832385 | K10: =(1-EXP(-D10/I10))/(D10/I10) -> 0.77616306 | L10: =K10-EXP(-D10/I10) -> 0.18764784 | M10: =(1-EXP(-D10/J10))/(D10/J10)-EXP(-D10/J10) -> 0.062759042 | N10: =(E10+F10*K10+G10*L10+H10*M10)/100 -> 0.019649879 | O10: =N10-q -> 0.013649879 | P10: =C10*SQRT(D10) -> 0.49279967 | Q10: =(O10-0.5*C10^2)/C10^2 -> -0.40082985 | R10: =LN(B10/Cap)/P10+(1+Q10)*P10 -> 0.16726026 | S10: =LN(B10/Barrier)/P10+(1+Q10)*P10 -> 1.4748038 | T10: =LN(Barrier^2/(B10*Cap))/P10+(1+Q10)*P10 -> -2.1918056 | U10: =LN(Barrier/B10)/P10+(1+Q10)*P10 -> -0.88426206 | V10: =-B10*EXP((O10-N10)*D10)*NORMSDIST(-R10)+Cap*EXP(-N10*D10)*NORMSDIST(-R10+P10) -> 406.87653 | W10: =-B10*EXP((O10-N10)*D10)*NORMSDIST(-S10)+Cap*EXP(-N10*D10)*NORMSDIST(-S10+P10) -> 184.68235 | X10: =-B10*EXP((O10-N10)*D10)*(Barrier/B10)^(2*(Q10+1))*NORMSDIST(T10)+Cap*EXP(-N10*D10)*(Barrier/B10)^(2*Q10)*NORMSDIST(T10-P10) -> -1.96597 | Y10: =-B10*EXP((O10-N10)*D10)*(Barrier/B10)^(2*(Q10+1))*NORMSDIST(U10)+Cap*EXP(-N10*D10)*(Barrier/B10)^(2*Q10)*NORMSDIST(U10-P10) -> 85.048729 | Z10: =IF(B10<=Barrier,0,V10-W10+X10-Y10) -> 135.17948 | AA10: =Cap*EXP(-N10*D10)-V10 -> 1524.9719 | AB10: =AA10+Z10 -> 1660.1513 | AC10: =INDEX(Data_Cert!$E$4:$E$195,MATCH($A10,Data_Cert!$A$4:$A$195,0)) -> 1713.91 | AD10: =AB10-AC10 -> -53.758667 | AE10: =AD10/AC10 -> -0.031366097 | AF10: =Data_Stock!D10 -> 1666.15
A11: =Data_Stock!A11 -> 45915 | B11: =Data_Stock!B11 -> 1930.7 | C11: =Data_Stock!C11 -> 0.376 | D11: =MAX((MaturityDate-A11)/365,1/365) -> 1.7561644 | E11: =INDEX(Data_Svensson!$B$4:$B$202,MATCH($A11,Data_Svensson!$A$4:$A$202,1)) -> 1.194697 | F11: =INDEX(Data_Svensson!$C$4:$C$202,MATCH($A11,Data_Svensson!$A$4:$A$202,1)) -> 0.750982 | G11: =INDEX(Data_Svensson!$D$4:$D$202,MATCH($A11,Data_Svensson!$A$4:$A$202,1)) -> -1.484931 | H11: =INDEX(Data_Svensson!$E$4:$E$202,MATCH($A11,Data_Svensson!$A$4:$A$202,1)) -> 7.34158 | I11: =INDEX(Data_Svensson!$F$4:$F$202,MATCH($A11,Data_Svensson!$A$4:$A$202,1)) -> 3.322536 | J11: =INDEX(Data_Svensson!$G$4:$G$202,MATCH($A11,Data_Svensson!$A$4:$A$202,1)) -> 12.848706 | K11: =(1-EXP(-D11/I11))/(D11/I11) -> 0.7767265 | L11: =K11-EXP(-D11/I11) -> 0.18727418 | M11: =(1-EXP(-D11/J11))/(D11/J11)-EXP(-D11/J11) -> 0.062420827 | N11: =(E11+F11*K11+G11*L11+H11*M11)/100 -> 0.019581829 | O11: =N11-q -> 0.013581829 | P11: =C11*SQRT(D11) -> 0.49827653 | Q11: =(O11-0.5*C11^2)/C11^2 -> -0.40393116 | R11: =LN(B11/Cap)/P11+(1+Q11)*P11 -> 0.22623406 | S11: =LN(B11/Barrier)/P11+(1+Q11)*P11 -> 1.5194056 | T11: =LN(Barrier^2/(B11*Cap))/P11+(1+Q11)*P11 -> -2.2185629 | U11: =LN(Barrier/B11)/P11+(1+Q11)*P11 -> -0.92539137 | V11: =-B11*EXP((O11-N11)*D11)*NORMSDIST(-R11)+Cap*EXP(-N11*D11)*NORMSDIST(-R11+P11) -> 389.0947 | W11: =-B11*EXP((O11-N11)*D11)*NORMSDIST(-S11)+Cap*EXP(-N11*D11)*NORMSDIST(-S11+P11) -> 173.90833 | X11: =-B11*EXP((O11-N11)*D11)*(Barrier/B11)^(2*(Q11+1))*NORMSDIST(T11)+Cap*EXP(-N11*D11)*(Barrier/B11)^(2*Q11)*NORMSDIST(T11-P11) -> -1.8377312 | Y11: =-B11*EXP((O11-N11)*D11)*(Barrier/B11)^(2*(Q11+1))*NORMSDIST(U11)+Cap*EXP(-N11*D11)*(Barrier/B11)^(2*Q11)*NORMSDIST(U11-P11) -> 80.294246 | Z11: =IF(B11<=Barrier,0,V11-W11+X11-Y11) -> 133.0544 | AA11: =Cap*EXP(-N11*D11)-V11 -> 1543.2966 | AB11: =AA11+Z11 -> 1676.351 | AC11: =INDEX(Data_Cert!$E$4:$E$195,MATCH($A11,Data_Cert!$A$4:$A$195,0)) -> 1735.5 | AD11: =AB11-AC11 -> -59.148967 | AE11: =AD11/AC11 -> -0.034081802 | AF11: =Data_Stock!D11 -> 1688.12
A12: =Data_Stock!A12 -> 45916 | B12: =Data_Stock!B12 -> 1882.19 | C12: =Data_Stock!C12 -> 0.377 | D12: =MAX((MaturityDate-A12)/365,1/365) -> 1.7534247 | E12: =INDEX(Data_Svensson!$B$4:$B$202,MATCH($A12,Data_Svensson!$A$4:$A$202,1)) -> 1.190226 | F12: =INDEX(Data_Svensson!$C$4:$C$202,MATCH($A12,Data_Svensson!$A$4:$A$202,1)) -> 0.772804 | G12: =INDEX(Data_Svensson!$D$4:$D$202,MATCH($A12,Data_Svensson!$A$4:$A$202,1)) -> -1.510362 | H12: =INDEX(Data_Svensson!$E$4:$E$202,MATCH($A12,Data_Svensson!$A$4:$A$202,1)) -> 7.343672 | I12: =INDEX(Data_Svensson!$F$4:$F$202,MATCH($A12,Data_Svensson!$A$4:$A$202,1)) -> 3.311418 | J12: =INDEX(Data_Svensson!$G$4:$G$202,MATCH($A12,Data_Svensson!$A$4:$A$202,1)) -> 12.845352 | K12: =(1-EXP(-D12/I12))/(D12/I12) -> 0.77639098 | L12: =K12-EXP(-D12/I12) -> 0.18749676 | M12: =(1-EXP(-D12/J12))/(D12/J12)-EXP(-D12/J12) -> 0.062347016 | N12: =(E12+F12*K12+G12*L12+H12*M12)/100 -> 0.019648921 | O12: =N12-q -> 0.013648921 | P12: =C12*SQRT(D12) -> 0.49921187 | Q12: =(O12-0.5*C12^2)/C12^2 -> -0.40396808 | R12: =LN(B12/Cap)/P12+(1+Q12)*P12 -> 0.17593214 | S12: =LN(B12/Barrier)/P12+(1+Q12)*P12 -> 1.4666807 | T12: =LN(Barrier^2/(B12*Cap))/P12+(1+Q12)*P12 -> -2.1623369 | U12: =LN(Barrier/B12)/P12+(1+Q12)*P12 -> -0.8715883 | V12: =-B12*EXP((O12-N12)*D12)*NORMSDIST(-R12)+Cap*EXP(-N12*D12)*NORMSDIST(-R12+P12) -> 409.86981 | W12: =-B12*EXP((O12-N12)*D12)*NORMSDIST(-S12)+Cap*EXP(-N12*D12)*NORMSDIST(-S12+P12) -> 189.35374 | X12: =-B12*EXP((O12-N12)*D12)*(Barrier/B12)^(2*(Q12+1))*NORMSDIST(T12)+Cap*EXP(-N12*D12)*(Barrier/B12)^(2*Q12)*NORMSDIST(T12-P12) -> -2.1652589 | Y12: =-B12*EXP((O12-N12)*D12)*(Barrier/B12)^(2*(Q12+1))*NORMSDIST(U12)+Cap*EXP(-N12*D12)*(Barrier/B12)^(2*Q12)*NORMSDIST(U12-P12) -> 85.799291 | Z12: =IF(B12<=Barrier,0,V12-W12+X12-Y12) -> 132.55152 | AA12: =Cap*EXP(-N12*D12)-V12 -> 1522.3979 | AB12: =AA12+Z12 -> 1654.9494 | AC12: =INDEX(Data_Cert!$E$4:$E$195,MATCH($A12,Data_Cert!$A$4:$A$195,0)) -> 1728.41 | AD12: =AB12-AC12 -> -73.460612 | AE12: =AD12/AC12 -> -0.042501844 | AF12: =Data_Stock!D12 -> 1663.42
A13: =Data_Stock!A13 -> 45917 | B13: =Data_Stock!B13 -> 1869.81 | C13: =Data_Stock!C13 -> 0.367 | D13: =MAX((MaturityDate-A13)/365,1/365) -> 1.7506849 | E13: =INDEX(Data_Svensson!$B$4:$B$202,MATCH($A13,Data_Svensson!$A$4:$A$202,1)) -> 1.203972 | F13: =INDEX(Data_Svensson!$C$4:$C$202,MATCH($A13,Data_Svensson!$A$4:$A$202,1)) -> 0.747581 | G13: =INDEX(Data_Svensson!$D$4:$D$202,MATCH($A13,Data_Svensson!$A$4:$A$202,1)) -> -1.13154 | H13: =INDEX(Data_Svensson!$E$4:$E$202,MATCH($A13,Data_Svensson!$A$4:$A$202,1)) -> 6.979307 | I13: =INDEX(Data_Svensson!$F$4:$F$202,MATCH($A13,Data_Svensson!$A$4:$A$202,1)) -> 2.868727 | J13: =INDEX(Data_Svensson!$G$4:$G$202,MATCH($A13,Data_Svensson!$A$4:$A$202,1)) -> 13.349989 | K13: =(1-EXP(-D13/I13))/(D13/I13) -> 0.74851583 | L13: =K13-EXP(-D13/I13) -> 0.20530916 | M13: =(1-EXP(-D13/J13))/(D13/J13)-EXP(-D13/J13) -> 0.060108728 | N13: =(E13+F13*K13+G13*L13+H13*M13)/100 -> 0.019507499 | O13: =N13-q -> 0.013507499 | P13: =C13*SQRT(D13) -> 0.48559037 | Q13: =(O13-0.5*C13^2)/C13^2 -> -0.39971342 | R13: =LN(B13/Cap)/P13+(1+Q13)*P13 -> 0.15287786 | S13: =LN(B13/Barrier)/P13+(1+Q13)*P13 -> 1.4798338 | T13: =LN(Barrier^2/(B13*Cap))/P13+(1+Q13)*P13 -> -2.223803 | U13: =LN(Barrier/B13)/P13+(1+Q13)*P13 -> -0.89684704 | V13: =-B13*EXP((O13-N13)*D13)*NORMSDIST(-R13)+Cap*EXP(-N13*D13)*NORMSDIST(-R13+P13) -> 405.59551 | W13: =-B13*EXP((O13-N13)*D13)*NORMSDIST(-S13)+Cap*EXP(-N13*D13)*NORMSDIST(-S13+P13) -> 180.83921 | X13: =-B13*EXP((O13-N13)*D13)*(Barrier/B13)^(2*(Q13+1))*NORMSDIST(T13)+Cap*EXP(-N13*D13)*(Barrier/B13)^(2*Q13)*NORMSDIST(T13-P13) -> -1.7732718 | Y13: =-B13*EXP((O13-N13)*D13)*(Barrier/B13)^(2*(Q13+1))*NORMSDIST(U13)+Cap*EXP(-N13*D13)*(Barrier/B13)^(2*Q13)*NORMSDIST(U13-P13) -> 84.62393 | Z13: =IF(B13<=Barrier,0,V13-W13+X13-Y13) -> 138.3591 | AA13: =Cap*EXP(-N13*D13)-V13 -> 1527.2547 | AB13: =AA13+Z13 -> 1665.6138 | AC13: =INDEX(Data_Cert!$E$4:$E$195,MATCH($A13,Data_Cert!$A$4:$A$195,0)) -> 1699.94 | AD13: =AB13-AC13 -> -34.32622 | AE13: =AD13/AC13 -> -0.020192607 | AF13: =Data_Stock!D13 -> 1669.48
A14: =Data_Stock!A14 -> 45918 | B14: =Data_Stock!B14 -> 1900.5 | C14: =Data_Stock!C14 -> 0.361 | D14: =MAX((MaturityDate-A14)/365,1/365) -> 1.7479452 | E14: =INDEX(Data_Svensson!$B$4:$B$202,MATCH($A14,Data_Svensson!$A$4:$A$202,1)) -> 1.213035 | F14: =INDEX(Data_Svensson!$C$4:$C$202,MATCH($A14,Data_Svensson!$A$4:$A$202,1)) -> 0.746271 | G14: =INDEX(Data_Svensson!$D$4:$D$202,MATCH($A14,Data_Svensson!$A$4:$A$202,1)) -> -1.778341 | H14: =INDEX(Data_Svensson!$E$4:$E$202,MATCH($A14,Data_Svensson!$A$4:$A$202,1)) -> 7.497673 | I14: =INDEX(Data_Svensson!$F$4:$F$202,MATCH($A14,Data_Svensson!$A$4:$A$202,1)) -> 3.456473 | J14: =INDEX(Data_Svensson!$G$4:$G$202,MATCH($A14,Data_Svensson!$A$4:$A$202,1)) -> 12.195202 | K14: =(1-EXP(-D14/I14))/(D14/I14) -> 0.78488506 | L14: =K14-EXP(-D14/I14) -> 0.18180297 | M14: =(1-EXP(-D14/J14))/(D14/J14)-EXP(-D14/J14) -> 0.065171808 | N14: =(E14+F14*K14+G14*L14+H14*M14)/100 -> 0.019641012 | O14: =N14-q -> 0.013641012 | P14: =C14*SQRT(D14) -> 0.47727766 | Q14: =(O14-0.5*C14^2)/C14^2 -> -0.3953276 | R14: =LN(B14/Cap)/P14+(1+Q14)*P14 -> 0.18167738 | S14: =LN(B14/Barrier)/P14+(1+Q14)*P14 -> 1.5317448 | T14: =LN(Barrier^2/(B14*Cap))/P14+(1+Q14)*P14 -> -2.3046189 | U14: =LN(Barrier/B14)/P14+(1+Q14)*P14 -> -0.95455153 | V14: =-B14*EXP((O14-N14)*D14)*NORMSDIST(-R14)+Cap*EXP(-N14*D14)*NORMSDIST(-R14+P14) -> 386.097 | W14: =-B14*EXP((O14-N14)*D14)*NORMSDIST(-S14)+Cap*EXP(-N14*D14)*NORMSDIST(-S14+P14) -> 163.73311 | X14: =-B14*EXP((O14-N14)*D14)*(Barrier/B14)^(2*(Q14+1))*NORMSDIST(T14)+Cap*EXP(-N14*D14)*(Barrier/B14)^(2*Q14)*NORMSDIST(T14-P14) -> -1.3743204 | Y14: =-B14*EXP((O14-N14)*D14)*(Barrier/B14)^(2*(Q14+1))*NORMSDIST(U14)+Cap*EXP(-N14*D14)*(Barrier/B14)^(2*Q14)*NORMSDIST(U14-P14) -> 79.165917 | Z14: =IF(B14<=Barrier,0,V14-W14+X14-Y14) -> 141.82365 | AA14: =Cap*EXP(-N14*D14)-V14 -> 1546.4054 | AB14: =AA14+Z14 -> 1688.2291 | AC14: =INDEX(Data_Cert!$E$4:$E$195,MATCH($A14,Data_Cert!$A$4:$A$195,0)) -> 1708.18 | AD14: =AB14-AC14 -> -19.950901 | AE14: =AD14/AC14 -> -0.011679625 | AF14: =Data_Stock!D14 -> 1694.37
A15: =Data_Stock!A15 -> 45919 | B15: =Data_Stock!B15 -> 1908.92 | C15: =Data_Stock!C15 -> 0.351 | D15: =MAX((MaturityDate-A15)/365,1/365) -> 1.7452055 | E15: =INDEX(Data_Svensson!$B$4:$B$202,MATCH($A15,Data_Svensson!$A$4:$A$202,1)) -> 1.202443 | F15: =INDEX(Data_Svensson!$C$4:$C$202,MATCH($A15,Data_Svensson!$A$4:$A$202,1)) -> 0.767881 | G15: =INDEX(Data_Svensson!$D$4:$D$202,MATCH($A15,Data_Svensson!$A$4:$A$202,1)) -> -1.45466 | H15: =INDEX(Data_Svensson!$E$4:$E$202,MATCH($A15,Data_Svensson!$A$4:$A$202,1)) -> 7.402585 | I15: =INDEX(Data_Svensson!$F$4:$F$202,MATCH($A15,Data_Svensson!$A$4:$A$202,1)) -> 3.145587 | J15: =INDEX(Data_Svensson!$G$4:$G$202,MATCH($A15,Data_Svensson!$A$4:$A$202,1)) -> 12.699912 | K15: =(1-EXP(-D15/I15))/(D15/I15) -> 0.76750331 | L15: =K15-EXP(-D15/I15) -> 0.19332239 | M15: =(1-EXP(-D15/J15))/(D15/J15)-EXP(-D15/J15) -> 0.06272754 | N15: =(E15+F15*K15+G15*L15+H15*M15)/100 -> 0.019749218 | O15: =N15-q -> 0.013749218 | P15: =C15*SQRT(D15) -> 0.46369285 | Q15: =(O15-0.5*C15^2)/C15^2 -> -0.38840011 | R15: =LN(B15/Cap)/P15+(1+Q15)*P15 -> 0.18307636 | S15: =LN(B15/Barrier)/P15+(1+Q15)*P15 -> 1.5726967 | T15: =LN(Barrier^2/(B15*Cap))/P15+(1+Q15)*P15 -> -2.395128 | U15: =LN(Barrier/B15)/P15+(1+Q15)*P15 -> -1.0055077 | V15: =-B15*EXP((O15-N15)*D15)*NORMSDIST(-R15)+Cap*EXP(-N15*D15)*NORMSDIST(-R15+P15) -> 372.31371 | W15: =-B15*EXP((O15-N15)*D15)*NORMSDIST(-S15)+Cap*EXP(-N15*D15)*NORMSDIST(-S15+P15) -> 149.00342 | X15: =-B15*EXP((O15-N15)*D15)*(Barrier/B15)^(2*(Q15+1))*NORMSDIST(T15)+Cap*EXP(-N15*D15)*(Barrier/B15)^(2*Q15)*NORMSDIST(T15-P15) -> -1.0178565 | Y15: =-B15*EXP((O15-N15)*D15)*(Barrier/B15)^(2*(Q15+1))*NORMSDIST(U15)+Cap*EXP(-N15*D15)*(Barrier/B15)^(2*Q15)*NORMSDIST(U15-P15) -> 74.866095 | Z15: =IF(B15<=Barrier,0,V15-W15+X15-Y15) -> 147.42634 | AA15: =Cap*EXP(-N15*D15)-V15 -> 1559.9278 | AB15: =AA15+Z15 -> 1707.3541 | AC15: =INDEX(Data_Cert!$E$4:$E$195,MATCH($A15,Data_Cert!$A$4:$A$195,0)) -> 1711.35 | AD15: =AB15-AC15 -> -3.9958523 | AE15: =AD15/AC15 -> -0.0023349124 | AF15: =Data_Stock!D15 -> 1721
... A186: =Data_Stock!A186 -> 46174 | B186: =Data_Stock!B186 -> 1207 | C186: =Data_Stock!C186 -> 0.542 | D186: =MAX((MaturityDate-A186)/365,1/365) -> 1.0465753 | E186: =INDEX(Data_Svensson!$B$4:$B$202,MATCH($A186,Data_Svensson!$A$4:$A$202,1)) -> 1.330382 | F186: =INDEX(Data_Svensson!$C$4:$C$202,MATCH($A186,Data_Svensson!$A$4:$A$202,1)) -> 0.700052 | G186: =INDEX(Data_Svensson!$D$4:$D$202,MATCH($A186,Data_Svensson!$A$4:$A$202,1)) -> 1.816755 | H186: =INDEX(Data_Svensson!$E$4:$E$202,MATCH($A186,Data_Svensson!$A$4:$A$202,1)) -> 7.130184 | I186: =INDEX(Data_Svensson!$F$4:$F$202,MATCH($A186,Data_Svensson!$A$4:$A$202,1)) -> 0.966763 | J186: =INDEX(Data_Svensson!$G$4:$G$202,MATCH($A186,Data_Svensson!$A$4:$A$202,1)) -> 15.839369 | K186: =(1-EXP(-D186/I186))/(D186/I186) -> 0.61084258 | L186: =K186-EXP(-D186/I186) -> 0.27211404 | M186: =(1-EXP(-D186/J186))/(D186/J186)-EXP(-D186/J186) -> 0.031617314 | N186: =(E186+F186*K186+G186*L186+H186*M186)/100 -> 0.024778054 | O186: =N186-q -> 0.018778054 | P186: =C186*SQRT(D186) -> 0.55447828 | Q186: =(O186-0.5*C186^2)/C186^2 -> -0.43607776 | R186: =LN(B186/Cap)/P186+(1+Q186)*P186 -> -0.5981001 | S186: =LN(B186/Barrier)/P186+(1+Q186)*P186 -> 0.56399596 | T186: =LN(Barrier^2/(B186*Cap))/P186+(1+Q186)*P186 -> -1.1007267 | U186: =LN(Barrier/B186)/P186+(1+Q186)*P186 -> 0.061369311 | V186: =-B186*EXP((O186-N186)*D186)*NORMSDIST(-R186)+Cap*EXP(-N186*D186)*NORMSDIST(-R186+P186) -> 836.36197 | W186: =-B186*EXP((O186-N186)*D186)*NORMSDIST(-S186)+Cap*EXP(-N186*D186)*NORMSDIST(-S186+P186) -> 623.50672 | X186: =-B186*EXP((O186-N186)*D186)*(Barrier/B186)^(2*(Q186+1))*NORMSDIST(T186)+Cap*EXP(-N186*D186)*(Barrier/B186)^(2*Q186)*NORMSDIST(T186-P186) -> -31.19344 | Y186: =-B186*EXP((O186-N186)*D186)*(Barrier/B186)^(2*(Q186+1))*NORMSDIST(U186)+Cap*EXP(-N186*D186)*(Barrier/B186)^(2*Q186)*NORMSDIST(U186-P186) -> 146.74714 | Z186: =IF(B186<=Barrier,0,V186-W186+X186-Y186) -> 34.91467 | AA186: =Cap*EXP(-N186*D186)-V186 -> 1112.4405 | AB186: =AA186+Z186 -> 1147.3552 | AC186: =INDEX(Data_Cert!$E$4:$E$195,MATCH($A186,Data_Cert!$A$4:$A$195,0)) -> 1236.07 | AD186: =AB186-AC186 -> -88.714797 | AE186: =AD186/AC186 -> -0.071771661 | AF186: =Data_Stock!D186 -> 1153.79
AA188: ME | AB188: =AVERAGE(AD4:AD186) -> -94.293549
AA189: MAE | AB189: =SUMPRODUCT(ABS(AD4:AD186))/COUNT(AD4:AD186) -> 101.88208
AA190: RMSE | AB190: =SQRT(SUMSQ(AD4:AD186)/COUNT(AD4:AD186)) -> 116.44496
AA191: n days | AB191: =COUNT(AD4:AD186) -> 183

Sheet P2_TaskVI_Greeks
A1: Task VI — Greeks via central finite differences (closed-form RR price)
A2: Reference: S = first-day close; sigma = median EWMA over window; T = remaining maturity on day 1; r = Svensson r(T) on day 1. Bumps from Inputs (dS, dSig, dT, dR). Theta on 365-day convention.
A4: Reference inputs
A5: S_ref | B5: =Data_Stock!B4 -> 1707.93
A6: sigma_ref | B6: =MEDIAN(Data_Stock!C4:C186) -> 0.446
A7: T_ref | B7: =MAX((MaturityDate-Data_Stock!A4)/365,1/365) -> 1.7863014
A8: r_ref (Svensson) | B8: =(INDEX(Data_Svensson!$B$4:$B$202,MATCH(Data_Stock!A4,Data_Svensson!$A$4:$A$202,1))+INDEX(Data_Svensson!$C$4:$C$202,MATCH(Data_Stock!A4,Data_Svensson!$A$4:$A$202,1))*((1-EXP(-B7/INDEX(Data_Svensson!$F$4:$F$202,MATCH(Data_Stock!A4,Data_Svensson!$A$4:$A$202,1))))/(B7/INDEX(Data_Svensson!$F$4:$F$202,MATCH(Data_Stock!A4,Data_Svensson!$A$4:$A$202,1))))+INDEX(Data_Svensson!$D$4:$D$202,MATCH(Data_Stock!A4,Data_Svensson!$A$4:$A$202,1))*((1-EXP(-B7/INDEX(Data_Svensson!$F$4:$F$202,MATCH(Data_Stock!A4,Data_Svensson!$A$4:$A$202,1))))/(B7/INDEX(Data_Svensson!$F$4:$F$202,MATCH(Data_Stock!A4,Data_Svensson!$A$4:$A$202,1)))-EXP(-B7/INDEX(Data_Svensson!$F$4:$F$202,MATCH(Data_Stock!A4,Data_Svensson!$A$4:$A$202,1))))+INDEX(Data_Svensson!$E$4:$E$202,MATCH(Data_Stock!A4,Data_Svensson!$A$4:$A$202,1))*((1-EXP(-B7/INDEX(Data_Svensson!$G$4:$G$202,MATCH(Data_Stock!A4,Data_Svensson!$A$4:$A$202,1))))/(B7/INDEX(Data_Svensson!$G$4:$G$202,MATCH(Data_Stock!A4,Data_Svensson!$A$4:$A$202,1)))-EXP(-B7/INDEX(Data_Svensson!$G$4:$G$202,MATCH(Data_Stock!A4,Data_Svensson!$A$4:$A$202,1)))))/100 -> 0.019161407
A10: Quantity | B10: Base | C10: S+ | D10: S- | E10: sig+ | F10: sig- | G10: T- | H10: r+ | I10: r-
A11: S | B11: =$B$5 -> 1707.93 | C11: =$B$5*(1+dS) -> 1725.0093 | D11: =$B$5*(1-dS) -> 1690.8507 | E11: =$B$5 -> 1707.93 | F11: =$B$5 -> 1707.93 | G11: =$B$5 -> 1707.93 | H11: =$B$5 -> 1707.93 | I11: =$B$5 -> 1707.93
A12: sigma | B12: =$B$6 -> 0.446 | C12: =$B$6 -> 0.446 | D12: =$B$6 -> 0.446 | E12: =$B$6+dSig -> 0.466 | F12: =$B$6-dSig -> 0.426 | G12: =$B$6 -> 0.446 | H12: =$B$6 -> 0.446 | I12: =$B$6 -> 0.446
A13: T | B13: =$B$7 -> 1.7863014 | C13: =$B$7 -> 1.7863014 | D13: =$B$7 -> 1.7863014 | E13: =$B$7 -> 1.7863014 | F13: =$B$7 -> 1.7863014 | G13: =MAX($B$7-dT,1/365) -> 1.7823331 | H13: =$B$7 -> 1.7863014 | I13: =$B$7 -> 1.7863014
A14: r | B14: =$B$8 -> 0.019161407 | C14: =$B$8 -> 0.019161407 | D14: =$B$8 -> 0.019161407 | E14: =$B$8 -> 0.019161407 | F14: =$B$8 -> 0.019161407 | G14: =$B$8 -> 0.019161407 | H14: =$B$8+dR -> 0.019261407 | I14: =$B$8-dR -> 0.019061407
A15: carry b | B15: =B14-q -> 0.013161407 | C15: =C14-q -> 0.013161407 | D15: =D14-q -> 0.013161407 | E15: =E14-q -> 0.013161407 | F15: =F14-q -> 0.013161407 | G15: =G14-q -> 0.013161407 | H15: =H14-q -> 0.013261407 | I15: =I14-q -> 0.013061407
A16: sig*sqrtT | B16: =B12*SQRT(B13) -> 0.59609053 | C16: =C12*SQRT(C13) -> 0.59609053 | D16: =D12*SQRT(D13) -> 0.59609053 | E16: =E12*SQRT(E13) -> 0.62282105 | F16: =F12*SQRT(F13) -> 0.56936002 | G16: =G12*SQRT(G13) -> 0.59542806 | H16: =H12*SQRT(H13) -> 0.59609053 | I16: =I12*SQRT(I13) -> 0.59609053
A17: mu | B17: =(B15-0.5*B12^2)/B12^2 -> -0.43383435 | C17: =(C15-0.5*C12^2)/C12^2 -> -0.43383435 | D17: =(D15-0.5*D12^2)/D12^2 -> -0.43383435 | E17: =(E15-0.5*E12^2)/E12^2 -> -0.43939192 | F17: =(F15-0.5*F12^2)/F12^2 -> -0.42747577 | G17: =(G15-0.5*G12^2)/G12^2 -> -0.43383435 | H17: =(H15-0.5*H12^2)/H12^2 -> -0.43333162 | I17: =(I15-0.5*I12^2)/I12^2 -> -0.43433707
A18: x1 | B18: =LN(B11/Cap)/B16+(1+B17)*B16 -> 0.072651937 | C18: =LN(C11/Cap)/C16+(1+C17)*C16 -> 0.089344588 | D18: =LN(D11/Cap)/D16+(1+D17)*D16 -> 0.055791519 | E18: =LN(E11/Cap)/E16+(1+E17)*E16 -> 0.095690729 | F18: =LN(F11/Cap)/F16+(1+F17)*F16 -> 0.048704832 | G18: =LN(G11/Cap)/G16+(1+G17)*G16 -> 0.071982213 | H18: =LN(H11/Cap)/H16+(1+H17)*H16 -> 0.072951607 | I18: =LN(I11/Cap)/I16+(1+I17)*I16 -> 0.072352268
A19: x2 | B19: =LN(B11/Barrier)/B16+(1+B17)*B16 -> 1.1536237 | C19: =LN(C11/Barrier)/C16+(1+C17)*C16 -> 1.1703163 | D19: =LN(D11/Barrier)/D16+(1+D17)*D16 -> 1.1367633 | E19: =LN(E11/Barrier)/E16+(1+E17)*E16 -> 1.1302688 | F19: =LN(F11/Barrier)/F16+(1+F17)*F16 -> 1.1804264 | G19: =LN(G11/Barrier)/G16+(1+G17)*G16 -> 1.1541566 | H19: =LN(H11/Barrier)/H16+(1+H17)*H16 -> 1.1539233 | I19: =LN(I11/Barrier)/I16+(1+I17)*I16 -> 1.153324
A20: y1 | B20: =LN(Barrier^2/(B11*Cap))/B16+(1+B17)*B16 -> -1.5596234 | C20: =LN(Barrier^2/(C11*Cap))/C16+(1+C17)*C16 -> -1.5763161 | D20: =LN(Barrier^2/(D11*Cap))/D16+(1+D17)*D16 -> -1.542763 | E20: =LN(Barrier^2/(E11*Cap))/E16+(1+E17)*E16 -> -1.4665299 | F20: =LN(Barrier^2/(F11*Cap))/F16+(1+F17)*F16 -> -1.6602032 | G20: =LN(Barrier^2/(G11*Cap))/G16+(1+G17)*G16 -> -1.5621092 | H20: =LN(Barrier^2/(H11*Cap))/H16+(1+H17)*H16 -> -1.5593238 | I20: =LN(Barrier^2/(I11*Cap))/I16+(1+I17)*I16 -> -1.5599231
A21: y2 | B21: =LN(Barrier/B11)/B16+(1+B17)*B16 -> -0.4786517 | C21: =LN(Barrier/C11)/C16+(1+C17)*C16 -> -0.49534435 | D21: =LN(Barrier/D11)/D16+(1+D17)*D16 -> -0.46179128 | E21: =LN(Barrier/E11)/E16+(1+E17)*E16 -> -0.4319518 | F21: =LN(Barrier/F11)/F16+(1+F17)*F16 -> -0.5284816 | G21: =LN(Barrier/G11)/G16+(1+G17)*G16 -> -0.4799348 | H21: =LN(Barrier/H11)/H16+(1+H17)*H16 -> -0.47835203 | I21: =LN(Barrier/I11)/I16+(1+I17)*I16 -> -0.47895137
A22: A | B22: =-B11*EXP((B15-B14)*B13)*NORMSDIST(-B18)+Cap*EXP(-B14*B13)*NORMSDIST(-B18+B16) -> 556.3155 | C22: =-C11*EXP((C15-C14)*C13)*NORMSDIST(-C18)+Cap*EXP(-C14*C13)*NORMSDIST(-C18+C16) -> 548.41238 | D22: =-D11*EXP((D15-D14)*D13)*NORMSDIST(-D18)+Cap*EXP(-D14*D13)*NORMSDIST(-D18+D16) -> 564.3314 | E22: =-E11*EXP((E15-E14)*E13)*NORMSDIST(-E18)+Cap*EXP(-E14*E13)*NORMSDIST(-E18+E16) -> 574.27036 | F22: =-F11*EXP((F15-F14)*F13)*NORMSDIST(-F18)+Cap*EXP(-F14*F13)*NORMSDIST(-F18+F16) -> 538.33007 | G22: =-G11*EXP((G15-G14)*G13)*NORMSDIST(-G18)+Cap*EXP(-G14*G13)*NORMSDIST(-G18+G16) -> 555.95395 | H22: =-H11*EXP((H15-H14)*H13)*NORMSDIST(-H18)+Cap*EXP(-H14*H13)*NORMSDIST(-H18+H16) -> 556.07398 | I22: =-I11*EXP((I15-I14)*I13)*NORMSDIST(-I18)+Cap*EXP(-I14*I13)*NORMSDIST(-I18+I16) -> 556.55709
A23: B | B23: =-B11*EXP((B15-B14)*B13)*NORMSDIST(-B19)+Cap*EXP(-B14*B13)*NORMSDIST(-B19+B16) -> 347.66378 | C23: =-C11*EXP((C15-C14)*C13)*NORMSDIST(-C19)+Cap*EXP(-C14*C13)*NORMSDIST(-C19+C16) -> 340.38276 | D23: =-D11*EXP((D15-D14)*D13)*NORMSDIST(-D19)+Cap*EXP(-D14*D13)*NORMSDIST(-D19+D16) -> 355.10472 | E23: =-E11*EXP((E15-E14)*E13)*NORMSDIST(-E19)+Cap*EXP(-E14*E13)*NORMSDIST(-E19+E16) -> 372.97205 | F23: =-F11*EXP((F15-F14)*F13)*NORMSDIST(-F19)+Cap*EXP(-F14*F13)*NORMSDIST(-F19+F16) -> 322.01243 | G23: =-G11*EXP((G15-G14)*G13)*NORMSDIST(-G19)+Cap*EXP(-G14*G13)*NORMSDIST(-G19+G16) -> 347.09698 | H23: =-H11*EXP((H15-H14)*H13)*NORMSDIST(-H19)+Cap*EXP(-H14*H13)*NORMSDIST(-H19+H16) -> 347.47024 | I23: =-I11*EXP((I15-I14)*I13)*NORMSDIST(-I19)+Cap*EXP(-I14*I13)*NORMSDIST(-I19+I16) -> 347.85741
A24: C | B24: =-B11*EXP((B15-B14)*B13)*(Barrier/B11)^(2*(B17+1))*NORMSDIST(B20)+Cap*EXP(-B14*B13)*(Barrier/B11)^(2*B17)*NORMSDIST(B20-B16) -> -12.03568 | C24: =-C11*EXP((C15-C14)*C13)*(Barrier/C11)^(2*(C17+1))*NORMSDIST(C20)+Cap*EXP(-C14*C13)*(Barrier/C11)^(2*C17)*NORMSDIST(C20-C16) -> -11.571486 | D24: =-D11*EXP((D15-D14)*D13)*(Barrier/D11)^(2*(D17+1))*NORMSDIST(D20)+Cap*EXP(-D14*D13)*(Barrier/D11)^(2*D17)*NORMSDIST(D20-D16) -> -12.52059 | E24: =-E11*EXP((E15-E14)*E13)*(Barrier/E11)^(2*(E17+1))*NORMSDIST(E20)+Cap*EXP(-E14*E13)*(Barrier/E11)^(2*E17)*NORMSDIST(E20-E16) -> -15.429748 | F24: =-F11*EXP((F15-F14)*F13)*(Barrier/F11)^(2*(F17+1))*NORMSDIST(F20)+Cap*EXP(-F14*F13)*(Barrier/F11)^(2*F17)*NORMSDIST(F20-F16) -> -9.1316445 | G24: =-G11*EXP((G15-G14)*G13)*(Barrier/G11)^(2*(G17+1))*NORMSDIST(G20)+Cap*EXP(-G14*G13)*(Barrier/G11)^(2*G17)*NORMSDIST(G20-G16) -> -11.957435 | H24: =-H11*EXP((H15-H14)*H13)*(Barrier/H11)^(2*(H17+1))*NORMSDIST(H20)+Cap*EXP(-H14*H13)*(Barrier/H11)^(2*H17)*NORMSDIST(H20-H16) -> -12.037982 | I24: =-I11*EXP((I15-I14)*I13)*(Barrier/I11)^(2*(I17+1))*NORMSDIST(I20)+Cap*EXP(-I14*I13)*(Barrier/I11)^(2*I17)*NORMSDIST(I20-I16) -> -12.033378
A25: D | B25: =-B11*EXP((B15-B14)*B13)*(Barrier/B11)^(2*(B17+1))*NORMSDIST(B21)+Cap*EXP(-B14*B13)*(Barrier/B11)^(2*B17)*NORMSDIST(B21-B16) -> 108.46478 | C25: =-C11*EXP((C15-C14)*C13)*(Barrier/C11)^(2*(C17+1))*NORMSDIST(C21)+Cap*EXP(-C14*C13)*(Barrier/C11)^(2*C17)*NORMSDIST(C21-C16) -> 107.21973 | D25: =-D11*EXP((D15-D14)*D13)*(Barrier/D11)^(2*(D17+1))*NORMSDIST(D21)+Cap*EXP(-D14*D13)*(Barrier/D11)^(2*D17)*NORMSDIST(D21-D16) -> 109.69845 | E25: =-E11*EXP((E15-E14)*E13)*(Barrier/E11)^(2*(E17+1))*NORMSDIST(E21)+Cap*EXP(-E14*E13)*(Barrier/E11)^(2*E17)*NORMSDIST(E21-E16) -> 105.9998 | F25: =-F11*EXP((F15-F14)*F13)*(Barrier/F11)^(2*(F17+1))*NORMSDIST(F21)+Cap*EXP(-F14*F13)*(Barrier/F11)^(2*F17)*NORMSDIST(F21-F16) -> 109.78181 | G25: =-G11*EXP((G15-G14)*G13)*(Barrier/G11)^(2*(G17+1))*NORMSDIST(G21)+Cap*EXP(-G14*G13)*(Barrier/G11)^(2*G17)*NORMSDIST(G21-G16) -> 108.52407 | H25: =-H11*EXP((H15-H14)*H13)*(Barrier/H11)^(2*(H17+1))*NORMSDIST(H21)+Cap*EXP(-H14*H13)*(Barrier/H11)^(2*H17)*NORMSDIST(H21-H16) -> 108.4313 | I25: =-I11*EXP((I15-I14)*I13)*(Barrier/I11)^(2*(I17+1))*NORMSDIST(I21)+Cap*EXP(-I14*I13)*(Barrier/I11)^(2*I17)*NORMSDIST(I21-I16) -> 108.49825
A26: DO put | B26: =IF(B11<=Barrier,0,B22-B23+B24-B25) -> 88.151256 | C26: =IF(C11<=Barrier,0,C22-C23+C24-C25) -> 89.238408 | D26: =IF(D11<=Barrier,0,D22-D23+D24-D25) -> 87.007631 | E26: =IF(E11<=Barrier,0,E22-E23+E24-E25) -> 79.868765 | F26: =IF(F11<=Barrier,0,F22-F23+F24-F25) -> 97.40418 | G26: =IF(G11<=Barrier,0,G22-G23+G24-G25) -> 88.375469 | H26: =IF(H11<=Barrier,0,H22-H23+H24-H25) -> 88.134457 | I26: =IF(I11<=Barrier,0,I22-I23+I24-I25) -> 88.168051
A27: capped fwd | B27: =Cap*EXP(-B14*B13)-B22 -> 1376.3867 | C27: =Cap*EXP(-C14*C13)-C22 -> 1384.2898 | D27: =Cap*EXP(-D14*D13)-D22 -> 1368.3708 | E27: =Cap*EXP(-E14*E13)-E22 -> 1358.4318 | F27: =Cap*EXP(-F14*F13)-F22 -> 1394.3721 | G27: =Cap*EXP(-G14*G13)-G22 -> 1376.8952 | H27: =Cap*EXP(-H14*H13)-H22 -> 1376.283 | I27: =Cap*EXP(-I14*I13)-I22 -> 1376.4904
A28: PRICE | B28: =B27+B26 -> 1464.538 | C28: =C27+C26 -> 1473.5282 | D28: =D27+D26 -> 1455.3784 | E28: =E27+E26 -> 1438.3006 | F28: =F27+F26 -> 1491.7763 | G28: =G27+G26 -> 1465.2707 | H28: =H27+H26 -> 1464.4175 | I28: =I27+I26 -> 1464.6584
A31: GREEKS
A32: Price | B32: =B28 -> 1464.538
A33: Delta | B33: =(C28-D28)/(2*dS*$B$5) -> 0.53133878
A34: Gamma | B34: =(C28-2*B28+D28)/(dS*$B$5)^2 -> -0.00058025449
A35: Vega (per +1 vol pt) | B35: =(E28-F28)/(2*dSig)/100 -> -13.368929
A36: Theta (per day, /365) | B36: =(G28-B28)/dT/365 -> 0.50587839
A37: Rho (per +1% rate) | B37: =(H28-I28)/(2*dR)*0.01 -> -12.048387

Sheet P2_TaskVII_Replication
A1: Task VII — Daily replicating portfolio (Delta hedge + bond)
A2: Delta via central FD on the closed-form price (reusing daily r, sigma, T from Task V). Equity leg = Delta*S; Bond leg = Price - Delta*S; Equity fraction = Delta*S / Price.
A3: Date | B3: S | C3: r | D3: sigma | E3: T | F3: carry | G3: sig*sqrtT | H3: mu | I3: Price | J3: S+ | K3: x1+ | L3: x2+ | M3: y1+ | N3: y2+ | O3: A+ | P3: B+ | Q3: C+ | R3: D+ | S3: Price+ | T3: S- | U3: x1- | V3: x2- | W3: y1- | X3: y2- | Y3: A- | Z3: B- | AA3: C- | AB3: D- | AC3: Price- | AD3: Delta | AE3: Equity EUR | AF3: Bond EUR | AG3: Equity frac
A4: =P2_TaskV_Valuation!A4 -> 45904 | B4: =P2_TaskV_Valuation!B4 -> 1707.93 | C4: =P2_TaskV_Valuation!N4 -> 0.019161407 | D4: =P2_TaskV_Valuation!C4 -> 0.39 | E4: =P2_TaskV_Valuation!D4 -> 1.7863014 | F4: =P2_TaskV_Valuation!O4 -> 0.013161407 | G4: =P2_TaskV_Valuation!P4 -> 0.52124508 | H4: =P2_TaskV_Valuation!Q4 -> -0.41346872 | I4: =P2_TaskV_Valuation!AB4 -> 1543.6153 | J4: =B4*(1+dS) -> 1725.0093 | K4: =LN(J4/Cap)/G4+(1+H4)*G4 -> 0.021954587 | L4: =LN(J4/Barrier)/G4+(1+H4)*G4 -> 1.2581428 | M4: =LN(Barrier^2/(J4*Cap))/G4+(1+H4)*G4 -> -1.8828779 | N4: =LN(Barrier/J4)/G4+(1+H4)*G4 -> -0.64668968 | O4: =-J4*EXP((F4-C4)*E4)*NORMSDIST(-K4)+Cap*EXP(-C4*E4)*NORMSDIST(-K4+G4) -> 497.54474 | P4: =-J4*EXP((F4-C4)*E4)*NORMSDIST(-L4)+Cap*EXP(-C4*E4)*NORMSDIST(-L4+G4) -> 267.88754 | Q4: =-J4*EXP((F4-C4)*E4)*(Barrier/J4)^(2*(H4+1))*NORMSDIST(M4)+Cap*EXP(-C4*E4)*(Barrier/J4)^(2*H4)*NORMSDIST(M4-G4) -> -4.845587 | R4: =-J4*EXP((F4-C4)*E4)*(Barrier/J4)^(2*(H4+1))*NORMSDIST(N4)+Cap*EXP(-C4*E4)*(Barrier/J4)^(2*H4)*NORMSDIST(N4-G4) -> 106.95852 | S4: =Cap*EXP(-C4*E4)-O4+IF(J4<=Barrier,0,O4-P4+Q4-R4) -> 1553.0106 | T4: =B4*(1-dS) -> 1690.8507 | U4: =LN(T4/Cap)/G4+(1+H4)*G4 -> -0.016416359 | V4: =LN(T4/Barrier)/G4+(1+H4)*G4 -> 1.2197718 | W4: =LN(Barrier^2/(T4*Cap))/G4+(1+H4)*G4 -> -1.8445069 | X4: =LN(Barrier/T4)/G4+(1+H4)*G4 -> -0.60831874 | Y4: =-T4*EXP((F4-C4)*E4)*NORMSDIST(-U4)+Cap*EXP(-C4*E4)*NORMSDIST(-U4+G4) -> 514.40377 | Z4: =-T4*EXP((F4-C4)*E4)*NORMSDIST(-V4)+Cap*EXP(-C4*E4)*NORMSDIST(-V4+G4) -> 282.38846 | AA4: =-T4*EXP((F4-C4)*E4)*(Barrier/T4)^(2*(H4+1))*NORMSDIST(W4)+Cap*EXP(-C4*E4)*(Barrier/T4)^(2*H4)*NORMSDIST(W4-G4) -> -5.3570098 | AB4: =-T4*EXP((F4-C4)*E4)*(Barrier/T4)^(2*(H4+1))*NORMSDIST(X4)+Cap*EXP(-C4*E4)*(Barrier/T4)^(2*H4)*NORMSDIST(X4-G4) -> 110.95349 | AC4: =Cap*EXP(-C4*E4)-Y4+IF(T4<=Barrier,0,Y4-Z4+AA4-AB4) -> 1534.0032 | AD4: =(S4-AC4)/(2*dS*B4) -> 0.55644312 | AE4: =AD4*B4 -> 950.36589 | AF4: =I4-AE4 -> 593.2494 | AG4: =AE4/I4 -> 0.61567536
A5: =P2_TaskV_Valuation!A5 -> 45905 | B5: =P2_TaskV_Valuation!B5 -> 1727.24 | C5: =P2_TaskV_Valuation!N5 -> 0.01893438 | D5: =P2_TaskV_Valuation!C5 -> 0.38 | E5: =P2_TaskV_Valuation!D5 -> 1.7835616 | F5: =P2_TaskV_Valuation!O5 -> 0.01293438 | G5: =P2_TaskV_Valuation!P5 -> 0.5074902 | H5: =P2_TaskV_Valuation!Q5 -> -0.41042673 | I5: =P2_TaskV_Valuation!AB5 -> 1570.1788 | J5: =B5*(1+dS) -> 1744.5124 | K5: =LN(J5/Cap)/G5+(1+H5)*G5 -> 0.029892841 | L5: =LN(J5/Barrier)/G5+(1+H5)*G5 -> 1.2995864 | M5: =LN(Barrier^2/(J5*Cap))/G5+(1+H5)*G5 -> -1.9708746 | N5: =LN(Barrier/J5)/G5+(1+H5)*G5 -> -0.70118105 | O5: =-J5*EXP((F5-C5)*E5)*NORMSDIST(-K5)+Cap*EXP(-C5*E5)*NORMSDIST(-K5+G5) -> 479.2755 | P5: =-J5*EXP((F5-C5)*E5)*NORMSDIST(-L5)+Cap*EXP(-C5*E5)*NORMSDIST(-L5+G5) -> 246.88747 | Q5: =-J5*EXP((F5-C5)*E5)*(Barrier/J5)^(2*(H5+1))*NORMSDIST(M5)+Cap*EXP(-C5*E5)*(Barrier/J5)^(2*H5)*NORMSDIST(M5-G5) -> -3.7569619 | R5: =-J5*EXP((F5-C5)*E5)*(Barrier/J5)^(2*(H5+1))*NORMSDIST(N5)+Cap*EXP(-C5*E5)*(Barrier/J5)^(2*H5)*NORMSDIST(N5-G5) -> 103.45913 | S5: =Cap*EXP(-C5*E5)-O5+IF(J5<=Barrier,0,O5-P5+Q5-R5) -> 1579.4829 | T5: =B5*(1-dS) -> 1709.9676 | U5: =LN(T5/Cap)/G5+(1+H5)*G5 -> -0.0095181009 | V5: =LN(T5/Barrier)/G5+(1+H5)*G5 -> 1.2601754 | W5: =LN(Barrier^2/(T5*Cap))/G5+(1+H5)*G5 -> -1.9314636 | X5: =LN(Barrier/T5)/G5+(1+H5)*G5 -> -0.66177011 | Y5: =-T5*EXP((F5-C5)*E5)*NORMSDIST(-U5)+Cap*EXP(-C5*E5)*NORMSDIST(-U5+G5) -> 496.22427 | Z5: =-T5*EXP((F5-C5)*E5)*NORMSDIST(-V5)+Cap*EXP(-C5*E5)*NORMSDIST(-V5+G5) -> 261.03114 | AA5: =-T5*EXP((F5-C5)*E5)*(Barrier/T5)^(2*(H5+1))*NORMSDIST(W5)+Cap*EXP(-C5*E5)*(Barrier/T5)^(2*H5)*NORMSDIST(W5-G5) -> -4.177019 | AB5: =-T5*EXP((F5-C5)*E5)*(Barrier/T5)^(2*(H5+1))*NORMSDIST(X5)+Cap*EXP(-C5*E5)*(Barrier/T5)^(2*H5)*NORMSDIST(X5-G5) -> 107.73186 | AC5: =Cap*EXP(-C5*E5)-Y5+IF(T5<=Barrier,0,Y5-Z5+AA5-AB5) -> 1560.6464 | AD5: =(S5-AC5)/(2*dS*B5) -> 0.545276 | AE5: =AD5*B5 -> 941.82252 | AF5: =I5-AE5 -> 628.35626 | AG5: =AE5/I5 -> 0.59981865
A6: =P2_TaskV_Valuation!A6 -> 45908 | B6: =P2_TaskV_Valuation!B6 -> 1773.27 | C6: =P2_TaskV_Valuation!N6 -> 0.018881794 | D6: =P2_TaskV_Valuation!C6 -> 0.383 | E6: =P2_TaskV_Valuation!D6 -> 1.7753425 | F6: =P2_TaskV_Valuation!O6 -> 0.012881794 | G6: =P2_TaskV_Valuation!P6 -> 0.51031678 | H6: =P2_TaskV_Valuation!Q6 -> -0.41218296 | I6: =P2_TaskV_Valuation!AB6 -> 1591.473 | J6: =B6*(1+dS) -> 1791.0027 | K6: =LN(J6/Cap)/G6+(1+H6)*G6 -> 0.08369243 | L6: =LN(J6/Barrier)/G6+(1+H6)*G6 -> 1.3463533 | M6: =LN(Barrier^2/(J6*Cap))/G6+(1+H6)*G6 -> -2.0090684 | N6: =LN(Barrier/J6)/G6+(1+H6)*G6 -> -0.74640749 | O6: =-J6*EXP((F6-C6)*E6)*NORMSDIST(-K6)+Cap*EXP(-C6*E6)*NORMSDIST(-K6+G6) -> 459.57394 | P6: =-J6*EXP((F6-C6)*E6)*NORMSDIST(-L6)+Cap*EXP(-C6*E6)*NORMSDIST(-L6+G6) -> 231.96719 | Q6: =-J6*EXP((F6-C6)*E6)*(Barrier/J6)^(2*(H6+1))*NORMSDIST(M6)+Cap*EXP(-C6*E6)*(Barrier/J6)^(2*H6)*NORMSDIST(M6-G6) -> -3.4043917 | R6: =-J6*EXP((F6-C6)*E6)*(Barrier/J6)^(2*(H6+1))*NORMSDIST(N6)+Cap*EXP(-C6*E6)*(Barrier/J6)^(2*H6)*NORMSDIST(N6-G6) -> 98.275235 | S6: =Cap*EXP(-C6*E6)-O6+IF(J6<=Barrier,0,O6-P6+Q6-R6) -> 1600.4211 | T6: =B6*(1-dS) -> 1755.5373 | U6: =LN(T6/Cap)/G6+(1+H6)*G6 -> 0.04449978 | V6: =LN(T6/Barrier)/G6+(1+H6)*G6 -> 1.3071606 | W6: =LN(Barrier^2/(T6*Cap))/G6+(1+H6)*G6 -> -1.9698757 | X6: =LN(Barrier/T6)/G6+(1+H6)*G6 -> -0.70721484 | Y6: =-T6*EXP((F6-C6)*E6)*NORMSDIST(-U6)+Cap*EXP(-C6*E6)*NORMSDIST(-U6+G6) -> 476.22125 | Z6: =-T6*EXP((F6-C6)*E6)*NORMSDIST(-V6)+Cap*EXP(-C6*E6)*NORMSDIST(-V6+G6) -> 245.49851 | AA6: =-T6*EXP((F6-C6)*E6)*(Barrier/T6)^(2*(H6+1))*NORMSDIST(W6)+Cap*EXP(-C6*E6)*(Barrier/T6)^(2*H6)*NORMSDIST(W6-G6) -> -3.7873302 | AB6: =-T6*EXP((F6-C6)*E6)*(Barrier/T6)^(2*(H6+1))*NORMSDIST(X6)+Cap*EXP(-C6*E6)*(Barrier/T6)^(2*H6)*NORMSDIST(X6-G6) -> 102.48412 | AC6: =Cap*EXP(-C6*E6)-Y6+IF(T6<=Barrier,0,Y6-Z6+AA6-AB6) -> 1582.298 | AD6: =(S6-AC6)/(2*dS*B6) -> 0.51100897 | AE6: =AD6*B6 -> 906.15688 | AF6: =I6-AE6 -> 685.31613 | AG6: =AE6/I6 -> 0.5693825
A7: =P2_TaskV_Valuation!A7 -> 45909 | B7: =P2_TaskV_Valuation!B7 -> 1761.39 | C7: =P2_TaskV_Valuation!N7 -> 0.018955417 | D7: =P2_TaskV_Valuation!C7 -> 0.372 | E7: =P2_TaskV_Valuation!D7 -> 1.7726027 | F7: =P2_TaskV_Valuation!O7 -> 0.012955417 | G7: =P2_TaskV_Valuation!P7 -> 0.49527756 | H7: =P2_TaskV_Valuation!Q7 -> -0.40638068 | I7: =P2_TaskV_Valuation!AB7 -> 1602.7091 | J7: =B7*(1+dS) -> 1779.0039 | K7: =LN(J7/Cap)/G7+(1+H7)*G7 -> 0.057586208 | L7: =LN(J7/Barrier)/G7+(1+H7)*G7 -> 1.3585881 | M7: =LN(Barrier^2/(J7*Cap))/G7+(1+H7)*G7 -> -2.0715772 | N7: =LN(Barrier/J7)/G7+(1+H7)*G7 -> -0.7705754 | O7: =-J7*EXP((F7-C7)*E7)*NORMSDIST(-K7)+Cap*EXP(-C7*E7)*NORMSDIST(-K7+G7) -> 454.49029 | P7: =-J7*EXP((F7-C7)*E7)*NORMSDIST(-L7)+Cap*EXP(-C7*E7)*NORMSDIST(-L7+G7) -> 221.76762 | Q7: =-J7*EXP((F7-C7)*E7)*(Barrier/J7)^(2*(H7+1))*NORMSDIST(M7)+Cap*EXP(-C7*E7)*(Barrier/J7)^(2*H7)*NORMSDIST(M7-G7) -> -2.7941728 | R7: =-J7*EXP((F7-C7)*E7)*(Barrier/J7)^(2*(H7+1))*NORMSDIST(N7)+Cap*EXP(-C7*E7)*(Barrier/J7)^(2*H7)*NORMSDIST(N7-G7) -> 97.598504 | S7: =Cap*EXP(-C7*E7)-O7+IF(J7<=Barrier,0,O7-P7+Q7-R7) -> 1611.7553 | T7: =B7*(1-dS) -> 1743.7761 | U7: =LN(T7/Cap)/G7+(1+H7)*G7 -> 0.017203464 | V7: =LN(T7/Barrier)/G7+(1+H7)*G7 -> 1.3182053 | W7: =LN(Barrier^2/(T7*Cap))/G7+(1+H7)*G7 -> -2.0311945 | X7: =LN(Barrier/T7)/G7+(1+H7)*G7 -> -0.73019266 | Y7: =-T7*EXP((F7-C7)*E7)*NORMSDIST(-U7)+Cap*EXP(-C7*E7)*NORMSDIST(-U7+G7) -> 471.39709 | Z7: =-T7*EXP((F7-C7)*E7)*NORMSDIST(-V7)+Cap*EXP(-C7*E7)*NORMSDIST(-V7+G7) -> 235.29025 | AA7: =-T7*EXP((F7-C7)*E7)*(Barrier/T7)^(2*(H7+1))*NORMSDIST(W7)+Cap*EXP(-C7*E7)*(Barrier/T7)^(2*H7)*NORMSDIST(W7-G7) -> -3.1256146 | AB7: =-T7*EXP((F7-C7)*E7)*(Barrier/T7)^(2*(H7+1))*NORMSDIST(X7)+Cap*EXP(-C7*E7)*(Barrier/T7)^(2*H7)*NORMSDIST(X7-G7) -> 102.07531 | AC7: =Cap*EXP(-C7*E7)-Y7+IF(T7<=Barrier,0,Y7-Z7+AA7-AB7) -> 1593.4244 | AD7: =(S7-AC7)/(2*dS*B7) -> 0.52035252 | AE7: =AD7*B7 -> 916.54373 | AF7: =I7-AE7 -> 686.16541 | AG7: =AE7/I7 -> 0.57187153
A8: =P2_TaskV_Valuation!A8 -> 45910 | B8: =P2_TaskV_Valuation!B8 -> 1819.31 | C8: =P2_TaskV_Valuation!N8 -> 0.019053388 | D8: =P2_TaskV_Valuation!C8 -> 0.382 | E8: =P2_TaskV_Valuation!D8 -> 1.769863 | F8: =P2_TaskV_Valuation!O8 -> 0.013053388 | G8: =P2_TaskV_Valuation!P8 -> 0.50819828 | H8: =P2_TaskV_Valuation!Q8 -> -0.41054666 | I8: =P2_TaskV_Valuation!AB8 -> 1616.53 | J8: =B8*(1+dS) -> 1837.5031 | K8: =LN(J8/Cap)/G8+(1+H8)*G8 -> 0.13281413 | L8: =LN(J8/Barrier)/G8+(1+H8)*G8 -> 1.4007386 | M8: =LN(Barrier^2/(J8*Cap))/G8+(1+H8)*G8 -> -2.0695447 | N8: =LN(Barrier/J8)/G8+(1+H8)*G8 -> -0.80162023 | O8: =-J8*EXP((F8-C8)*E8)*NORMSDIST(-K8)+Cap*EXP(-C8*E8)*NORMSDIST(-K8+G8) -> 436.76497 | P8: =-J8*EXP((F8-C8)*E8)*NORMSDIST(-L8)+Cap*EXP(-C8*E8)*NORMSDIST(-L8+G8) -> 213.14238 | Q8: =-J8*EXP((F8-C8)*E8)*(Barrier/J8)^(2*(H8+1))*NORMSDIST(M8)+Cap*EXP(-C8*E8)*(Barrier/J8)^(2*H8)*NORMSDIST(M8-G8) -> -2.8680573 | R8: =-J8*EXP((F8-C8)*E8)*(Barrier/J8)^(2*(H8+1))*NORMSDIST(N8)+Cap*EXP(-C8*E8)*(Barrier/J8)^(2*H8)*NORMSDIST(N8-G8) -> 92.552983 | S8: =Cap*EXP(-C8*E8)-O8+IF(J8<=Barrier,0,O8-P8+Q8-R8) -> 1625.1173 | T8: =B8*(1-dS) -> 1801.1169 | U8: =LN(T8/Cap)/G8+(1+H8)*G8 -> 0.093458102 | V8: =LN(T8/Barrier)/G8+(1+H8)*G8 -> 1.3613825 | W8: =LN(Barrier^2/(T8*Cap))/G8+(1+H8)*G8 -> -2.0301886 | X8: =LN(Barrier/T8)/G8+(1+H8)*G8 -> -0.7622642 | Y8: =-T8*EXP((F8-C8)*E8)*NORMSDIST(-U8)+Cap*EXP(-C8*E8)*NORMSDIST(-U8+G8) -> 453.14359 | Z8: =-T8*EXP((F8-C8)*E8)*NORMSDIST(-V8)+Cap*EXP(-C8*E8)*NORMSDIST(-V8+G8) -> 226.00595 | AA8: =-T8*EXP((F8-C8)*E8)*(Barrier/T8)^(2*(H8+1))*NORMSDIST(W8)+Cap*EXP(-C8*E8)*(Barrier/T8)^(2*H8)*NORMSDIST(W8-G8) -> -3.1986316 | AB8: =-T8*EXP((F8-C8)*E8)*(Barrier/T8)^(2*(H8+1))*NORMSDIST(X8)+Cap*EXP(-C8*E8)*(Barrier/T8)^(2*H8)*NORMSDIST(X8-G8) -> 96.761706 | AC8: =Cap*EXP(-C8*E8)-Y8+IF(T8<=Barrier,0,Y8-Z8+AA8-AB8) -> 1607.7144 | AD8: =(S8-AC8)/(2*dS*B8) -> 0.47828223 | AE8: =AD8*B8 -> 870.14364 | AF8: =I8-AE8 -> 746.38636 | AG8: =AE8/I8 -> 0.53827868
A9: =P2_TaskV_Valuation!A9 -> 45911 | B9: =P2_TaskV_Valuation!B9 -> 1861.89 | C9: =P2_TaskV_Valuation!N9 -> 0.019423606 | D9: =P2_TaskV_Valuation!C9 -> 0.381 | E9: =P2_TaskV_Valuation!D9 -> 1.7671233 | F9: =P2_TaskV_Valuation!O9 -> 0.013423606 | G9: =P2_TaskV_Valuation!P9 -> 0.50647545 | H9: =P2_TaskV_Valuation!Q9 -> -0.40752609 | I9: =P2_TaskV_Valuation!AB9 -> 1637.7149 | J9: =B9*(1+dS) -> 1880.5089 | K9: =LN(J9/Cap)/G9+(1+H9)*G9 -> 0.17843927 | L9: =LN(J9/Barrier)/G9+(1+H9)*G9 -> 1.4506767 | M9: =LN(Barrier^2/(J9*Cap))/G9+(1+H9)*G9 -> -2.1227671 | N9: =LN(Barrier/J9)/G9+(1+H9)*G9 -> -0.85052969 | O9: =-J9*EXP((F9-C9)*E9)*NORMSDIST(-K9)+Cap*EXP(-C9*E9)*NORMSDIST(-K9+G9) -> 416.11715 | P9: =-J9*EXP((F9-C9)*E9)*NORMSDIST(-L9)+Cap*EXP(-C9*E9)*NORMSDIST(-L9+G9) -> 196.78511 | Q9: =-J9*EXP((F9-C9)*E9)*(Barrier/J9)^(2*(H9+1))*NORMSDIST(M9)+Cap*EXP(-C9*E9)*(Barrier/J9)^(2*H9)*NORMSDIST(M9-G9) -> -2.455505 | R9: =-J9*EXP((F9-C9)*E9)*(Barrier/J9)^(2*(H9+1))*NORMSDIST(N9)+Cap*EXP(-C9*E9)*(Barrier/J9)^(2*H9)*NORMSDIST(N9-G9) -> 87.320508 | S9: =Cap*EXP(-C9*E9)-O9+IF(J9<=Barrier,0,O9-P9+Q9-R9) -> 1645.9558 | T9: =B9*(1-dS) -> 1843.2711 | U9: =LN(T9/Cap)/G9+(1+H9)*G9 -> 0.13894937 | V9: =LN(T9/Barrier)/G9+(1+H9)*G9 -> 1.4111868 | W9: =LN(Barrier^2/(T9*Cap))/G9+(1+H9)*G9 -> -2.0832772 | X9: =LN(Barrier/T9)/G9+(1+H9)*G9 -> -0.81103979 | Y9: =-T9*EXP((F9-C9)*E9)*NORMSDIST(-U9)+Cap*EXP(-C9*E9)*NORMSDIST(-U9+G9) -> 432.21597 | Z9: =-T9*EXP((F9-C9)*E9)*NORMSDIST(-V9)+Cap*EXP(-C9*E9)*NORMSDIST(-V9+G9) -> 209.02635 | AA9: =-T9*EXP((F9-C9)*E9)*(Barrier/T9)^(2*(H9+1))*NORMSDIST(W9)+Cap*EXP(-C9*E9)*(Barrier/T9)^(2*H9)*NORMSDIST(W9-G9) -> -2.7447012 | AB9: =-T9*EXP((F9-C9)*E9)*(Barrier/T9)^(2*(H9+1))*NORMSDIST(X9)+Cap*EXP(-C9*E9)*(Barrier/T9)^(2*H9)*NORMSDIST(X9-G9) -> 91.500189 | AC9: =Cap*EXP(-C9*E9)-Y9+IF(T9<=Barrier,0,Y9-Z9+AA9-AB9) -> 1629.2457 | AD9: =(S9-AC9)/(2*dS*B9) -> 0.44874072 | AE9: =AD9*B9 -> 835.50586 | AF9: =I9-AE9 -> 802.20908 | AG9: =AE9/I9 -> 0.51016562
A10: =P2_TaskV_Valuation!A10 -> 45912 | B10: =P2_TaskV_Valuation!B10 -> 1877.73 | C10: =P2_TaskV_Valuation!N10 -> 0.019649879 | D10: =P2_TaskV_Valuation!C10 -> 0.371 | E10: =P2_TaskV_Valuation!D10 -> 1.7643836 | F10: =P2_TaskV_Valuation!O10 -> 0.013649879 | G10: =P2_TaskV_Valuation!P10 -> 0.49279967 | H10: =P2_TaskV_Valuation!Q10 -> -0.40082985 | I10: =P2_TaskV_Valuation!AB10 -> 1660.1513 | J10: =B10*(1+dS) -> 1896.5073 | K10: =LN(J10/Cap)/G10+(1+H10)*G10 -> 0.18745169 | L10: =LN(J10/Barrier)/G10+(1+H10)*G10 -> 1.4949952 | M10: =LN(Barrier^2/(J10*Cap))/G10+(1+H10)*G10 -> -2.211997 | N10: =LN(Barrier/J10)/G10+(1+H10)*G10 -> -0.90445349 | O10: =-J10*EXP((F10-C10)*E10)*NORMSDIST(-K10)+Cap*EXP(-C10*E10)*NORMSDIST(-K10+G10) -> 398.89458 | P10: =-J10*EXP((F10-C10)*E10)*NORMSDIST(-L10)+Cap*EXP(-C10*E10)*NORMSDIST(-L10+G10) -> 178.88563 | Q10: =-J10*EXP((F10-C10)*E10)*(Barrier/J10)^(2*(H10+1))*NORMSDIST(M10)+Cap*EXP(-C10*E10)*(Barrier/J10)^(2*H10)*NORMSDIST(M10-G10) -> -1.8538533 | R10: =-J10*EXP((F10-C10)*E10)*(Barrier/J10)^(2*(H10+1))*NORMSDIST(N10)+Cap*EXP(-C10*E10)*(Barrier/J10)^(2*H10)*NORMSDIST(N10-G10) -> 82.907695 | S10: =Cap*EXP(-C10*E10)-O10+IF(J10<=Barrier,0,O10-P10+Q10-R10) -> 1668.2012 | T10: =B10*(1-dS) -> 1858.9527 | U10: =LN(T10/Cap)/G10+(1+H10)*G10 -> 0.1468659 | V10: =LN(T10/Barrier)/G10+(1+H10)*G10 -> 1.4544094 | W10: =LN(Barrier^2/(T10*Cap))/G10+(1+H10)*G10 -> -2.1714112 | X10: =LN(Barrier/T10)/G10+(1+H10)*G10 -> -0.8638677 | Y10: =-T10*EXP((F10-C10)*E10)*NORMSDIST(-U10)+Cap*EXP(-C10*E10)*NORMSDIST(-U10+G10) -> 415.0068 | Z10: =-T10*EXP((F10-C10)*E10)*NORMSDIST(-V10)+Cap*EXP(-C10*E10)*NORMSDIST(-V10+G10) -> 190.66705 | AA10: =-T10*EXP((F10-C10)*E10)*(Barrier/T10)^(2*(H10+1))*NORMSDIST(W10)+Cap*EXP(-C10*E10)*(Barrier/T10)^(2*H10)*NORMSDIST(W10-G10) -> -2.0853652 | AB10: =-T10*EXP((F10-C10)*E10)*(Barrier/T10)^(2*(H10+1))*NORMSDIST(X10)+Cap*EXP(-C10*E10)*(Barrier/T10)^(2*H10)*NORMSDIST(X10-G10) -> 87.231288 | AC10: =Cap*EXP(-C10*E10)-Y10+IF(T10<=Barrier,0,Y10-Z10+AA10-AB10) -> 1651.8647 | AD10: =(S10-AC10)/(2*dS*B10) -> 0.43500738 | AE10: =AD10*B10 -> 816.82641 | AF10: =I10-AE10 -> 843.32492 | AG10: =AE10/I10 -> 0.49201925
A11: =P2_TaskV_Valuation!A11 -> 45915 | B11: =P2_TaskV_Valuation!B11 -> 1930.7 | C11: =P2_TaskV_Valuation!N11 -> 0.019581829 | D11: =P2_TaskV_Valuation!C11 -> 0.376 | E11: =P2_TaskV_Valuation!D11 -> 1.7561644 | F11: =P2_TaskV_Valuation!O11 -> 0.013581829 | G11: =P2_TaskV_Valuation!P11 -> 0.49827653 | H11: =P2_TaskV_Valuation!Q11 -> -0.40393116 | I11: =P2_TaskV_Valuation!AB11 -> 1676.351 | J11: =B11*(1+dS) -> 1950.007 | K11: =LN(J11/Cap)/G11+(1+H11)*G11 -> 0.24620356 | L11: =LN(J11/Barrier)/G11+(1+H11)*G11 -> 1.5393751 | M11: =LN(Barrier^2/(J11*Cap))/G11+(1+H11)*G11 -> -2.2385324 | N11: =LN(Barrier/J11)/G11+(1+H11)*G11 -> -0.94536086 | O11: =-J11*EXP((F11-C11)*E11)*NORMSDIST(-K11)+Cap*EXP(-C11*E11)*NORMSDIST(-K11+G11) -> 381.32625 | P11: =-J11*EXP((F11-C11)*E11)*NORMSDIST(-L11)+Cap*EXP(-C11*E11)*NORMSDIST(-L11+G11) -> 168.40581 | Q11: =-J11*EXP((F11-C11)*E11)*(Barrier/J11)^(2*(H11+1))*NORMSDIST(M11)+Cap*EXP(-C11*E11)*(Barrier/J11)^(2*H11)*NORMSDIST(M11-G11) -> -1.7333438 | R11: =-J11*EXP((F11-C11)*E11)*(Barrier/J11)^(2*(H11+1))*NORMSDIST(N11)+Cap*EXP(-C11*E11)*(Barrier/J11)^(2*H11)*NORMSDIST(N11-G11) -> 78.240156 | S11: =Cap*EXP(-C11*E11)-O11+IF(J11<=Barrier,0,O11-P11+Q11-R11) -> 1684.012 | T11: =B11*(1-dS) -> 1911.393 | U11: =LN(T11/Cap)/G11+(1+H11)*G11 -> 0.20606387 | V11: =LN(T11/Barrier)/G11+(1+H11)*G11 -> 1.4992354 | W11: =LN(Barrier^2/(T11*Cap))/G11+(1+H11)*G11 -> -2.1983927 | X11: =LN(Barrier/T11)/G11+(1+H11)*G11 -> -0.90522117 | Y11: =-T11*EXP((F11-C11)*E11)*NORMSDIST(-U11)+Cap*EXP(-C11*E11)*NORMSDIST(-U11+G11) -> 397.01224 | Z11: =-T11*EXP((F11-C11)*E11)*NORMSDIST(-V11)+Cap*EXP(-C11*E11)*NORMSDIST(-V11+G11) -> 179.59213 | AA11: =-T11*EXP((F11-C11)*E11)*(Barrier/T11)^(2*(H11+1))*NORMSDIST(W11)+Cap*EXP(-C11*E11)*(Barrier/T11)^(2*H11)*NORMSDIST(W11-G11) -> -1.9488794 | AB11: =-T11*EXP((F11-C11)*E11)*(Barrier/T11)^(2*(H11+1))*NORMSDIST(X11)+Cap*EXP(-C11*E11)*(Barrier/T11)^(2*H11)*NORMSDIST(X11-G11) -> 82.390356 | AC11: =Cap*EXP(-C11*E11)-Y11+IF(T11<=Barrier,0,Y11-Z11+AA11-AB11) -> 1668.46 | AD11: =(S11-AC11)/(2*dS*B11) -> 0.40275709 | AE11: =AD11*B11 -> 777.60312 | AF11: =I11-AE11 -> 898.74792 | AG11: =AE11/I11 -> 0.46386652
A12: =P2_TaskV_Valuation!A12 -> 45916 | B12: =P2_TaskV_Valuation!B12 -> 1882.19 | C12: =P2_TaskV_Valuation!N12 -> 0.019648921 | D12: =P2_TaskV_Valuation!C12 -> 0.377 | E12: =P2_TaskV_Valuation!D12 -> 1.7534247 | F12: =P2_TaskV_Valuation!O12 -> 0.013648921 | G12: =P2_TaskV_Valuation!P12 -> 0.49921187 | H12: =P2_TaskV_Valuation!Q12 -> -0.40396808 | I12: =P2_TaskV_Valuation!AB12 -> 1654.9494 | J12: =B12*(1+dS) -> 1901.0119 | K12: =LN(J12/Cap)/G12+(1+H12)*G12 -> 0.19586422 | L12: =LN(J12/Barrier)/G12+(1+H12)*G12 -> 1.4866128 | M12: =LN(Barrier^2/(J12*Cap))/G12+(1+H12)*G12 -> -2.182269 | N12: =LN(Barrier/J12)/G12+(1+H12)*G12 -> -0.89152038 | O12: =-J12*EXP((F12-C12)*E12)*NORMSDIST(-K12)+Cap*EXP(-C12*E12)*NORMSDIST(-K12+G12) -> 401.93081 | P12: =-J12*EXP((F12-C12)*E12)*NORMSDIST(-L12)+Cap*EXP(-C12*E12)*NORMSDIST(-L12+G12) -> 183.52559 | Q12: =-J12*EXP((F12-C12)*E12)*(Barrier/J12)^(2*(H12+1))*NORMSDIST(M12)+Cap*EXP(-C12*E12)*(Barrier/J12)^(2*H12)*NORMSDIST(M12-G12) -> -2.0444339 | R12: =-J12*EXP((F12-C12)*E12)*(Barrier/J12)^(2*(H12+1))*NORMSDIST(N12)+Cap*EXP(-C12*E12)*(Barrier/J12)^(2*H12)*NORMSDIST(N12-G12) -> 83.6993 | S12: =Cap*EXP(-C12*E12)-O12+IF(J12<=Barrier,0,O12-P12+Q12-R12) -> 1662.9984 | T12: =B12*(1-dS) -> 1863.3681 | U12: =LN(T12/Cap)/G12+(1+H12)*G12 -> 0.15579974 | V12: =LN(T12/Barrier)/G12+(1+H12)*G12 -> 1.4465483 | W12: =LN(Barrier^2/(T12*Cap))/G12+(1+H12)*G12 -> -2.1422045 | X12: =LN(Barrier/T12)/G12+(1+H12)*G12 -> -0.85145589 | Y12: =-T12*EXP((F12-C12)*E12)*NORMSDIST(-U12)+Cap*EXP(-C12*E12)*NORMSDIST(-U12+G12) -> 417.95537 | Z12: =-T12*EXP((F12-C12)*E12)*NORMSDIST(-V12)+Cap*EXP(-C12*E12)*NORMSDIST(-V12+G12) -> 195.36763 | AA12: =-T12*EXP((F12-C12)*E12)*(Barrier/T12)^(2*(H12+1))*NORMSDIST(W12)+Cap*EXP(-C12*E12)*(Barrier/T12)^(2*H12)*NORMSDIST(W12-G12) -> -2.2937645 | AB12: =-T12*EXP((F12-C12)*E12)*(Barrier/T12)^(2*(H12+1))*NORMSDIST(X12)+Cap*EXP(-C12*E12)*(Barrier/T12)^(2*H12)*NORMSDIST(X12-G12) -> 87.938174 | AC12: =Cap*EXP(-C12*E12)-Y12+IF(T12<=Barrier,0,Y12-Z12+AA12-AB12) -> 1646.6681 | AD12: =(S12-AC12)/(2*dS*B12) -> 0.4338098 | AE12: =AD12*B12 -> 816.51247 | AF12: =I12-AE12 -> 838.43692 | AG12: =AE12/I12 -> 0.4933761
A13: =P2_TaskV_Valuation!A13 -> 45917 | B13: =P2_TaskV_Valuation!B13 -> 1869.81 | C13: =P2_TaskV_Valuation!N13 -> 0.019507499 | D13: =P2_TaskV_Valuation!C13 -> 0.367 | E13: =P2_TaskV_Valuation!D13 -> 1.7506849 | F13: =P2_TaskV_Valuation!O13 -> 0.013507499 | G13: =P2_TaskV_Valuation!P13 -> 0.48559037 | H13: =P2_TaskV_Valuation!Q13 -> -0.39971342 | I13: =P2_TaskV_Valuation!AB13 -> 1665.6138 | J13: =B13*(1+dS) -> 1888.5081 | K13: =LN(J13/Cap)/G13+(1+H13)*G13 -> 0.17336907 | L13: =LN(J13/Barrier)/G13+(1+H13)*G13 -> 1.500325 | M13: =LN(Barrier^2/(J13*Cap))/G13+(1+H13)*G13 -> -2.2442942 | N13: =LN(Barrier/J13)/G13+(1+H13)*G13 -> -0.91733824 | O13: =-J13*EXP((F13-C13)*E13)*NORMSDIST(-K13)+Cap*EXP(-C13*E13)*NORMSDIST(-K13+G13) -> 397.54303 | P13: =-J13*EXP((F13-C13)*E13)*NORMSDIST(-L13)+Cap*EXP(-C13*E13)*NORMSDIST(-L13+G13) -> 175.04735 | Q13: =-J13*EXP((F13-C13)*E13)*(Barrier/J13)^(2*(H13+1))*NORMSDIST(M13)+Cap*EXP(-C13*E13)*(Barrier/J13)^(2*H13)*NORMSDIST(M13-G13) -> -1.6697475 | R13: =-J13*EXP((F13-C13)*E13)*(Barrier/J13)^(2*(H13+1))*NORMSDIST(N13)+Cap*EXP(-C13*E13)*(Barrier/J13)^(2*H13)*NORMSDIST(N13-G13) -> 82.432581 | S13: =Cap*EXP(-C13*E13)-O13+IF(J13<=Barrier,0,O13-P13+Q13-R13) -> 1673.7005 | T13: =B13*(1-dS) -> 1851.1119 | U13: =LN(T13/Cap)/G13+(1+H13)*G13 -> 0.13218072 | V13: =LN(T13/Barrier)/G13+(1+H13)*G13 -> 1.4591366 | W13: =LN(Barrier^2/(T13*Cap))/G13+(1+H13)*G13 -> -2.2031058 | X13: =LN(Barrier/T13)/G13+(1+H13)*G13 -> -0.87614989 | Y13: =-T13*EXP((F13-C13)*E13)*NORMSDIST(-U13)+Cap*EXP(-C13*E13)*NORMSDIST(-U13+G13) -> 413.79823 | Z13: =-T13*EXP((F13-C13)*E13)*NORMSDIST(-V13)+Cap*EXP(-C13*E13)*NORMSDIST(-V13+G13) -> 186.82216 | AA13: =-T13*EXP((F13-C13)*E13)*(Barrier/T13)^(2*(H13+1))*NORMSDIST(W13)+Cap*EXP(-C13*E13)*(Barrier/T13)^(2*H13)*NORMSDIST(W13-G13) -> -1.8836704 | AB13: =-T13*EXP((F13-C13)*E13)*(Barrier/T13)^(2*(H13+1))*NORMSDIST(X13)+Cap*EXP(-C13*E13)*(Barrier/T13)^(2*H13)*NORMSDIST(X13-G13) -> 86.85963 | AC13: =Cap*EXP(-C13*E13)-Y13+IF(T13<=Barrier,0,Y13-Z13+AA13-AB13) -> 1657.2847 | AD13: =(S13-AC13)/(2*dS*B13) -> 0.43896938 | AE13: =AD13*B13 -> 820.78933 | AF13: =I13-AE13 -> 844.82445 | AG13: =AE13/I13 -> 0.49278491
A14: =P2_TaskV_Valuation!A14 -> 45918 | B14: =P2_TaskV_Valuation!B14 -> 1900.5 | C14: =P2_TaskV_Valuation!N14 -> 0.019641012 | D14: =P2_TaskV_Valuation!C14 -> 0.361 | E14: =P2_TaskV_Valuation!D14 -> 1.7479452 | F14: =P2_TaskV_Valuation!O14 -> 0.013641012 | G14: =P2_TaskV_Valuation!P14 -> 0.47727766 | H14: =P2_TaskV_Valuation!Q14 -> -0.3953276 | I14: =P2_TaskV_Valuation!AB14 -> 1688.2291 | J14: =B14*(1+dS) -> 1919.505 | K14: =LN(J14/Cap)/G14+(1+H14)*G14 -> 0.20252547 | L14: =LN(J14/Barrier)/G14+(1+H14)*G14 -> 1.5525929 | M14: =LN(Barrier^2/(J14*Cap))/G14+(1+H14)*G14 -> -2.325467 | N14: =LN(Barrier/J14)/G14+(1+H14)*G14 -> -0.97539962 | O14: =-J14*EXP((F14-C14)*E14)*NORMSDIST(-K14)+Cap*EXP(-C14*E14)*NORMSDIST(-K14+G14) -> 378.12622 | P14: =-J14*EXP((F14-C14)*E14)*NORMSDIST(-L14)+Cap*EXP(-C14*E14)*NORMSDIST(-L14+G14) -> 158.24557 | Q14: =-J14*EXP((F14-C14)*E14)*(Barrier/J14)^(2*(H14+1))*NORMSDIST(M14)+Cap*EXP(-C14*E14)*(Barrier/J14)^(2*H14)*NORMSDIST(M14-G14) -> -1.2907877 | R14: =-J14*EXP((F14-C14)*E14)*(Barrier/J14)^(2*(H14+1))*NORMSDIST(N14)+Cap*EXP(-C14*E14)*(Barrier/J14)^(2*H14)*NORMSDIST(N14-G14) -> 76.97542 | S14: =Cap*EXP(-C14*E14)-O14+IF(J14<=Barrier,0,O14-P14+Q14-R14) -> 1695.9907 | T14: =B14*(1-dS) -> 1881.495 | U14: =LN(T14/Cap)/G14+(1+H14)*G14 -> 0.16061975 | V14: =LN(T14/Barrier)/G14+(1+H14)*G14 -> 1.5106872 | W14: =LN(Barrier^2/(T14*Cap))/G14+(1+H14)*G14 -> -2.2835613 | X14: =LN(Barrier/T14)/G14+(1+H14)*G14 -> -0.9334939 | Y14: =-T14*EXP((F14-C14)*E14)*NORMSDIST(-U14)+Cap*EXP(-C14*E14)*NORMSDIST(-U14+G14) -> 394.2224 | Z14: =-T14*EXP((F14-C14)*E14)*NORMSDIST(-V14)+Cap*EXP(-C14*E14)*NORMSDIST(-V14+G14) -> 169.41053 | AA14: =-T14*EXP((F14-C14)*E14)*(Barrier/T14)^(2*(H14+1))*NORMSDIST(W14)+Cap*EXP(-C14*E14)*(Barrier/T14)^(2*H14)*NORMSDIST(W14-G14) -> -1.463629 | AB14: =-T14*EXP((F14-C14)*E14)*(Barrier/T14)^(2*(H14+1))*NORMSDIST(X14)+Cap*EXP(-C14*E14)*(Barrier/T14)^(2*H14)*NORMSDIST(X14-G14) -> 81.406364 | AC14: =Cap*EXP(-C14*E14)-Y14+IF(T14<=Barrier,0,Y14-Z14+AA14-AB14) -> 1680.2219 | AD14: =(S14-AC14)/(2*dS*B14) -> 0.41485779 | AE14: =AD14*B14 -> 788.43723 | AF14: =I14-AE14 -> 899.79187 | AG14: =AE14/I14 -> 0.46702028
A15: =P2_TaskV_Valuation!A15 -> 45919 | B15: =P2_TaskV_Valuation!B15 -> 1908.92 | C15: =P2_TaskV_Valuation!N15 -> 0.019749218 | D15: =P2_TaskV_Valuation!C15 -> 0.351 | E15: =P2_TaskV_Valuation!D15 -> 1.7452055 | F15: =P2_TaskV_Valuation!O15 -> 0.013749218 | G15: =P2_TaskV_Valuation!P15 -> 0.46369285 | H15: =P2_TaskV_Valuation!Q15 -> -0.38840011 | I15: =P2_TaskV_Valuation!AB15 -> 1707.3541 | J15: =B15*(1+dS) -> 1928.0092 | K15: =LN(J15/Cap)/G15+(1+H15)*G15 -> 0.20453524 | L15: =LN(J15/Barrier)/G15+(1+H15)*G15 -> 1.5941556 | M15: =LN(Barrier^2/(J15*Cap))/G15+(1+H15)*G15 -> -2.4165869 | N15: =LN(Barrier/J15)/G15+(1+H15)*G15 -> -1.0269666 | O15: =-J15*EXP((F15-C15)*E15)*NORMSDIST(-K15)+Cap*EXP(-C15*E15)*NORMSDIST(-K15+G15) -> 364.32009 | P15: =-J15*EXP((F15-C15)*E15)*NORMSDIST(-L15)+Cap*EXP(-C15*E15)*NORMSDIST(-L15+G15) -> 143.73529 | Q15: =-J15*EXP((F15-C15)*E15)*(Barrier/J15)^(2*(H15+1))*NORMSDIST(M15)+Cap*EXP(-C15*E15)*(Barrier/J15)^(2*H15)*NORMSDIST(M15-G15) -> -0.95254987 | R15: =-J15*EXP((F15-C15)*E15)*(Barrier/J15)^(2*(H15+1))*NORMSDIST(N15)+Cap*EXP(-C15*E15)*(Barrier/J15)^(2*H15)*NORMSDIST(N15-G15) -> 72.637098 | S15: =Cap*EXP(-C15*E15)-O15+IF(J15<=Barrier,0,O15-P15+Q15-R15) -> 1714.9166 | T15: =B15*(1-dS) -> 1889.8308 | U15: =LN(T15/Cap)/G15+(1+H15)*G15 -> 0.1614018 | V15: =LN(T15/Barrier)/G15+(1+H15)*G15 -> 1.5510221 | W15: =LN(Barrier^2/(T15*Cap))/G15+(1+H15)*G15 -> -2.3734535 | X15: =LN(Barrier/T15)/G15+(1+H15)*G15 -> -0.98383315 | Y15: =-T15*EXP((F15-C15)*E15)*NORMSDIST(-U15)+Cap*EXP(-C15*E15)*NORMSDIST(-U15+G15) -> 380.46714 | Z15: =-T15*EXP((F15-C15)*E15)*NORMSDIST(-V15)+Cap*EXP(-C15*E15)*NORMSDIST(-V15+G15) -> 154.46355 | AA15: =-T15*EXP((F15-C15)*E15)*(Barrier/T15)^(2*(H15+1))*NORMSDIST(W15)+Cap*EXP(-C15*E15)*(Barrier/T15)^(2*H15)*NORMSDIST(W15-G15) -> -1.087928 | AB15: =-T15*EXP((F15-C15)*E15)*(Barrier/T15)^(2*(H15+1))*NORMSDIST(X15)+Cap*EXP(-C15*E15)*(Barrier/T15)^(2*H15)*NORMSDIST(X15-G15) -> 77.151851 | AC15: =Cap*EXP(-C15*E15)-Y15+IF(T15<=Barrier,0,Y15-Z15+AA15-AB15) -> 1699.5382 | AD15: =(S15-AC15)/(2*dS*B15) -> 0.40280344 | AE15: =AD15*B15 -> 768.91954 | AF15: =I15-AE15 -> 938.43461 | AG15: =AE15/I15 -> 0.45035738
... A186: =P2_TaskV_Valuation!A186 -> 46174 | B186: =P2_TaskV_Valuation!B186 -> 1207 | C186: =P2_TaskV_Valuation!N186 -> 0.024778054 | D186: =P2_TaskV_Valuation!C186 -> 0.542 | E186: =P2_TaskV_Valuation!D186 -> 1.0465753 | F186: =P2_TaskV_Valuation!O186 -> 0.018778054 | G186: =P2_TaskV_Valuation!P186 -> 0.55447828 | H186: =P2_TaskV_Valuation!Q186 -> -0.43607776 | I186: =P2_TaskV_Valuation!AB186 -> 1147.3552 | J186: =B186*(1+dS) -> 1219.07 | K186: =LN(J186/Cap)/G186+(1+H186)*G186 -> -0.5801547 | L186: =LN(J186/Barrier)/G186+(1+H186)*G186 -> 0.58194135 | M186: =LN(Barrier^2/(J186*Cap))/G186+(1+H186)*G186 -> -1.1186721 | N186: =LN(Barrier/J186)/G186+(1+H186)*G186 -> 0.043423917 | O186: =-J186*EXP((F186-C186)*E186)*NORMSDIST(-K186)+Cap*EXP(-C186*E186)*NORMSDIST(-K186+G186) -> 827.70072 | P186: =-J186*EXP((F186-C186)*E186)*NORMSDIST(-L186)+Cap*EXP(-C186*E186)*NORMSDIST(-L186+G186) -> 613.48243 | Q186: =-J186*EXP((F186-C186)*E186)*(Barrier/J186)^(2*(H186+1))*NORMSDIST(M186)+Cap*EXP(-C186*E186)*(Barrier/J186)^(2*H186)*NORMSDIST(M186-G186) -> -30.097959 | R186: =-J186*EXP((F186-C186)*E186)*(Barrier/J186)^(2*(H186+1))*NORMSDIST(N186)+Cap*EXP(-C186*E186)*(Barrier/J186)^(2*H186)*NORMSDIST(N186-G186) -> 146.70391 | S186: =Cap*EXP(-C186*E186)-O186+IF(J186<=Barrier,0,O186-P186+Q186-R186) -> 1158.5182 | T186: =B186*(1-dS) -> 1194.93 | U186: =LN(T186/Cap)/G186+(1+H186)*G186 -> -0.61622585 | V186: =LN(T186/Barrier)/G186+(1+H186)*G186 -> 0.5458702 | W186: =LN(Barrier^2/(T186*Cap))/G186+(1+H186)*G186 -> -1.082601 | X186: =LN(Barrier/T186)/G186+(1+H186)*G186 -> 0.079495063 | Y186: =-T186*EXP((F186-C186)*E186)*NORMSDIST(-U186)+Cap*EXP(-C186*E186)*NORMSDIST(-U186+G186) -> 845.09537 | Z186: =-T186*EXP((F186-C186)*E186)*NORMSDIST(-V186)+Cap*EXP(-C186*E186)*NORMSDIST(-V186+G186) -> 633.67235 | AA186: =-T186*EXP((F186-C186)*E186)*(Barrier/T186)^(2*(H186+1))*NORMSDIST(W186)+Cap*EXP(-C186*E186)*(Barrier/T186)^(2*H186)*NORMSDIST(W186-G186) -> -32.332372 | AB186: =-T186*EXP((F186-C186)*E186)*(Barrier/T186)^(2*(H186+1))*NORMSDIST(X186)+Cap*EXP(-C186*E186)*(Barrier/T186)^(2*H186)*NORMSDIST(X186-G186) -> 146.71103 | AC186: =Cap*EXP(-C186*E186)-Y186+IF(T186<=Barrier,0,Y186-Z186+AA186-AB186) -> 1136.0868 | AD186: =(S186-AC186)/(2*dS*B186) -> 0.92922325 | AE186: =AD186*B186 -> 1121.5725 | AF186: =I186-AE186 -> 25.782742 | AG186: =AE186/I186 -> 0.97752854

Sheet CRR_CrossCheck
A1: CRR binomial cross-check (N=25) — Bonus Cap on day 1
A2: Live 25-step CRR tree for the first valuation day. DO-put absorbs at the barrier; capped forward = min(S_T,Cap). Root sum compared to the closed-form and the Python N=200 tree. (Coarse N for legibility.)
A4: Parameters
A5: S0 | B5: =Data_Stock!B4 -> 1707.93
A6: sigma | B6: =Data_Stock!C4 -> 0.39
A7: T | B7: =MAX((MaturityDate-Data_Stock!A4)/365,1/365) -> 1.7863014
A8: r | B8: =P2_TaskVI_Greeks!B8 -> 0.019161407
A9: div q | B9: =q -> 0.006
A10: N | B10: 25
A11: dt | B11: =B7/B10 -> 0.071452055
A12: u | B12: =EXP(B6*SQRT(B11)) -> 1.1098768
A13: d | B13: =1/B12 -> 0.9010009
A14: p | B14: =(EXP((B8-B9)*B11)-B13)/(B12-B13) -> 0.47846568
A15: df | B15: =EXP(-B8*B11) -> 0.99863181
A17: Asset tree S(i,j)=S0*u^j*d^(i-j) [row=j node, col=i step] | B17: 0 | C17: 1 | D17: 2 | E17: 3 | F17: 4 | G17: 5 | H17: 6 | I17: 7 | J17: 8 | K17: 9 | L17: 10 | M17: 11 | N17: 12 | O17: 13 | P17: 14 | Q17: 15 | R17: 16 | S17: 17 | T17: 18 | U17: 19 | V17: 20 | W17: 21 | X17: 22 | Y17: 23 | Z17: 24 | AA17: 25
B18: =$B$5*($B$12^0)*($B$13^0) -> 1707.93 | C18: =$B$5*($B$12^0)*($B$13^1) -> 1538.8465 | D18: =$B$5*($B$12^0)*($B$13^2) -> 1386.5021 | E18: =$B$5*($B$12^0)*($B$13^3) -> 1249.2396 | F18: =$B$5*($B$12^0)*($B$13^4) -> 1125.566 | G18: =$B$5*($B$12^0)*($B$13^5) -> 1014.136 | H18: =$B$5*($B$12^0)*($B$13^6) -> 913.73746 | I18: =$B$5*($B$12^0)*($B$13^7) -> 823.27828 | J18: =$B$5*($B$12^0)*($B$13^8) -> 741.77447 | K18: =$B$5*($B$12^0)*($B$13^9) -> 668.33947 | L18: =$B$5*($B$12^0)*($B$13^10) -> 602.17447 | M18: =$B$5*($B$12^0)*($B$13^11) -> 542.55974 | N18: =$B$5*($B$12^0)*($B$13^12) -> 488.84682 | O18: =$B$5*($B$12^0)*($B$13^13) -> 440.45143 | P18: =$B$5*($B$12^0)*($B$13^14) -> 396.84713 | Q18: =$B$5*($B$12^0)*($B$13^15) -> 357.55963 | R18: =$B$5*($B$12^0)*($B$13^16) -> 322.16155 | S18: =$B$5*($B$12^0)*($B$13^17) -> 290.26785 | T18: =$B$5*($B$12^0)*($B$13^18) -> 261.53159 | U18: =$B$5*($B$12^0)*($B$13^19) -> 235.6402 | V18: =$B$5*($B$12^0)*($B$13^20) -> 212.31203 | W18: =$B$5*($B$12^0)*($B$13^21) -> 191.29333 | X18: =$B$5*($B$12^0)*($B$13^22) -> 172.35547 | Y18: =$B$5*($B$12^0)*($B$13^23) -> 155.29243 | Z18: =$B$5*($B$12^0)*($B$13^24) -> 139.91862 | AA18: =$B$5*($B$12^0)*($B$13^25) -> 126.06681
C19: =$B$5*($B$12^1)*($B$13^0) -> 1895.5919 | D19: =$B$5*($B$12^1)*($B$13^1) -> 1707.93 | E19: =$B$5*($B$12^1)*($B$13^2) -> 1538.8465 | F19: =$B$5*($B$12^1)*($B$13^3) -> 1386.5021 | G19: =$B$5*($B$12^1)*($B$13^4) -> 1249.2396 | H19: =$B$5*($B$12^1)*($B$13^5) -> 1125.566 | I19: =$B$5*($B$12^1)*($B$13^6) -> 1014.136 | J19: =$B$5*($B$12^1)*($B$13^7) -> 913.73746 | K19: =$B$5*($B$12^1)*($B$13^8) -> 823.27828 | L19: =$B$5*($B$12^1)*($B$13^9) -> 741.77447 | M19: =$B$5*($B$12^1)*($B$13^10) -> 668.33947 | N19: =$B$5*($B$12^1)*($B$13^11) -> 602.17447 | O19: =$B$5*($B$12^1)*($B$13^12) -> 542.55974 | P19: =$B$5*($B$12^1)*($B$13^13) -> 488.84682 | Q19: =$B$5*($B$12^1)*($B$13^14) -> 440.45143 | R19: =$B$5*($B$12^1)*($B$13^15) -> 396.84713 | S19: =$B$5*($B$12^1)*($B$13^16) -> 357.55963 | T19: =$B$5*($B$12^1)*($B$13^17) -> 322.16155 | U19: =$B$5*($B$12^1)*($B$13^18) -> 290.26785 | V19: =$B$5*($B$12^1)*($B$13^19) -> 261.53159 | W19: =$B$5*($B$12^1)*($B$13^20) -> 235.6402 | X19: =$B$5*($B$12^1)*($B$13^21) -> 212.31203 | Y19: =$B$5*($B$12^1)*($B$13^22) -> 191.29333 | Z19: =$B$5*($B$12^1)*($B$13^23) -> 172.35547 | AA19: =$B$5*($B$12^1)*($B$13^24) -> 155.29243
D20: =$B$5*($B$12^2)*($B$13^0) -> 2103.8734 | E20: =$B$5*($B$12^2)*($B$13^1) -> 1895.5919 | F20: =$B$5*($B$12^2)*($B$13^2) -> 1707.93 | G20: =$B$5*($B$12^2)*($B$13^3) -> 1538.8465 | H20: =$B$5*($B$12^2)*($B$13^4) -> 1386.5021 | I20: =$B$5*($B$12^2)*($B$13^5) -> 1249.2396 | J20: =$B$5*($B$12^2)*($B$13^6) -> 1125.566 | K20: =$B$5*($B$12^2)*($B$13^7) -> 1014.136 | L20: =$B$5*($B$12^2)*($B$13^8) -> 913.73746 | M20: =$B$5*($B$12^2)*($B$13^9) -> 823.27828 | N20: =$B$5*($B$12^2)*($B$13^10) -> 741.77447 | O20: =$B$5*($B$12^2)*($B$13^11) -> 668.33947 | P20: =$B$5*($B$12^2)*($B$13^12) -> 602.17447 | Q20: =$B$5*($B$12^2)*($B$13^13) -> 542.55974 | R20: =$B$5*($B$12^2)*($B$13^14) -> 488.84682 | S20: =$B$5*($B$12^2)*($B$13^15) -> 440.45143 | T20: =$B$5*($B$12^2)*($B$13^16) -> 396.84713 | U20: =$B$5*($B$12^2)*($B$13^17) -> 357.55963 | V20: =$B$5*($B$12^2)*($B$13^18) -> 322.16155 | W20: =$B$5*($B$12^2)*($B$13^19) -> 290.26785 | X20: =$B$5*($B$12^2)*($B$13^20) -> 261.53159 | Y20: =$B$5*($B$12^2)*($B$13^21) -> 235.6402 | Z20: =$B$5*($B$12^2)*($B$13^22) -> 212.31203 | AA20: =$B$5*($B$12^2)*($B$13^23) -> 191.29333
E21: =$B$5*($B$12^3)*($B$13^0) -> 2335.0403 | F21: =$B$5*($B$12^3)*($B$13^1) -> 2103.8734 | G21: =$B$5*($B$12^3)*($B$13^2) -> 1895.5919 | H21: =$B$5*($B$12^3)*($B$13^3) -> 1707.93 | I21: =$B$5*($B$12^3)*($B$13^4) -> 1538.8465 | J21: =$B$5*($B$12^3)*($B$13^5) -> 1386.5021 | K21: =$B$5*($B$12^3)*($B$13^6) -> 1249.2396 | L21: =$B$5*($B$12^3)*($B$13^7) -> 1125.566 | M21: =$B$5*($B$12^3)*($B$13^8) -> 1014.136 | N21: =$B$5*($B$12^3)*($B$13^9) -> 913.73746 | O21: =$B$5*($B$12^3)*($B$13^10) -> 823.27828 | P21: =$B$5*($B$12^3)*($B$13^11) -> 741.77447 | Q21: =$B$5*($B$12^3)*($B$13^12) -> 668.33947 | R21: =$B$5*($B$12^3)*($B$13^13) -> 602.17447 | S21: =$B$5*($B$12^3)*($B$13^14) -> 542.55974 | T21: =$B$5*($B$12^3)*($B$13^15) -> 488.84682 | U21: =$B$5*($B$12^3)*($B$13^16) -> 440.45143 | V21: =$B$5*($B$12^3)*($B$13^17) -> 396.84713 | W21: =$B$5*($B$12^3)*($B$13^18) -> 357.55963 | X21: =$B$5*($B$12^3)*($B$13^19) -> 322.16155 | Y21: =$B$5*($B$12^3)*($B$13^20) -> 290.26785 | Z21: =$B$5*($B$12^3)*($B$13^21) -> 261.53159 | AA21: =$B$5*($B$12^3)*($B$13^22) -> 235.6402
F22: =$B$5*($B$12^4)*($B$13^0) -> 2591.6071 | G22: =$B$5*($B$12^4)*($B$13^1) -> 2335.0403 | H22: =$B$5*($B$12^4)*($B$13^2) -> 2103.8734 | I22: =$B$5*($B$12^4)*($B$13^3) -> 1895.5919 | J22: =$B$5*($B$12^4)*($B$13^4) -> 1707.93 | K22: =$B$5*($B$12^4)*($B$13^5) -> 1538.8465 | L22: =$B$5*($B$12^4)*($B$13^6) -> 1386.5021 | M22: =$B$5*($B$12^4)*($B$13^7) -> 1249.2396 | N22: =$B$5*($B$12^4)*($B$13^8) -> 1125.566 | O22: =$B$5*($B$12^4)*($B$13^9) -> 1014.136 | P22: =$B$5*($B$12^4)*($B$13^10) -> 913.73746 | Q22: =$B$5*($B$12^4)*($B$13^11) -> 823.27828 | R22: =$B$5*($B$12^4)*($B$13^12) -> 741.77447 | S22: =$B$5*($B$12^4)*($B$13^13) -> 668.33947 | T22: =$B$5*($B$12^4)*($B$13^14) -> 602.17447 | U22: =$B$5*($B$12^4)*($B$13^15) -> 542.55974 | V22: =$B$5*($B$12^4)*($B$13^16) -> 488.84682 | W22: =$B$5*($B$12^4)*($B$13^17) -> 440.45143 | X22: =$B$5*($B$12^4)*($B$13^18) -> 396.84713 | Y22: =$B$5*($B$12^4)*($B$13^19) -> 357.55963 | Z22: =$B$5*($B$12^4)*($B$13^20) -> 322.16155 | AA22: =$B$5*($B$12^4)*($B$13^21) -> 290.26785
G23: =$B$5*($B$12^5)*($B$13^0) -> 2876.3646 | H23: =$B$5*($B$12^5)*($B$13^1) -> 2591.6071 | I23: =$B$5*($B$12^5)*($B$13^2) -> 2335.0403 | J23: =$B$5*($B$12^5)*($B$13^3) -> 2103.8734 | K23: =$B$5*($B$12^5)*($B$13^4) -> 1895.5919 | L23: =$B$5*($B$12^5)*($B$13^5) -> 1707.93 | M23: =$B$5*($B$12^5)*($B$13^6) -> 1538.8465 | N23: =$B$5*($B$12^5)*($B$13^7) -> 1386.5021 | O23: =$B$5*($B$12^5)*($B$13^8) -> 1249.2396 | P23: =$B$5*($B$12^5)*($B$13^9) -> 1125.566 | Q23: =$B$5*($B$12^5)*($B$13^10) -> 1014.136 | R23: =$B$5*($B$12^5)*($B$13^11) -> 913.73746 | S23: =$B$5*($B$12^5)*($B$13^12) -> 823.27828 | T23: =$B$5*($B$12^5)*($B$13^13) -> 741.77447 | U23: =$B$5*($B$12^5)*($B$13^14) -> 668.33947 | V23: =$B$5*($B$12^5)*($B$13^15) -> 602.17447 | W23: =$B$5*($B$12^5)*($B$13^16) -> 542.55974 | X23: =$B$5*($B$12^5)*($B$13^17) -> 488.84682 | Y23: =$B$5*($B$12^5)*($B$13^18) -> 440.45143 | Z23: =$B$5*($B$12^5)*($B$13^19) -> 396.84713 | AA23: =$B$5*($B$12^5)*($B$13^20) -> 357.55963
H24: =$B$5*($B$12^6)*($B$13^0) -> 3192.4103 | I24: =$B$5*($B$12^6)*($B$13^1) -> 2876.3646 | J24: =$B$5*($B$12^6)*($B$13^2) -> 2591.6071 | K24: =$B$5*($B$12^6)*($B$13^3) -> 2335.0403 | L24: =$B$5*($B$12^6)*($B$13^4) -> 2103.8734 | M24: =$B$5*($B$12^6)*($B$13^5) -> 1895.5919 | N24: =$B$5*($B$12^6)*($B$13^6) -> 1707.93 | O24: =$B$5*($B$12^6)*($B$13^7) -> 1538.8465 | P24: =$B$5*($B$12^6)*($B$13^8) -> 1386.5021 | Q24: =$B$5*($B$12^6)*($B$13^9) -> 1249.2396 | R24: =$B$5*($B$12^6)*($B$13^10) -> 1125.566 | S24: =$B$5*($B$12^6)*($B$13^11) -> 1014.136 | T24: =$B$5*($B$12^6)*($B$13^12) -> 913.73746 | U24: =$B$5*($B$12^6)*($B$13^13) -> 823.27828 | V24: =$B$5*($B$12^6)*($B$13^14) -> 741.77447 | W24: =$B$5*($B$12^6)*($B$13^15) -> 668.33947 | X24: =$B$5*($B$12^6)*($B$13^16) -> 602.17447 | Y24: =$B$5*($B$12^6)*($B$13^17) -> 542.55974 | Z24: =$B$5*($B$12^6)*($B$13^18) -> 488.84682 | AA24: =$B$5*($B$12^6)*($B$13^19) -> 440.45143
I25: =$B$5*($B$12^7)*($B$13^0) -> 3543.1821 | J25: =$B$5*($B$12^7)*($B$13^1) -> 3192.4103 | K25: =$B$5*($B$12^7)*($B$13^2) -> 2876.3646 | L25: =$B$5*($B$12^7)*($B$13^3) -> 2591.6071 | M25: =$B$5*($B$12^7)*($B$13^4) -> 2335.0403 | N25: =$B$5*($B$12^7)*($B$13^5) -> 2103.8734 | O25: =$B$5*($B$12^7)*($B$13^6) -> 1895.5919 | P25: =$B$5*($B$12^7)*($B$13^7) -> 1707.93 | Q25: =$B$5*($B$12^7)*($B$13^8) -> 1538.8465 | R25: =$B$5*($B$12^7)*($B$13^9) -> 1386.5021 | S25: =$B$5*($B$12^7)*($B$13^10) -> 1249.2396 | T25: =$B$5*($B$12^7)*($B$13^11) -> 1125.566 | U25: =$B$5*($B$12^7)*($B$13^12) -> 1014.136 | V25: =$B$5*($B$12^7)*($B$13^13) -> 913.73746 | W25: =$B$5*($B$12^7)*($B$13^14) -> 823.27828 | X25: =$B$5*($B$12^7)*($B$13^15) -> 741.77447 | Y25: =$B$5*($B$12^7)*($B$13^16) -> 668.33947 | Z25: =$B$5*($B$12^7)*($B$13^17) -> 602.17447 | AA25: =$B$5*($B$12^7)*($B$13^18) -> 542.55974
J26: =$B$5*($B$12^8)*($B$13^0) -> 3932.4956 | K26: =$B$5*($B$12^8)*($B$13^1) -> 3543.1821 | L26: =$B$5*($B$12^8)*($B$13^2) -> 3192.4103 | M26: =$B$5*($B$12^8)*($B$13^3) -> 2876.3646 | N26: =$B$5*($B$12^8)*($B$13^4) -> 2591.6071 | O26: =$B$5*($B$12^8)*($B$13^5) -> 2335.0403 | P26: =$B$5*($B$12^8)*($B$13^6) -> 2103.8734 | Q26: =$B$5*($B$12^8)*($B$13^7) -> 1895.5919 | R26: =$B$5*($B$12^8)*($B$13^8) -> 1707.93 | S26: =$B$5*($B$12^8)*($B$13^9) -> 1538.8465 | T26: =$B$5*($B$12^8)*($B$13^10) -> 1386.5021 | U26: =$B$5*($B$12^8)*($B$13^11) -> 1249.2396 | V26: =$B$5*($B$12^8)*($B$13^12) -> 1125.566 | W26: =$B$5*($B$12^8)*($B$13^13) -> 1014.136 | X26: =$B$5*($B$12^8)*($B$13^14) -> 913.73746 | Y26: =$B$5*($B$12^8)*($B$13^15) -> 823.27828 | Z26: =$B$5*($B$12^8)*($B$13^16) -> 741.77447 | AA26: =$B$5*($B$12^8)*($B$13^17) -> 668.33947
K27: =$B$5*($B$12^9)*($B$13^0) -> 4364.5857 | L27: =$B$5*($B$12^9)*($B$13^1) -> 3932.4956 | M27: =$B$5*($B$12^9)*($B$13^2) -> 3543.1821 | N27: =$B$5*($B$12^9)*($B$13^3) -> 3192.4103 | O27: =$B$5*($B$12^9)*($B$13^4) -> 2876.3646 | P27: =$B$5*($B$12^9)*($B$13^5) -> 2591.6071 | Q27: =$B$5*($B$12^9)*($B$13^6) -> 2335.0403 | R27: =$B$5*($B$12^9)*($B$13^7) -> 2103.8734 | S27: =$B$5*($B$12^9)*($B$13^8) -> 1895.5919 | T27: =$B$5*($B$12^9)*($B$13^9) -> 1707.93 | U27: =$B$5*($B$12^9)*($B$13^10) -> 1538.8465 | V27: =$B$5*($B$12^9)*($B$13^11) -> 1386.5021 | W27: =$B$5*($B$12^9)*($B$13^12) -> 1249.2396 | X27: =$B$5*($B$12^9)*($B$13^13) -> 1125.566 | Y27: =$B$5*($B$12^9)*($B$13^14) -> 1014.136 | Z27: =$B$5*($B$12^9)*($B$13^15) -> 913.73746 | AA27: =$B$5*($B$12^9)*($B$13^16) -> 823.27828
L28: =$B$5*($B$12^10)*($B$13^0) -> 4844.1524 | M28: =$B$5*($B$12^10)*($B$13^1) -> 4364.5857 | N28: =$B$5*($B$12^10)*($B$13^2) -> 3932.4956 | O28: =$B$5*($B$12^10)*($B$13^3) -> 3543.1821 | P28: =$B$5*($B$12^10)*($B$13^4) -> 3192.4103 | Q28: =$B$5*($B$12^10)*($B$13^5) -> 2876.3646 | R28: =$B$5*($B$12^10)*($B$13^6) -> 2591.6071 | S28: =$B$5*($B$12^10)*($B$13^7) -> 2335.0403 | T28: =$B$5*($B$12^10)*($B$13^8) -> 2103.8734 | U28: =$B$5*($B$12^10)*($B$13^9) -> 1895.5919 | V28: =$B$5*($B$12^10)*($B$13^10) -> 1707.93 | W28: =$B$5*($B$12^10)*($B$13^11) -> 1538.8465 | X28: =$B$5*($B$12^10)*($B$13^12) -> 1386.5021 | Y28: =$B$5*($B$12^10)*($B$13^13) -> 1249.2396 | Z28: =$B$5*($B$12^10)*($B$13^14) -> 1125.566 | AA28: =$B$5*($B$12^10)*($B$13^15) -> 1014.136
M29: =$B$5*($B$12^11)*($B$13^0) -> 5376.4123 | N29: =$B$5*($B$12^11)*($B$13^1) -> 4844.1524 | O29: =$B$5*($B$12^11)*($B$13^2) -> 4364.5857 | P29: =$B$5*($B$12^11)*($B$13^3) -> 3932.4956 | Q29: =$B$5*($B$12^11)*($B$13^4) -> 3543.1821 | R29: =$B$5*($B$12^11)*($B$13^5) -> 3192.4103 | S29: =$B$5*($B$12^11)*($B$13^6) -> 2876.3646 | T29: =$B$5*($B$12^11)*($B$13^7) -> 2591.6071 | U29: =$B$5*($B$12^11)*($B$13^8) -> 2335.0403 | V29: =$B$5*($B$12^11)*($B$13^9) -> 2103.8734 | W29: =$B$5*($B$12^11)*($B$13^10) -> 1895.5919 | X29: =$B$5*($B$12^11)*($B$13^11) -> 1707.93 | Y29: =$B$5*($B$12^11)*($B$13^12) -> 1538.8465 | Z29: =$B$5*($B$12^11)*($B$13^13) -> 1386.5021 | AA29: =$B$5*($B$12^11)*($B$13^14) -> 1249.2396
N30: =$B$5*($B$12^12)*($B$13^0) -> 5967.1553 | O30: =$B$5*($B$12^12)*($B$13^1) -> 5376.4123 | P30: =$B$5*($B$12^12)*($B$13^2) -> 4844.1524 | Q30: =$B$5*($B$12^12)*($B$13^3) -> 4364.5857 | R30: =$B$5*($B$12^12)*($B$13^4) -> 3932.4956 | S30: =$B$5*($B$12^12)*($B$13^5) -> 3543.1821 | T30: =$B$5*($B$12^12)*($B$13^6) -> 3192.4103 | U30: =$B$5*($B$12^12)*($B$13^7) -> 2876.3646 | V30: =$B$5*($B$12^12)*($B$13^8) -> 2591.6071 | W30: =$B$5*($B$12^12)*($B$13^9) -> 2335.0403 | X30: =$B$5*($B$12^12)*($B$13^10) -> 2103.8734 | Y30: =$B$5*($B$12^12)*($B$13^11) -> 1895.5919 | Z30: =$B$5*($B$12^12)*($B$13^12) -> 1707.93 | AA30: =$B$5*($B$12^12)*($B$13^13) -> 1538.8465
O31: =$B$5*($B$12^13)*($B$13^0) -> 6622.8072 | P31: =$B$5*($B$12^13)*($B$13^1) -> 5967.1553 | Q31: =$B$5*($B$12^13)*($B$13^2) -> 5376.4123 | R31: =$B$5*($B$12^13)*($B$13^3) -> 4844.1524 | S31: =$B$5*($B$12^13)*($B$13^4) -> 4364.5857 | T31: =$B$5*($B$12^13)*($B$13^5) -> 3932.4956 | U31: =$B$5*($B$12^13)*($B$13^6) -> 3543.1821 | V31: =$B$5*($B$12^13)*($B$13^7) -> 3192.4103 | W31: =$B$5*($B$12^13)*($B$13^8) -> 2876.3646 | X31: =$B$5*($B$12^13)*($B$13^9) -> 2591.6071 | Y31: =$B$5*($B$12^13)*($B$13^10) -> 2335.0403 | Z31: =$B$5*($B$12^13)*($B$13^11) -> 2103.8734 | AA31: =$B$5*($B$12^13)*($B$13^12) -> 1895.5919
P32: =$B$5*($B$12^14)*($B$13^0) -> 7350.5001 | Q32: =$B$5*($B$12^14)*($B$13^1) -> 6622.8072 | R32: =$B$5*($B$12^14)*($B$13^2) -> 5967.1553 | S32: =$B$5*($B$12^14)*($B$13^3) -> 5376.4123 | T32: =$B$5*($B$12^14)*($B$13^4) -> 4844.1524 | U32: =$B$5*($B$12^14)*($B$13^5) -> 4364.5857 | V32: =$B$5*($B$12^14)*($B$13^6) -> 3932.4956 | W32: =$B$5*($B$12^14)*($B$13^7) -> 3543.1821 | X32: =$B$5*($B$12^14)*($B$13^8) -> 3192.4103 | Y32: =$B$5*($B$12^14)*($B$13^9) -> 2876.3646 | Z32: =$B$5*($B$12^14)*($B$13^10) -> 2591.6071 | AA32: =$B$5*($B$12^14)*($B$13^11) -> 2335.0403
Q33: =$B$5*($B$12^15)*($B$13^0) -> 8158.1495 | R33: =$B$5*($B$12^15)*($B$13^1) -> 7350.5001 | S33: =$B$5*($B$12^15)*($B$13^2) -> 6622.8072 | T33: =$B$5*($B$12^15)*($B$13^3) -> 5967.1553 | U33: =$B$5*($B$12^15)*($B$13^4) -> 5376.4123 | V33: =$B$5*($B$12^15)*($B$13^5) -> 4844.1524 | W33: =$B$5*($B$12^15)*($B$13^6) -> 4364.5857 | X33: =$B$5*($B$12^15)*($B$13^7) -> 3932.4956 | Y33: =$B$5*($B$12^15)*($B$13^8) -> 3543.1821 | Z33: =$B$5*($B$12^15)*($B$13^9) -> 3192.4103 | AA33: =$B$5*($B$12^15)*($B$13^10) -> 2876.3646
R34: =$B$5*($B$12^16)*($B$13^0) -> 9054.5408 | S34: =$B$5*($B$12^16)*($B$13^1) -> 8158.1495 | T34: =$B$5*($B$12^16)*($B$13^2) -> 7350.5001 | U34: =$B$5*($B$12^16)*($B$13^3) -> 6622.8072 | V34: =$B$5*($B$12^16)*($B$13^4) -> 5967.1553 | W34: =$B$5*($B$12^16)*($B$13^5) -> 5376.4123 | X34: =$B$5*($B$12^16)*($B$13^6) -> 4844.1524 | Y34: =$B$5*($B$12^16)*($B$13^7) -> 4364.5857 | Z34: =$B$5*($B$12^16)*($B$13^8) -> 3932.4956 | AA34: =$B$5*($B$12^16)*($B$13^9) -> 3543.1821
S35: =$B$5*($B$12^17)*($B$13^0) -> 10049.425 | T35: =$B$5*($B$12^17)*($B$13^1) -> 9054.5408 | U35: =$B$5*($B$12^17)*($B$13^2) -> 8158.1495 | V35: =$B$5*($B$12^17)*($B$13^3) -> 7350.5001 | W35: =$B$5*($B$12^17)*($B$13^4) -> 6622.8072 | X35: =$B$5*($B$12^17)*($B$13^5) -> 5967.1553 | Y35: =$B$5*($B$12^17)*($B$13^6) -> 5376.4123 | Z35: =$B$5*($B$12^17)*($B$13^7) -> 4844.1524 | AA35: =$B$5*($B$12^17)*($B$13^8) -> 4364.5857
T36: =$B$5*($B$12^18)*($B$13^0) -> 11153.623 | U36: =$B$5*($B$12^18)*($B$13^1) -> 10049.425 | V36: =$B$5*($B$12^18)*($B$13^2) -> 9054.5408 | W36: =$B$5*($B$12^18)*($B$13^3) -> 8158.1495 | X36: =$B$5*($B$12^18)*($B$13^4) -> 7350.5001 | Y36: =$B$5*($B$12^18)*($B$13^5) -> 6622.8072 | Z36: =$B$5*($B$12^18)*($B$13^6) -> 5967.1553 | AA36: =$B$5*($B$12^18)*($B$13^7) -> 5376.4123
U37: =$B$5*($B$12^19)*($B$13^0) -> 12379.148 | V37: =$B$5*($B$12^19)*($B$13^1) -> 11153.623 | W37: =$B$5*($B$12^19)*($B$13^2) -> 10049.425 | X37: =$B$5*($B$12^19)*($B$13^3) -> 9054.5408 | Y37: =$B$5*($B$12^19)*($B$13^4) -> 8158.1495 | Z37: =$B$5*($B$12^19)*($B$13^5) -> 7350.5001 | AA37: =$B$5*($B$12^19)*($B$13^6) -> 6622.8072
V38: =$B$5*($B$12^20)*($B$13^0) -> 13739.329 | W38: =$B$5*($B$12^20)*($B$13^1) -> 12379.148 | X38: =$B$5*($B$12^20)*($B$13^2) -> 11153.623 | Y38: =$B$5*($B$12^20)*($B$13^3) -> 10049.425 | Z38: =$B$5*($B$12^20)*($B$13^4) -> 9054.5408 | AA38: =$B$5*($B$12^20)*($B$13^5) -> 8158.1495
W39: =$B$5*($B$12^21)*($B$13^0) -> 15248.962 | X39: =$B$5*($B$12^21)*($B$13^1) -> 13739.329 | Y39: =$B$5*($B$12^21)*($B$13^2) -> 12379.148 | Z39: =$B$5*($B$12^21)*($B$13^3) -> 11153.623 | AA39: =$B$5*($B$12^21)*($B$13^4) -> 10049.425
X40: =$B$5*($B$12^22)*($B$13^0) -> 16924.47 | Y40: =$B$5*($B$12^22)*($B$13^1) -> 15248.962 | Z40: =$B$5*($B$12^22)*($B$13^2) -> 13739.329 | AA40: =$B$5*($B$12^22)*($B$13^3) -> 12379.148
Y41: =$B$5*($B$12^23)*($B$13^0) -> 18784.076 | Z41: =$B$5*($B$12^23)*($B$13^1) -> 16924.47 | AA41: =$B$5*($B$12^23)*($B$13^2) -> 15248.962
Z42: =$B$5*($B$12^24)*($B$13^0) -> 20848.01 | AA42: =$B$5*($B$12^24)*($B$13^1) -> 18784.076
AA43: =$B$5*($B$12^25)*($B$13^0) -> 23138.723
A45: Down-and-out put value tree (absorb at barrier)
B46: =IF(B18<=Barrier,0,$B$15*($B$14*C47+(1-$B$14)*C46)) -> 127.12606 | C46: =IF(C18<=Barrier,0,$B$15*($B$14*D47+(1-$B$14)*D46)) -> 117.69458 | D46: =IF(D18<=Barrier,0,$B$15*($B$14*E47+(1-$B$14)*E46)) -> 99.772939 | E46: =IF(E18<=Barrier,0,$B$15*($B$14*F47+(1-$B$14)*F46)) -> 73.255206 | F46: =IF(F18<=Barrier,0,$B$15*($B$14*G47+(1-$B$14)*G46)) -> 39.195387 | G46: =IF(G18<=Barrier,0,$B$15*($B$14*H47+(1-$B$14)*H46)) -> 0 | H46: =IF(H18<=Barrier,0,$B$15*($B$14*I47+(1-$B$14)*I46)) -> 0 | I46: =IF(I18<=Barrier,0,$B$15*($B$14*J47+(1-$B$14)*J46)) -> 0 | ... Z46: =IF(Z18<=Barrier,0,$B$15*($B$14*AA47+(1-$B$14)*AA46)) -> 0 | AA46: =IF(AA18<=Barrier,0,MAX(Cap-AA18,0)) -> 0
C47: =IF(C19<=Barrier,0,$B$15*($B$14*D48+(1-$B$14)*D47)) -> 137.77052 | D47: =IF(D19<=Barrier,0,$B$15*($B$14*E48+(1-$B$14)*E47)) -> 137.56644 | E47: =IF(E19<=Barrier,0,$B$15*($B$14*F48+(1-$B$14)*F47)) -> 128.96333 | F47: =IF(F19<=Barrier,0,$B$15*($B$14*G48+(1-$B$14)*G47)) -> 110.59065 | G47: =IF(G19<=Barrier,0,$B$15*($B$14*H48+(1-$B$14)*H47)) -> 82.031144 | H47: =IF(H19<=Barrier,0,$B$15*($B$14*I48+(1-$B$14)*I47)) -> 44.267766 | I47: =IF(I19<=Barrier,0,$B$15*($B$14*J48+(1-$B$14)*J47)) -> 0 | J47: =IF(J19<=Barrier,0,$B$15*($B$14*K48+(1-$B$14)*K47)) -> 0 | ... Z47: =IF(Z19<=Barrier,0,$B$15*($B$14*AA48+(1-$B$14)*AA47)) -> 0 | AA47: =IF(AA19<=Barrier,0,MAX(Cap-AA19,0)) -> 0
D48: =IF(D20<=Barrier,0,$B$15*($B$14*E49+(1-$B$14)*E48)) -> 138.38746 | E48: =IF(E20<=Barrier,0,$B$15*($B$14*F49+(1-$B$14)*F48)) -> 147.33785 | F48: =IF(F20<=Barrier,0,$B$15*($B$14*G49+(1-$B$14)*G48)) -> 149.3591 | G48: =IF(G20<=Barrier,0,$B$15*($B$14*H49+(1-$B$14)*H48)) -> 142.03758 | H48: =IF(H20<=Barrier,0,$B$15*($B$14*I49+(1-$B$14)*I48)) -> 123.42865 | I48: =IF(I20<=Barrier,0,$B$15*($B$14*J49+(1-$B$14)*J48)) -> 92.647011 | J48: =IF(J20<=Barrier,0,$B$15*($B$14*K49+(1-$B$14)*K48)) -> 50.500442 | K48: =IF(K20<=Barrier,0,$B$15*($B$14*L49+(1-$B$14)*L48)) -> 0 | ... Z48: =IF(Z20<=Barrier,0,$B$15*($B$14*AA49+(1-$B$14)*AA48)) -> 0 | AA48: =IF(AA20<=Barrier,0,MAX(Cap-AA20,0)) -> 0
E49: =IF(E21<=Barrier,0,$B$15*($B$14*F50+(1-$B$14)*F49)) -> 129.02768 | F49: =IF(F21<=Barrier,0,$B$15*($B$14*G50+(1-$B$14)*G49)) -> 145.55656 | G49: =IF(G21<=Barrier,0,$B$15*($B$14*H50+(1-$B$14)*H49)) -> 157.76733 | H49: =IF(H21<=Barrier,0,$B$15*($B$14*I50+(1-$B$14)*I49)) -> 162.7283 | I49: =IF(I21<=Barrier,0,$B$15*($B$14*J50+(1-$B$14)*J49)) -> 157.3345 | J49: =IF(J21<=Barrier,0,$B$15*($B$14*K50+(1-$B$14)*K49)) -> 138.85265 | K49: =IF(K21<=Barrier,0,$B$15*($B$14*L50+(1-$B$14)*L49)) -> 105.69124 | L49: =IF(L21<=Barrier,0,$B$15*($B$14*M50+(1-$B$14)*M49)) -> 58.302335 | ... Z49: =IF(Z21<=Barrier,0,$B$15*($B$14*AA50+(1-$B$14)*AA49)) -> 0 | AA49: =IF(AA21<=Barrier,0,MAX(Cap-AA21,0)) -> 0
F50: =IF(F22<=Barrier,0,$B$15*($B$14*G51+(1-$B$14)*G50)) -> 111.38044 | G50: =IF(G22<=Barrier,0,$B$15*($B$14*H51+(1-$B$14)*H50)) -> 132.66343 | H50: =IF(H22<=Barrier,0,$B$15*($B$14*I51+(1-$B$14)*I50)) -> 152.81157 | I50: =IF(I22<=Barrier,0,$B$15*($B$14*J51+(1-$B$14)*J50)) -> 169.07359 | J50: =IF(J22<=Barrier,0,$B$15*($B$14*K51+(1-$B$14)*K50)) -> 177.93048 | K50: =IF(K22<=Barrier,0,$B$15*($B$14*L51+(1-$B$14)*L50)) -> 175.39666 | L50: =IF(L22<=Barrier,0,$B$15*($B$14*M51+(1-$B$14)*M50)) -> 157.64845 | M50: =IF(M22<=Barrier,0,$B$15*($B$14*N51+(1-$B$14)*N50)) -> 122.01964 | ... Z50: =IF(Z22<=Barrier,0,$B$15*($B$14*AA51+(1-$B$14)*AA50)) -> 0 | AA50: =IF(AA22<=Barrier,0,MAX(Cap-AA22,0)) -> 0
G51: =IF(G23<=Barrier,0,$B$15*($B$14*H52+(1-$B$14)*H51)) -> 88.500607 | H51: =IF(H23<=Barrier,0,$B$15*($B$14*I52+(1-$B$14)*I51)) -> 111.08155 | I51: =IF(I23<=Barrier,0,$B$15*($B$14*J52+(1-$B$14)*J51)) -> 135.5233 | J51: =IF(J23<=Barrier,0,$B$15*($B$14*K52+(1-$B$14)*K51)) -> 159.90358 | K51: =IF(K23<=Barrier,0,$B$15*($B$14*L52+(1-$B$14)*L51)) -> 181.20188 | L51: =IF(L23<=Barrier,0,$B$15*($B$14*M52+(1-$B$14)*M51)) -> 195.24469 | M51: =IF(M23<=Barrier,0,$B$15*($B$14*N52+(1-$B$14)*N51)) -> 196.93577 | N51: =IF(N23<=Barrier,0,$B$15*($B$14*O52+(1-$B$14)*O51)) -> 180.9355 | ... Z51: =IF(Z23<=Barrier,0,$B$15*($B$14*AA52+(1-$B$14)*AA51)) -> 0 | AA51: =IF(AA23<=Barrier,0,MAX(Cap-AA23,0)) -> 0
H52: =IF(H24<=Barrier,0,$B$15*($B$14*I53+(1-$B$14)*I52)) -> 64.140476 | I52: =IF(I24<=Barrier,0,$B$15*($B$14*J53+(1-$B$14)*J52)) -> 84.757775 | J52: =IF(J24<=Barrier,0,$B$15*($B$14*K53+(1-$B$14)*K52)) -> 109.33652 | K52: =IF(K24<=Barrier,0,$B$15*($B$14*L53+(1-$B$14)*L52)) -> 137.14601 | L52: =IF(L24<=Barrier,0,$B$15*($B$14*M53+(1-$B$14)*M52)) -> 166.41388 | M52: =IF(M24<=Barrier,0,$B$15*($B$14*N53+(1-$B$14)*N52)) -> 193.96045 | N52: =IF(N24<=Barrier,0,$B$15*($B$14*O53+(1-$B$14)*O52)) -> 214.94021 | O52: =IF(O24<=Barrier,0,$B$15*($B$14*P53+(1-$B$14)*P52)) -> 222.889 | ... Z52: =IF(Z24<=Barrier,0,$B$15*($B$14*AA53+(1-$B$14)*AA52)) -> 0 | AA52: =IF(AA24<=Barrier,0,MAX(Cap-AA24,0)) -> 0
I53: =IF(I25<=Barrier,0,$B$15*($B$14*J54+(1-$B$14)*J53)) -> 41.850992 | J53: =IF(J25<=Barrier,0,$B$15*($B$14*K54+(1-$B$14)*K53)) -> 58.209296 | K53: =IF(K25<=Barrier,0,$B$15*($B$14*L54+(1-$B$14)*L53)) -> 79.336867 | L53: =IF(L25<=Barrier,0,$B$15*($B$14*M54+(1-$B$14)*M53)) -> 105.63633 | M53: =IF(M25<=Barrier,0,$B$15*($B$14*N54+(1-$B$14)*N53)) -> 136.86424 | N53: =IF(N25<=Barrier,0,$B$15*($B$14*O54+(1-$B$14)*O53)) -> 171.64762 | O53: =IF(O25<=Barrier,0,$B$15*($B$14*P54+(1-$B$14)*P53)) -> 206.89139 | P53: =IF(P25<=Barrier,0,$B$15*($B$14*Q54+(1-$B$14)*Q53)) -> 237.18858 | ... Z53: =IF(Z25<=Barrier,0,$B$15*($B$14*AA54+(1-$B$14)*AA53)) -> 0 | AA53: =IF(AA25<=Barrier,0,MAX(Cap-AA25,0)) -> 0
J54: =IF(J26<=Barrier,0,$B$15*($B$14*K55+(1-$B$14)*K54)) -> 24.140049 | K54: =IF(K26<=Barrier,0,$B$15*($B$14*L55+(1-$B$14)*L54)) -> 35.346625 | L54: =IF(L26<=Barrier,0,$B$15*($B$14*M55+(1-$B$14)*M54)) -> 50.897258 | M54: =IF(M26<=Barrier,0,$B$15*($B$14*N55+(1-$B$14)*N54)) -> 71.899951 | N54: =IF(N26<=Barrier,0,$B$15*($B$14*O55+(1-$B$14)*O54)) -> 99.34178 | O54: =IF(O26<=Barrier,0,$B$15*($B$14*P55+(1-$B$14)*P54)) -> 133.72292 | P54: =IF(P26<=Barrier,0,$B$15*($B$14*Q55+(1-$B$14)*Q54)) -> 174.45945 | Q54: =IF(Q26<=Barrier,0,$B$15*($B$14*R55+(1-$B$14)*R54)) -> 219.01905 | ... Z54: =IF(Z26<=Barrier,0,$B$15*($B$14*AA55+(1-$B$14)*AA54)) -> 0 | AA54: =IF(AA26<=Barrier,0,MAX(Cap-AA26,0)) -> 0
K55: =IF(K27<=Barrier,0,$B$15*($B$14*L56+(1-$B$14)*L55)) -> 11.993848 | L55: =IF(L27<=Barrier,0,$B$15*($B$14*M56+(1-$B$14)*M55)) -> 18.497429 | M55: =IF(M27<=Barrier,0,$B$15*($B$14*N56+(1-$B$14)*N55)) -> 28.14977 | N55: =IF(N27<=Barrier,0,$B$15*($B$14*O56+(1-$B$14)*O55)) -> 42.193853 | O55: =IF(O27<=Barrier,0,$B$15*($B$14*P56+(1-$B$14)*P55)) -> 62.150317 | P55: =IF(P27<=Barrier,0,$B$15*($B$14*Q56+(1-$B$14)*Q55)) -> 89.702429 | Q55: =IF(Q27<=Barrier,0,$B$15*($B$14*R56+(1-$B$14)*R55)) -> 126.38842 | R55: =IF(R27<=Barrier,0,$B$15*($B$14*S56+(1-$B$14)*S55)) -> 172.97377 | ... Z55: =IF(Z27<=Barrier,0,$B$15*($B$14*AA56+(1-$B$14)*AA55)) -> 0 | AA55: =IF(AA27<=Barrier,0,MAX(Cap-AA27,0)) -> 0
L56: =IF(L28<=Barrier,0,$B$15*($B$14*M57+(1-$B$14)*M56)) -> 4.9391975 | M56: =IF(M28<=Barrier,0,$B$15*($B$14*N57+(1-$B$14)*N56)) -> 8.0292083 | N56: =IF(N28<=Barrier,0,$B$15*($B$14*O57+(1-$B$14)*O56)) -> 12.922127 | O56: =IF(O28<=Barrier,0,$B$15*($B$14*P57+(1-$B$14)*P56)) -> 20.561845 | P56: =IF(P28<=Barrier,0,$B$15*($B$14*Q57+(1-$B$14)*Q56)) -> 32.296092 | Q56: =IF(Q28<=Barrier,0,$B$15*($B$14*R57+(1-$B$14)*R56)) -> 49.971043 | R56: =IF(R28<=Barrier,0,$B$15*($B$14*S57+(1-$B$14)*S56)) -> 75.971632 | S56: =IF(S28<=Barrier,0,$B$15*($B$14*T57+(1-$B$14)*T56)) -> 113.10894 | ... Z56: =IF(Z28<=Barrier,0,$B$15*($B$14*AA57+(1-$B$14)*AA56)) -> 358.72161 | AA56: =IF(AA28<=Barrier,0,MAX(Cap-AA28,0)) -> 0
M57: =IF(M29<=Barrier,0,$B$15*($B$14*N58+(1-$B$14)*N57)) -> 1.5851853 | N57: =IF(N29<=Barrier,0,$B$15*($B$14*O58+(1-$B$14)*O57)) -> 2.7188492 | O57: =IF(O29<=Barrier,0,$B$15*($B$14*P58+(1-$B$14)*P57)) -> 4.6317287 | P57: =IF(P29<=Barrier,0,$B$15*($B$14*Q58+(1-$B$14)*Q57)) -> 7.8302291 | Q57: =IF(Q29<=Barrier,0,$B$15*($B$14*R58+(1-$B$14)*R57)) -> 13.122625 | R57: =IF(R29<=Barrier,0,$B$15*($B$14*S58+(1-$B$14)*S57)) -> 21.773125 | S57: =IF(S29<=Barrier,0,$B$15*($B$14*T58+(1-$B$14)*T57)) -> 35.708986 | T57: =IF(T29<=Barrier,0,$B$15*($B$14*U58+(1-$B$14)*U57)) -> 57.77095 | ... Z57: =IF(Z29<=Barrier,0,$B$15*($B$14*AA58+(1-$B$14)*AA57)) -> 611.35585 | AA57: =IF(AA29<=Barrier,0,MAX(Cap-AA29,0)) -> 750.76038
N58: =IF(N30<=Barrier,0,$B$15*($B$14*O59+(1-$B$14)*O58)) -> 0.35401483 | O58: =IF(O30<=Barrier,0,$B$15*($B$14*P59+(1-$B$14)*P58)) -> 0.64156898 | P58: =IF(P30<=Barrier,0,$B$15*($B$14*Q59+(1-$B$14)*Q58)) -> 1.1585811 | Q58: =IF(Q30<=Barrier,0,$B$15*($B$14*R59+(1-$B$14)*R58)) -> 2.0838647 | R58: =IF(R30<=Barrier,0,$B$15*($B$14*S59+(1-$B$14)*S58)) -> 3.7310341 | S58: =IF(S30<=Barrier,0,$B$15*($B$14*T59+(1-$B$14)*T58)) -> 6.645187 | T58: =IF(T30<=Barrier,0,$B$15*($B$14*U59+(1-$B$14)*U58)) -> 11.763386 | U58: =IF(U30<=Barrier,0,$B$15*($B$14*V59+(1-$B$14)*V58)) -> 20.674493 | ... Z58: =IF(Z30<=Barrier,0,$B$15*($B$14*AA59+(1-$B$14)*AA58)) -> 290.06568 | AA58: =IF(AA30<=Barrier,0,MAX(Cap-AA30,0)) -> 461.15352
O59: =IF(O31<=Barrier,0,$B$15*($B$14*P60+(1-$B$14)*P59)) -> 0.041590462 | P59: =IF(P31<=Barrier,0,$B$15*($B$14*Q60+(1-$B$14)*Q59)) -> 0.079855614 | Q59: =IF(Q31<=Barrier,0,$B$15*($B$14*R60+(1-$B$14)*R59)) -> 0.15332648 | R59: =IF(R31<=Barrier,0,$B$15*($B$14*S60+(1-$B$14)*S59)) -> 0.29439395 | S59: =IF(S31<=Barrier,0,$B$15*($B$14*T60+(1-$B$14)*T59)) -> 0.56525002 | T59: =IF(T31<=Barrier,0,$B$15*($B$14*U60+(1-$B$14)*U59)) -> 1.0853062 | U59: =IF(U31<=Barrier,0,$B$15*($B$14*V60+(1-$B$14)*V59)) -> 2.0838383 | V59: =IF(V31<=Barrier,0,$B$15*($B$14*W60+(1-$B$14)*W59)) -> 4.001066 | ... Z59: =IF(Z31<=Barrier,0,$B$15*($B$14*AA60+(1-$B$14)*AA59)) -> 54.377916 | AA59: =IF(AA31<=Barrier,0,MAX(Cap-AA31,0)) -> 104.40812
P60: =IF(P32<=Barrier,0,$B$15*($B$14*Q61+(1-$B$14)*Q60)) -> 0 | Q60: =IF(Q32<=Barrier,0,$B$15*($B$14*R61+(1-$B$14)*R60)) -> 0 | R60: =IF(R32<=Barrier,0,$B$15*($B$14*S61+(1-$B$14)*S60)) -> 0 | S60: =IF(S32<=Barrier,0,$B$15*($B$14*T61+(1-$B$14)*T60)) -> 0 | T60: =IF(T32<=Barrier,0,$B$15*($B$14*U61+(1-$B$14)*U60)) -> 0 | U60: =IF(U32<=Barrier,0,$B$15*($B$14*V61+(1-$B$14)*V60)) -> 0 | V60: =IF(V32<=Barrier,0,$B$15*($B$14*W61+(1-$B$14)*W60)) -> 0 | W60: =IF(W32<=Barrier,0,$B$15*($B$14*X61+(1-$B$14)*X60)) -> 0 | ... Z60: =IF(Z32<=Barrier,0,$B$15*($B$14*AA61+(1-$B$14)*AA60)) -> 0 | AA60: =IF(AA32<=Barrier,0,MAX(Cap-AA32,0)) -> 0
Q61: =IF(Q33<=Barrier,0,$B$15*($B$14*R62+(1-$B$14)*R61)) -> 0 | R61: =IF(R33<=Barrier,0,$B$15*($B$14*S62+(1-$B$14)*S61)) -> 0 | S61: =IF(S33<=Barrier,0,$B$15*($B$14*T62+(1-$B$14)*T61)) -> 0 | T61: =IF(T33<=Barrier,0,$B$15*($B$14*U62+(1-$B$14)*U61)) -> 0 | U61: =IF(U33<=Barrier,0,$B$15*($B$14*V62+(1-$B$14)*V61)) -> 0 | V61: =IF(V33<=Barrier,0,$B$15*($B$14*W62+(1-$B$14)*W61)) -> 0 | W61: =IF(W33<=Barrier,0,$B$15*($B$14*X62+(1-$B$14)*X61)) -> 0 | X61: =IF(X33<=Barrier,0,$B$15*($B$14*Y62+(1-$B$14)*Y61)) -> 0 | ... Z61: =IF(Z33<=Barrier,0,$B$15*($B$14*AA62+(1-$B$14)*AA61)) -> 0 | AA61: =IF(AA33<=Barrier,0,MAX(Cap-AA33,0)) -> 0
R62: =IF(R34<=Barrier,0,$B$15*($B$14*S63+(1-$B$14)*S62)) -> 0 | S62: =IF(S34<=Barrier,0,$B$15*($B$14*T63+(1-$B$14)*T62)) -> 0 | T62: =IF(T34<=Barrier,0,$B$15*($B$14*U63+(1-$B$14)*U62)) -> 0 | U62: =IF(U34<=Barrier,0,$B$15*($B$14*V63+(1-$B$14)*V62)) -> 0 | V62: =IF(V34<=Barrier,0,$B$15*($B$14*W63+(1-$B$14)*W62)) -> 0 | W62: =IF(W34<=Barrier,0,$B$15*($B$14*X63+(1-$B$14)*X62)) -> 0 | X62: =IF(X34<=Barrier,0,$B$15*($B$14*Y63+(1-$B$14)*Y62)) -> 0 | Y62: =IF(Y34<=Barrier,0,$B$15*($B$14*Z63+(1-$B$14)*Z62)) -> 0 | Z62: =IF(Z34<=Barrier,0,$B$15*($B$14*AA63+(1-$B$14)*AA62)) -> 0 | AA62: =IF(AA34<=Barrier,0,MAX(Cap-AA34,0)) -> 0
S63: =IF(S35<=Barrier,0,$B$15*($B$14*T64+(1-$B$14)*T63)) -> 0 | T63: =IF(T35<=Barrier,0,$B$15*($B$14*U64+(1-$B$14)*U63)) -> 0 | U63: =IF(U35<=Barrier,0,$B$15*($B$14*V64+(1-$B$14)*V63)) -> 0 | V63: =IF(V35<=Barrier,0,$B$15*($B$14*W64+(1-$B$14)*W63)) -> 0 | W63: =IF(W35<=Barrier,0,$B$15*($B$14*X64+(1-$B$14)*X63)) -> 0 | X63: =IF(X35<=Barrier,0,$B$15*($B$14*Y64+(1-$B$14)*Y63)) -> 0 | Y63: =IF(Y35<=Barrier,0,$B$15*($B$14*Z64+(1-$B$14)*Z63)) -> 0 | Z63: =IF(Z35<=Barrier,0,$B$15*($B$14*AA64+(1-$B$14)*AA63)) -> 0 | AA63: =IF(AA35<=Barrier,0,MAX(Cap-AA35,0)) -> 0
T64: =IF(T36<=Barrier,0,$B$15*($B$14*U65+(1-$B$14)*U64)) -> 0 | U64: =IF(U36<=Barrier,0,$B$15*($B$14*V65+(1-$B$14)*V64)) -> 0 | V64: =IF(V36<=Barrier,0,$B$15*($B$14*W65+(1-$B$14)*W64)) -> 0 | W64: =IF(W36<=Barrier,0,$B$15*($B$14*X65+(1-$B$14)*X64)) -> 0 | X64: =IF(X36<=Barrier,0,$B$15*($B$14*Y65+(1-$B$14)*Y64)) -> 0 | Y64: =IF(Y36<=Barrier,0,$B$15*($B$14*Z65+(1-$B$14)*Z64)) -> 0 | Z64: =IF(Z36<=Barrier,0,$B$15*($B$14*AA65+(1-$B$14)*AA64)) -> 0 | AA64: =IF(AA36<=Barrier,0,MAX(Cap-AA36,0)) -> 0
U65: =IF(U37<=Barrier,0,$B$15*($B$14*V66+(1-$B$14)*V65)) -> 0 | V65: =IF(V37<=Barrier,0,$B$15*($B$14*W66+(1-$B$14)*W65)) -> 0 | W65: =IF(W37<=Barrier,0,$B$15*($B$14*X66+(1-$B$14)*X65)) -> 0 | X65: =IF(X37<=Barrier,0,$B$15*($B$14*Y66+(1-$B$14)*Y65)) -> 0 | Y65: =IF(Y37<=Barrier,0,$B$15*($B$14*Z66+(1-$B$14)*Z65)) -> 0 | Z65: =IF(Z37<=Barrier,0,$B$15*($B$14*AA66+(1-$B$14)*AA65)) -> 0 | AA65: =IF(AA37<=Barrier,0,MAX(Cap-AA37,0)) -> 0
V66: =IF(V38<=Barrier,0,$B$15*($B$14*W67+(1-$B$14)*W66)) -> 0 | W66: =IF(W38<=Barrier,0,$B$15*($B$14*X67+(1-$B$14)*X66)) -> 0 | X66: =IF(X38<=Barrier,0,$B$15*($B$14*Y67+(1-$B$14)*Y66)) -> 0 | Y66: =IF(Y38<=Barrier,0,$B$15*($B$14*Z67+(1-$B$14)*Z66)) -> 0 | Z66: =IF(Z38<=Barrier,0,$B$15*($B$14*AA67+(1-$B$14)*AA66)) -> 0 | AA66: =IF(AA38<=Barrier,0,MAX(Cap-AA38,0)) -> 0
W67: =IF(W39<=Barrier,0,$B$15*($B$14*X68+(1-$B$14)*X67)) -> 0 | X67: =IF(X39<=Barrier,0,$B$15*($B$14*Y68+(1-$B$14)*Y67)) -> 0 | Y67: =IF(Y39<=Barrier,0,$B$15*($B$14*Z68+(1-$B$14)*Z67)) -> 0 | Z67: =IF(Z39<=Barrier,0,$B$15*($B$14*AA68+(1-$B$14)*AA67)) -> 0 | AA67: =IF(AA39<=Barrier,0,MAX(Cap-AA39,0)) -> 0
X68: =IF(X40<=Barrier,0,$B$15*($B$14*Y69+(1-$B$14)*Y68)) -> 0 | Y68: =IF(Y40<=Barrier,0,$B$15*($B$14*Z69+(1-$B$14)*Z68)) -> 0 | Z68: =IF(Z40<=Barrier,0,$B$15*($B$14*AA69+(1-$B$14)*AA68)) -> 0 | AA68: =IF(AA40<=Barrier,0,MAX(Cap-AA40,0)) -> 0
Y69: =IF(Y41<=Barrier,0,$B$15*($B$14*Z70+(1-$B$14)*Z69)) -> 0 | Z69: =IF(Z41<=Barrier,0,$B$15*($B$14*AA70+(1-$B$14)*AA69)) -> 0 | AA69: =IF(AA41<=Barrier,0,MAX(Cap-AA41,0)) -> 0
Z70: =IF(Z42<=Barrier,0,$B$15*($B$14*AA71+(1-$B$14)*AA70)) -> 0 | AA70: =IF(AA42<=Barrier,0,MAX(Cap-AA42,0)) -> 0
AA71: =IF(AA43<=Barrier,0,MAX(Cap-AA43,0)) -> 0
A73: Capped-forward value tree (min(S_T,Cap))
B74: =$B$15*($B$14*C75+(1-$B$14)*C74) -> 1425.2436 | C74: =$B$15*($B$14*D75+(1-$B$14)*D74) -> 1342.9417 | D74: =$B$15*($B$14*E75+(1-$B$14)*E74) -> 1255.7126 | E74: =$B$15*($B$14*F75+(1-$B$14)*F74) -> 1165.3481 | F74: =$B$15*($B$14*G75+(1-$B$14)*G74) -> 1073.8624 | G74: =$B$15*($B$14*H75+(1-$B$14)*H74) -> 983.31801 | H74: =$B$15*($B$14*I75+(1-$B$14)*I74) -> 895.63162 | I74: =$B$15*($B$14*J75+(1-$B$14)*J74) -> 812.39381 | ... Z74: =$B$15*($B$14*AA75+(1-$B$14)*AA74) -> 139.85865 | AA74: =MIN(AA18,Cap) -> 126.06681
C75: =$B$15*($B$14*D76+(1-$B$14)*D75) -> 1519.0349 | D75: =$B$15*($B$14*E76+(1-$B$14)*E75) -> 1441.8681 | E75: =$B$15*($B$14*F76+(1-$B$14)*F75) -> 1357.8067 | F75: =$B$15*($B$14*G76+(1-$B$14)*G75) -> 1268.4057 | G75: =$B$15*($B$14*H76+(1-$B$14)*H75) -> 1175.6321 | H75: =$B$15*($B$14*I76+(1-$B$14)*I75) -> 1081.7131 | I75: =$B$15*($B$14*J76+(1-$B$14)*J75) -> 988.92659 | J75: =$B$15*($B$14*K76+(1-$B$14)*K75) -> 899.36501 | ... Z75: =$B$15*($B$14*AA76+(1-$B$14)*AA75) -> 172.28159 | AA75: =MIN(AA19,Cap) -> 155.29243
D76: =$B$15*($B$14*E77+(1-$B$14)*E76) -> 1607.4974 | E76: =$B$15*($B$14*F77+(1-$B$14)*F76) -> 1537.6248 | F76: =$B$15*($B$14*G77+(1-$B$14)*G76) -> 1459.1431 | G76: =$B$15*($B$14*H77+(1-$B$14)*H76) -> 1373.1624 | H76: =$B$15*($B$14*I77+(1-$B$14)*I76) -> 1281.3715 | I76: =$B$15*($B$14*J77+(1-$B$14)*J76) -> 1185.9491 | J76: =$B$15*($B$14*K77+(1-$B$14)*K76) -> 1089.3817 | K76: =$B$15*($B$14*L77+(1-$B$14)*L76) -> 994.20597 | ... Z76: =$B$15*($B$14*AA77+(1-$B$14)*AA76) -> 212.22103 | AA76: =MIN(AA20,Cap) -> 191.29333
E77: =$B$15*($B$14*F78+(1-$B$14)*F77) -> 1688.2626 | F77: =$B$15*($B$14*G78+(1-$B$14)*G77) -> 1627.5739 | G77: =$B$15*($B$14*H78+(1-$B$14)*H77) -> 1557.0415 | H77: =$B$15*($B$14*I78+(1-$B$14)*I77) -> 1477.1477 | I77: =$B$15*($B$14*J78+(1-$B$14)*J77) -> 1389.0524 | J77: =$B$15*($B$14*K78+(1-$B$14)*K77) -> 1294.6047 | K77: =$B$15*($B$14*L78+(1-$B$14)*L77) -> 1196.244 | L77: =$B$15*($B$14*M78+(1-$B$14)*M77) -> 1096.7786 | ... Z77: =$B$15*($B$14*AA78+(1-$B$14)*AA77) -> 261.41949 | AA77: =MIN(AA21,Cap) -> 235.6402
F78: =$B$15*($B$14*G79+(1-$B$14)*G78) -> 1759.2483 | G78: =$B$15*($B$14*H79+(1-$B$14)*H78) -> 1709.1157 | H78: =$B$15*($B$14*I79+(1-$B$14)*I78) -> 1648.5854 | I78: =$B$15*($B$14*J79+(1-$B$14)*J78) -> 1577.4024 | J78: =$B$15*($B$14*K79+(1-$B$14)*K78) -> 1495.9792 | K78: =$B$15*($B$14*L79+(1-$B$14)*L78) -> 1405.5264 | L78: =$B$15*($B$14*M79+(1-$B$14)*M78) -> 1308.0881 | M78: =$B$15*($B$14*N79+(1-$B$14)*N78) -> 1206.4333 | ... Z78: =$B$15*($B$14*AA79+(1-$B$14)*AA78) -> 322.02346 | AA78: =MIN(AA22,Cap) -> 290.26785
G79: =$B$15*($B$14*H80+(1-$B$14)*H79) -> 1818.931 | H79: =$B$15*($B$14*I80+(1-$B$14)*I79) -> 1779.9885 | I79: =$B$15*($B$14*J80+(1-$B$14)*J79) -> 1730.8965 | J79: =$B$15*($B$14*K80+(1-$B$14)*K79) -> 1670.6718 | K79: =$B$15*($B$14*L80+(1-$B$14)*L79) -> 1598.8576 | L79: =$B$15*($B$14*M80+(1-$B$14)*M79) -> 1515.7601 | M79: =$B$15*($B$14*N80+(1-$B$14)*N79) -> 1422.6389 | N79: =$B$15*($B$14*O80+(1-$B$14)*O79) -> 1321.7819 | ... Z79: =$B$15*($B$14*AA80+(1-$B$14)*AA79) -> 396.67704 | AA79: =MIN(AA23,Cap) -> 357.55963
H80: =$B$15*($B$14*I81+(1-$B$14)*I80) -> 1866.5874 | I80: =$B$15*($B$14*J81+(1-$B$14)*J80) -> 1838.5963 | J80: =$B$15*($B$14*K81+(1-$B$14)*K80) -> 1801.4986 | K80: =$B$15*($B$14*L81+(1-$B$14)*L80) -> 1753.7341 | L80: =$B$15*($B$14*M81+(1-$B$14)*M80) -> 1694.0133 | M80: =$B$15*($B$14*N81+(1-$B$14)*N80) -> 1621.6038 | N80: =$B$15*($B$14*O81+(1-$B$14)*O80) -> 1536.6482 | O80: =$B$15*($B$14*P81+(1-$B$14)*P80) -> 1440.4479 | ... Z80: =$B$15*($B$14*AA81+(1-$B$14)*AA80) -> 488.63729 | AA80: =MIN(AA24,Cap) -> 440.45143
I81: =$B$15*($B$14*J82+(1-$B$14)*J81) -> 1902.443 | J81: =$B$15*($B$14*K82+(1-$B$14)*K81) -> 1884.298 | K81: =$B$15*($B$14*L82+(1-$B$14)*L81) -> 1858.7211 | L81: =$B$15*($B$14*M82+(1-$B$14)*M81) -> 1823.8523 | M81: =$B$15*($B$14*N82+(1-$B$14)*N81) -> 1777.7915 | N81: =$B$15*($B$14*O82+(1-$B$14)*O81) -> 1718.8499 | O81: =$B$15*($B$14*P82+(1-$B$14)*P81) -> 1645.9079 | P81: =$B$15*($B$14*Q82+(1-$B$14)*Q81) -> 1558.8525 | ... Z81: =$B$15*($B$14*AA82+(1-$B$14)*AA81) -> 601.91637 | AA81: =MIN(AA25,Cap) -> 542.55974
J82: =$B$15*($B$14*K83+(1-$B$14)*K82) -> 1927.6688 | K82: =$B$15*($B$14*L83+(1-$B$14)*L82) -> 1917.5727 | L82: =$B$15*($B$14*M83+(1-$B$14)*M82) -> 1902.051 | M82: =$B$15*($B$14*N83+(1-$B$14)*N82) -> 1879.2816 | N82: =$B$15*($B$14*O83+(1-$B$14)*O82) -> 1847.1293 | O82: =$B$15*($B$14*P83+(1-$B$14)*P82) -> 1803.2795 | P82: =$B$15*($B$14*Q83+(1-$B$14)*Q82) -> 1745.5126 | Q82: =$B$15*($B$14*R83+(1-$B$14)*R82) -> 1672.1494 | ... Z82: =$B$15*($B$14*AA83+(1-$B$14)*AA82) -> 741.45653 | AA82: =MIN(AA26,Cap) -> 668.33947
K83: =$B$15*($B$14*L84+(1-$B$14)*L83) -> 1944.1935 | L83: =$B$15*($B$14*M84+(1-$B$14)*M83) -> 1939.9825 | M83: =$B$15*($B$14*N84+(1-$B$14)*N83) -> 1932.3163 | N83: =$B$15*($B$14*O84+(1-$B$14)*O83) -> 1919.7093 | O83: =$B$15*($B$14*P84+(1-$B$14)*P83) -> 1900.2154 | P83: =$B$15*($B$14*Q84+(1-$B$14)*Q83) -> 1871.4099 | Q83: =$B$15*($B$14*R84+(1-$B$14)*R83) -> 1830.4776 | R83: =$B$15*($B$14*S84+(1-$B$14)*S83) -> 1774.4815 | ... Z83: =$B$15*($B$14*AA84+(1-$B$14)*AA83) -> 913.34581 | AA83: =MIN(AA27,Cap) -> 823.27828
L84: =$B$15*($B$14*M85+(1-$B$14)*M84) -> 1954.3506 | M84: =$B$15*($B$14*N85+(1-$B$14)*N84) -> 1953.8939 | N84: =$B$15*($B$14*O85+(1-$B$14)*O84) -> 1951.5911 | O84: =$B$15*($B$14*P85+(1-$B$14)*P84) -> 1946.455 | P84: =$B$15*($B$14*Q85+(1-$B$14)*Q84) -> 1937.0549 | Q84: =$B$15*($B$14*R85+(1-$B$14)*R84) -> 1921.3853 | R84: =$B$15*($B$14*S85+(1-$B$14)*S84) -> 1896.7556 | S84: =$B$15*($B$14*T85+(1-$B$14)*T84) -> 1859.7673 | ... Z84: =$B$15*($B$14*AA85+(1-$B$14)*AA84) -> 1125.0836 | AA84: =MIN(AA28,Cap) -> 1014.136
M85: =$B$15*($B$14*N86+(1-$B$14)*N85) -> 1960.4445 | N85: =$B$15*($B$14*O86+(1-$B$14)*O85) -> 1961.9989 | O85: =$B$15*($B$14*P86+(1-$B$14)*P85) -> 1962.7778 | P85: =$B$15*($B$14*Q86+(1-$B$14)*Q85) -> 1962.2748 | Q85: =$B$15*($B$14*R86+(1-$B$14)*R85) -> 1959.6815 | R85: =$B$15*($B$14*S86+(1-$B$14)*S85) -> 1953.7339 | S85: =$B$15*($B$14*T86+(1-$B$14)*T85) -> 1942.5046 | T85: =$B$15*($B$14*U86+(1-$B$14)*U85) -> 1923.1529 | ... Z85: =$B$15*($B$14*AA86+(1-$B$14)*AA85) -> 1385.9078 | AA85: =MIN(AA29,Cap) -> 1249.2396
N86: =$B$15*($B$14*O87+(1-$B$14)*O86) -> 1964.3637 | O86: =$B$15*($B$14*P87+(1-$B$14)*P86) -> 1966.768 | P86: =$B$15*($B$14*Q87+(1-$B$14)*Q86) -> 1968.9464 | Q86: =$B$15*($B$14*R87+(1-$B$14)*R86) -> 1970.7203 | R86: =$B$15*($B$14*S87+(1-$B$14)*S86) -> 1971.776 | S86: =$B$15*($B$14*T87+(1-$B$14)*T86) -> 1971.5684 | T86: =$B$15*($B$14*U87+(1-$B$14)*U86) -> 1969.1605 | U86: =$B$15*($B$14*V87+(1-$B$14)*V86) -> 1962.9633 | ... Z86: =$B$15*($B$14*AA87+(1-$B$14)*AA86) -> 1707.1979 | AA86: =MIN(AA30,Cap) -> 1538.8465
O87: =$B$15*($B$14*P88+(1-$B$14)*P87) -> 1967.3679 | P87: =$B$15*($B$14*Q88+(1-$B$14)*Q87) -> 1970.0251 | Q87: =$B$15*($B$14*R88+(1-$B$14)*R87) -> 1972.6508 | R87: =$B$15*($B$14*S88+(1-$B$14)*S87) -> 1975.2126 | S87: =$B$15*($B$14*T88+(1-$B$14)*T87) -> 1977.6483 | T87: =$B$15*($B$14*U88+(1-$B$14)*U87) -> 1979.8385 | U87: =$B$15*($B$14*V88+(1-$B$14)*V87) -> 1981.554 | V87: =$B$15*($B$14*W88+(1-$B$14)*W87) -> 1982.3545 | ... Z87: =$B$15*($B$14*AA88+(1-$B$14)*AA87) -> 1942.8857 | AA87: =MIN(AA31,Cap) -> 1895.5919
P88: =$B$15*($B$14*Q89+(1-$B$14)*Q88) -> 1970.105 | Q88: =$B$15*($B$14*R89+(1-$B$14)*R88) -> 1972.8042 | R88: =$B$15*($B$14*S89+(1-$B$14)*S88) -> 1975.507 | S88: =$B$15*($B$14*T89+(1-$B$14)*T88) -> 1978.2136 | T88: =$B$15*($B$14*U89+(1-$B$14)*U88) -> 1980.9239 | U88: =$B$15*($B$14*V89+(1-$B$14)*V88) -> 1983.6378 | V88: =$B$15*($B$14*W89+(1-$B$14)*W88) -> 1986.3555 | W88: =$B$15*($B$14*X89+(1-$B$14)*X88) -> 1989.077 | ... Z88: =$B$15*($B$14*AA89+(1-$B$14)*AA88) -> 1997.2636 | AA88: =MIN(AA32,Cap) -> 2000
Q89: =$B$15*($B$14*R90+(1-$B$14)*R89) -> 1972.8042 | R89: =$B$15*($B$14*S90+(1-$B$14)*S89) -> 1975.507 | S89: =$B$15*($B$14*T90+(1-$B$14)*T89) -> 1978.2136 | T89: =$B$15*($B$14*U90+(1-$B$14)*U89) -> 1980.9239 | U89: =$B$15*($B$14*V90+(1-$B$14)*V89) -> 1983.6378 | V89: =$B$15*($B$14*W90+(1-$B$14)*W89) -> 1986.3555 | W89: =$B$15*($B$14*X90+(1-$B$14)*X89) -> 1989.077 | X89: =$B$15*($B$14*Y90+(1-$B$14)*Y89) -> 1991.8021 | ... Z89: =$B$15*($B$14*AA90+(1-$B$14)*AA89) -> 1997.2636 | AA89: =MIN(AA33,Cap) -> 2000
R90: =$B$15*($B$14*S91+(1-$B$14)*S90) -> 1975.507 | S90: =$B$15*($B$14*T91+(1-$B$14)*T90) -> 1978.2136 | T90: =$B$15*($B$14*U91+(1-$B$14)*U90) -> 1980.9239 | U90: =$B$15*($B$14*V91+(1-$B$14)*V90) -> 1983.6378 | V90: =$B$15*($B$14*W91+(1-$B$14)*W90) -> 1986.3555 | W90: =$B$15*($B$14*X91+(1-$B$14)*X90) -> 1989.077 | X90: =$B$15*($B$14*Y91+(1-$B$14)*Y90) -> 1991.8021 | Y90: =$B$15*($B$14*Z91+(1-$B$14)*Z90) -> 1994.531 | Z90: =$B$15*($B$14*AA91+(1-$B$14)*AA90) -> 1997.2636 | AA90: =MIN(AA34,Cap) -> 2000
S91: =$B$15*($B$14*T92+(1-$B$14)*T91) -> 1978.2136 | T91: =$B$15*($B$14*U92+(1-$B$14)*U91) -> 1980.9239 | U91: =$B$15*($B$14*V92+(1-$B$14)*V91) -> 1983.6378 | V91: =$B$15*($B$14*W92+(1-$B$14)*W91) -> 1986.3555 | W91: =$B$15*($B$14*X92+(1-$B$14)*X91) -> 1989.077 | X91: =$B$15*($B$14*Y92+(1-$B$14)*Y91) -> 1991.8021 | Y91: =$B$15*($B$14*Z92+(1-$B$14)*Z91) -> 1994.531 | Z91: =$B$15*($B$14*AA92+(1-$B$14)*AA91) -> 1997.2636 | AA91: =MIN(AA35,Cap) -> 2000
T92: =$B$15*($B$14*U93+(1-$B$14)*U92) -> 1980.9239 | U92: =$B$15*($B$14*V93+(1-$B$14)*V92) -> 1983.6378 | V92: =$B$15*($B$14*W93+(1-$B$14)*W92) -> 1986.3555 | W92: =$B$15*($B$14*X93+(1-$B$14)*X92) -> 1989.077 | X92: =$B$15*($B$14*Y93+(1-$B$14)*Y92) -> 1991.8021 | Y92: =$B$15*($B$14*Z93+(1-$B$14)*Z92) -> 1994.531 | Z92: =$B$15*($B$14*AA93+(1-$B$14)*AA92) -> 1997.2636 | AA92: =MIN(AA36,Cap) -> 2000
U93: =$B$15*($B$14*V94+(1-$B$14)*V93) -> 1983.6378 | V93: =$B$15*($B$14*W94+(1-$B$14)*W93) -> 1986.3555 | W93: =$B$15*($B$14*X94+(1-$B$14)*X93) -> 1989.077 | X93: =$B$15*($B$14*Y94+(1-$B$14)*Y93) -> 1991.8021 | Y93: =$B$15*($B$14*Z94+(1-$B$14)*Z93) -> 1994.531 | Z93: =$B$15*($B$14*AA94+(1-$B$14)*AA93) -> 1997.2636 | AA93: =MIN(AA37,Cap) -> 2000
V94: =$B$15*($B$14*W95+(1-$B$14)*W94) -> 1986.3555 | W94: =$B$15*($B$14*X95+(1-$B$14)*X94) -> 1989.077 | X94: =$B$15*($B$14*Y95+(1-$B$14)*Y94) -> 1991.8021 | Y94: =$B$15*($B$14*Z95+(1-$B$14)*Z94) -> 1994.531 | Z94: =$B$15*($B$14*AA95+(1-$B$14)*AA94) -> 1997.2636 | AA94: =MIN(AA38,Cap) -> 2000
W95: =$B$15*($B$14*X96+(1-$B$14)*X95) -> 1989.077 | X95: =$B$15*($B$14*Y96+(1-$B$14)*Y95) -> 1991.8021 | Y95: =$B$15*($B$14*Z96+(1-$B$14)*Z95) -> 1994.531 | Z95: =$B$15*($B$14*AA96+(1-$B$14)*AA95) -> 1997.2636 | AA95: =MIN(AA39,Cap) -> 2000
X96: =$B$15*($B$14*Y97+(1-$B$14)*Y96) -> 1991.8021 | Y96: =$B$15*($B$14*Z97+(1-$B$14)*Z96) -> 1994.531 | Z96: =$B$15*($B$14*AA97+(1-$B$14)*AA96) -> 1997.2636 | AA96: =MIN(AA40,Cap) -> 2000
Y97: =$B$15*($B$14*Z98+(1-$B$14)*Z97) -> 1994.531 | Z97: =$B$15*($B$14*AA98+(1-$B$14)*AA97) -> 1997.2636 | AA97: =MIN(AA41,Cap) -> 2000
Z98: =$B$15*($B$14*AA99+(1-$B$14)*AA98) -> 1997.2636 | AA98: =MIN(AA42,Cap) -> 2000
AA99: =MIN(AA43,Cap) -> 2000
A102: CROSS-CHECK
A103: CRR DO-put (root) | B103: =B46 -> 127.12606
A104: CRR capped fwd (root) | B104: =B74 -> 1425.2436
A105: CRR Bonus Cap (root) | B105: =B46+B74 -> 1552.3696
A106: Closed-form (Task V day 1) | B106: =P2_TaskV_Valuation!AB4 -> 1543.6153
...

Sheet Results
A1: Results summary — DU2076 Bonus Cap
A3: Metric | B3: Value
A4: Valuation window start | B4: =Data_Stock!A4 -> 45904
A5: Valuation window end | B5: =Data_Stock!A186 -> 46174
A6: Number of trading days | B6: =COUNT(P2_TaskV_Valuation!AD4:AD186) -> 183
A7: Mean model price (EUR) | B7: =AVERAGE(P2_TaskV_Valuation!AB4:AB186) -> 1480.4561
A8: Mean market price (EUR) | B8: =AVERAGE(P2_TaskV_Valuation!AC4:AC186) -> 1574.7496
A9: ME (EUR) | B9: =P2_TaskV_Valuation!AB188 -> -94.293549
A10: MAE (EUR) | B10: =P2_TaskV_Valuation!AB189 -> 101.88208
A11: RMSE (EUR) | B11: =P2_TaskV_Valuation!AB190 -> 116.44496
A12: Delta (Task VI, day-1 ref) | B12: =P2_TaskVI_Greeks!B33 -> 0.53133878
A13: Vega (per +1 vol pt) | B13: =P2_TaskVI_Greeks!B35 -> -13.368929
A14: Theta (per day, /365) | B14: =P2_TaskVI_Greeks!B36 -> 0.50587839
A15: Mean equity fraction (Task VII) | B15: =AVERAGE(P2_TaskVII_Replication!AG4:AG186) -> 0.67710126
A16: Part 1 participation alpha | B16: =P1_Tasks_I_IV!B28 -> #DIV/0!
A17: Part 1 participation-note market (EUR bn) | B17: =P1_Tasks_I_IV!B49 -> 2.3408
